Workbook
Name CANTIDAD_POR_DEPARTAMENTO: #REF!
Name SUELDOS_POR_DEPARTAMENTO: #REF!

Sheet OCTUBRE 2025
B2: COOPERATIVA DE AHORRO Y CRÉDITO "LOS ANDES LATINOS" LTDA. | AN2: COOPERATIVA DE AHORRO Y CRÉDITO "LOS ANDES LATINOS" LTDA.
B3: ROL DE PAGOS | R3: MES DE OCTUBRE 2025 | AN3: BENEFICIOS SOCIALES | AU3: =+R3 -> MES DE OCTUBRE 2025
C4: 1 | D4: 2 | E4: 3 | F4: 4 | G4: 5 | H4: 6 | I4: 7 | J4: 8 | K4: 9 | L4: 10 | M4: 11 | N4: 12 | O4: 13 | P4: 14 | Q4: 15 | R4: 16 | S4: 17 | T4: 18 | U4: 19 | V4: 20 | W4: 21 | X4: 22 | Y4: 23 | Z4: 24 | AA4: 25 | AB4: 26 | AC4: 27 | AD4: 28 | AE4: 29 | AF4: 30 | AG4: 31 | AH4: 32 | AI4: 33
J5: INGRESOS | Z5: EGRESOS
B6: No. | C6: CEDULA | D6: NOMBRE | E6: FECHA DE INGRESO | F6: CARGO | G6: GÉNERO | H6: AGENCIA | I6: DIAS TRABAJADOS | J6: SUELDO BRUTO | K6: BONO VEHICULAR | L6: Bono General Mensual | M6: BONO CUMPLIMIENTO | N6: COMISIÓN SUP. META | O6: COMISION POR PLAZOS FIJOS | P6: COM. SOCIOS NUEVOS Y COLOCACION | Q6: VALOR EN HORAS EXTRAS | S6: TOTAL POR VARIACION | T6: INGRESOS APORTE AL IESS | U6: FONDO RESERVAS | V6: FONDO DE RESERVA (BONO NAVIDEÑO) | W6: DECIMO TERCERO | X6: DECIMO CUARTO | Y6: TOTAL DE Ingresos | Z6: IESS | AA6: RET IMP A LA RENTA | AB6: DSCTOS | AC6: PRESTAMO PQ- HIP | AD6: SUBSIDIOS MONETARIO | AE6: EXT. SALUD | AF6: PENSION ALIMENTICIA | AG6: C*C | AH6: ANTICP. SUELD. | AI6: TOTAL DESCTS. | AJ6: NETO | AK6: RECIBI CONFORME | AN6: No. | AO6: NOMBRE | AP6: FECHA DE INGRESO. | AQ6: DIAS TRABAJADOS | AR6: AGENCIA | AS6: TOTAL GANADO EN EL MES GRAVABLE | AT6: 13ER. SUELDO | AU6: FONDO DE RESERVA | AV6: 14TO. SUELDO | AW6: 14TO. SUELDO | AX6: VACACIONES | AY6: TOTAL SUELDO + B.SOCIAL | AZ6: APORTE AL IESS
Q7: 0.5 | R7: 1 | Z7: 0.0945 | AT7: 12 | AU7: 0.0833 | AV7: AJUSTE | AW7: 470 | AX7: 24 | AZ7: Patronal 11,15% | BA7: CCC 1% | BB7: TOTAL
B8: 1 | C8: 925813685 | D8: ASITIMBAY CRIOLLO JOHN ANDERSON | E8: 44292 | F8: JEFE DE MARKETING | G8: M | H8: Matriz | I8: 30 | J8: 817.76 | K8: =IFERROR(VLOOKUP(C8,Tabla15[[CEDULA]:[BONO VEHICULAR]],8,0),0) -> 0 | L8: 17.78 | M8: =+VLOOKUP(C8,Tabla335[[CEDULA ]:[US$,,]],9,0) -> 0 | P8: =+VLOOKUP(C8,'COMISIONES-SOCIOS'!$C$8:$L$57,10,0) -> 0 | Q8: =+VLOOKUP(C8,Tabla3[[CEDULA ]:[US$,]],8,0) -> 0 | R8: =+VLOOKUP($C8,Tabla3[[CEDULA ]:[US$,]],9,0) -> 0 | S8: =SUM(K8:R8) -> 17.78 | T8: =+J8+S8 -> 835.54 | U8: =VLOOKUP(C8,FR!$C$6:$M$55,11,0) -> 69.600482 | Y8: =SUM(T8:X8) -> 905.14048 | Z8: =T8*9.45% -> 78.95853 | AB8: 0 | AC8: =IFERROR(+VLOOKUP(D8,PQ!$D$35:$E$45,2,0),0) -> 0 | AH8: 720.63 | AI8: =SUM(Z8:AH8) -> 799.58853 | AJ8: =+Y8-AI8 -> 105.55195 | AK8: 600101009364 | AN8: 1 | AO8: =+D8 -> ASITIMBAY CRIOLLO JOHN ANDERSON | AP8: =+E8 -> 44292 | AQ8: =+I8 -> 30 | AR8: =+H8 -> Matriz | AS8: =T8 -> 835.54 | AT8: =+AS8/12 -> 69.628333 | AU8: 0 | AW8: =($AW$7/360)*AQ8 -> 39.166667 | AX8: =+AS8/24 -> 34.814167 | AY8: =SUM(AS8:AX8) -> 979.14917 | AZ8: =+AS8*11.15% -> 93.16271 | BA8: =+AS8*1% -> 8.3554 | BB8: =SUM(AZ8:BA8) -> 101.51811
B9: =+B8+1 -> 2 | C9: 944405737 | D9: BARAHONA ZAMBRANO DAYANA NICOLE | E9: 45029 | F9: CAJERO FINANCIERO | G9: F | H9: Matriz | I9: 1 | J9: 15.86 | K9: =IFERROR(VLOOKUP(C9,Tabla15[[CEDULA]:[BONO VEHICULAR]],8,0),0) -> 0 | L9: 35.02 | M9: =+VLOOKUP(C9,Tabla335[[CEDULA ]:[US$,,]],9,0) -> 0 | P9: =+VLOOKUP(C9,'COMISIONES-SOCIOS'!$C$8:$L$57,10,0) -> 0 | Q9: =+VLOOKUP(C9,Tabla3[[CEDULA ]:[US$,]],8,0) -> 0 | R9: =+VLOOKUP($C9,Tabla3[[CEDULA ]:[US$,]],9,0) -> 0 | S9: =SUM(K9:R9) -> 35.02 | T9: =+J9+S9 -> 50.88 | U9: =VLOOKUP(C9,FR!$C$6:$M$55,11,0) -> ACUMULA | Y9: =SUM(T9:X9) -> 50.88 | Z9: =T9*9.45% -> 4.80816 | AC9: =IFERROR(+VLOOKUP(D9,PQ!$D$35:$E$45,2,0),0) -> 0 | AH9: 0 | AI9: =SUM(Z9:AH9) -> 4.80816 | AJ9: =+Y9-AI9 -> 46.07184 | AK9: 600301314479 | AN9: =+AN8+1 -> 2 | AO9: =+D9 -> BARAHONA ZAMBRANO DAYANA NICOLE | AP9: =+E9 -> 45029 | AQ9: =+I9 -> 1 | AR9: =+H9 -> Matriz | AS9: =T9 -> 50.88 | AT9: =+AS9/12 -> 4.24 | AU9: =+AS9*AU7 -> 4.238304 | AW9: =($AW$7/360)*AQ9 -> 1.3055556 | AX9: =+AS9/24 -> 2.12 | AY9: =SUM(AS9:AX9) -> 62.78386 | AZ9: =+AS9*11.15% -> 5.67312 | BA9: =+AS9*1% -> 0.5088 | BB9: =SUM(AZ9:BA9) -> 6.18192
B10: =+B9+1 -> 3 | C10: 604394502 | D10: BETUN CHAFLA JULIO CESAR | E10: 44735 | F10: ASESOR DE NEGOCIOS | G10: M | H10: Matriz | I10: 30 | J10: 613.32 | K10: =IFERROR(VLOOKUP(C10,Tabla15[[CEDULA]:[BONO VEHICULAR]],8,0),0) -> 0 | L10: 13.33 | M10: =+VLOOKUP(C10,Tabla335[[CEDULA ]:[US$,,]],9,0) -> 0 | P10: =+VLOOKUP(C10,'COMISIONES-SOCIOS'!$C$8:$L$57,10,0) -> 0 | Q10: =+VLOOKUP(C10,Tabla3[[CEDULA ]:[US$,]],8,0) -> 0 | R10: =+VLOOKUP($C10,Tabla3[[CEDULA ]:[US$,]],9,0) -> 0 | S10: =SUM(K10:R10) -> 13.33 | T10: =+J10+S10 -> 626.65 | U10: =VLOOKUP(C10,FR!$C$6:$M$55,11,0) -> 52.199945 | Y10: =SUM(T10:X10) -> 678.84995 | Z10: =T10*9.45% -> 59.218425 | AC10: =IFERROR(+VLOOKUP(D10,PQ!$D$35:$E$45,2,0),0) -> 0 | AH10: 0 | AI10: =SUM(Z10:AH10) -> 59.218425 | AJ10: =+Y10-AI10 -> 619.63152 | AK10: 600101311713 | AN10: =+AN9+1 -> 3 | AO10: =+D10 -> BETUN CHAFLA JULIO CESAR | AP10: =+E10 -> 44735 | AQ10: =+I10 -> 30 | AR10: =+H10 -> Matriz | AS10: =T10 -> 626.65 | AT10: =+AS10/12 -> 52.220833 | AU10: 0 | AW10: =($AW$7/360)*AQ10 -> 39.166667 | AX10: =+AS10/24 -> 26.110417 | AY10: =SUM(AS10:AX10) -> 744.14792 | AZ10: =+AS10*11.15% -> 69.871475 | BA10: =+AS10*1% -> 6.2665 | BB10: =SUM(AZ10:BA10) -> 76.137975
B11: =+B10+1 -> 4 | C11: 955741970 | D11: CHACAGUASAY CHACAGUASAY ROBERTH CRISTHIAN | E11: 44986 | F11: OFICIAL DE RECAUDACIONES | G11: M | H11: Matriz | I11: 30 | J11: 473.88 | K11: =IFERROR(VLOOKUP(C11,Tabla15[[CEDULA]:[BONO VEHICULAR]],8,0),0) -> 100 | L11: 10.03 | M11: =+VLOOKUP(C11,Tabla335[[CEDULA ]:[US$,,]],9,0) -> 0 | P11: =+VLOOKUP(C11,'COMISIONES-SOCIOS'!$C$8:$L$57,10,0) -> 0 | Q11: =+VLOOKUP(C11,Tabla3[[CEDULA ]:[US$,]],8,0) -> 0 | R11: =+VLOOKUP($C11,Tabla3[[CEDULA ]:[US$,]],9,0) -> 0 | S11: =SUM(K11:R11) -> 110.03 | T11: =+J11+S11 -> 583.91 | U11: =VLOOKUP(C11,FR!$C$6:$M$55,11,0) -> 48.639703 | Y11: =SUM(T11:X11) -> 632.5497 | Z11: =T11*9.45% -> 55.179495 | AC11: =IFERROR(+VLOOKUP(D11,PQ!$D$35:$E$45,2,0),0) -> 0 | AH11: 400 | AI11: =SUM(Z11:AH11) -> 455.17949 | AJ11: =+Y11-AI11 -> 177.37021 | AK11: 600101313870 | AN11: =+AN10+1 -> 4 | AO11: =+D11 -> CHACAGUASAY CHACAGUASAY ROBERTH CRISTHIAN | AP11: =+E11 -> 44986 | AQ11: =+I11 -> 30 | AR11: =+H11 -> Matriz | AS11: =T11 -> 583.91 | AT11: =+AS11/12 -> 48.659167 | AU11: 0 | AW11: =($AW$7/360)*AQ11 -> 39.166667 | AX11: =+AS11/24 -> 24.329583 | AY11: =SUM(AS11:AX11) -> 696.06542 | AZ11: =+AS11*11.15% -> 65.105965 | BA11: =+AS11*1% -> 5.8391 | BB11: =SUM(AZ11:BA11) -> 70.945065
B12: =+B11+1 -> 5 | C12: 0943964973 | D12: CHACAGUASAY GUAMAN KEVIN NEHEMIAS | E12: 45945 | F12: ASESOR DE NEGOCIOS | G12: M | H12: Matriz | I12: 16 | J12: 256.53 | M12: =+VLOOKUP(C12,Tabla335[[CEDULA ]:[US$,,]],9,0) -> 368.77 | P12: =+VLOOKUP(C12,'COMISIONES-SOCIOS'!$C$8:$L$57,10,0) -> 0 | Q12: =+VLOOKUP(C12,Tabla3[[CEDULA ]:[US$,]],8,0) -> 0 | R12: =+VLOOKUP($C12,Tabla3[[CEDULA ]:[US$,]],9,0) -> 0 | S12: =SUM(K12:R12) -> 368.77 | T12: =+J12+S12 -> 625.3 | Y12: =SUM(T12:X12) -> 625.3 | Z12: =T12*9.45% -> 59.09085 | AN12: =+AN11+1 -> 5 | AO12: =+D12 -> CHACAGUASAY GUAMAN KEVIN NEHEMIAS | AP12: =+E12 -> 45945 | AQ12: =+I12 -> 16 | AW12: =($AW$7/360)*AQ12 -> 20.888889
B13: =+B12+1 -> 6 | C13: 944143148 | D13: CHIMBOLEMA YUNGAN MARIO EFRAIN | E13: 45884 | F13: OFICIAL DE RECAUDACIONES | G13: M | H13: Durán | I13: 9 | J13: 142.16 | K13: =IFERROR(VLOOKUP(C13,Tabla15[[CEDULA]:[BONO VEHICULAR]],8,0),0) -> 30 | L13: 0 | M13: =+VLOOKUP(C13,Tabla335[[CEDULA ]:[US$,,]],9,0) -> 0 | P13: =+VLOOKUP(C13,'COMISIONES-SOCIOS'!$C$8:$L$57,10,0) -> 0 | Q13: =+VLOOKUP(C13,Tabla3[[CEDULA ]:[US$,]],8,0) -> 0 | R13: =+VLOOKUP($C13,Tabla3[[CEDULA ]:[US$,]],9,0) -> 0 | S13: =SUM(K13:R13) -> 30 | T13: =+J13+S13 -> 172.16 | U13: =VLOOKUP(C13,FR!$C$6:$M$55,11,0) -> 0 | Y13: =SUM(T13:X13) -> 172.16 | Z13: =T13*9.45% -> 16.26912 | AH13: 0 | AI13: =SUM(Z13:AH13) -> 16.26912 | AJ13: =+Y13-AI13 -> 155.89088 | AK13: 600301320262 | AN13: =+AN12+1 -> 6 | AO13: =+D13 -> CHIMBOLEMA YUNGAN MARIO EFRAIN | AP13: =+E13 -> 45884 | AQ13: =+I13 -> 9 | AR13: =+H13 -> Durán | AS13: =T13 -> 172.16 | AT13: =+AS13/12 -> 14.346667 | AU13: 0 | AW13: =($AW$7/360)*AQ13 -> 11.75 | AX13: =+AS13/24 -> 7.1733333 | AY13: =SUM(AS13:AX13) -> 205.43 | AZ13: =+AS13*11.15% -> 19.19584 | BA13: =+AS13*1% -> 1.7216 | BB13: =SUM(AZ13:BA13) -> 20.91744
B14: =+B13+1 -> 7 | C14: 955325238 | D14: CHOCA CEPEDA INES VIVIANA | E14: 45945 | F14: CAJERA FINANCIERA | G14: F | H14: Matriz | I14: 16 | J14: 256.53 | M14: =+VLOOKUP(C14,Tabla335[[CEDULA ]:[US$,,]],9,0) -> 0 | P14: =+VLOOKUP(C14,'COMISIONES-SOCIOS'!$C$8:$L$57,10,0) -> 0 | Q14: =+VLOOKUP(C14,Tabla3[[CEDULA ]:[US$,]],8,0) -> 0 | R14: =+VLOOKUP($C14,Tabla3[[CEDULA ]:[US$,]],9,0) -> 0 | S14: =SUM(K14:R14) -> 0 | T14: =+J14+S14 -> 256.53 | Y14: =SUM(T14:X14) -> 256.53 | Z14: =T14*9.45% -> 24.242085 | AH14: 0 | AN14: =+AN13+1 -> 7 | AO14: =+D14 -> CHOCA CEPEDA INES VIVIANA | AP14: =+E14 -> 45945 | AQ14: =+I14 -> 16 | AW14: =($AW$7/360)*AQ14 -> 20.888889
B15: =+B14+1 -> 8 | C15: 914163654 | D15: COCA BENITEZ JORGE MANUEL | E15: 44470 | F15: ANALISTA DE RIESGO | G15: M | H15: Matriz | I15: 15 | J15: 1200 | K15: =IFERROR(VLOOKUP(C15,Tabla15[[CEDULA]:[BONO VEHICULAR]],8,0),0) -> 0 | L15: 0 | M15: =+VLOOKUP(C15,Tabla335[[CEDULA ]:[US$,,]],9,0) -> 0 | P15: =+VLOOKUP(C15,'COMISIONES-SOCIOS'!$C$8:$L$57,10,0) -> 0 | Q15: =+VLOOKUP(C15,Tabla3[[CEDULA ]:[US$,]],8,0) -> 0 | R15: =+VLOOKUP($C15,Tabla3[[CEDULA ]:[US$,]],9,0) -> 0 | S15: =SUM(K15:R15) -> 0 | T15: =+J15+S15 -> 1200 | U15: =VLOOKUP(C15,FR!$C$6:$M$55,11,0) -> 99.96 | Y15: =SUM(T15:X15) -> 1299.96 | Z15: =T15*9.45% -> 113.4 | AB15: 0 | AC15: =IFERROR(+VLOOKUP(D15,PQ!$D$35:$E$45,2,0),0) -> 0 | AD15: 624.02405 | AH15: 0 | AI15: =SUM(Z15:AH15) -> 737.42405 | AJ15: =+Y15-AI15 -> 562.53595 | AK15: 600101010004 | AN15: =+AN14+1 -> 8 | AO15: =+D15 -> COCA BENITEZ JORGE MANUEL | AP15: =+E15 -> 44470 | AQ15: =+I15 -> 15 | AR15: =+H15 -> Matriz | AS15: =T15 -> 1200 | AT15: =+AS15/12 -> 100 | AU15: 0 | AW15: =($AW$7/360)*AQ15 -> 19.583333 | AX15: =+AS15/24 -> 50 | AY15: =SUM(AS15:AX15) -> 1369.5833 | AZ15: =+AS15*11.15% -> 133.8 | BA15: =+AS15*1% -> 12 | BB15: =SUM(AZ15:BA15) -> 145.8
B16: =+B15+1 -> 9 | C16: 956668305 | D16: CORO YUQUILEMA RUTH NOEMI | E16: 45945 | F16: OFICIAL DE RECAUDACIONES | G16: F | H16: Matriz | I16: 16 | J16: 252.74 | M16: =+VLOOKUP(C16,Tabla335[[CEDULA ]:[US$,,]],9,0) -> 0 | P16: =+VLOOKUP(C16,'COMISIONES-SOCIOS'!$C$8:$L$57,10,0) -> 0 | Q16: =+VLOOKUP(C16,Tabla3[[CEDULA ]:[US$,]],8,0) -> 0 | R16: =+VLOOKUP($C16,Tabla3[[CEDULA ]:[US$,]],9,0) -> 0 | S16: =SUM(K16:R16) -> 0 | T16: =+J16+S16 -> 252.74 | Y16: =SUM(T16:X16) -> 252.74 | Z16: =T16*9.45% -> 23.88393 | AH16: 0 | AN16: =+AN15+1 -> 9 | AO16: =+D16 -> CORO YUQUILEMA RUTH NOEMI | AP16: =+E16 -> 45945 | AQ16: =+I16 -> 16 | AW16: =($AW$7/360)*AQ16 -> 20.888889
B17: =+B16+1 -> 10 | C17: 0918741448 | D17: DEFAS CHICAIZA JOEL ALBERTO | E17: 45823 | F17: ASESOR DE NEGOCIOS | G17: M | H17: Norte | I17: 30 | J17: 626.65 | K17: =IFERROR(VLOOKUP(C17,Tabla15[[CEDULA]:[BONO VEHICULAR]],8,0),0) -> 0 | L17: 0 | M17: =+VLOOKUP(C17,Tabla335[[CEDULA ]:[US$,,]],9,0) -> 0 | P17: =+VLOOKUP(C17,'COMISIONES-SOCIOS'!$C$8:$L$57,10,0) -> 0 | Q17: =+VLOOKUP(C17,Tabla3[[CEDULA ]:[US$,]],8,0) -> 0 | R17: =+VLOOKUP($C17,Tabla3[[CEDULA ]:[US$,]],9,0) -> 0 | S17: =SUM(K17:R17) -> 0 | T17: =+J17+S17 -> 626.65 | U17: =VLOOKUP(C17,FR!$C$6:$M$55,11,0) -> 0 | Y17: =SUM(T17:X17) -> 626.65 | Z17: =T17*9.45% -> 59.218425 | AC17: =IFERROR(+VLOOKUP(D17,PQ!$D$35:$E$45,2,0),0) -> 261.63 | AH17: 150 | AI17: =SUM(Z17:AH17) -> 470.84842 | AJ17: =+Y17-AI17 -> 155.80158 | AK17: 600201320019 | AN17: =+AN16+1 -> 10 | AO17: =+D17 -> DEFAS CHICAIZA JOEL ALBERTO | AP17: =+E17 -> 45823 | AQ17: =+I17 -> 30 | AR17: =+H17 -> Norte | AS17: =T17 -> 626.65 | AT17: =+AS17/12 -> 52.220833 | AU17: 0 | AW17: =($AW$7/360)*AQ17 -> 39.166667 | AX17: =+AS17/24 -> 26.110417 | AY17: =SUM(AS17:AX17) -> 744.14792 | AZ17: =+AS17*11.15% -> 69.871475 | BA17: =+AS17*1% -> 6.2665 | BB17: =SUM(AZ17:BA17) -> 76.137975
B18: =+B17+1 -> 11 | C18: 931097620 | D18: DEL ROSARIO RODRIGUEZ JUDY ANGELICA | E18: 45945 | F18: CAJERA FINANCIERA | G18: F | H18: Norte | I18: 16 | J18: 256.53 | M18: =+VLOOKUP(C18,Tabla335[[CEDULA ]:[US$,,]],9,0) -> 368.77 | P18: =+VLOOKUP(C18,'COMISIONES-SOCIOS'!$C$8:$L$57,10,0) -> 0 | Q18: =+VLOOKUP(C18,Tabla3[[CEDULA ]:[US$,]],8,0) -> 0 | R18: =+VLOOKUP($C18,Tabla3[[CEDULA ]:[US$,]],9,0) -> 0 | S18: =SUM(K18:R18) -> 368.77 | T18: =+J18+S18 -> 625.3 | Y18: =SUM(T18:X18) -> 625.3 | Z18: =T18*9.45% -> 59.09085 | AH18: 144.3 | AN18: =+AN17+1 -> 11 | AO18: =+D18 -> DEL ROSARIO RODRIGUEZ JUDY ANGELICA | AP18: =+E18 -> 45945 | AQ18: =+I18 -> 16 | AW18: =($AW$7/360)*AQ18 -> 20.888889
B19: =+B18+1 -> 12 | C19: 1105483422 | D19: FLORES HERRERA WENDY DEL CISNE | E19: 45065 | F19: CAJERO FINANCIERO | G19: F | H19: Durán | I19: 30 | J19: 650 | K19: =IFERROR(VLOOKUP(C19,Tabla15[[CEDULA]:[BONO VEHICULAR]],8,0),0) -> 0 | L19: 14.13 | M19: =+VLOOKUP(C19,Tabla335[[CEDULA ]:[US$,,]],9,0) -> 0 | P19: =+VLOOKUP(C19,'COMISIONES-SOCIOS'!$C$8:$L$57,10,0) -> 0 | Q19: =+VLOOKUP(C19,Tabla3[[CEDULA ]:[US$,]],8,0) -> 0 | R19: =+VLOOKUP($C19,Tabla3[[CEDULA ]:[US$,]],9,0) -> 0 | S19: =SUM(K19:R19) -> 14.13 | T19: =+J19+S19 -> 664.13 | U19: =VLOOKUP(C19,FR!$C$6:$M$55,11,0) -> 52.199945 | Y19: =SUM(T19:X19) -> 716.32994 | Z19: =T19*9.45% -> 62.760285 | AC19: =IFERROR(+VLOOKUP(D19,PQ!$D$35:$E$45,2,0),0) -> 0 | AH19: 0 | AI19: =SUM(Z19:AH19) -> 62.760285 | AJ19: =+Y19-AI19 -> 653.56966 | AK19: 600301314628 | AN19: =+AN18+1 -> 12 | AO19: =+D19 -> FLORES HERRERA WENDY DEL CISNE | AP19: =+E19 -> 45065 | AQ19: =+I19 -> 30 | AR19: =+H19 -> Durán | AS19: =T19 -> 664.13 | AT19: =+AS19/12 -> 55.344167 | AU19: 0 | AW19: =($AW$7/360)*AQ19 -> 39.166667 | AX19: =+AS19/24 -> 27.672083 | AY19: =SUM(AS19:AX19) -> 786.31292 | AZ19: =+AS19*11.15% -> 74.050495 | BA19: =+AS19*1% -> 6.6413 | BB19: =SUM(AZ19:BA19) -> 80.691795
B20: =+B19+1 -> 13 | C20: 942614645 | D20: FUELA TOABANDA JOSUE CHRISTIAN | E20: 45474 | F20: ASISTENTE CONTABLE | G20: M | H20: Matriz | I20: 30 | J20: 481 | K20: =IFERROR(VLOOKUP(C20,Tabla15[[CEDULA]:[BONO VEHICULAR]],8,0),0) -> 0 | L20: 219 | M20: =+VLOOKUP(C20,Tabla335[[CEDULA ]:[US$,,]],9,0) -> 0 | P20: =+VLOOKUP(C20,'COMISIONES-SOCIOS'!$C$8:$L$57,10,0) -> 0 | Q20: =+VLOOKUP(C20,Tabla3[[CEDULA ]:[US$,]],8,0) -> 0 | R20: =+VLOOKUP($C20,Tabla3[[CEDULA ]:[US$,]],9,0) -> 0 | S20: =SUM(K20:R20) -> 219 | T20: =+J20+S20 -> 700 | U20: =VLOOKUP(C20,FR!$C$6:$M$55,11,0) -> 58.31 | Y20: =SUM(T20:X20) -> 758.31 | Z20: =T20*9.45% -> 66.15 | AC20: =IFERROR(+VLOOKUP(D20,PQ!$D$35:$E$45,2,0),0) -> 0 | AG20: 0 | AH20: 350 | AI20: =SUM(Z20:AH20) -> 416.15 | AJ20: =+Y20-AI20 -> 342.16 | AK20: 600101317776 | AN20: =+AN19+1 -> 13 | AO20: =+D20 -> FUELA TOABANDA JOSUE CHRISTIAN | AP20: =+E20 -> 45474 | AQ20: =+I20 -> 30 | AR20: =+H20 -> Matriz | AS20: =T20 -> 700 | AT20: =+AS20/12 -> 58.333333 | AU20: 0 | AW20: =($AW$7/360)*AQ20 -> 39.166667 | AX20: =+AS20/24 -> 29.166667 | AY20: =SUM(AS20:AX20) -> 826.66667 | AZ20: =+AS20*11.15% -> 78.05 | BA20: =+AS20*1% -> 7 | BB20: =SUM(AZ20:BA20) -> 85.05
B21: =+B20+1 -> 14 | C21: 951200062 | D21: GALAN LEMACHE INGRID GISELA | E21: 45139 | F21: BACK UP ADMINISTRATIVO FINANCIERO | G21: F | H21: Norte | I21: 30 | J21: 473.88 | K21: =IFERROR(VLOOKUP(C21,Tabla15[[CEDULA]:[BONO VEHICULAR]],8,0),0) -> 0 | L21: 190.25 | M21: =+VLOOKUP(C21,Tabla335[[CEDULA ]:[US$,,]],9,0) -> 0 | P21: =+VLOOKUP(C21,'COMISIONES-SOCIOS'!$C$8:$L$57,10,0) -> 0 | Q21: =+VLOOKUP(C21,Tabla3[[CEDULA ]:[US$,]],8,0) -> 0 | R21: =+VLOOKUP($C21,Tabla3[[CEDULA ]:[US$,]],9,0) -> 0 | S21: =SUM(K21:R21) -> 190.25 | T21: =+J21+S21 -> 664.13 | U21: =VLOOKUP(C21,FR!$C$6:$M$55,11,0) -> 55.322029 | Y21: =SUM(T21:X21) -> 719.45203 | Z21: =T21*9.45% -> 62.760285 | AC21: =IFERROR(+VLOOKUP(D21,PQ!$D$35:$E$45,2,0),0) -> 0 | AG21: 0 | AH21: 300 | AI21: =SUM(Z21:AH21) -> 362.76029 | AJ21: =+Y21-AI21 -> 356.69174 | AK21: 600301315318 | AN21: =+AN20+1 -> 14 | AO21: =+D21 -> GALAN LEMACHE INGRID GISELA | AP21: =+E21 -> 45139 | AQ21: =+I21 -> 30 | AR21: =+H21 -> Norte | AS21: =T21 -> 664.13 | AT21: =+AS21/12 -> 55.344167 | AU21: 0 | AW21: =($AW$7/360)*AQ21 -> 39.166667 | AX21: =+AS21/24 -> 27.672083 | AY21: =SUM(AS21:AX21) -> 786.31292 | AZ21: =+AS21*11.15% -> 74.050495 | BA21: =+AS21*1% -> 6.6413 | BB21: =SUM(AZ21:BA21) -> 80.691795
B22: =+B21+1 -> 15 | C22: 950929232 | D22: GARCIA VERA HENRY LUIS | E22: 44726 | F22: OFICIAL DE RECAUDACIONES | G22: M | H22: Norte | I22: 30 | J22: 715.54 | K22: =IFERROR(VLOOKUP(C22,Tabla15[[CEDULA]:[BONO VEHICULAR]],8,0),0) -> 0 | L22: 0 | M22: =+VLOOKUP(C22,Tabla335[[CEDULA ]:[US$,,]],9,0) -> 0 | P22: =+VLOOKUP(C22,'COMISIONES-SOCIOS'!$C$8:$L$57,10,0) -> 0 | Q22: =+VLOOKUP(C22,Tabla3[[CEDULA ]:[US$,]],8,0) -> 0 | R22: =+VLOOKUP($C22,Tabla3[[CEDULA ]:[US$,]],9,0) -> 0 | S22: =SUM(K22:R22) -> 0 | T22: =+J22+S22 -> 715.54 | U22: =VLOOKUP(C22,FR!$C$6:$M$55,11,0) -> ACUMULA | Y22: =SUM(T22:X22) -> 715.54 | Z22: =T22*9.45% -> 67.61853 | AB22: 0 | AC22: =IFERROR(+VLOOKUP(D22,PQ!$D$35:$E$45,2,0),0) -> 87.66 | AE22: =+T22*3.41% -> 24.399914 | AH22: 300 | AI22: =SUM(Z22:AH22) -> 479.67844 | AJ22: =+Y22-AI22 -> 235.86156 | AK22: 600201311725 | AN22: =+AN21+1 -> 15 | AO22: =+D22 -> GARCIA VERA HENRY LUIS | AP22: =+E22 -> 44726 | AQ22: =+I22 -> 30 | AR22: =+H22 -> Norte | AS22: =T22 -> 715.54 | AT22: =+AS22/12 -> 59.628333 | AU22: =+AS22*$AU$7 -> 59.604482 | AW22: =($AW$7/360)*AQ22 -> 39.166667 | AX22: =+AS22/24 -> 29.814167 | AY22: =SUM(AS22:AX22) -> 903.75365 | AZ22: =+AS22*11.15% -> 79.78271 | BA22: =+AS22*1% -> 7.1554 | BB22: =SUM(AZ22:BA22) -> 86.93811
B23: =+B22+1 -> 16 | C23: 953819646 | D23: GUALACEO ÑAMO JONATHAN IVÁN | E23: 44637 | F23: OFICIAL DE RECAUDACIONES | G23: M | H23: Matriz | I23: 30 | J23: 511.1 | K23: =IFERROR(VLOOKUP(C23,Tabla15[[CEDULA]:[BONO VEHICULAR]],8,0),0) -> 100 | L23: 11.11 | M23: =+VLOOKUP(C23,Tabla335[[CEDULA ]:[US$,,]],9,0) -> 0 | P23: =+VLOOKUP(C23,'COMISIONES-SOCIOS'!$C$8:$L$57,10,0) -> 0 | Q23: =+VLOOKUP(C23,Tabla3[[CEDULA ]:[US$,]],8,0) -> 0 | R23: =+VLOOKUP($C23,Tabla3[[CEDULA ]:[US$,]],9,0) -> 0 | S23: =SUM(K23:R23) -> 111.11 | T23: =+J23+S23 -> 622.21 | U23: =VLOOKUP(C23,FR!$C$6:$M$55,11,0) -> 51.830093 | Y23: =SUM(T23:X23) -> 674.04009 | Z23: =T23*9.45% -> 58.798845 | AB23: 0 | AC23: =IFERROR(+VLOOKUP(D23,PQ!$D$35:$E$45,2,0),0) -> 0 | AH23: 0 | AI23: =SUM(Z23:AH23) -> 58.798845 | AJ23: =+Y23-AI23 -> 615.24125 | AK23: 600101311237 | AN23: =+AN22+1 -> 16 | AO23: =+D23 -> GUALACEO ÑAMO JONATHAN IVÁN | AP23: =+E23 -> 44637 | AQ23: =+I23 -> 30 | AR23: =+H23 -> Matriz | AS23: =T23 -> 622.21 | AT23: =+AS23/12 -> 51.850833 | AU23: 0 | AW23: =($AW$7/360)*AQ23 -> 39.166667 | AX23: =+AS23/24 -> 25.925417 | AY23: =SUM(AS23:AX23) -> 739.15292 | AZ23: =+AS23*11.15% -> 69.376415 | BA23: =+AS23*1% -> 6.2221 | BB23: =SUM(AZ23:BA23) -> 75.598515
B24: =+B23+1 -> 17 | C24: 956953392 | D24: GUAPI YUMAGLLA OSCAR EDUARDO | E24: 45357 | F24: OFICIAL DE RECAUDACIONES | G24: M | H24: Matriz | I24: 30 | J24: 473.88 | K24: =IFERROR(VLOOKUP(C24,Tabla15[[CEDULA]:[BONO VEHICULAR]],8,0),0) -> 0 | L24: =550-J24 -> 76.12 | M24: =+VLOOKUP(C24,Tabla335[[CEDULA ]:[US$,,]],9,0) -> 0 | P24: =+VLOOKUP(C24,'COMISIONES-SOCIOS'!$C$8:$L$57,10,0) -> 0 | Q24: =+VLOOKUP(C24,Tabla3[[CEDULA ]:[US$,]],8,0) -> 0 | R24: =+VLOOKUP($C24,Tabla3[[CEDULA ]:[US$,]],9,0) -> 0 | S24: =SUM(K24:R24) -> 76.12 | T24: =+J24+S24 -> 550 | U24: =VLOOKUP(C24,FR!$C$6:$M$55,11,0) -> 45.815 | Y24: =SUM(T24:X24) -> 595.815 | Z24: =T24*9.45% -> 51.975 | AC24: =IFERROR(+VLOOKUP(D24,PQ!$D$35:$E$45,2,0),0) -> 0 | AH24: 150 | AI24: =SUM(Z24:AH24) -> 201.975 | AJ24: =+Y24-AI24 -> 393.84 | AK24: 600101005932 | AN24: =+AN23+1 -> 17 | AO24: =+D24 -> GUAPI YUMAGLLA OSCAR EDUARDO | AP24: =+E24 -> 45357 | AQ24: =+I24 -> 30 | AR24: =+H24 -> Matriz | AS24: =T24 -> 550 | AT24: =+AS24/12 -> 45.833333 | AU24: 0 | AW24: =($AW$7/360)*AQ24 -> 39.166667 | AX24: =+AS24/24 -> 22.916667 | AY24: =SUM(AS24:AX24) -> 657.91667 | AZ24: =+AS24*11.15% -> 61.325 | BA24: =+AS24*1% -> 5.5 | BB24: =SUM(AZ24:BA24) -> 66.825
B25: =+B24+1 -> 18 | C25: 956796767 | D25: GUAYANLEMA RUIZ EDINSON DAVID | E25: 44763 | F25: OFICIAL DE RECAUDACIONES | G25: M | H25: Norte | I25: 30 | J25: 473.88 | K25: =IFERROR(VLOOKUP(C25,Tabla15[[CEDULA]:[BONO VEHICULAR]],8,0),0) -> 100 | L25: 10.3 | M25: =+VLOOKUP(C25,Tabla335[[CEDULA ]:[US$,,]],9,0) -> 0 | P25: =+VLOOKUP(C25,'COMISIONES-SOCIOS'!$C$8:$L$57,10,0) -> 0 | Q25: =+VLOOKUP(C25,Tabla3[[CEDULA ]:[US$,]],8,0) -> 0 | R25: =+VLOOKUP($C25,Tabla3[[CEDULA ]:[US$,]],9,0) -> 0 | S25: =SUM(K25:R25) -> 110.3 | T25: =+J25+S25 -> 584.18 | U25: =VLOOKUP(C25,FR!$C$6:$M$55,11,0) -> 48.662194 | Y25: =SUM(T25:X25) -> 632.84219 | Z25: =T25*9.45% -> 55.20501 | AC25: =IFERROR(+VLOOKUP(D25,PQ!$D$35:$E$45,2,0),0) -> 20.96 | AH25: 390 | AI25: =SUM(Z25:AH25) -> 466.16501 | AJ25: =+Y25-AI25 -> 166.67718 | AK25: 600201312138 | AN25: =+AN24+1 -> 18 | AO25: =+D25 -> GUAYANLEMA RUIZ EDINSON DAVID | AP25: =+E25 -> 44763 | AQ25: =+I25 -> 30 | AR25: =+H25 -> Norte | AS25: =T25 -> 584.18 | AT25: =+AS25/12 -> 48.681667 | AU25: 0 | AW25: =($AW$7/360)*AQ25 -> 39.166667 | AX25: =+AS25/24 -> 24.340833 | AY25: =SUM(AS25:AX25) -> 696.36917 | AZ25: =+AS25*11.15% -> 65.13607 | BA25: =+AS25*1% -> 5.8418 | BB25: =SUM(AZ25:BA25) -> 70.97787
B26: =+B25+1 -> 19 | C26: 0932036049 | D26: HERRERA JIMENEZ CAROLINA ADELIHER | E26: 45839 | F26: ASISTENTE DE OPERACIONES | G26: F | H26: Matriz | I26: 30 | J26: 481 | K26: =IFERROR(VLOOKUP(C26,Tabla15[[CEDULA]:[BONO VEHICULAR]],8,0),0) -> 0 | L26: 0 | M26: =+VLOOKUP(C26,Tabla335[[CEDULA ]:[US$,,]],9,0) -> 0 | P26: =+VLOOKUP(C26,'COMISIONES-SOCIOS'!$C$8:$L$57,10,0) -> 0 | Q26: =+VLOOKUP(C26,Tabla3[[CEDULA ]:[US$,]],8,0) -> 0 | R26: =+VLOOKUP($C26,Tabla3[[CEDULA ]:[US$,]],9,0) -> 0 | S26: =SUM(K26:R26) -> 0 | T26: =+J26+S26 -> 481 | U26: =VLOOKUP(C26,FR!$C$6:$M$55,11,0) -> 0 | Y26: =SUM(T26:X26) -> 481 | Z26: =T26*9.45% -> 45.4545 | AC26: =IFERROR(+VLOOKUP(D26,PQ!$D$35:$E$45,2,0),0) -> 0 | AH26: 0 | AI26: =SUM(Z26:AH26) -> 45.4545 | AJ26: =+Y26-AI26 -> 435.5455 | AK26: 600101320088 | AN26: =+AN25+1 -> 19 | AO26: =+D26 -> HERRERA JIMENEZ CAROLINA ADELIHER | AP26: =+E26 -> 45839 | AQ26: =+I26 -> 30 | AR26: =+H26 -> Matriz | AS26: =T26 -> 481 | AT26: =+AS26/12 -> 40.083333 | AU26: 0 | AW26: =($AW$7/360)*AQ26 -> 39.166667 | AX26: =+AS26/24 -> 20.041667 | AY26: =SUM(AS26:AX26) -> 580.29167 | AZ26: =+AS26*11.15% -> 53.6315 | BA26: =+AS26*1% -> 4.81 | BB26: =SUM(AZ26:BA26) -> 58.4415
B27: =+B26+1 -> 20 | C27: 1724102940 | D27: HIDALGO CHERRES NESTOR VLADIMIR | E27: 45308 | F27: JEFE DE CREDITO | G27: M | H27: Durán | I27: 30 | J27: 817.76 | K27: =IFERROR(VLOOKUP(C27,Tabla15[[CEDULA]:[BONO VEHICULAR]],8,0),0) -> 0 | L27: 17.78 | M27: =+VLOOKUP(C27,Tabla335[[CEDULA ]:[US$,,]],9,0) -> 0 | P27: =+VLOOKUP(C27,'COMISIONES-SOCIOS'!$C$8:$L$57,10,0) -> 0 | Q27: =+VLOOKUP(C27,Tabla3[[CEDULA ]:[US$,]],8,0) -> 0 | R27: =+VLOOKUP($C27,Tabla3[[CEDULA ]:[US$,]],9,0) -> 0 | S27: =SUM(K27:R27) -> 17.78 | T27: =+J27+S27 -> 835.54 | U27: =VLOOKUP(C27,FR!$C$6:$M$55,11,0) -> 69.600482 | Y27: =SUM(T27:X27) -> 905.14048 | Z27: =T27*9.45% -> 78.95853 | AC27: =IFERROR(+VLOOKUP(D27,PQ!$D$35:$E$45,2,0),0) -> 0 | AH27: 500 | AI27: =SUM(Z27:AH27) -> 578.95853 | AJ27: =+Y27-AI27 -> 326.18195 | AK27: 600101010744 | AN27: =+AN26+1 -> 20 | AO27: =+D27 -> HIDALGO CHERRES NESTOR VLADIMIR | AP27: =+E27 -> 45308 | AQ27: =+I27 -> 30 | AR27: =+H27 -> Durán | AS27: =T27 -> 835.54 | AT27: =+AS27/12 -> 69.628333 | AU27: 0 | AW27: =($AW$7/360)*AQ27 -> 39.166667 | AX27: =+AS27/24 -> 34.814167 | AY27: =SUM(AS27:AX27) -> 979.14917 | AZ27: =+AS27*11.15% -> 93.16271 | BA27: =+AS27*1% -> 8.3554 | BB27: =SUM(AZ27:BA27) -> 101.51811
B28: =+B27+1 -> 21 | C28: 943322974 | D28: JANETA RUIZ ALEXANDRA DEL ROCIO | E28: 45114 | F28: OFICIAL DE RECAUDACIONES | G28: F | H28: Norte | I28: 30 | J28: 473.88 | K28: =IFERROR(VLOOKUP(C28,Tabla15[[CEDULA]:[BONO VEHICULAR]],8,0),0) -> 0 | L28: 10.3 | M28: =+VLOOKUP(C28,Tabla335[[CEDULA ]:[US$,,]],9,0) -> 0 | P28: =+VLOOKUP(C28,'COMISIONES-SOCIOS'!$C$8:$L$57,10,0) -> 0 | Q28: =+VLOOKUP(C28,Tabla3[[CEDULA ]:[US$,]],8,0) -> 0 | R28: =+VLOOKUP($C28,Tabla3[[CEDULA ]:[US$,]],9,0) -> 0 | S28: =SUM(K28:R28) -> 10.3 | T28: =+J28+S28 -> 484.18 | U28: =VLOOKUP(C28,FR!$C$6:$M$55,11,0) -> 40.332194 | Y28: =SUM(T28:X28) -> 524.51219 | Z28: =T28*9.45% -> 45.75501 | AB28: 0 | AC28: =IFERROR(+VLOOKUP(D28,PQ!$D$35:$E$45,2,0),0) -> 0 | AH28: 100 | AI28: =SUM(Z28:AH28) -> 145.75501 | AJ28: =+Y28-AI28 -> 378.75718 | AK28: 600201315080 | AN28: =+AN27+1 -> 21 | AO28: =+D28 -> JANETA RUIZ ALEXANDRA DEL ROCIO | AP28: =+E28 -> 45114 | AQ28: =+I28 -> 30 | AR28: =+H28 -> Norte | AS28: =T28 -> 484.18 | AT28: =+AS28/12 -> 40.348333 | AU28: 0 | AW28: =($AW$7/360)*AQ28 -> 39.166667 | AX28: =+AS28/24 -> 20.174167 | AY28: =SUM(AS28:AX28) -> 583.86917 | AZ28: =+AS28*11.15% -> 53.98607 | BA28: =+AS28*1% -> 4.8418 | BB28: =SUM(AZ28:BA28) -> 58.82787
B29: =+B28+1 -> 22 | C29: 941096851 | D29: LEMA CHIRAU RAMONA MARIA | E29: 43033 | F29: ASESOR DE CAPTACIONES | G29: F | H29: Durán | I29: 30 | J29: 700 | K29: =IFERROR(VLOOKUP(C29,Tabla15[[CEDULA]:[BONO VEHICULAR]],8,0),0) -> 0 | L29: 0 | M29: =+VLOOKUP(C29,Tabla335[[CEDULA ]:[US$,,]],9,0) -> 0 | P29: =+VLOOKUP(C29,'COMISIONES-SOCIOS'!$C$8:$L$57,10,0) -> 0 | Q29: =+VLOOKUP(C29,Tabla3[[CEDULA ]:[US$,]],8,0) -> 0 | R29: =+VLOOKUP($C29,Tabla3[[CEDULA ]:[US$,]],9,0) -> 0 | S29: =SUM(K29:R29) -> 0 | T29: =+J29+S29 -> 700 | U29: =VLOOKUP(C29,FR!$C$6:$M$55,11,0) -> 58.31 | Y29: =SUM(T29:X29) -> 758.31 | Z29: =T29*9.45% -> 66.15 | AC29: =IFERROR(+VLOOKUP(D29,PQ!$D$35:$E$45,2,0),0) -> 0 | AH29: 480.64 | AI29: =SUM(Z29:AH29) -> 546.79 | AJ29: =+Y29-AI29 -> 211.52 | AK29: 600101005442 | AN29: =+AN28+1 -> 22 | AO29: =+D29 -> LEMA CHIRAU RAMONA MARIA | AP29: =+E29 -> 43033 | AQ29: =+I29 -> 30 | AR29: =+H29 -> Durán | AS29: =T29 -> 700 | AT29: =+AS29/12 -> 58.333333 | AU29: 0 | AW29: =($AW$7/360)*AQ29 -> 39.166667 | AX29: =+AS29/24 -> 29.166667 | AY29: =SUM(AS29:AX29) -> 826.66667 | AZ29: =+AS29*11.15% -> 78.05 | BA29: =+AS29*1% -> 7 | BB29: =SUM(AZ29:BA29) -> 85.05
B30: =+B29+1 -> 23 | C30: 957093800 | D30: LEMA TADAY BRAYAN WIDINSON | E30: 45793 | F30: OFICIAL DE RECAUDACIONES | G30: M | H30: Durán | I30: 30 | J30: 473.88 | K30: =IFERROR(VLOOKUP(C30,Tabla15[[CEDULA]:[BONO VEHICULAR]],8,0),0) -> 40 | M30: =+VLOOKUP(C30,Tabla335[[CEDULA ]:[US$,,]],9,0) -> 0 | P30: =+VLOOKUP(C30,'COMISIONES-SOCIOS'!$C$8:$L$57,10,0) -> 0 | Q30: =+VLOOKUP(C30,Tabla3[[CEDULA ]:[US$,]],8,0) -> 0 | R30: =+VLOOKUP($C30,Tabla3[[CEDULA ]:[US$,]],9,0) -> 0 | S30: =SUM(K30:R30) -> 40 | T30: =+J30+S30 -> 513.88 | U30: =VLOOKUP(C30,FR!$C$6:$M$55,11,0) -> 0 | Y30: =SUM(T30:X30) -> 513.88 | Z30: =T30*9.45% -> 48.56166 | AC30: =IFERROR(+VLOOKUP(D30,PQ!$D$35:$E$45,2,0),0) -> 0 | AD30: 288.8555 | AH30: 0 | AI30: =SUM(Z30:AH30) -> 337.41716 | AJ30: =+Y30-AI30 -> 176.46284 | AK30: 600301319714 | AN30: =+AN29+1 -> 23 | AO30: =+D30 -> LEMA TADAY BRAYAN WIDINSON | AP30: =+E30 -> 45793 | AQ30: =+I30 -> 30 | AR30: =+H30 -> Durán | AS30: =T30 -> 513.88 | AT30: =+AS30/12 -> 42.823333 | AU30: 0 | AW30: =($AW$7/360)*AQ30 -> 39.166667 | AX30: =+AS30/24 -> 21.411667 | AY30: =SUM(AS30:AX30) -> 617.28167 | AZ30: =+AS30*11.15% -> 57.29762 | BA30: =+AS30*1% -> 5.1388 | BB30: =SUM(AZ30:BA30) -> 62.43642
B31: =+B30+1 -> 24 | C31: 957924350 | D31: LLUMI YUQUILEMA MAYCOOL DANNY | E31: 45727 | F31: ASESOR DE NEGOCIOS | G31: M | H31: Matriz | I31: 30 | J31: 481 | K31: =IFERROR(VLOOKUP(C31,Tabla15[[CEDULA]:[BONO VEHICULAR]],8,0),0) -> 0 | M31: =+VLOOKUP(C31,Tabla335[[CEDULA ]:[US$,,]],9,0) -> 0 | P31: =+VLOOKUP(C31,'COMISIONES-SOCIOS'!$C$8:$L$57,10,0) -> 0 | Q31: =+VLOOKUP(C31,Tabla3[[CEDULA ]:[US$,]],8,0) -> 0 | R31: =+VLOOKUP($C31,Tabla3[[CEDULA ]:[US$,]],9,0) -> 0 | S31: =SUM(K31:R31) -> 0 | T31: =+J31+S31 -> 481 | U31: =VLOOKUP(C31,FR!$C$6:$M$55,11,0) -> 0 | Y31: =SUM(T31:X31) -> 481 | Z31: =T31*9.45% -> 45.4545 | AC31: =IFERROR(+VLOOKUP(D31,PQ!$D$35:$E$45,2,0),0) -> 0 | AH31: 0 | AI31: =SUM(Z31:AH31) -> 45.4545 | AJ31: =+Y31-AI31 -> 435.5455 | AK31: 600101000665 | AN31: =+AN30+1 -> 24 | AO31: =+D31 -> LLUMI YUQUILEMA MAYCOOL DANNY | AP31: =+E31 -> 45727 | AQ31: =+I31 -> 30 | AR31: =+H31 -> Matriz | AS31: =T31 -> 481 | AT31: =+AS31/12 -> 40.083333 | AU31: 0 | AW31: =($AW$7/360)*AQ31 -> 39.166667 | AX31: =+AS31/24 -> 20.041667 | AY31: =SUM(AS31:AX31) -> 580.29167 | AZ31: =+AS31*11.15% -> 53.6315 | BA31: =+AS31*1% -> 4.81 | BB31: =SUM(AZ31:BA31) -> 58.4415
B32: =+B31+1 -> 25 | C32: 603838657 | D32: MALAN DELGADO JOSE ALBERTO | E32: 44835 | F32: OFICIAL DE RECAUDACIONES | G32: M | H32: Durán | I32: 30 | J32: 473.88 | K32: =IFERROR(VLOOKUP(C32,Tabla15[[CEDULA]:[BONO VEHICULAR]],8,0),0) -> 200 | L32: 10.3 | M32: =+VLOOKUP(C32,Tabla335[[CEDULA ]:[US$,,]],9,0) -> 0 | P32: =+VLOOKUP(C32,'COMISIONES-SOCIOS'!$C$8:$L$57,10,0) -> 0 | Q32: =+VLOOKUP(C32,Tabla3[[CEDULA ]:[US$,]],8,0) -> 0 | R32: =+VLOOKUP($C32,Tabla3[[CEDULA ]:[US$,]],9,0) -> 0 | S32: =SUM(K32:R32) -> 210.3 | T32: =+J32+S32 -> 684.18 | U32: =VLOOKUP(C32,FR!$C$6:$M$55,11,0) -> 56.992194 | Y32: =SUM(T32:X32) -> 741.17219 | Z32: =T32*9.45% -> 64.65501 | AC32: =IFERROR(+VLOOKUP(D32,PQ!$D$35:$E$45,2,0),0) -> 36.13 | AH32: 400 | AI32: =SUM(Z32:AH32) -> 500.78501 | AJ32: =+Y32-AI32 -> 240.38718 | AK32: 600101000624 | AN32: =+AN31+1 -> 25 | AO32: =+D32 -> MALAN DELGADO JOSE ALBERTO | AP32: =+E32 -> 44835 | AQ32: =+I32 -> 30 | AR32: =+H32 -> Durán | AS32: =T32 -> 684.18 | AT32: =+AS32/12 -> 57.015 | AU32: 0 | AW32: =($AW$7/360)*AQ32 -> 39.166667 | AX32: =+AS32/24 -> 28.5075 | AY32: =SUM(AS32:AX32) -> 808.86917 | AZ32: =+AS32*11.15% -> 76.28607 | BA32: =+AS32*1% -> 6.8418 | BB32: =SUM(AZ32:BA32) -> 83.12787
B33: =+B32+1 -> 26 | C33: 925240525 | D33: MALAN YUQUILEMA RAUL ALBERTO | E33: 38869 | F33: ASESOR LEGAL | G33: M | H33: Matriz | I33: 30 | J33: 2700 | K33: =IFERROR(VLOOKUP(C33,Tabla15[[CEDULA]:[BONO VEHICULAR]],8,0),0) -> 0 | L33: 0 | M33: =+VLOOKUP(C33,Tabla335[[CEDULA ]:[US$,,]],9,0) -> 0 | P33: =+VLOOKUP(C33,'COMISIONES-SOCIOS'!$C$8:$L$57,10,0) -> 0 | Q33: =+VLOOKUP(C33,Tabla3[[CEDULA ]:[US$,]],8,0) -> 0 | R33: =+VLOOKUP($C33,Tabla3[[CEDULA ]:[US$,]],9,0) -> 0 | S33: =SUM(K33:R33) -> 0 | T33: =+J33+S33 -> 2700 | U33: =VLOOKUP(C33,FR!$C$6:$M$55,11,0) -> 224.91 | W33: =(+T33/12) -> 225 | X33: =(470/12) -> 39.166667 | Y33: =SUM(T33:X33) -> 3189.0767 | Z33: =T33*9.45% -> 255.15 | AA33: 51.88 | AB33: 0 | AC33: =IFERROR(+VLOOKUP(D33,PQ!$D$35:$E$45,2,0),0) -> 0 | AH33: 0 | AI33: =SUM(Z33:AH33) -> 307.03 | AJ33: =+Y33-AI33 -> 2882.0467 | AK33: 600101000359 | AN33: =+AN32+1 -> 26 | AO33: =+D33 -> MALAN YUQUILEMA RAUL ALBERTO | AP33: =+E33 -> 38869 | AQ33: =+I33 -> 30 | AR33: =+H33 -> Matriz | AS33: =T33 -> 2700 | AT33: 0 | AU33: 0 | AW33: 0 | AX33: =+AS33/24 -> 112.5 | AY33: =SUM(AS33:AX33) -> 2812.5 | AZ33: =+AS33*11.15% -> 301.05 | BA33: =+AS33*1% -> 27 | BB33: =SUM(AZ33:BA33) -> 328.05
B34: =+B33+1 -> 27 | C34: 954520599 | D34: MARSHALL VEGA YULIANA LISSETT | E34: 44743 | F34: ASESOR DE NEGOCIOS | G34: F | H34: Durán | I34: 30 | J34: 613.32 | K34: =IFERROR(VLOOKUP(C34,Tabla15[[CEDULA]:[BONO VEHICULAR]],8,0),0) -> 0 | L34: 13.33 | M34: =+VLOOKUP(C34,Tabla335[[CEDULA ]:[US$,,]],9,0) -> 0 | P34: =+VLOOKUP(C34,'COMISIONES-SOCIOS'!$C$8:$L$57,10,0) -> 0 | Q34: =+VLOOKUP(C34,Tabla3[[CEDULA ]:[US$,]],8,0) -> 0 | R34: =+VLOOKUP($C34,Tabla3[[CEDULA ]:[US$,]],9,0) -> 0 | S34: =SUM(K34:R34) -> 13.33 | T34: =+J34+S34 -> 626.65 | U34: =VLOOKUP(C34,FR!$C$6:$M$55,11,0) -> 52.199945 | Y34: =SUM(T34:X34) -> 678.84995 | Z34: =T34*9.45% -> 59.218425 | AC34: =IFERROR(+VLOOKUP(D34,PQ!$D$35:$E$45,2,0),0) -> 27.17 | AH34: 500 | AI34: =SUM(Z34:AH34) -> 586.38842 | AJ34: =+Y34-AI34 -> 92.46152 | AK34: 600201312163 | AN34: =+AN33+1 -> 27 | AO34: =+D34 -> MARSHALL VEGA YULIANA LISSETT | AP34: =+E34 -> 44743 | AQ34: =+I34 -> 30 | AR34: =+H34 -> Durán | AS34: =T34 -> 626.65 | AT34: =+AS34/12 -> 52.220833 | AU34: 0 | AW34: =($AW$7/360)*AQ34 -> 39.166667 | AX34: =+AS34/24 -> 26.110417 | AY34: =SUM(AS34:AX34) -> 744.14792 | AZ34: =+AS34*11.15% -> 69.871475 | BA34: =+AS34*1% -> 6.2665 | BB34: =SUM(AZ34:BA34) -> 76.137975
B35: =+B34+1 -> 28 | C35: 0943906032 | D35: MEZA RODRIGUEZ MICHAEL FERNANDO | E35: 45524 | F35: OFICIAL DE RECAUDACIONES | G35: M | H35: Norte | I35: 30 | J35: 473.88 | K35: =IFERROR(VLOOKUP(C35,Tabla15[[CEDULA]:[BONO VEHICULAR]],8,0),0) -> 100 | L35: 10.3 | M35: =+VLOOKUP(C35,Tabla335[[CEDULA ]:[US$,,]],9,0) -> 0 | P35: =+VLOOKUP(C35,'COMISIONES-SOCIOS'!$C$8:$L$57,10,0) -> 0 | Q35: =+VLOOKUP(C35,Tabla3[[CEDULA ]:[US$,]],8,0) -> 0 | R35: =+VLOOKUP($C35,Tabla3[[CEDULA ]:[US$,]],9,0) -> 0 | S35: =SUM(K35:R35) -> 110.3 | T35: =+J35+S35 -> 584.18 | U35: =VLOOKUP(C35,FR!$C$6:$M$55,11,0) -> 48.662194 | Y35: =SUM(T35:X35) -> 632.84219 | Z35: =T35*9.45% -> 55.20501 | AC35: =IFERROR(+VLOOKUP(D35,PQ!$D$35:$E$45,2,0),0) -> 0 | AD35: 0 | AH35: 300 | AI35: =SUM(Z35:AH35) -> 355.20501 | AJ35: =+Y35-AI35 -> 277.63718 | AK35: 600201318181 | AN35: =+AN34+1 -> 28 | AO35: =+D35 -> MEZA RODRIGUEZ MICHAEL FERNANDO | AP35: =+E35 -> 45524 | AQ35: =+I35 -> 30 | AR35: =+H35 -> Norte | AS35: =T35 -> 584.18 | AT35: =+AS35/12 -> 48.681667 | AU35: 0 | AW35: =($AW$7/360)*AQ35 -> 39.166667 | AX35: =+AS35/24 -> 24.340833 | AY35: =SUM(AS35:AX35) -> 696.36917 | AZ35: =+AS35*11.15% -> 65.13607 | BA35: =+AS35*1% -> 5.8418 | BB35: =SUM(AZ35:BA35) -> 70.97787
B36: =+B35+1 -> 29 | C36: 0919306050 | D36: MORAN GARCIA DANNY FAVIAN | E36: 45376 | F36: OFICIAL DE CUMPLIMIENTO | G36: M | H36: Matriz | I36: 30 | J36: 600 | K36: =IFERROR(VLOOKUP(C36,Tabla15[[CEDULA]:[BONO VEHICULAR]],8,0),0) -> 0 | L36: =200+13.044 -> 213.044 | M36: =+VLOOKUP(C36,Tabla335[[CEDULA ]:[US$,,]],9,0) -> 0 | P36: =+VLOOKUP(C36,'COMISIONES-SOCIOS'!$C$8:$L$57,10,0) -> 0 | Q36: =+VLOOKUP(C36,Tabla3[[CEDULA ]:[US$,]],8,0) -> 0 | R36: =+VLOOKUP($C36,Tabla3[[CEDULA ]:[US$,]],9,0) -> 0 | S36: =SUM(K36:R36) -> 213.044 | T36: =+J36+S36 -> 813.044 | U36: =VLOOKUP(C36,FR!$C$6:$M$55,11,0) -> 67.726565 | Y36: =SUM(T36:X36) -> 880.77057 | Z36: =T36*9.45% -> 76.832658 | AC36: =IFERROR(+VLOOKUP(D36,PQ!$D$35:$E$45,2,0),0) -> 0 | AE36: =+T36*3.41% -> 27.7248 | AH36: 550 | AI36: =SUM(Z36:AH36) -> 654.55746 | AJ36: =+Y36-AI36 -> 226.21311 | AK36: 600101317150 | AN36: =+AN35+1 -> 29 | AO36: =+D36 -> MORAN GARCIA DANNY FAVIAN | AP36: =+E36 -> 45376 | AQ36: =+I36 -> 30 | AR36: =+H36 -> Matriz | AS36: =T36 -> 813.044 | AT36: =+AS36/12 -> 67.753667 | AU36: 0 | AW36: =($AW$7/360)*AQ36 -> 39.166667 | AX36: =+AS36/24 -> 33.876833 | AY36: =SUM(AS36:AX36) -> 953.84117 | AZ36: =+AS36*11.15% -> 90.654406 | BA36: =+AS36*1% -> 8.13044 | BB36: =SUM(AZ36:BA36) -> 98.784846
B37: =+B36+1 -> 30 | C37: 0941235376 | D37: MOREIRA ESPINOZA LINDA ELIZABETH | E37: 45551 | F37: CAJERO FINANCIERO | G37: F | H37: Durán | I37: 30 | J37: 481 | K37: =IFERROR(VLOOKUP(C37,Tabla15[[CEDULA]:[BONO VEHICULAR]],8,0),0) -> 0 | L37: 10.46 | M37: =+VLOOKUP(C37,Tabla335[[CEDULA ]:[US$,,]],9,0) -> 0 | P37: =+VLOOKUP(C37,'COMISIONES-SOCIOS'!$C$8:$L$57,10,0) -> 0 | Q37: =+VLOOKUP(C37,Tabla3[[CEDULA ]:[US$,]],8,0) -> 0 | R37: =+VLOOKUP($C37,Tabla3[[CEDULA ]:[US$,]],9,0) -> 0 | S37: =SUM(K37:R37) -> 10.46 | T37: =+J37+S37 -> 491.46 | U37: =VLOOKUP(C37,FR!$C$6:$M$55,11,0) -> 19.104688 | Y37: =SUM(T37:X37) -> 510.56469 | Z37: =T37*9.45% -> 46.44297 | AC37: =IFERROR(+VLOOKUP(D37,PQ!$D$35:$E$45,2,0),0) -> 35.22 | AG37: 0 | AH37: 332.13 | AI37: =SUM(Z37:AH37) -> 413.79297 | AJ37: =+Y37-AI37 -> 96.771718 | AK37: 600301318316 | AN37: =+AN36+1 -> 30 | AO37: =+D37 -> MOREIRA ESPINOZA LINDA ELIZABETH | AP37: =+E37 -> 45551 | AQ37: =+I37 -> 30 | AR37: =+H37 -> Durán | AS37: =T37 -> 491.46 | AT37: =+AS37/12 -> 40.955 | AU37: 0 | AW37: =($AW$7/360)*AQ37 -> 39.166667 | AX37: =+AS37/24 -> 20.4775 | AY37: =SUM(AS37:AX37) -> 592.05917 | AZ37: =+AS37*11.15% -> 54.79779 | BA37: =+AS37*1% -> 4.9146 | BB37: =SUM(AZ37:BA37) -> 59.71239
B38: =+B37+1 -> 31 | C38: 955395686 | D38: MOROCHO DUCHI SANDRA STEPHANIE | E38: 44211 | F38: ASESOR DE NEGOCIOS | G38: F | H38: Norte | I38: 30 | J38: 613.32 | K38: =IFERROR(VLOOKUP(C38,Tabla15[[CEDULA]:[BONO VEHICULAR]],8,0),0) -> 0 | L38: 13.33 | M38: =+VLOOKUP(C38,Tabla335[[CEDULA ]:[US$,,]],9,0) -> 0 | P38: =+VLOOKUP(C38,'COMISIONES-SOCIOS'!$C$8:$L$57,10,0) -> 0 | Q38: =+VLOOKUP(C38,Tabla3[[CEDULA ]:[US$,]],8,0) -> 0 | R38: =+VLOOKUP($C38,Tabla3[[CEDULA ]:[US$,]],9,0) -> 0 | S38: =SUM(K38:R38) -> 13.33 | T38: =+J38+S38 -> 626.65 | U38: =VLOOKUP(C38,FR!$C$6:$M$55,11,0) -> 52.199945 | Y38: =SUM(T38:X38) -> 678.84995 | Z38: =T38*9.45% -> 59.218425 | AC38: =IFERROR(+VLOOKUP(D38,PQ!$D$35:$E$45,2,0),0) -> 0 | AH38: 100 | AI38: =SUM(Z38:AH38) -> 159.21842 | AJ38: =+Y38-AI38 -> 519.63152 | AK38: 600101012152 | AN38: =+AN37+1 -> 31 | AO38: =+D38 -> MOROCHO DUCHI SANDRA STEPHANIE | AP38: =+E38 -> 44211 | AQ38: =+I38 -> 30 | AR38: =+H38 -> Norte | AS38: =T38 -> 626.65 | AT38: =+AS38/12 -> 52.220833 | AU38: 0 | AW38: =($AW$7/360)*AQ38 -> 39.166667 | AX38: =+AS38/24 -> 26.110417 | AY38: =SUM(AS38:AX38) -> 744.14792 | AZ38: =+AS38*11.15% -> 69.871475 | BA38: =+AS38*1% -> 6.2665 | BB38: =SUM(AZ38:BA38) -> 76.137975
B39: =+B38+1 -> 32 | C39: 940991987 | D39: MOROCHO YANTALEMA DINA MAGALY | E39: 43074 | F39: TALENTO HUMANO | G39: F | H39: Matriz | I39: 30 | J39: 766.65 | K39: =IFERROR(VLOOKUP(C39,Tabla15[[CEDULA]:[BONO VEHICULAR]],8,0),0) -> 0 | L39: =850-J39 -> 83.35 | M39: =+VLOOKUP(C39,Tabla335[[CEDULA ]:[US$,,]],9,0) -> 0 | P39: =+VLOOKUP(C39,'COMISIONES-SOCIOS'!$C$8:$L$57,10,0) -> 0 | Q39: =+VLOOKUP(C39,Tabla3[[CEDULA ]:[US$,]],8,0) -> 0 | R39: =+VLOOKUP($C39,Tabla3[[CEDULA ]:[US$,]],9,0) -> 0 | S39: =SUM(K39:R39) -> 83.35 | T39: =+J39+S39 -> 850 | U39: =VLOOKUP(C39,FR!$C$6:$M$55,11,0) -> 70.805 | Y39: =SUM(T39:X39) -> 920.805 | Z39: =T39*9.45% -> 80.325 | AC39: =IFERROR(+VLOOKUP(D39,PQ!$D$35:$E$45,2,0),0) -> 0 | AD39: 0 | AH39: 700 | AI39: =SUM(Z39:AH39) -> 780.325 | AJ39: =+Y39-AI39 -> 140.48 | AK39: 600101009583 | AN39: =+AN38+1 -> 32 | AO39: =+D39 -> MOROCHO YANTALEMA DINA MAGALY | AP39: =+E39 -> 43074 | AQ39: =+I39 -> 30 | AR39: =+H39 -> Matriz | AS39: =T39 -> 850 | AT39: =+AS39/12 -> 70.833333 | AU39: 0 | AW39: =($AW$7/360)*AQ39 -> 39.166667 | AX39: =+AS39/24 -> 35.416667 | AY39: =SUM(AS39:AX39) -> 995.41667 | AZ39: =+AS39*11.15% -> 94.775 | BA39: =+AS39*1% -> 8.5 | BB39: =SUM(AZ39:BA39) -> 103.275
B40: =+B39+1 -> 33 | C40: 956929277 | D40: NAULA CRIOLLO CINTHYA ABIGAIL | E40: 45721 | F40: CAJERO FINANCIERO | G40: M | H40: Matriz | I40: 30 | J40: 481 | K40: =IFERROR(VLOOKUP(C40,Tabla15[[CEDULA]:[BONO VEHICULAR]],8,0),0) -> 0 | L40: =650-J40 -> 169 | M40: =+VLOOKUP(C40,Tabla335[[CEDULA ]:[US$,,]],9,0) -> 0 | P40: =+VLOOKUP(C40,'COMISIONES-SOCIOS'!$C$8:$L$57,10,0) -> 0 | Q40: =+VLOOKUP(C40,Tabla3[[CEDULA ]:[US$,]],8,0) -> 0 | R40: =+VLOOKUP($C40,Tabla3[[CEDULA ]:[US$,]],9,0) -> 0 | S40: =SUM(K40:R40) -> 169 | T40: =+J40+S40 -> 650 | U40: =VLOOKUP(C40,FR!$C$6:$M$55,11,0) -> 0 | Y40: =SUM(T40:X40) -> 650 | Z40: =T40*9.45% -> 61.425 | AC40: =IFERROR(+VLOOKUP(D40,PQ!$D$35:$E$45,2,0),0) -> 0 | AH40: 0 | AI40: =SUM(Z40:AH40) -> 61.425 | AJ40: =+Y40-AI40 -> 588.575 | AK40: 600201319284 | AN40: =+AN39+1 -> 33 | AO40: =+D40 -> NAULA CRIOLLO CINTHYA ABIGAIL | AP40: =+E40 -> 45721 | AQ40: =+I40 -> 30 | AR40: =+H40 -> Matriz | AS40: =T40 -> 650 | AT40: =+AS40/12 -> 54.166667 | AU40: 0 | AW40: =($AW$7/360)*AQ40 -> 39.166667 | AX40: =+AS40/24 -> 27.083333 | AY40: =SUM(AS40:AX40) -> 770.41667 | AZ40: =+AS40*11.15% -> 72.475 | BA40: =+AS40*1% -> 6.5 | BB40: =SUM(AZ40:BA40) -> 78.975
B41: =+B40+1 -> 34 | C41: 951763994 | D41: NEVAREZ PEÑAFIEL EVELYN JULEXY | E41: 45240 | F41: ASESOR DE CAPTACIONES | G41: F | H41: Norte | I41: 30 | J41: 475.85 | K41: =IFERROR(VLOOKUP(C41,Tabla15[[CEDULA]:[BONO VEHICULAR]],8,0),0) -> 0 | L41: =700-J41-30.32 -> 193.83 | M41: =+VLOOKUP(C41,Tabla335[[CEDULA ]:[US$,,]],9,0) -> 0 | P41: =+VLOOKUP(C41,'COMISIONES-SOCIOS'!$C$8:$L$57,10,0) -> 0 | Q41: =+VLOOKUP(C41,Tabla3[[CEDULA ]:[US$,]],8,0) -> 0 | R41: =+VLOOKUP($C41,Tabla3[[CEDULA ]:[US$,]],9,0) -> 0 | S41: =SUM(K41:R41) -> 193.83 | T41: =+J41+S41 -> 669.68 | U41: =VLOOKUP(C41,FR!$C$6:$M$55,11,0) -> ACUMULA | Y41: =SUM(T41:X41) -> 669.68 | Z41: =T41*9.45% -> 63.28476 | AC41: =IFERROR(+VLOOKUP(D41,PQ!$D$35:$E$45,2,0),0) -> 0 | AH41: 0 | AI41: =SUM(Z41:AH41) -> 63.28476 | AJ41: =+Y41-AI41 -> 606.39524 | AK41: 600101315986 | AN41: =+AN40+1 -> 34 | AO41: =+D41 -> NEVAREZ PEÑAFIEL EVELYN JULEXY | AP41: =+E41 -> 45240 | AQ41: =+I41 -> 30 | AR41: =+H41 -> Norte | AS41: =T41 -> 669.68 | AT41: =+AS41/12 -> 55.806667 | AU41: =+AS41*$AU$7 -> 55.784344 | AW41: =($AW$7/360)*AQ41 -> 39.166667 | AX41: =+AS41/24 -> 27.903333 | AY41: =SUM(AS41:AX41) -> 848.34101 | AZ41: =+AS41*11.15% -> 74.66932 | BA41: =+AS41*1% -> 6.6968 | BB41: =SUM(AZ41:BA41) -> 81.36612
B42: =+B41+1 -> 35 | C42: 950703199 | D42: ÑAMO GUALACEO BRYAN JAVIER | E42: 44847 | F42: OFICIAL DE RECAUDACIONES | G42: M | H42: Matriz | I42: 30 | J42: 473.88 | K42: =IFERROR(VLOOKUP(C42,Tabla15[[CEDULA]:[BONO VEHICULAR]],8,0),0) -> 100 | L42: 10.3 | M42: =+VLOOKUP(C42,Tabla335[[CEDULA ]:[US$,,]],9,0) -> 0 | P42: =+VLOOKUP(C42,'COMISIONES-SOCIOS'!$C$8:$L$57,10,0) -> 0 | Q42: =+VLOOKUP(C42,Tabla3[[CEDULA ]:[US$,]],8,0) -> 0 | R42: =+VLOOKUP($C42,Tabla3[[CEDULA ]:[US$,]],9,0) -> 0 | S42: =SUM(K42:R42) -> 110.3 | T42: =+J42+S42 -> 584.18 | U42: =VLOOKUP(C42,FR!$C$6:$M$55,11,0) -> 48.662194 | Y42: =SUM(T42:X42) -> 632.84219 | Z42: =T42*9.45% -> 55.20501 | AC42: =IFERROR(+VLOOKUP(D42,PQ!$D$35:$E$45,2,0),0) -> 0 | AH42: 0 | AI42: =SUM(Z42:AH42) -> 55.20501 | AJ42: =+Y42-AI42 -> 577.63718 | AK42: 600101312755 | AN42: =+AN41+1 -> 35 | AO42: =+D42 -> ÑAMO GUALACEO BRYAN JAVIER | AP42: =+E42 -> 44847 | AQ42: =+I42 -> 30 | AR42: =+H42 -> Matriz | AS42: =T42 -> 584.18 | AT42: =+AS42/12 -> 48.681667 | AU42: 0 | AW42: =($AW$7/360)*AQ42 -> 39.166667 | AX42: =+AS42/24 -> 24.340833 | AY42: =SUM(AS42:AX42) -> 696.36917 | AZ42: =+AS42*11.15% -> 65.13607 | BA42: =+AS42*1% -> 5.8418 | BB42: =SUM(AZ42:BA42) -> 70.97787
B43: =+B42+1 -> 36 | C43: 0923715692 | D43: ORELLANA MANZO WHITNEY YAILYN | E43: 45870 | F43: OFICIAL DE SEGURIDAD DE LA INFORMACIÓN | G43: F | H43: Matriz | I43: 30 | J43: 600 | K43: =IFERROR(VLOOKUP(C43,Tabla15[[CEDULA]:[BONO VEHICULAR]],8,0),0) -> 0 | M43: =+VLOOKUP(C43,Tabla335[[CEDULA ]:[US$,,]],9,0) -> 0 | P43: =+VLOOKUP(C43,'COMISIONES-SOCIOS'!$C$8:$L$57,10,0) -> 0 | Q43: =+VLOOKUP(C43,Tabla3[[CEDULA ]:[US$,]],8,0) -> 0 | R43: =+VLOOKUP($C43,Tabla3[[CEDULA ]:[US$,]],9,0) -> 0 | S43: =SUM(K43:R43) -> 0 | T43: =+J43+S43 -> 600 | U43: =VLOOKUP(C43,FR!$C$6:$M$55,11,0) -> 0 | Y43: =SUM(T43:X43) -> 600 | Z43: =T43*9.45% -> 56.7 | AH43: 400 | AI43: =SUM(Z43:AH43) -> 456.7 | AJ43: =+Y43-AI43 -> 143.3 | AK43: 600101320247 | AN43: =+AN42+1 -> 36 | AO43: =+D43 -> ORELLANA MANZO WHITNEY YAILYN | AP43: =+E43 -> 45870 | AQ43: =+I43 -> 30 | AR43: =+H43 -> Matriz | AS43: =T43 -> 600 | AT43: =+AS43/12 -> 50 | AU43: 0 | AW43: =($AW$7/360)*AQ43 -> 39.166667 | AX43: =+AS43/24 -> 25 | AY43: =SUM(AS43:AX43) -> 714.16667 | AZ43: =+AS43*11.15% -> 66.9 | BA43: =+AS43*1% -> 6 | BB43: =SUM(AZ43:BA43) -> 72.9
B44: =+B43+1 -> 37 | C44: 925830689 | D44: PERALTA MENDEZ LINA LISSETTE | E44: 43678 | F44: JEFE DE CRÉDITO | G44: F | H44: Matriz | I44: 30 | J44: 1022.2 | K44: =IFERROR(VLOOKUP(C44,Tabla15[[CEDULA]:[BONO VEHICULAR]],8,0),0) -> 0 | L44: 22.22 | M44: =+VLOOKUP(C44,Tabla335[[CEDULA ]:[US$,,]],9,0) -> 0 | P44: =+VLOOKUP(C44,'COMISIONES-SOCIOS'!$C$8:$L$57,10,0) -> 0 | Q44: =+VLOOKUP(C44,Tabla3[[CEDULA ]:[US$,]],8,0) -> 0 | R44: =+VLOOKUP($C44,Tabla3[[CEDULA ]:[US$,]],9,0) -> 0 | S44: =SUM(K44:R44) -> 22.22 | T44: =+J44+S44 -> 1044.42 | U44: =VLOOKUP(C44,FR!$C$6:$M$55,11,0) -> 87.000186 | Y44: =SUM(T44:X44) -> 1131.4202 | Z44: =T44*9.45% -> 98.69769 | AB44: 0 | AC44: =IFERROR(+VLOOKUP(D44,PQ!$D$35:$E$45,2,0),0) -> 80.94 | AH44: 831.44 | AI44: =SUM(Z44:AH44) -> 1011.0777 | AJ44: =+Y44-AI44 -> 120.3425 | AK44: 600101005135 | AN44: =+AN43+1 -> 37 | AO44: =+D44 -> PERALTA MENDEZ LINA LISSETTE | AP44: =+E44 -> 43678 | AQ44: =+I44 -> 30 | AR44: =+H44 -> Matriz | AS44: =T44 -> 1044.42 | AT44: =+AS44/12 -> 87.035 | AU44: 0 | AW44: =($AW$7/360)*AQ44 -> 39.166667 | AX44: =+AS44/24 -> 43.5175 | AY44: =SUM(AS44:AX44) -> 1214.1392 | AZ44: =+AS44*11.15% -> 116.45283 | BA44: =+AS44*1% -> 10.4442 | BB44: =SUM(AZ44:BA44) -> 126.89703
B45: =+B44+1 -> 38 | C45: 944034842 | D45: PEREZ ZAMORA ANA DE LOS ANGELES | E45: 45945 | F45: CAJERO FINANCIERO | G45: F | H45: Matriz | I45: 16 | J45: 256.53 | M45: =+VLOOKUP(C45,Tabla335[[CEDULA ]:[US$,,]],9,0) -> 0 | P45: =+VLOOKUP(C45,'COMISIONES-SOCIOS'!$C$8:$L$57,10,0) -> 0 | Q45: =+VLOOKUP(C45,Tabla3[[CEDULA ]:[US$,]],8,0) -> 0 | R45: =+VLOOKUP($C45,Tabla3[[CEDULA ]:[US$,]],9,0) -> 0 | S45: =SUM(K45:R45) -> 0 | T45: =+J45+S45 -> 256.53 | Y45: =SUM(T45:X45) -> 256.53 | Z45: =T45*9.45% -> 24.242085 | AH45: 0 | AN45: =+AN44+1 -> 38 | AO45: =+D45 -> PEREZ ZAMORA ANA DE LOS ANGELES | AP45: =+E45 -> 45945 | AQ45: =+I45 -> 16 | AR45: =+H45 -> Matriz | AW45: =($AW$7/360)*AQ45 -> 20.888889
B46: =+B45+1 -> 39 | C46: 951340702 | D46: QUITO CALDERON JONATHAN ENRIQUE | E46: 44579 | F46: JEFE DE COBRANZAS | G46: M | H46: Matriz | I46: 30 | J46: 817.76 | K46: =IFERROR(VLOOKUP(C46,Tabla15[[CEDULA]:[BONO VEHICULAR]],8,0),0) -> 0 | L46: 17.78 | M46: =+VLOOKUP(C46,Tabla335[[CEDULA ]:[US$,,]],9,0) -> 0 | P46: =+VLOOKUP(C46,'COMISIONES-SOCIOS'!$C$8:$L$57,10,0) -> 0 | Q46: =+VLOOKUP(C46,Tabla3[[CEDULA ]:[US$,]],8,0) -> 0 | R46: =+VLOOKUP($C46,Tabla3[[CEDULA ]:[US$,]],9,0) -> 0 | S46: =SUM(K46:R46) -> 17.78 | T46: =+J46+S46 -> 835.54 | U46: =VLOOKUP(C46,FR!$C$6:$M$55,11,0) -> 69.600482 | Y46: =SUM(T46:X46) -> 905.14048 | Z46: =T46*9.45% -> 78.95853 | AB46: 0 | AC46: =IFERROR(+VLOOKUP(D46,PQ!$D$35:$E$45,2,0),0) -> 0 | AH46: 400 | AI46: =SUM(Z46:AH46) -> 478.95853 | AJ46: =+Y46-AI46 -> 426.18195 | AK46: 600101310821 | AN46: =+AN45+1 -> 39 | AO46: =+D46 -> QUITO CALDERON JONATHAN ENRIQUE | AP46: =+E46 -> 44579 | AQ46: =+I46 -> 30 | AR46: =+H46 -> Matriz | AS46: =T46 -> 835.54 | AT46: =+AS46/12 -> 69.628333 | AU46: 0 | AW46: =($AW$7/360)*AQ46 -> 39.166667 | AX46: =+AS46/24 -> 34.814167 | AY46: =SUM(AS46:AX46) -> 979.14917 | AZ46: =+AS46*11.15% -> 93.16271 | BA46: =+AS46*1% -> 8.3554 | BB46: =SUM(AZ46:BA46) -> 101.51811
B47: =+B46+1 -> 40 | C47: 650112949 | D47: QUITO UCHUBANDA JANETH ALEXANDRA | E47: 44929 | F47: OFICIAL DE RECAUDACIONES | G47: F | H47: Norte | I47: 30 | J47: 473.88 | K47: =IFERROR(VLOOKUP(C47,Tabla15[[CEDULA]:[BONO VEHICULAR]],8,0),0) -> 0 | L47: 10.3 | M47: =+VLOOKUP(C47,Tabla335[[CEDULA ]:[US$,,]],9,0) -> 0 | P47: =+VLOOKUP(C47,'COMISIONES-SOCIOS'!$C$8:$L$57,10,0) -> 0 | Q47: =+VLOOKUP(C47,Tabla3[[CEDULA ]:[US$,]],8,0) -> 0 | R47: =+VLOOKUP($C47,Tabla3[[CEDULA ]:[US$,]],9,0) -> 0 | S47: =SUM(K47:R47) -> 10.3 | T47: =+J47+S47 -> 484.18 | U47: =VLOOKUP(C47,FR!$C$6:$M$55,11,0) -> 40.332194 | Y47: =SUM(T47:X47) -> 524.51219 | Z47: =T47*9.45% -> 45.75501 | AB47: 0 | AC47: =IFERROR(+VLOOKUP(D47,PQ!$D$35:$E$45,2,0),0) -> 0 | AH47: 200 | AI47: =SUM(Z47:AH47) -> 245.75501 | AJ47: =+Y47-AI47 -> 278.75718 | AK47: 600201313418 | AN47: =+AN46+1 -> 40 | AO47: =+D47 -> QUITO UCHUBANDA JANETH ALEXANDRA | AP47: =+E47 -> 44929 | AQ47: =+I47 -> 30 | AR47: =+H47 -> Norte | AS47: =T47 -> 484.18 | AT47: =+AS47/12 -> 40.348333 | AU47: 0 | AW47: =($AW$7/360)*AQ47 -> 39.166667 | AX47: =+AS47/24 -> 20.174167 | AY47: =SUM(AS47:AX47) -> 583.86917 | AZ47: =+AS47*11.15% -> 53.98607 | BA47: =+AS47*1% -> 4.8418 | BB47: =SUM(AZ47:BA47) -> 58.82787
B48: =+B47+1 -> 41 | C48: 924232804 | D48: RECALDE NARANJO ANGEL ALEXIS | E48: 44532 | F48: JEFE TI | G48: M | H48: Matriz | I48: 30 | J48: 1022.2 | K48: =IFERROR(VLOOKUP(C48,Tabla15[[CEDULA]:[BONO VEHICULAR]],8,0),0) -> 0 | L48: 22.22 | M48: =+VLOOKUP(C48,Tabla335[[CEDULA ]:[US$,,]],9,0) -> 0 | P48: =+VLOOKUP(C48,'COMISIONES-SOCIOS'!$C$8:$L$57,10,0) -> 0 | Q48: =+VLOOKUP(C48,Tabla3[[CEDULA ]:[US$,]],8,0) -> 0 | R48: =+VLOOKUP($C48,Tabla3[[CEDULA ]:[US$,]],9,0) -> 0 | S48: =SUM(K48:R48) -> 22.22 | T48: =+J48+S48 -> 1044.42 | U48: =VLOOKUP(C48,FR!$C$6:$M$55,11,0) -> 87.000186 | Y48: =SUM(T48:X48) -> 1131.4202 | Z48: =T48*9.45% -> 98.69769 | AB48: 0 | AC48: =IFERROR(+VLOOKUP(D48,PQ!$D$35:$E$45,2,0),0) -> 71.05 | AH48: 900 | AI48: =SUM(Z48:AH48) -> 1069.7477 | AJ48: =+Y48-AI48 -> 61.672496 | AK48: 600101310624 | AN48: =+AN47+1 -> 41 | AO48: =+D48 -> RECALDE NARANJO ANGEL ALEXIS | AP48: =+E48 -> 44532 | AQ48: =+I48 -> 30 | AR48: =+H48 -> Matriz | AS48: =T48 -> 1044.42 | AT48: =+AS48/12 -> 87.035 | AU48: 0 | AW48: =($AW$7/360)*AQ48 -> 39.166667 | AX48: =+AS48/24 -> 43.5175 | AY48: =SUM(AS48:AX48) -> 1214.1392 | AZ48: =+AS48*11.15% -> 116.45283 | BA48: =+AS48*1% -> 10.4442 | BB48: =SUM(AZ48:BA48) -> 126.89703
B49: =+B48+1 -> 42 | C49: 605031145 | D49: SALAO PEREZ GERMAN FABRICIO | E49: 45066 | F49: ASESOR DE NEGOCIOS | G49: M | H49: Durán | I49: 30 | J49: 613.32 | K49: =IFERROR(VLOOKUP(C49,Tabla15[[CEDULA]:[BONO VEHICULAR]],8,0),0) -> 0 | L49: 13.33 | M49: =+VLOOKUP(C49,Tabla335[[CEDULA ]:[US$,,]],9,0) -> 0 | P49: =+VLOOKUP(C49,'COMISIONES-SOCIOS'!$C$8:$L$57,10,0) -> 0 | Q49: =+VLOOKUP(C49,Tabla3[[CEDULA ]:[US$,]],8,0) -> 0 | R49: =+VLOOKUP($C49,Tabla3[[CEDULA ]:[US$,]],9,0) -> 0 | S49: =SUM(K49:R49) -> 13.33 | T49: =+J49+S49 -> 626.65 | U49: =VLOOKUP(C49,FR!$C$6:$M$55,11,0) -> 52.199945 | Y49: =SUM(T49:X49) -> 678.84995 | Z49: =T49*9.45% -> 59.218425 | AC49: =IFERROR(+VLOOKUP(D49,PQ!$D$35:$E$45,2,0),0) -> 0 | AH49: 0 | AI49: =SUM(Z49:AH49) -> 59.218425 | AJ49: =+Y49-AI49 -> 619.63152 | AK49: 600301314632 | AN49: =+AN48+1 -> 42 | AO49: =+D49 -> SALAO PEREZ GERMAN FABRICIO | AP49: =+E49 -> 45066 | AQ49: =+I49 -> 30 | AR49: =+H49 -> Durán | AS49: =T49 -> 626.65 | AT49: =+AS49/12 -> 52.220833 | AU49: 0 | AW49: =($AW$7/360)*AQ49 -> 39.166667 | AX49: =+AS49/24 -> 26.110417 | AY49: =SUM(AS49:AX49) -> 744.14792 | AZ49: =+AS49*11.15% -> 69.871475 | BA49: =+AS49*1% -> 6.2665 | BB49: =SUM(AZ49:BA49) -> 76.137975
B50: =+B49+1 -> 43 | C50: 927257576 | D50: SANISACA MITE ISRAEL BENJAMIN | E50: 44139 | F50: JEFE DE CRÉDITO | G50: M | H50: Norte | I50: 30 | J50: 1022.2 | K50: =IFERROR(VLOOKUP(C50,Tabla15[[CEDULA]:[BONO VEHICULAR]],8,0),0) -> 0 | L50: 22.222628 | M50: =+VLOOKUP(C50,Tabla335[[CEDULA ]:[US$,,]],9,0) -> 0 | P50: =+VLOOKUP(C50,'COMISIONES-SOCIOS'!$C$8:$L$57,10,0) -> 0 | Q50: =+VLOOKUP(C50,Tabla3[[CEDULA ]:[US$,]],8,0) -> 0 | R50: =+VLOOKUP($C50,Tabla3[[CEDULA ]:[US$,]],9,0) -> 0 | S50: =SUM(K50:R50) -> 22.222628 | T50: =+J50+S50 -> 1044.4226 | U50: =VLOOKUP(C50,FR!$C$6:$M$55,11,0) -> 87.000405 | Y50: =SUM(T50:X50) -> 1131.423 | Z50: =T50*9.45% -> 98.697938 | AB50: 0 | AC50: =IFERROR(+VLOOKUP(D50,PQ!$D$35:$E$45,2,0),0) -> 55.57 | AE50: =+T50*3.41% -> 35.614812 | AH50: 426.97 | AI50: =SUM(Z50:AH50) -> 616.85275 | AJ50: =+Y50-AI50 -> 514.57028 | AK50: 600101012010 | AN50: =+AN49+1 -> 43 | AO50: =+D50 -> SANISACA MITE ISRAEL BENJAMIN | AP50: =+E50 -> 44139 | AQ50: =+I50 -> 30 | AR50: =+H50 -> Norte | AS50: =T50 -> 1044.4226 | AT50: =+AS50/12 -> 87.035219 | AU50: 0 | AW50: =($AW$7/360)*AQ50 -> 39.166667 | AX50: =+AS50/24 -> 43.517609 | AY50: =SUM(AS50:AX50) -> 1214.1421 | AZ50: =+AS50*11.15% -> 116.45312 | BA50: =+AS50*1% -> 10.444226 | BB50: =SUM(AZ50:BA50) -> 126.89735
B51: =+B50+1 -> 44 | C51: 928901800 | D51: TADAY GUAMAN NÉSTOR ALONSO | E51: 42856 | F51: JEFE DE BOVEDA | G51: M | H51: Matriz | I51: 30 | J51: 511.1 | K51: =IFERROR(VLOOKUP(C51,Tabla15[[CEDULA]:[BONO VEHICULAR]],8,0),0) -> 100 | L51: 11.11 | M51: =+VLOOKUP(C51,Tabla335[[CEDULA ]:[US$,,]],9,0) -> 0 | P51: =+VLOOKUP(C51,'COMISIONES-SOCIOS'!$C$8:$L$57,10,0) -> 0 | Q51: =+VLOOKUP(C51,Tabla3[[CEDULA ]:[US$,]],8,0) -> 0 | R51: =+VLOOKUP($C51,Tabla3[[CEDULA ]:[US$,]],9,0) -> 0 | S51: =SUM(K51:R51) -> 111.11 | T51: =+J51+S51 -> 622.21 | U51: =VLOOKUP(C51,FR!$C$6:$M$55,11,0) -> 51.830093 | Y51: =SUM(T51:X51) -> 674.04009 | Z51: =T51*9.45% -> 58.798845 | AC51: =IFERROR(+VLOOKUP(D51,PQ!$D$35:$E$45,2,0),0) -> 84.3 | AD51: 0 | AF51: 0 | AH51: 150 | AI51: =SUM(Z51:AH51) -> 293.09884 | AJ51: =+Y51-AI51 -> 380.94125 | AK51: 600101008569 | AN51: =+AN50+1 -> 44 | AO51: =+D51 -> TADAY GUAMAN NÉSTOR ALONSO | AP51: =+E51 -> 42856 | AQ51: =+I51 -> 30 | AR51: =+H51 -> Matriz | AS51: =T51 -> 622.21 | AT51: =+AS51/12 -> 51.850833 | AU51: 0 | AW51: =($AW$7/360)*AQ51 -> 39.166667 | AX51: =+AS51/24 -> 25.925417 | AY51: =SUM(AS51:AX51) -> 739.15292 | AZ51: =+AS51*11.15% -> 69.376415 | BA51: =+AS51*1% -> 6.2221 | BB51: =SUM(AZ51:BA51) -> 75.598515
B52: =+B51+1 -> 45 | C52: 951315746 | D52: TIGUA MONTERO KAREN LISBETH | E52: 44837 | F52: ASESOR DE NEGOCIOS | G52: F | H52: Matriz | I52: 30 | J52: 613.32 | K52: =IFERROR(VLOOKUP(C52,Tabla15[[CEDULA]:[BONO VEHICULAR]],8,0),0) -> 0 | L52: 13.33 | M52: =+VLOOKUP(C52,Tabla335[[CEDULA ]:[US$,,]],9,0) -> 0 | P52: =+VLOOKUP(C52,'COMISIONES-SOCIOS'!$C$8:$L$57,10,0) -> 0 | Q52: =+VLOOKUP(C52,Tabla3[[CEDULA ]:[US$,]],8,0) -> 0 | R52: =+VLOOKUP($C52,Tabla3[[CEDULA ]:[US$,]],9,0) -> 0 | S52: =SUM(K52:R52) -> 13.33 | T52: =+J52+S52 -> 626.65 | U52: =VLOOKUP(C52,FR!$C$6:$M$55,11,0) -> 52.199945 | Y52: =SUM(T52:X52) -> 678.84995 | Z52: =T52*9.45% -> 59.218425 | AC52: =IFERROR(+VLOOKUP(D52,PQ!$D$35:$E$45,2,0),0) -> 0 | AH52: 350 | AI52: =SUM(Z52:AH52) -> 409.21843 | AJ52: =+Y52-AI52 -> 269.63152 | AK52: 600201312646 | AN52: =+AN51+1 -> 45 | AO52: =+D52 -> TIGUA MONTERO KAREN LISBETH | AP52: =+E52 -> 44837 | AQ52: =+I52 -> 30 | AR52: =+H52 -> Matriz | AS52: =T52 -> 626.65 | AT52: =+AS52/12 -> 52.220833 | AU52: 0 | AW52: =($AW$7/360)*AQ52 -> 39.166667 | AX52: =+AS52/24 -> 26.110417 | AY52: =SUM(AS52:AX52) -> 744.14792 | AZ52: =+AS52*11.15% -> 69.871475 | BA52: =+AS52*1% -> 6.2665 | BB52: =SUM(AZ52:BA52) -> 76.137975
B53: =+B52+1 -> 46 | C53: 954184321 | D53: URQUIZO GUARANGA ALEX EFRAIN | E53: 44378 | F53: OFICIAL DE RECAUDACIONES | G53: M | H53: Matriz | I53: 30 | J53: 511.1 | K53: =IFERROR(VLOOKUP(C53,Tabla15[[CEDULA]:[BONO VEHICULAR]],8,0),0) -> 100 | L53: 11.11 | M53: =+VLOOKUP(C53,Tabla335[[CEDULA ]:[US$,,]],9,0) -> 0 | P53: =+VLOOKUP(C53,'COMISIONES-SOCIOS'!$C$8:$L$57,10,0) -> 0 | Q53: =+VLOOKUP(C53,Tabla3[[CEDULA ]:[US$,]],8,0) -> 0 | R53: =+VLOOKUP($C53,Tabla3[[CEDULA ]:[US$,]],9,0) -> 0 | S53: =SUM(K53:R53) -> 111.11 | T53: =+J53+S53 -> 622.21 | U53: =VLOOKUP(C53,FR!$C$6:$M$55,11,0) -> 51.830093 | Y53: =SUM(T53:X53) -> 674.04009 | Z53: =T53*9.45% -> 58.798845 | AC53: =IFERROR(+VLOOKUP(D53,PQ!$D$35:$E$45,2,0),0) -> 0 | AH53: 200 | AI53: =SUM(Z53:AH53) -> 258.79884 | AJ53: =+Y53-AI53 -> 415.24125 | AK53: 600101008248 | AN53: =+AN52+1 -> 46 | AO53: =+D53 -> URQUIZO GUARANGA ALEX EFRAIN | AP53: =+E53 -> 44378 | AQ53: =+I53 -> 30 | AR53: =+H53 -> Matriz | AS53: =T53 -> 622.21 | AT53: =+AS53/12 -> 51.850833 | AU53: 0 | AW53: =($AW$7/360)*AQ53 -> 39.166667 | AX53: =+AS53/24 -> 25.925417 | AY53: =SUM(AS53:AX53) -> 739.15292 | AZ53: =+AS53*11.15% -> 69.376415 | BA53: =+AS53*1% -> 6.2221 | BB53: =SUM(AZ53:BA53) -> 75.598515
B54: =+B53+1 -> 47 | C54: 922034772 | D54: VERA GUEVARA PAOLA KARINA | E54: 44110 | F54: ASESOR DE CAPTACIONES | G54: F | H54: Matriz | I54: 30 | J54: 700 | K54: =IFERROR(VLOOKUP(C54,Tabla15[[CEDULA]:[BONO VEHICULAR]],8,0),0) -> 0 | L54: 0 | M54: =+VLOOKUP(C54,Tabla335[[CEDULA ]:[US$,,]],9,0) -> 0 | P54: =+VLOOKUP(C54,'COMISIONES-SOCIOS'!$C$8:$L$57,10,0) -> 0 | Q54: =+VLOOKUP(C54,Tabla3[[CEDULA ]:[US$,]],8,0) -> 0 | R54: =+VLOOKUP($C54,Tabla3[[CEDULA ]:[US$,]],9,0) -> 0 | S54: =SUM(K54:R54) -> 0 | T54: =+J54+S54 -> 700 | U54: =VLOOKUP(C54,FR!$C$6:$M$55,11,0) -> 58.31 | Y54: =SUM(T54:X54) -> 758.31 | Z54: =T54*9.45% -> 66.15 | AC54: =IFERROR(+VLOOKUP(D54,PQ!$D$35:$E$45,2,0),0) -> 0 | AH54: 600 | AI54: =SUM(Z54:AH54) -> 666.15 | AJ54: =+Y54-AI54 -> 92.16 | AK54: 600101011966 | AN54: =+AN53+1 -> 47 | AO54: =+D54 -> VERA GUEVARA PAOLA KARINA | AP54: =+E54 -> 44110 | AQ54: =+I54 -> 30 | AR54: =+H54 -> Matriz | AS54: =T54 -> 700 | AT54: =+AS54/12 -> 58.333333 | AU54: 0 | AW54: =($AW$7/360)*AQ54 -> 39.166667 | AX54: =+AS54/24 -> 29.166667 | AY54: =SUM(AS54:AX54) -> 826.66667 | AZ54: =+AS54*11.15% -> 78.05 | BA54: =+AS54*1% -> 7 | BB54: =SUM(AZ54:BA54) -> 85.05
B55: =+B54+1 -> 48 | C55: 923837991 | D55: YUNDA CUJILEMA MARIA TERESA | E55: 41426 | F55: CONTADOR GENERAL | G55: F | H55: Matriz | I55: 30 | J55: 1022.2 | K55: =IFERROR(VLOOKUP(C55,Tabla15[[CEDULA]:[BONO VEHICULAR]],8,0),0) -> 0 | L55: 100 | M55: =+VLOOKUP(C55,Tabla335[[CEDULA ]:[US$,,]],9,0) -> 0 | P55: =+VLOOKUP(C55,'COMISIONES-SOCIOS'!$C$8:$L$57,10,0) -> 0 | Q55: =+VLOOKUP(C55,Tabla3[[CEDULA ]:[US$,]],8,0) -> 0 | R55: =+VLOOKUP($C55,Tabla3[[CEDULA ]:[US$,]],9,0) -> 0 | S55: =SUM(K55:R55) -> 100 | T55: =+J55+S55 -> 1122.2 | U55: =VLOOKUP(C55,FR!$C$6:$M$55,11,0) -> 93.47926 | Y55: =SUM(T55:X55) -> 1215.6793 | Z55: =T55*9.45% -> 106.0479 | AC55: =IFERROR(+VLOOKUP(D55,PQ!$D$35:$E$45,2,0),0) -> 0 | AD55: 0 | AH55: 850 | AI55: =SUM(Z55:AH55) -> 956.0479 | AJ55: =+Y55-AI55 -> 259.63136 | AK55: 600101004961 | AN55: =+AN54+1 -> 48 | AO55: =+D55 -> YUNDA CUJILEMA MARIA TERESA | AP55: =+E55 -> 41426 | AQ55: =+I55 -> 30 | AR55: =+H55 -> Matriz | AS55: =T55 -> 1122.2 | AT55: =+AS55/12 -> 93.516667 | AU55: 0 | AW55: =($AW$7/360)*AQ55 -> 39.166667 | AX55: =+AS55/24 -> 46.758333 | AY55: =SUM(AS55:AX55) -> 1301.6417 | AZ55: =+AS55*11.15% -> 125.1253 | BA55: =+AS55*1% -> 11.222 | BB55: =SUM(AZ55:BA55) -> 136.3473
B56: =+B55+1 -> 49 | C56: 941508905 | D56: YUQUILEMA CACUANGO ANGEL JOSE | E56: 43567 | F56: OFICIAL DE RECAUDACIONES | G56: M | H56: Matriz | I56: 30 | J56: 511.1 | K56: =IFERROR(VLOOKUP(C56,Tabla15[[CEDULA]:[BONO VEHICULAR]],8,0),0) -> 100 | L56: 11.11 | M56: =+VLOOKUP(C56,Tabla335[[CEDULA ]:[US$,,]],9,0) -> 0 | P56: =+VLOOKUP(C56,'COMISIONES-SOCIOS'!$C$8:$L$57,10,0) -> 0 | Q56: =+VLOOKUP(C56,Tabla3[[CEDULA ]:[US$,]],8,0) -> 0 | R56: =+VLOOKUP($C56,Tabla3[[CEDULA ]:[US$,]],9,0) -> 0 | S56: =SUM(K56:R56) -> 111.11 | T56: =+J56+S56 -> 622.21 | U56: =VLOOKUP(C56,FR!$C$6:$M$55,11,0) -> 51.830093 | Y56: =SUM(T56:X56) -> 674.04009 | Z56: =T56*9.45% -> 58.798845 | AC56: =IFERROR(+VLOOKUP(D56,PQ!$D$35:$E$45,2,0),0) -> 0 | AH56: 500 | AI56: =SUM(Z56:AH56) -> 558.79885 | AJ56: =+Y56-AI56 -> 115.24125 | AK56: 600101008981 | AN56: =+AN55+1 -> 49 | AO56: =+D56 -> YUQUILEMA CACUANGO ANGEL JOSE | AP56: =+E56 -> 43567 | AQ56: =+I56 -> 30 | AR56: =+H56 -> Matriz | AS56: =T56 -> 622.21 | AT56: =+AS56/12 -> 51.850833 | AU56: 0 | AW56: =($AW$7/360)*AQ56 -> 39.166667 | AX56: =+AS56/24 -> 25.925417 | AY56: =SUM(AS56:AX56) -> 739.15292 | AZ56: =+AS56*11.15% -> 69.376415 | BA56: =+AS56*1% -> 6.2221 | BB56: =SUM(AZ56:BA56) -> 75.598515
B57: =+B56+1 -> 50 | C57: 604154575 | D57: YUQUILEMA DELGADO PEDRO ANTONIO | E57: 43379 | F57: JEFE DE CRÉDITO | G57: M | H57: Durán | I57: 30 | J57: 1022.2 | K57: =IFERROR(VLOOKUP(C57,Tabla15[[CEDULA]:[BONO VEHICULAR]],8,0),0) -> 0 | L57: 0 | M57: =+VLOOKUP(C57,Tabla335[[CEDULA ]:[US$,,]],9,0) -> 0 | P57: =+VLOOKUP(C57,'COMISIONES-SOCIOS'!$C$8:$L$57,10,0) -> 0 | Q57: =+VLOOKUP(C57,Tabla3[[CEDULA ]:[US$,]],8,0) -> 0 | R57: =+VLOOKUP($C57,Tabla3[[CEDULA ]:[US$,]],9,0) -> 0 | S57: =SUM(K57:R57) -> 0 | T57: =+J57+S57 -> 1022.2 | U57: =VLOOKUP(C57,FR!$C$6:$M$55,11,0) -> 85.14926 | Y57: =SUM(T57:X57) -> 1107.3493 | Z57: =T57*9.45% -> 96.5979 | AB57: 0 | AC57: =IFERROR(+VLOOKUP(D57,PQ!$D$35:$E$45,2,0),0) -> 0 | AG57: 0 | AH57: 800 | AI57: =SUM(Z57:AH57) -> 896.5979 | AJ57: =+Y57-AI57 -> 210.75136 | AK57: 600101003932 | AN57: =+AN56+1 -> 50 | AO57: =+D57 -> YUQUILEMA DELGADO PEDRO ANTONIO | AP57: =+E57 -> 43379 | AQ57: =+I57 -> 30 | AR57: =+H57 -> Durán | AS57: =T57 -> 1022.2 | AT57: =+AS57/12 -> 85.183333 | AU57: 0 | AW57: =($AW$7/360)*AQ57 -> 39.166667 | AX57: =+AS57/24 -> 42.591667 | AY57: =SUM(AS57:AX57) -> 1189.1417 | AZ57: =+AS57*11.15% -> 113.9753 | BA57: =+AS57*1% -> 10.222 | BB57: =SUM(AZ57:BA57) -> 124.1973
D58: TOTALES | J58: =SUBTOTAL(9,J8:J57) -> 30990.65 | K58: =SUBTOTAL(9,K8:K57) -> 1070 | L58: =SUBTOTAL(9,L8:L57) -> 1607.1266 | M58: =SUBTOTAL(9,M8:M57) -> 737.54 | N58: =SUBTOTAL(9,N8:N57) -> 0 | O58: =SUBTOTAL(9,O8:O57) -> 0 | P58: =SUBTOTAL(9,P8:P57) -> 0 | Q58: =SUBTOTAL(9,Q8:Q57) -> 0 | ... Y58: =SUBTOTAL(9,Y8:Y57) -> 36929.29 | Z58: =T58*9.45% -> 3251.3024 | AA58: =+SUBTOTAL(9,AA8:AA57) -> 51.88 | AB58: =SUBTOTAL(9,AB8:AB57) -> 0 | AC58: =SUBTOTAL(9,AC8:AC57) -> 760.63 | AD58: =SUBTOTAL(9,AD8:AD57) -> 912.87955 | AE58: =SUBTOTAL(9,AE8:AE57) -> 87.739526 | AF58: =SUBTOTAL(9,AF8:AF57) -> 0 | AG58: =SUBTOTAL(9,AG8:AG57) -> 0 | AH58: =SUBTOTAL(9,AH8:AH57) -> 13476.11 | AI58: =SUBTOTAL(9,AI8:AI57) -> 18205.692 | AJ58: =SUBTOTAL(9,AJ8:AJ57) -> 16707.199 | AO58: =+D58 -> TOTALES | AS58: =SUBTOTAL(9,AS8:AS57) -> 32388.917 | AT58: =SUBTOTAL(9,AT8:AT57) -> 2474.0764 | AU58: =SUBTOTAL(9,AU8:AU57) -> 119.62713 | AV58: =SUBTOTAL(9,AV8:AV57) -> 0 | AW58: =SUBTOTAL(9,AW8:AW57) -> 1742.9167 | AX58: =SUBTOTAL(9,AX8:AX57) -> 1349.5382 | AY58: =SUM(AS58:AX58) -> 38075.075 | AZ58: =+AS58*11.15% -> 3611.3642 | BA58: =+AS58*1% -> 323.88917 | BB58: =SUM(AZ58:BA58) -> 3935.2534
AT59: 45011005 | AU59: 450135 | AW59: 45011010 | AX59: 45019020 | AZ59: 45012005 | BA59: 45012015
J60: 45010505 | K60: 45019005 | Q60: 45019015 | U60: 450135 | W60: 45011005 | X60: 45011010 | Z60: 25031505 | AA60: 25040505 | AC60: 25039001 | AD60: 45010505 | AE60: 25039002 | AF60: 25039003 | AG60: 16909005 | AH60: 169005 | AJ60: 250305 | AT60: 25031005 | AU60: 250320 | AW60: 25031010 | AX60: 25031025 | AZ60: 25031510 | BA60: 25031510
I74: NORMAL: | J74: =J58 -> 30990.65 | O74: AJUSTE: | P74: =+S58 -> 3414.6666
I75: 0.0945 | J75: =+J74*I75 -> 2928.6164 | O75: 0.0945 | P75: =+P74*O75 -> 322.686
I76: 0.1215 | J76: =+J74*I76 -> 3765.364 | O76: 0.1215 | P76: =+P74*O76 -> 414.882 | AT76: 45011005 | AU76: 13° | AV76: =+#REF! -> #REF! | AW76: =+AT58 -> 2474.0764
I77: TOTAL | J77: =SUM(J75:J76) -> 6693.9804 | O77: TOTAL | P77: =SUM(P75:P76) -> 737.56799 | AT77: 450135 | AU77: FR | AW77: =+AU58 -> 119.62713
AT78: 45011010 | AU78: 14° | AV78: =SUM(#REF!) -> #REF! | AW78: =+AW58 -> 1742.9167
AT79: 45019020 | AU79: Vacaciones | AV79: =SUM(#REF!) -> #REF! | AW79: =+AX58 -> 1349.5382
AT80: 45012005 | AU80: Aporte 11.15% | AV80: =+#REF! -> #REF! | AW80: =+AZ58 -> 3611.3642
I81: 25031505 | J81: Personal IESS | K81: 2910.88 | O81: 25031505 | P81: Personal IESS | Q81: 657.98 | S81: =+K81+Q81 -> 3568.86 | W81: Cuadre | X81: Personal | Y81: Patronal | Z81: Remuneración | AT81: 45012015 | AU81: Aporte 1% | AV81: =+#REF! -> #REF! | AW81: =+BA58 -> 323.88917
I82: 25031510 | J82: Patronal IESS | K82: 3742.58 | O82: 25031510 | P82: Patronal IESS | Q82: 845.91 | S82: =+K82+Q82 -> 4588.49 | X82: 25031505 | Y82: 25031510 | Z82: 250305 | AT82: 25031005 | AU82: 13° | AX82: =+AT58 -> 2474.0764
I83: 45039005 | J83: Gtos Banca | K83: 0 | O83: 45039005 | P83: Gtos Banca | Q83: 0 | W83: Consolidado | X83: =+S81 -> 3568.86 | Y83: =+S82 -> 4588.49 | Z83: 22934.41 | AT83: 250320 | AU83: FR | AX83: =+AU58 -> 119.62713
I84: 25031505 | J84: Personal IESS | M84: 0 | O84: 11031020 | P84: Produbanco | R84: 1503.89 | W84: Matriz | X84: 2129.96 | Y84: 2674.74 | Z84: 13492.95 | AT84: 25031010 | AU84: 14° | AX84: =+AW58 -> 1742.9167
I85: 25031510 | J85: Patronal IESS | M85: 0 | Q85: =SUM(Q81:Q84) -> 1503.89 | R85: =SUM(R81:R84) -> 1503.89 | W85: Norte | X85: 866.39 | Y85: 1102.87 | Z85: 5495.22 | AT85: 25031025 | AU85: Vacaciones | AX85: =+AX58 -> 1349.5382
I86: 11031020 | J86: Produbanco | M86: 6653.46 | R86: =+Q85-R85 -> 0 | W86: Durán | X86: 572.51 | Y86: 783.26 | Z86: 3946.23 | AT86: 25031510 | AU86: Aporte 11.15% | AX86: =+AZ58 -> 3611.3642
K87: =SUM(K81:K86) -> 6653.46 | M87: =SUM(M81:M86) -> 6653.46 | W87: Diferencia | X87: =+X83-X84-X85-X86 -> 0 | Y87: =+Y83-Y84-Y85-Y86 -> 27.62 | Z87: =+Z83-Z84-Z85-Z86 -> 0.01 | AT87: 25031510 | AU87: Aporte 1% | AX87: =+BA58 -> 323.88917
M88: =+K87-M87 -> 0 | AW88: =SUM(AW76:AW87) -> 9621.4117 | AX88: =SUM(AX76:AX87) -> 9621.4117 | AY88: =+AW88-AX88 -> 0
I91: NOTAS DE CRÉDITO IESS
I92: Colaborador | J92: Sueldo | K92: Personal | M92: Patronal
K93: 0.0945 | M93: 0.1115
I94: …... | J94: 0 | K94: =+J94*K93 -> 0 | M94: =+J94*M93 -> 0
I98: 45010505 | J98: Sueldo | K98: =+J58 -> 30990.65
I99: 45019005 | J99: Comisiones | K99: =SUM(K58:P58) -> 3414.6666
I100: 45019015 | J100: Horas Extras | K100: =SUM(Q58:R58) -> 0
I101: 450135 | J101: FR | K101: =+U58 -> 2259.8069
I102: 45011005 | J102: 13° | K102: =+W58 -> 225
I103: 45011010 | J103: 14° | K103: =+X58 -> 39.166667
I104: 25031505 | J104: Apor Personal | M104: =+Z58 -> 3251.3024
I105: 25040505 | J105: Retención del Personal | M105: =+AA58 -> 51.88
I106: 25039001 | J106: Prestamos Q/H | M106: =+AC58 -> 760.63
I107: 45010505 | J107: Subsidios | M107: =+AD58 -> 912.87955
I108: 25039002 | J108: Ext Salud | M108: =+AE58 -> 87.739526
I109: 25039003 | J109: Pens Alimen | M109: =+AF58 -> 0
I110: 16909005 | J110: Ctas x Cobrar | M110: =+AG58 -> 0
I111: 169005 | J111: Anticipo | M111: =+AH58 -> 13476.11
I112: 250305 | J112: Remunerac | M112: =+AJ58 -> 16707.199
K113: =SUM(K98:K103) -> 36929.29 | M113: =SUM(M104:M112) -> 35247.74 | N113: =+K113-M113 -> 1681.5502

Sheet BONO vehicular
B2: CALCULO BONO VEHICULAR
B3: NOMINA SEPTIEMBRE 2025
B6: No. | C6: CEDULA | D6: NOMBRE | E6: FECHA DE INGRESO | F6: CARGO | G6: AGENCIA | H6: DIAS TRABAJADOS | I6: SUELDO | J6: BONO VEHICULAR | K6: Columna1 | N6: DEPARTAMENTOS RECIBEN BONO | O6: BONOS
B7: 1 | C7: 955741970 | D7: =+VLOOKUP(Tabla15[[#This Row],[CEDULA]],'OCTUBRE 2025'!$C$8:$J$57,2,0) -> CHACAGUASAY CHACAGUASAY ROBERTH CRISTHIAN | E7: 01/MARZO/2023 | F7: =+VLOOKUP(Tabla15[[#This Row],[CEDULA]],'OCTUBRE 2025'!$C$8:$J$57,4,0) -> OFICIAL DE RECAUDACIONES | G7: Matriz | H7: =+VLOOKUP(Tabla15[[#This Row],[CEDULA]],'OCTUBRE 2025'!$C$8:$J$57,7,0) -> 30 | I7: =+VLOOKUP(Tabla15[[#This Row],[CEDULA]],'OCTUBRE 2025'!$C$8:$J$57,8,0) -> 473.88 | J7: =100 -> 100 | N7: EJECUTIVO DE CAPTACIONES | O7: 100
B8: 2 | C8: 944143148 | D8: =+VLOOKUP(Tabla15[[#This Row],[CEDULA]],'OCTUBRE 2025'!$C$8:$J$57,2,0) -> CHIMBOLEMA YUNGAN MARIO EFRAIN | E8: 27/ABRIL/2023 | F8: EJECUTIVO DE RECAUDACION | G8: Matriz | H8: =+VLOOKUP(Tabla15[[#This Row],[CEDULA]],'OCTUBRE 2025'!$C$8:$J$57,7,0) -> 9 | I8: =+VLOOKUP(Tabla15[[#This Row],[CEDULA]],'OCTUBRE 2025'!$C$8:$J$57,8,0) -> 142.16 | J8: =+(3.33333333333333)*Tabla15[[#This Row],[DIAS TRABAJADOS]] -> 30 | N8: ASESOR LEGAL | O8: 200
B9: 3 | C9: 950929232 | D9: =+VLOOKUP(Tabla15[[#This Row],[CEDULA]],'OCTUBRE 2025'!$C$8:$J$57,2,0) -> GARCIA VERA HENRY LUIS | E9: 14/JUNIO/2022 | F9: EJECUTIVO DE RECAUDACION | G9: Norte | H9: =+VLOOKUP(Tabla15[[#This Row],[CEDULA]],'OCTUBRE 2025'!$C$8:$J$57,7,0) -> 30 | I9: =+VLOOKUP(Tabla15[[#This Row],[CEDULA]],'OCTUBRE 2025'!$C$8:$J$57,8,0) -> 715.54 | J9: 0 | N9: JEFE DE AGENCIA | O9: 200
B10: 4 | C10: 953819646 | D10: =+VLOOKUP(Tabla15[[#This Row],[CEDULA]],'OCTUBRE 2025'!$C$8:$J$57,2,0) -> GUALACEO ÑAMO JONATHAN IVÁN | E10: 17/MARZO/2022 | F10: EJECUTIVO DE RECAUDACION | G10: Matriz | H10: =+VLOOKUP(Tabla15[[#This Row],[CEDULA]],'OCTUBRE 2025'!$C$8:$J$57,7,0) -> 30 | I10: =+VLOOKUP(Tabla15[[#This Row],[CEDULA]],'OCTUBRE 2025'!$C$8:$J$57,8,0) -> 511.1 | J10: =100 -> 100 | N10: JEFE DE BOVEDA | O10: 300
B11: 5 | C11: 956796767 | D11: =+VLOOKUP(Tabla15[[#This Row],[CEDULA]],'OCTUBRE 2025'!$C$8:$J$57,2,0) -> GUAYANLEMA RUIZ EDINSON DAVID | E11: 21/JULIO/2022 | F11: EJECUTIVO DE RECAUDACION | G11: Norte | H11: =+VLOOKUP(Tabla15[[#This Row],[CEDULA]],'OCTUBRE 2025'!$C$8:$J$57,7,0) -> 30 | I11: =+VLOOKUP(Tabla15[[#This Row],[CEDULA]],'OCTUBRE 2025'!$C$8:$J$57,8,0) -> 473.88 | J11: =100 -> 100 | N11: JEFE DE RECAUDACIÓN | O11: 200
B12: 6 | C12: 957093800 | D12: =+VLOOKUP(Tabla15[[#This Row],[CEDULA]],'OCTUBRE 2025'!$C$8:$J$57,2,0) -> LEMA TADAY BRAYAN WIDINSON | E12: 01/MAYO/2023 | F12: EJECUTIVO DE RECAUDACION | G12: Durán | H12: =+VLOOKUP(Tabla15[[#This Row],[CEDULA]],'OCTUBRE 2025'!$C$8:$J$57,7,0) -> 30 | I12: =+VLOOKUP(Tabla15[[#This Row],[CEDULA]],'OCTUBRE 2025'!$C$8:$J$57,8,0) -> 473.88 | J12: =+(3.33333333333333)*Tabla15[[#This Row],[DIAS TRABAJADOS]]-60 -> 40
B13: 7 | C13: 603838657 | D13: =+VLOOKUP(Tabla15[[#This Row],[CEDULA]],'OCTUBRE 2025'!$C$8:$J$57,2,0) -> MALAN DELGADO JOSE ALBERTO | E13: 01/OCTUBRE/2022 | F13: EJECUTIVO DE RECAUDACION | G13: Durán | H13: =+VLOOKUP(Tabla15[[#This Row],[CEDULA]],'OCTUBRE 2025'!$C$8:$J$57,7,0) -> 30 | I13: =+VLOOKUP(Tabla15[[#This Row],[CEDULA]],'OCTUBRE 2025'!$C$8:$J$57,8,0) -> 473.88 | J13: 200
B14: 8 | C14: 925240525 | D14: =+VLOOKUP(Tabla15[[#This Row],[CEDULA]],'OCTUBRE 2025'!$C$8:$J$57,2,0) -> MALAN YUQUILEMA RAUL ALBERTO | E14: 01/JUNIO/2006 | F14: ASESOR LEGAL | G14: Matriz | H14: =+VLOOKUP(Tabla15[[#This Row],[CEDULA]],'OCTUBRE 2025'!$C$8:$J$57,7,0) -> 30 | I14: =+VLOOKUP(Tabla15[[#This Row],[CEDULA]],'OCTUBRE 2025'!$C$8:$J$57,8,0) -> 2700 | J14: =200-200 -> 0
C15: 0943906032 | D15: =+VLOOKUP(Tabla15[[#This Row],[CEDULA]],'OCTUBRE 2025'!$C$8:$J$57,2,0) -> MEZA RODRIGUEZ MICHAEL FERNANDO | F15: EJECUTIVO DE RECAUDACION | G15: Norte | H15: 30 | I15: 473.88 | J15: =100 -> 100
B16: 9 | C16: 950703199 | D16: =+VLOOKUP(Tabla15[[#This Row],[CEDULA]],'OCTUBRE 2025'!$C$8:$J$57,2,0) -> ÑAMO GUALACEO BRYAN JAVIER | E16: 13/OCTUBRE/2022 | F16: EJECUTIVO DE RECAUDACION | G16: Matriz | H16: =+VLOOKUP(Tabla15[[#This Row],[CEDULA]],'OCTUBRE 2025'!$C$8:$J$57,7,0) -> 30 | I16: =+VLOOKUP(Tabla15[[#This Row],[CEDULA]],'OCTUBRE 2025'!$C$8:$J$57,8,0) -> 473.88 | J16: =100 -> 100
B17: 10 | C17: 925830689 | D17: =+VLOOKUP(Tabla15[[#This Row],[CEDULA]],'OCTUBRE 2025'!$C$8:$J$57,2,0) -> PERALTA MENDEZ LINA LISSETTE | E17: 01/AGOSTO/2019 | F17: JEFE DE AGENCIA | G17: Matriz | H17: =+VLOOKUP(Tabla15[[#This Row],[CEDULA]],'OCTUBRE 2025'!$C$8:$J$57,7,0) -> 30 | I17: =+VLOOKUP(Tabla15[[#This Row],[CEDULA]],'OCTUBRE 2025'!$C$8:$J$57,8,0) -> 1022.2 | J17: 0
B18: 12 | C18: 951340702 | D18: =+VLOOKUP(Tabla15[[#This Row],[CEDULA]],'OCTUBRE 2025'!$C$8:$J$57,2,0) -> QUITO CALDERON JONATHAN ENRIQUE | E18: 18/ENERO/2022 | F18: JEFE DE CAPTACIONES | G18: Matriz | H18: =+VLOOKUP(Tabla15[[#This Row],[CEDULA]],'OCTUBRE 2025'!$C$8:$J$57,7,0) -> 30 | I18: =+VLOOKUP(Tabla15[[#This Row],[CEDULA]],'OCTUBRE 2025'!$C$8:$J$57,8,0) -> 817.76 | J18: 0
B19: 13 | C19: 927257576 | D19: =+VLOOKUP(Tabla15[[#This Row],[CEDULA]],'OCTUBRE 2025'!$C$8:$J$57,2,0) -> SANISACA MITE ISRAEL BENJAMIN | E19: 04/NOVIEMBRE/2020 | F19: JEFE DE AGENCIA | G19: Norte | H19: =+VLOOKUP(Tabla15[[#This Row],[CEDULA]],'OCTUBRE 2025'!$C$8:$J$57,7,0) -> 30 | I19: =+VLOOKUP(Tabla15[[#This Row],[CEDULA]],'OCTUBRE 2025'!$C$8:$J$57,8,0) -> 1022.2 | J19: =200-200 -> 0
B20: 14 | C20: 928901800 | D20: =+VLOOKUP(Tabla15[[#This Row],[CEDULA]],'OCTUBRE 2025'!$C$8:$J$57,2,0) -> TADAY GUAMAN NÉSTOR ALONSO | E20: 01/MAYO/2017 | F20: JEFE DE BOVEDA | G20: Matriz | H20: =+VLOOKUP(Tabla15[[#This Row],[CEDULA]],'OCTUBRE 2025'!$C$8:$J$57,7,0) -> 30 | I20: =+VLOOKUP(Tabla15[[#This Row],[CEDULA]],'OCTUBRE 2025'!$C$8:$J$57,8,0) -> 511.1 | J20: =300-100-100 -> 100
B21: 15 | C21: 954184321 | D21: =+VLOOKUP(Tabla15[[#This Row],[CEDULA]],'OCTUBRE 2025'!$C$8:$J$57,2,0) -> URQUIZO GUARANGA ALEX EFRAIN | E21: 01/JULIO/2021 | F21: EJECUTIVO DE RECAUDACION | G21: Matriz | H21: =+VLOOKUP(Tabla15[[#This Row],[CEDULA]],'OCTUBRE 2025'!$C$8:$J$57,7,0) -> 30 | I21: =+VLOOKUP(Tabla15[[#This Row],[CEDULA]],'OCTUBRE 2025'!$C$8:$J$57,8,0) -> 511.1 | J21: =100 -> 100
B22: 16 | C22: 941508905 | D22: =+VLOOKUP(Tabla15[[#This Row],[CEDULA]],'OCTUBRE 2025'!$C$8:$J$57,2,0) -> YUQUILEMA CACUANGO ANGEL JOSE | E22: 12/ABRIL/2019 | F22: EJECUTIVO DE RECAUDACION | G22: Matriz | H22: =+VLOOKUP(Tabla15[[#This Row],[CEDULA]],'OCTUBRE 2025'!$C$8:$J$57,7,0) -> 30 | I22: =+VLOOKUP(Tabla15[[#This Row],[CEDULA]],'OCTUBRE 2025'!$C$8:$J$57,8,0) -> 511.1 | J22: =(100/30)*Tabla15[[#This Row],[DIAS TRABAJADOS]] -> 100
B23: 18 | C23: 604154575 | D23: =+VLOOKUP(Tabla15[[#This Row],[CEDULA]],'OCTUBRE 2025'!$C$8:$J$57,2,0) -> YUQUILEMA DELGADO PEDRO ANTONIO | E23: 06/OCTUBRE/2018 | F23: JEFE DE AGENCIA | G23: Durán | H23: =+VLOOKUP(Tabla15[[#This Row],[CEDULA]],'OCTUBRE 2025'!$C$8:$J$57,7,0) -> 30 | I23: =+VLOOKUP(Tabla15[[#This Row],[CEDULA]],'OCTUBRE 2025'!$C$8:$J$57,8,0) -> 1022.2 | J23: =200-200 -> 0
D25: TOTALES | J25: =SUM(Tabla15[BONO VEHICULAR]) -> 1070
B44: 4

Sheet COMISIONES
B2: CALCULO DE APERTURA CUENTA- COLOCACIONES - PLAZO FIJO
B3: NOMINA AGOSTO 2023
B4: DEL CORTE DEL 01 DE AGOSTO AL 31 DE AGOSTO DEL 2023
B6: No. | C6: CEDULA | D6: NOMBRE | E6: BONO POR CUMPLIMIENTO | F6: COMISIÓN META | G6: COMISION POR PLAZOS FIJOS | H6: COM. SOCIOS NUEVOS Y COLOCACION | I6: ANTICIPO A SUELDO
B8: 1 | C8: =+'OCTUBRE 2025'!C8 -> 925813685 | D8: =+VLOOKUP(C8,'OCTUBRE 2025'!$C$8:$F$57,2,0) -> ASITIMBAY CRIOLLO JOHN ANDERSON
B9: 2 | C9: =+'OCTUBRE 2025'!C9 -> 944405737 | D9: =+VLOOKUP(C9,'OCTUBRE 2025'!$C$8:$F$57,2,0) -> BARAHONA ZAMBRANO DAYANA NICOLE
B10: 3 | C10: =+'OCTUBRE 2025'!C10 -> 604394502 | D10: =+VLOOKUP(C10,'OCTUBRE 2025'!$C$8:$F$57,2,0) -> BETUN CHAFLA JULIO CESAR
B11: 4 | C11: =+'OCTUBRE 2025'!#REF! -> #REF! | D11: =+VLOOKUP(C11,'OCTUBRE 2025'!$C$8:$F$57,2,0) -> #REF! | E11: 100 | F11: 236.65 | H11: 30
B12: 5 | C12: =+'OCTUBRE 2025'!C11 -> 955741970 | D12: =+VLOOKUP(C12,'OCTUBRE 2025'!$C$8:$F$57,2,0) -> CHACAGUASAY CHACAGUASAY ROBERTH CRISTHIAN | E12: 100 | F12: 99.5
B13: 6 | C13: =+'OCTUBRE 2025'!C15 -> 914163654 | D13: =+VLOOKUP(C13,'OCTUBRE 2025'!$C$8:$F$57,2,0) -> COCA BENITEZ JORGE MANUEL
B14: 7 | C14: =+'OCTUBRE 2025'!C19 -> 1105483422 | D14: =+VLOOKUP(C14,'OCTUBRE 2025'!$C$8:$F$57,2,0) -> FLORES HERRERA WENDY DEL CISNE
B15: 8 | C15: =+'OCTUBRE 2025'!C20 -> 942614645 | D15: =+VLOOKUP(C15,'OCTUBRE 2025'!$C$8:$F$57,2,0) -> FUELA TOABANDA JOSUE CHRISTIAN
B16: 9 | C16: =+'OCTUBRE 2025'!C21 -> 951200062 | D16: =+VLOOKUP(C16,'OCTUBRE 2025'!$C$8:$F$57,2,0) -> GALAN LEMACHE INGRID GISELA
B17: 10 | C17: =+'OCTUBRE 2025'!C22 -> 950929232 | D17: =+VLOOKUP(C17,'OCTUBRE 2025'!$C$8:$F$57,2,0) -> GARCIA VERA HENRY LUIS
B18: 11 | C18: =+'OCTUBRE 2025'!C23 -> 953819646 | D18: =+VLOOKUP(C18,'OCTUBRE 2025'!$C$8:$F$57,2,0) -> GUALACEO ÑAMO JONATHAN IVÁN
B19: 12 | C19: =+'OCTUBRE 2025'!#REF! -> #REF! | D19: =+VLOOKUP(C19,'OCTUBRE 2025'!$C$8:$F$57,2,0) -> #REF!
B20: 13 | C20: =+'OCTUBRE 2025'!C24 -> 956953392 | D20: =+VLOOKUP(C20,'OCTUBRE 2025'!$C$8:$F$57,2,0) -> GUAPI YUMAGLLA OSCAR EDUARDO
B21: 14 | C21: =+'OCTUBRE 2025'!#REF! -> #REF! | D21: =+VLOOKUP(C21,'OCTUBRE 2025'!$C$8:$F$57,2,0) -> #REF!
B22: 15 | C22: =+'OCTUBRE 2025'!C25 -> 956796767 | D22: =+VLOOKUP(C22,'OCTUBRE 2025'!$C$8:$F$57,2,0) -> GUAYANLEMA RUIZ EDINSON DAVID | F22: 7.31
B23: 16 | C23: =+'OCTUBRE 2025'!C27 -> 1724102940 | D23: =+VLOOKUP(C23,'OCTUBRE 2025'!$C$8:$F$57,2,0) -> HIDALGO CHERRES NESTOR VLADIMIR
B24: 17 | C24: =+'OCTUBRE 2025'!C28 -> 943322974 | D24: =+VLOOKUP(C24,'OCTUBRE 2025'!$C$8:$F$57,2,0) -> JANETA RUIZ ALEXANDRA DEL ROCIO | F24: 10.84
B25: 18 | C25: =+'OCTUBRE 2025'!C29 -> 941096851 | D25: =+VLOOKUP(C25,'OCTUBRE 2025'!$C$8:$F$57,2,0) -> LEMA CHIRAU RAMONA MARIA
B26: 19 | C26: =+'OCTUBRE 2025'!#REF! -> #REF! | D26: =+VLOOKUP(C26,'OCTUBRE 2025'!$C$8:$F$57,2,0) -> #REF!
B27: 20 | C27: =+'OCTUBRE 2025'!C32 -> 603838657 | D27: =+VLOOKUP(C27,'OCTUBRE 2025'!$C$8:$F$57,2,0) -> MALAN DELGADO JOSE ALBERTO
B28: 21 | C28: =+'OCTUBRE 2025'!C33 -> 925240525 | D28: =+VLOOKUP(C28,'OCTUBRE 2025'!$C$8:$F$57,2,0) -> MALAN YUQUILEMA RAUL ALBERTO
B29: 22 | C29: =+'OCTUBRE 2025'!C34 -> 954520599 | D29: =+VLOOKUP(C29,'OCTUBRE 2025'!$C$8:$F$57,2,0) -> MARSHALL VEGA YULIANA LISSETT
B30: 23 | C30: =+'OCTUBRE 2025'!#REF! -> #REF! | D30: =+VLOOKUP(C30,'OCTUBRE 2025'!$C$8:$F$57,2,0) -> #REF! | E30: 100 | F30: 518.5
B31: 24 | C31: =+'OCTUBRE 2025'!C35 -> 0943906032 | D31: =+VLOOKUP(C31,'OCTUBRE 2025'!$C$8:$F$57,2,0) -> MEZA RODRIGUEZ MICHAEL FERNANDO
B32: 25 | C32: =+'OCTUBRE 2025'!C36 -> 0919306050 | D32: =+VLOOKUP(C32,'OCTUBRE 2025'!$C$8:$F$57,2,0) -> MORAN GARCIA DANNY FAVIAN
B33: 26 | C33: =+'OCTUBRE 2025'!C37 -> 0941235376 | D33: =+VLOOKUP(C33,'OCTUBRE 2025'!$C$8:$F$57,2,0) -> MOREIRA ESPINOZA LINDA ELIZABETH
B34: 27 | C34: =+'OCTUBRE 2025'!C38 -> 955395686 | D34: =+VLOOKUP(C34,'OCTUBRE 2025'!$C$8:$F$57,2,0) -> MOROCHO DUCHI SANDRA STEPHANIE
B35: 28 | C35: =+'OCTUBRE 2025'!C39 -> 940991987 | D35: =+VLOOKUP(C35,'OCTUBRE 2025'!$C$8:$F$57,2,0) -> MOROCHO YANTALEMA DINA MAGALY
B36: 29 | C36: =+'OCTUBRE 2025'!#REF! -> #REF! | D36: =+VLOOKUP(C36,'OCTUBRE 2025'!$C$8:$F$57,2,0) -> #REF!
B37: 30 | C37: =+'OCTUBRE 2025'!C41 -> 951763994 | D37: =+VLOOKUP(C37,'OCTUBRE 2025'!$C$8:$F$57,2,0) -> NEVAREZ PEÑAFIEL EVELYN JULEXY
B38: 31 | C38: =+'OCTUBRE 2025'!C42 -> 950703199 | D38: =+VLOOKUP(C38,'OCTUBRE 2025'!$C$8:$F$57,2,0) -> ÑAMO GUALACEO BRYAN JAVIER | F38: 60.37
B39: 32 | C39: =+'OCTUBRE 2025'!C44 -> 925830689 | D39: =+VLOOKUP(C39,'OCTUBRE 2025'!$C$8:$F$57,2,0) -> PERALTA MENDEZ LINA LISSETTE
B40: 33 | C40: =+'OCTUBRE 2025'!C46 -> 951340702 | D40: =+VLOOKUP(C40,'OCTUBRE 2025'!$C$8:$F$57,2,0) -> QUITO CALDERON JONATHAN ENRIQUE | E40: 100 | F40: 75
B41: 34 | C41: =+'OCTUBRE 2025'!C47 -> 650112949 | D41: =+VLOOKUP(C41,'OCTUBRE 2025'!$C$8:$F$57,2,0) -> QUITO UCHUBANDA JANETH ALEXANDRA
B42: 35 | C42: =+'OCTUBRE 2025'!C48 -> 924232804 | D42: =+VLOOKUP(C42,'OCTUBRE 2025'!$C$8:$F$57,2,0) -> RECALDE NARANJO ANGEL ALEXIS
B43: 36 | C43: =+'OCTUBRE 2025'!C49 -> 605031145 | D43: =+VLOOKUP(C43,'OCTUBRE 2025'!$C$8:$F$57,2,0) -> SALAO PEREZ GERMAN FABRICIO
B44: 37 | C44: =+'OCTUBRE 2025'!C50 -> 927257576 | D44: =+VLOOKUP(C44,'OCTUBRE 2025'!$C$8:$F$57,2,0) -> SANISACA MITE ISRAEL BENJAMIN
B45: 38 | C45: =+'OCTUBRE 2025'!#REF! -> #REF! | D45: =+VLOOKUP(C45,'OCTUBRE 2025'!$C$8:$F$57,2,0) -> #REF! | E45: 100 | F45: 222.5
B46: 39 | C46: =+'OCTUBRE 2025'!C51 -> 928901800 | D46: =+VLOOKUP(C46,'OCTUBRE 2025'!$C$8:$F$57,2,0) -> TADAY GUAMAN NÉSTOR ALONSO | F46: 203.97
B47: 40 | C47: =+'OCTUBRE 2025'!C52 -> 951315746 | D47: =+VLOOKUP(C47,'OCTUBRE 2025'!$C$8:$F$57,2,0) -> TIGUA MONTERO KAREN LISBETH
B48: 41 | C48: =+'OCTUBRE 2025'!C53 -> 954184321 | D48: =+VLOOKUP(C48,'OCTUBRE 2025'!$C$8:$F$57,2,0) -> URQUIZO GUARANGA ALEX EFRAIN
B49: 42 | C49: =+'OCTUBRE 2025'!C54 -> 922034772 | D49: =+VLOOKUP(C49,'OCTUBRE 2025'!$C$8:$F$57,2,0) -> VERA GUEVARA PAOLA KARINA
B50: 43 | C50: =+'OCTUBRE 2025'!#REF! -> #REF! | D50: =+VLOOKUP(C50,'OCTUBRE 2025'!$C$8:$F$57,2,0) -> #REF! | F50: 50.03
B51: 44 | C51: =+'OCTUBRE 2025'!#REF! -> #REF! | D51: =+VLOOKUP(C51,'OCTUBRE 2025'!$C$8:$F$57,2,0) -> #REF!
B52: 45 | C52: =+'OCTUBRE 2025'!C55 -> 923837991 | D52: =+VLOOKUP(C52,'OCTUBRE 2025'!$C$8:$F$57,2,0) -> YUNDA CUJILEMA MARIA TERESA
D54: TOTALES | E54: =SUM(E8:E52) -> 500 | F54: =SUM(F8:F50) -> 1484.67 | G54: =SUM(G8:G50) -> 0 | H54: =SUM(H8:H52) -> 30 | I54: =SUM(I8:I52) -> 0

Sheet ROL INDIVIDUAL
F5: ROL INDIVIDUAL | H5: 45931
C7: Identificación: | D7: 955325238 | F7: Oficina: | G7: =VLOOKUP($D$7,'OCTUBRE 2025'!$C$8:$AJ$57,6,0) -> Matriz
C8: Nombres: | D8: ='OCTUBRE 2025'!F12 -> ASESOR DE NEGOCIOS | F8: No. días: | G8: =VLOOKUP($D$7,'OCTUBRE 2025'!$C$8:$AJ$57,7,0) -> 16
C9: Cargo: | D9: =VLOOKUP($D$7,'OCTUBRE 2025'!$C$8:$AJ$57,4,0) -> CAJERA FINANCIERA
C11: INGRESOS | E11: VALOR | F11: EGRESOS | H11: VALOR
C12: Sueldo básico cooperativa | E12: =VLOOKUP($D$7,'OCTUBRE 2025'!$C$8:$AJ$57,8,0) -> 256.53 | F12: Aporte Individual IESS 9.45% | H12: =VLOOKUP($D$7,'OCTUBRE 2025'!$C$8:$AJ$57,24,0) -> 24.242085
C13: Bono Movilización | E13: =VLOOKUP($D$7,'OCTUBRE 2025'!$C$8:$AJ$57,9,0) -> 0 | F13: Préstamos Quirografarios o Hipotecarios | H13: =VLOOKUP($D$7,'OCTUBRE 2025'!$C$8:$AJ$57,27,0) -> 0
C14: Bono mensual (2.174%) | E14: =VLOOKUP($D$7,'OCTUBRE 2025'!$C$8:$AJ$57,10,0) -> 0 | F14: Subsidio Monetario | H14: =VLOOKUP($D$7,'OCTUBRE 2025'!$C$8:$AJ$57,28,0) -> 0
C15: Bono cumplimiento | E15: =VLOOKUP($D$7,'OCTUBRE 2025'!$C$8:$AJ$57,11,0) -> 0 | F15: Extensión de Salud | H15: =VLOOKUP($D$7,'OCTUBRE 2025'!$C$8:$AJ$57,29,0) -> 0
C16: Comisión por superación de meta | E16: =VLOOKUP($D$7,'OCTUBRE 2025'!$C$8:$AJ$57,12,0) -> 0 | F16: Pensión alimenticia | H16: =VLOOKUP($D$7,'OCTUBRE 2025'!$C$8:$AJ$57,30,0) -> 0
C17: Comisión por Depósito a Plazo Fijo | E17: =VLOOKUP($D$7,'OCTUBRE 2025'!$C$8:$AJ$57,13,0) -> 0 | F17: Cuentas por cobrar | H17: =VLOOKUP($D$7,'OCTUBRE 2025'!$C$8:$AJ$57,31,0) -> 0
C18: Comisión socios nuevos | E18: =VLOOKUP($D$7,'OCTUBRE 2025'!$C$8:$AJ$57,14,0) -> 0 | F18: Anticipo de Sueldo | H18: =VLOOKUP($D$7,'OCTUBRE 2025'!$C$8:$AJ$57,32,0) -> 0
C19: Horas Extras 50% | E19: =VLOOKUP($D$7,'OCTUBRE 2025'!$C$8:$AJ$57,15,0) -> 0 | F19: Ret Imp. A la Renta | H19: =VLOOKUP($D$7,'OCTUBRE 2025'!$C$8:$AJ$57,25,0) -> 0
C20: Horas Extras 100% | E20: =VLOOKUP($D$7,'OCTUBRE 2025'!$C$8:$AJ$57,16,0) -> 0 | F20: Descuentos | H20: =VLOOKUP($D$7,'OCTUBRE 2025'!$C$8:$AJ$57,26,0) -> 0
C21: Fondo de Reserva | E21: =VLOOKUP($D$7,'OCTUBRE 2025'!$C$8:$AJ$57,19,0) -> 0
C22: Fondo de Reserva (ajustes) | E22: =VLOOKUP($D$7,'OCTUBRE 2025'!$C$8:$AJ$57,20,0) -> 0
C23: Décimo Tercero | E23: =VLOOKUP($D$7,'OCTUBRE 2025'!$C$8:$AJ$57,21,0) -> 0
C24: Décimo Cuarto | E24: =VLOOKUP($D$7,'OCTUBRE 2025'!$C$8:$AJ$57,22,0) -> 0
C25: TOTAL DE INGRESOS | E25: =SUM(E12:E24) -> 256.53 | F25: TOTAL EGRESOS | H25: =SUM(H12:H23) -> 24.242085
F26: VALOR NETO A RECIBIR | H26: =+E25-H25 -> 232.28791
C28: Elaborado por: | G28: Recibí Conforme:
C31: Ing. Magaly Morocho | G31: =+$D$8 -> ASESOR DE NEGOCIOS
C32: Talento Humano | G32: Funcionario

Sheet ROL INDIVIDUAL (2)
F5: ROL INDIVIDUAL | H5: 45839
C7: Identificación: | D7: 0943906032 | F7: Oficina: | G7: =VLOOKUP($D$7,'OCTUBRE 2025'!$C$8:$AJ$57,6,0) -> Norte
C8: Nombres: | D8: =VLOOKUP($D$7,'OCTUBRE 2025'!$C$8:$AJ$57,2,0) -> MEZA RODRIGUEZ MICHAEL FERNANDO | F8: No. días: | G8: =VLOOKUP($D$7,'OCTUBRE 2025'!$C$8:$AJ$57,7,0) -> 30
C9: Cargo: | D9: =VLOOKUP($D$7,'OCTUBRE 2025'!$C$8:$AJ$57,4,0) -> OFICIAL DE RECAUDACIONES
C11: INGRESOS | E11: VALOR | F11: EGRESOS | H11: VALOR
C12: Sueldo básico cooperativa | E12: =VLOOKUP($D$7,'OCTUBRE 2025'!$C$8:$AJ$57,8,0) -> 473.88 | F12: Aporte Individual IESS 9.45% | H12: =VLOOKUP($D$7,'OCTUBRE 2025'!$C$8:$AJ$57,24,0) -> 55.20501
C13: Bono Movilización | E13: =VLOOKUP($D$7,'OCTUBRE 2025'!$C$8:$AJ$57,9,0) -> 100 | F13: Préstamos Quirografarios o Hipotecarios | H13: =VLOOKUP($D$7,'OCTUBRE 2025'!$C$8:$AJ$57,27,0) -> 0
C14: Bono mensual (2.174%) | E14: =VLOOKUP($D$7,'OCTUBRE 2025'!$C$8:$AJ$57,10,0) -> 10.3 | F14: Subsidio Monetario | H14: =VLOOKUP($D$7,'OCTUBRE 2025'!$C$8:$AJ$57,28,0) -> 0
C15: Bono cumplimiento | E15: =VLOOKUP($D$7,'OCTUBRE 2025'!$C$8:$AJ$57,11,0) -> 0 | F15: Extensión de Salud | H15: =VLOOKUP($D$7,'OCTUBRE 2025'!$C$8:$AJ$57,29,0) -> 0
C16: Comisión por cumplimiento de meta | E16: =VLOOKUP($D$7,'OCTUBRE 2025'!$C$8:$AJ$57,12,0) -> 0 | F16: Pensión alimenticia | H16: =VLOOKUP($D$7,'OCTUBRE 2025'!$C$8:$AJ$57,30,0) -> 0
C17: Comisión por Depósito a Plazo Fijo | E17: =VLOOKUP($D$7,'OCTUBRE 2025'!$C$8:$AJ$57,13,0) -> 0 | F17: Cuentas por cobrar | H17: =VLOOKUP($D$7,'OCTUBRE 2025'!$C$8:$AJ$57,31,0) -> 0
C18: Comisión socios nuevos | E18: =VLOOKUP($D$7,'OCTUBRE 2025'!$C$8:$AJ$57,14,0) -> 0 | F18: Anticipo de Sueldo | H18: 0
C19: Horas Extras 50% | E19: =VLOOKUP($D$7,'OCTUBRE 2025'!$C$8:$AJ$57,15,0) -> 0 | F19: Ret Imp. A la Renta | H19: =VLOOKUP($D$7,'OCTUBRE 2025'!$C$8:$AJ$57,25,0) -> 0
C20: Horas Extras 100% | E20: =VLOOKUP($D$7,'OCTUBRE 2025'!$C$8:$AJ$57,16,0) -> 0 | F20: Descuentos | H20: =VLOOKUP($D$7,'OCTUBRE 2025'!$C$8:$AJ$57,26,0) -> 0
C21: Fondo de Reserva | E21: =VLOOKUP($D$7,'OCTUBRE 2025'!$C$8:$AJ$57,19,0) -> 48.662194
C22: Fondo de Reserva (ajustes) | E22: =VLOOKUP($D$7,'OCTUBRE 2025'!$C$8:$AJ$57,20,0) -> 0
C23: Décimo Tercero | E23: =VLOOKUP($D$7,'OCTUBRE 2025'!$C$8:$AJ$57,21,0) -> 0
C24: Décimo Cuarto | E24: =VLOOKUP($D$7,'OCTUBRE 2025'!$C$8:$AJ$57,22,0) -> 0
C25: TOTAL DE INGRESOS | E25: =SUM(E12:E24) -> 632.84219 | F25: TOTAL EGRESOS | H25: =SUM(H12:H23) -> 55.20501
F26: VALOR NETO A RECIBIR | H26: =+E25-H25 -> 577.63718
C28: Elaborado por: | G28: Recibí Conforme:
C31: Ing. Magaly Morocho | G31: =+$D$8 -> MEZA RODRIGUEZ MICHAEL FERNANDO
C32: Talento Humano | G32: Funcionario

Sheet ROL INDIVIDUAL Prueba
F5: ROL INDIVIDUAL
C7: Identificación: | F7: Oficina:
C8: Nombres: | F8: No. días:
C9: Cargo:
C11: INGRESOS | E11: VALOR | F11: EGRESOS | H11: VALOR
C12: Sueldo básico cooperativa | E12: $ | F12: Aporte Individual IESS 9.45% | H12: $
C13: Bono Movilización | E13: $ | F13: Préstamos Quirografarios o Hipotecarios | H13: $
C14: Bono mensual (2.174%) | E14: $ | F14: Subsidio Monetario | H14: $
C15: Bono cumplimiento | E15: $ | F15: Extensión de Salud | H15: $
C16: Comisión por superación de meta | E16: $ | F16: Pensión alimenticia | H16: $
C17: Comisión por Depósito a Plazo Fijo | E17: $ | F17: Cuentas por cobrar | H17: $
C18: Comisión socios nuevos | E18: $ | F18: Anticipo de Sueldo | H18: $
C19: Horas Extras 50% | E19: $ | F19: Ret Imp. A la Renta | H19: $
C20: Horas Extras 100% | E20: $ | F20: Descuentos | H20: $
C21: Fondo de Reserva | E21: $
C22: Fondo de Reserva (ajustes) | E22: $
C23: Décimo Tercero | E23: $
C24: Décimo Cuarto | E24: $
C25: TOTAL DE INGRESOS | E25: $ | F25: TOTAL EGRESOS | H25: $
F26: VALOR NETO A RECIBIR | H26: $
C28: Elaborado por: | G28: Recibí Conforme:
C31: Ing. Magaly Morocho | G31: =+$D$8 -> 0
C32: Talento Humano | G32: Funcionario

Sheet CHIMBOLEMA
B8: Trabajador(a): | C8: CHIMBOLEMA YUNGAN MARIO EFRAIN | F8: Inicio: | G8: 45884
B9: Fecha de ingreso: | C9: 45884 | F9: Fin: | G9: 45681
B10: Sueldo: | C10: 473.88 | F10: Total de dias | G10: =+_xlfn.DAYS(G9,G8) -> -203
B11: Subsidio: | C11: MATERNIDAD
B13: Calculo para el Pago:
B14: Sueldo Promedio Diario: | D14: =+C10/30 -> 15.796 | E14: (1-3 dias) | F14: =+C10/30 -> 15.796
B15: Promedio Diario (25%): | D15: =+D14*25% -> 3.949 | E15: (4-70 dias) | F15: =+F14*25% -> 3.949
B17: Nº | C17: Periodo | E17: Pocentaje | F17: Num. Dias | G17: Valor | M17: Nº | N17: Periodo | P17: Pocentaje | Q17: Num. Dias | R17: Valor
C18: Desde | D18: Hasta | N18: Desde | O18: Hasta
B19: 1 | C19: 45931 | D19: 45939 | E19: 100 | F19: =+D19-C19+1 -> 9 | G19: =+F14*F19 -> 142.164 | M19: 1 | N19: 45593 | O19: 45596 | P19: 25 | Q19: 4 | R19: =+Q15*Q19 -> 0
B20: 2 | M20: 2 | N20: 45597 | O20: 45626 | P20: 25 | Q20: 30 | R20: =+Q15*Q20 -> 0
B21: 3 | M21: 3 | N21: 45992 | O21: 45657 | P21: 25 | Q21: 31 | R21: =+Q21*Q15 -> 0
B22: 4 | M22: 4 | N22: 45658 | O22: 45676 | P22: 25 | Q22: 19 | R22: =+Q22*Q14 -> 0
B27: TOTAL | F27: =SUM(F19:F22) -> 9 | G27: =SUM(G19:G26) -> 142.164 | M27: TOTAL | Q27: =SUM(Q19:Q24) -> 84 | R27: =SUM(R19:R26) -> 0
B29: ROL PROPORCIONAL OCTUBRE 2024
B31: INGRESOS | C31: VALOR | D31: EGRESOS | E31: VALOR
B32: SUELDO BÁSICO COOPERATIVA | C32: =+G19 -> 142.164 | D32: APORTE INDIVIDUAL AL IESS 9.45 | E32: =+((C32+C33+C34+C39)*9.45%) -> 16.269498
B33: BONO MOVILIZACION | C33: =+(3.33333333333333)*9 -> 30 | D33: CUENTAS POR COBRAR | E33: 0
B34: BONO CUMPLIMIENTO | C34: 0
B35: COMISION POR SUPERAR LA META | C35: 0
B36: COMISION POR PLAZOS FIJOS | C36: 0 | D36: anticipo | E36: 0
B37: COMISION POR SOCIOS NUEVOS | C37: 0
B38: HORAS EXTRAS 50% | C38: 0
B39: HORAS EXTRAS 100% | C39: 0
B40: FONDO DE RESERVA | C40: 0
B41: DECIMO TERCERO | C41: 0
B42: DECIMO CUARTO | C42: 0
B43: TOTAL INGRESOS | C43: =SUM(C32:C42) -> 172.164 | D43: TOTAL EGRESOS | E43: =SUM(E32:E42) -> 16.269498
D44: VALOR NETO A RECIBIR | E44: =+C43-E43 -> 155.8945
E48: 645.95749

Sheet coca
B8: Trabajador(a): | C8: COCA BENITEZ JORGE | F8: Inicio:
B9: Fecha de ingreso: | C9: 45762 | F9: Fin:
B10: Sueldo: | C10: 715.54 | F10: Total de dias | G10: =+_xlfn.DAYS(G9,G8)+1 -> 1
B11: Subsidio: | C11: MATERNIDAD
B13: Calculo para el Pago: | H13: =+C10/30 -> 23.851333
B14: Sueldo Promedio Diario: | D14: =+C10/30 -> 23.851333 | E14: (1-3 dias) | F14: =+C10/30 -> 23.851333
B15: Promedio Diario (25%): | D15: =+D14*25% -> 5.9628333 | E15: (4-70 dias) | F15: =+F14*25% -> 5.9628333
B17: Nº | C17: Periodo | E17: Pocentaje | F17: Num. Dias | G17: Valor | M17: Nº | N17: Periodo | P17: Pocentaje | Q17: Num. Dias | R17: Valor
C18: Desde | D18: Hasta | N18: Desde | O18: Hasta
B19: 1 | C19: 45658 | D19: 45674 | E19: 100 | F19: 17 | G19: =+F14*F19 -> 405.47267 | M19: 1 | N19: 45593 | O19: 45596 | P19: 25 | Q19: 4 | R19: =+Q15*Q19 -> 0
B20: 2 | C20: 45675 | D20: 45688 | E20: 25 | F20: 14 | G20: =+F15*F20 -> 83.479667 | M20: 2 | N20: 45597 | O20: 45626 | P20: 25 | Q20: 30 | R20: =+Q15*Q20 -> 0
B21: 3 | G21: =+F21*F15 -> 0 | M21: 3 | N21: 45992 | O21: 45657 | P21: 25 | Q21: 31 | R21: =+Q21*Q15 -> 0
B22: 4 | G22: =+F22*F14 -> 0 | M22: 4 | N22: 45658 | O22: 45676 | P22: 25 | Q22: 19 | R22: =+Q22*Q14 -> 0
B27: TOTAL | F27: =SUM(F19:F22) -> 31 | G27: =SUM(G19:G26) -> 488.95233 | M27: TOTAL | Q27: =SUM(Q19:Q24) -> 84 | R27: =SUM(R19:R26) -> 0
B29: ROL PROPORCIONAL JUNIO 2024
B31: INGRESOS | C31: VALOR | D31: EGRESOS | E31: VALOR
B32: SUELDO BÁSICO COOPERATIVA | C32: 715.54 | D32: APORTE INDIVIDUAL AL IESS 9.45 | E32: =+((C10*9.45%)) -> 67.61853
B33: BONO MOVILIZACION | C33: 0 | D33: descuento | E33: 0 | H33: =1200-C32 -> 484.46
B34: BONO CUMPLIMIENTO | C34: 0 | E34: 145 | H34: =+ROUND(H33*9.45%,2) -> 45.78
B35: COMISION POR SUPERAR LA META | C35: 0 | H35: =+ROUND(H33*12.15%,2) -> 58.86
B36: COMISION POR PLAZOS FIJOS | C36: 0 | H36: =+H33*8.33% -> 40.355518
B37: COMISION POR SOCIOS NUEVOS | C37: 0
B38: HORAS EXTRAS 50% | C38: 0 | H38: =+SUM(H34:H36) -> 144.99552
B39: HORAS EXTRAS 100% | C39: 0
B40: FONDO DE RESERVA | C40: =+(C32*8.33%) -> 59.604482
B41: DECIMO TERCERO | C41: 0
B42: DECIMO CUARTO | C42: 0
B43: TOTAL INGRESOS | C43: =SUM(C32:C42) -> 775.14448 | D43: TOTAL EGRESOS | E43: =SUM(E32:E42) -> 212.61853 | G43: 1186.55
D44: VALOR NETO A RECIBIR | E44: =+C43-E43 -> 562.52595 | G44: =+G43-E44 -> 624.02405
K47: 602.89
B50: INGRESOS | C50: VALOR | D50: EGRESOS | E50: VALOR
B51: SUELDO BÁSICO COOPERATIVA | C51: 1200 | D51: APORTE INDIVIDUAL AL IESS 9.45 | E51: =+((C51*9.45%)) -> 113.4
B52: BONO MOVILIZACION | C52: 0 | D52: descuento | E52: 36
B53: BONO CUMPLIMIENTO | C53: 0 | E53: 0
B54: COMISION POR SUPERAR LA META | C54: 0
B55: COMISION POR PLAZOS FIJOS | C55: 0
B56: COMISION POR SOCIOS NUEVOS | C56: 0
B57: HORAS EXTRAS 50% | C57: 0
B58: HORAS EXTRAS 100% | C58: 0
B59: FONDO DE RESERVA | C59: =+(C51*8.33%) -> 99.96
B60: DECIMO TERCERO | C60: 0
B61: DECIMO CUARTO | C61: 0
B62: TOTAL INGRESOS | C62: =SUM(C51:C61) -> 1299.96 | D62: TOTAL EGRESOS | E62: =SUM(E51:E61) -> 149.4
D63: VALOR NETO A RECIBIR | E63: =+C62-E62 -> 1150.56 | I63: =+E63-E44 -> 588.03405

Sheet coca (2)
B8: Trabajador(a): | C8: COCA BENITEZ JORGE | F8: Inicio:
B9: Fecha de ingreso: | C9: 45762 | F9: Fin:
B10: Sueldo: | C10: 715.54 | F10: Total de dias | G10: =+_xlfn.DAYS(G9,G8)+1 -> 1
B11: Subsidio: | C11: MATERNIDAD
B13: Calculo para el Pago: | H13: =+C10/30 -> 23.851333
B14: Sueldo Promedio Diario: | D14: =+C10/30 -> 23.851333 | E14: (1-3 dias) | F14: =+C10/30 -> 23.851333
B15: Promedio Diario (25%): | D15: =+D14*25% -> 5.9628333 | E15: (4-70 dias) | F15: =+F14*25% -> 5.9628333
B17: Nº | C17: Periodo | E17: Pocentaje | F17: Num. Dias | G17: Valor | M17: Nº | N17: Periodo | P17: Pocentaje | Q17: Num. Dias | R17: Valor
C18: Desde | D18: Hasta | N18: Desde | O18: Hasta
B19: 1 | C19: 45658 | D19: 45674 | E19: 100 | F19: 17 | G19: =+F14*F19 -> 405.47267 | M19: 1 | N19: 45593 | O19: 45596 | P19: 25 | Q19: 4 | R19: =+Q15*Q19 -> 0
B20: 2 | C20: 45675 | D20: 45688 | E20: 25 | F20: 14 | G20: =+F15*F20 -> 83.479667 | M20: 2 | N20: 45597 | O20: 45626 | P20: 25 | Q20: 30 | R20: =+Q15*Q20 -> 0
B21: 3 | G21: =+F21*F15 -> 0 | M21: 3 | N21: 45992 | O21: 45657 | P21: 25 | Q21: 31 | R21: =+Q21*Q15 -> 0
B22: 4 | G22: =+F22*F14 -> 0 | M22: 4 | N22: 45658 | O22: 45676 | P22: 25 | Q22: 19 | R22: =+Q22*Q14 -> 0
B27: TOTAL | F27: =SUM(F19:F22) -> 31 | G27: =SUM(G19:G26) -> 488.95233 | M27: TOTAL | Q27: =SUM(Q19:Q24) -> 84 | R27: =SUM(R19:R26) -> 0
B29: ROL PROPORCIONAL JUNIO 2024
B31: INGRESOS | C31: VALOR | D31: EGRESOS | E31: VALOR
B32: SUELDO BÁSICO COOPERATIVA | C32: 700 | D32: APORTE INDIVIDUAL AL IESS 9.45 | E32: =+SUM(C32:C34)*9.45% -> 115.46766
B33: BONO MOVILIZACION | C33: 21.88 | D33: descuento | E33: 0 | H33: =1200-C32 -> 500 | J33: =+SUM(C32:C34) -> 1221.88
B34: BONO CUMPLIMIENTO | C34: 500 | E34: 360 | H34: =+ROUND(H33*9.45%,2) -> 47.25 | J34: =+J33*9.45% -> 115.46766
B35: COMISION POR SUPERAR LA META | C35: 0 | H35: =+ROUND(H33*12.15%,2) -> 60.75
B36: COMISION POR PLAZOS FIJOS | C36: 0 | H36: =+H33*8.33% -> 41.65
B37: COMISION POR SOCIOS NUEVOS | C37: 0
B38: HORAS EXTRAS 50% | C38: 0 | H38: =+SUM(H34:H36) -> 149.65
B39: HORAS EXTRAS 100% | C39: 0
B40: FONDO DE RESERVA | C40: =+((C32+C33+C34)*8.33%) -> 101.7826
B41: DECIMO TERCERO | C41: 0
B42: DECIMO CUARTO | C42: 0
B43: TOTAL INGRESOS | C43: =SUM(C32:C42) -> 1323.6626 | D43: TOTAL EGRESOS | E43: =SUM(E32:E42) -> 475.46766 | G43: 1186.55
D44: VALOR NETO A RECIBIR | E44: =+C43-E43 -> 848.19494 | G44: =+G43-E44 -> 338.35506
K47: 602.89
B50: INGRESOS | C50: VALOR | D50: EGRESOS | E50: VALOR
B51: SUELDO BÁSICO COOPERATIVA | C51: 1200 | D51: APORTE INDIVIDUAL AL IESS 9.45 | E51: =+((C51*9.45%)) -> 113.4
B52: BONO MOVILIZACION | C52: 0 | D52: descuento | E52: 36
B53: BONO CUMPLIMIENTO | C53: 0 | E53: 0
B54: COMISION POR SUPERAR LA META | C54: 0
B55: COMISION POR PLAZOS FIJOS | C55: 0
B56: COMISION POR SOCIOS NUEVOS | C56: 0
B57: HORAS EXTRAS 50% | C57: 0
B58: HORAS EXTRAS 100% | C58: 0
B59: FONDO DE RESERVA | C59: =+(C51*8.33%) -> 99.96
B60: DECIMO TERCERO | C60: 0
B61: DECIMO CUARTO | C61: 0
B62: TOTAL INGRESOS | C62: =SUM(C51:C61) -> 1299.96 | D62: TOTAL EGRESOS | E62: =SUM(E51:E61) -> 149.4
D63: VALOR NETO A RECIBIR | E63: =+C62-E62 -> 1150.56 | I63: =+E63-E44 -> 302.36506

Sheet Enfermedad-Meza)
B8: Trabajador(a): | C8: MEZA RODRIGUEZ MICHAEL FERNANDO | F8: Inicio: | G8: 45850
B9: Fecha de ingreso: | C9: 45762 | F9: Fin: | G9: 45869
B10: Sueldo: | C10: 473.88 | F10: Total de dias | G10: =+_xlfn.DAYS(G9,G8)+1 -> 20
B11: Subsidio: | C11: ENFERMEDAD GENERAL
B13: Calculo para el Pago:
B14: Sueldo Promedio Diario: | D14: =+C10/30 -> 15.796 | E14: (1-3 dias) | F14: =+C10/30 -> 15.796
B15: Promedio Diario (25%): | D15: =+D14*25% -> 3.949 | E15: (4-70 dias) | F15: =+F14*25% -> 3.949 | G15: =+F14*75% -> 11.847
B17: Nº | C17: Periodo | E17: Pocentaje | F17: Num. Dias | G17: Valor | M17: Nº | N17: Periodo | P17: Pocentaje | Q17: Num. Dias | R17: Valor
C18: Desde | D18: Hasta | N18: Desde | O18: Hasta
B19: 1 | C19: 45839 | D19: 45849 | E19: 100 | F19: 11 | G19: =IF(E19=100,$F$14*F19,$F$15*F19) -> 173.756 | M19: 1 | N19: 45593 | O19: 45596 | P19: 25 | Q19: 4 | R19: =+Q15*Q19 -> 0
B20: 2 | C20: 45850 | D20: 45852 | E20: 100 | F20: 19 | G20: =IF(E20=100,$F$14*F20,$F$15*F20) -> 300.124 | M20: 2 | N20: 45597 | O20: 45626 | P20: 25 | Q20: 30 | R20: =+Q15*Q20 -> 0
B21: 3 | E21: 0 | F21: 0 | G21: =IF(E21=100,$F$14*F21,$F$15*F21) -> 0 | M21: 3 | N21: 45992 | O21: 45657 | P21: 25 | Q21: 31 | R21: =+Q21*Q15 -> 0
B22: 4 | M22: 4 | N22: 45658 | O22: 45676 | P22: 25 | Q22: 19 | R22: =+Q22*Q14 -> 0
B23: 5
B24: 6
B25: 7
B26: 8
B27: TOTAL | F27: =SUM(F19:F22) -> 30 | G27: =SUM(G19:G26) -> 473.88 | M27: TOTAL | Q27: =SUM(Q19:Q24) -> 84 | R27: =SUM(R19:R26) -> 0
B29: ROL PROPORCIONAL FEBRERO 2025
B31: INGRESOS | C31: VALOR | D31: EGRESOS | E31: VALOR
B32: SUELDO BÁSICO COOPERATIVA | C32: =+G19 -> 173.756 | D32: APORTE INDIVIDUAL AL IESS 9.45 | E32: =+((C10+C34+C33+C37+C39)*9.45%) -> 51.596055
B33: BONO MOVILIZACION | C33: 36.67 | D33: CUENTAS POR COBRAR | E33: 0
B34: BONO CUMPLIMIENTO | C34: 10.3 | D34: anticipo de sueldo
B35: COMISION POR SUPERAR LA META | C35: 0
B36: COMISION POR PLAZOS FIJOS | C36: 0
B37: COMISION POR SOCIOS NUEVOS | C37: 5
B38: HORAS EXTRAS 50% | C38: 0
B39: HORAS EXTRAS 100% | C39: 20.14
B40: FONDO DE RESERVA | C40: 0
B41: DECIMO TERCERO | C41: 0
B42: DECIMO CUARTO | C42: 0
B43: TOTAL INGRESOS | C43: =SUM(C32:C42) -> 245.866 | D43: TOTAL EGRESOS | E43: =SUM(E32:E42) -> 51.596055 | G43: 494.39385
D44: VALOR NETO A RECIBIR | E44: =+C43-E43 -> 194.26995 | G44: =+G43-E44 -> 300.12391
J45: =100/30 -> 3.3333333
J46: =+J45*11 -> 36.666667

Sheet Cálculo Morocho
B8: Trabajador(a): | C8: MOROCHO YANTALEMA DINA | F8: Inicio: | G8: 45850
B9: Fecha de ingreso: | C9: 43074 | F9: Fin: | G9: 45869
B10: Sueldo: | C10: 766.65 | F10: Total de dias | G10: =+_xlfn.DAYS(G9,G8)+1 -> 20
B11: Subsidio: | C11: ENFERMEDAD GENERAL
B13: Calculo para el Pago:
B14: Sueldo Promedio Diario: | D14: =+C10/30 -> 25.555 | E14: (1-3 dias) | F14: =+C10/30 -> 25.555
B15: Promedio Diario (25%): | D15: =+D14*25% -> 6.38875 | E15: (4-70 dias) | F15: =+F14*25% -> 6.38875 | G15: =+F14*75% -> 19.16625
B17: Nº | C17: Periodo | E17: Pocentaje | F17: Num. Dias | G17: Valor | M17: Nº | N17: Periodo | P17: Pocentaje | Q17: Num. Dias | R17: Valor
C18: Desde | D18: Hasta | N18: Desde | O18: Hasta
B19: 1 | C19: 45839 | D19: 45849 | E19: 100 | F19: 19 | G19: =IF(E19=100,$F$14*F19,$F$15*F19) -> 485.545 | M19: 1 | N19: 45593 | O19: 45596 | P19: 25 | Q19: 4 | R19: =+Q15*Q19 -> 0
B20: 2 | C20: 45850 | D20: 45852 | E20: 0 | F20: 0 | G20: =IF(E20=100,$F$14*F20,$F$15*F20) -> 0 | M20: 2 | N20: 45597 | O20: 45626 | P20: 25 | Q20: 30 | R20: =+Q15*Q20 -> 0
B21: 3 | E21: 0 | F21: 0 | G21: =IF(E21=100,$F$14*F21,$F$15*F21) -> 0 | M21: 3 | N21: 45992 | O21: 45657 | P21: 25 | Q21: 31 | R21: =+Q21*Q15 -> 0
B22: 4 | M22: 4 | N22: 45658 | O22: 45676 | P22: 25 | Q22: 19 | R22: =+Q22*Q14 -> 0
B23: 5
B24: 6
B25: 7
B26: 8
B27: TOTAL | F27: =SUM(F19:F22) -> 19 | G27: =SUM(G19:G26) -> 485.545 | M27: TOTAL | Q27: =SUM(Q19:Q24) -> 84 | R27: =SUM(R19:R26) -> 0
B29: ROL PROPORCIONAL FEBRERO 2025
B31: INGRESOS | C31: VALOR | D31: EGRESOS | E31: VALOR
B32: SUELDO BÁSICO COOPERATIVA | C32: =+G19 -> 485.545 | D32: APORTE INDIVIDUAL AL IESS 9.45 | E32: =+((C10+C34+C33+C37+C39+C35)*9.45%) -> 78.74874
B33: BONO MOVILIZACION | D33: CUENTAS POR COBRAR | E33: 0
B34: BONO CUMPLIMIENTO | C34: 16.67 | D34: anticipo de sueldo
B35: COMISION POR SUPERAR LA META | C35: 50
B36: COMISION POR PLAZOS FIJOS
B37: COMISION POR SOCIOS NUEVOS
B38: HORAS EXTRAS 50%
B39: HORAS EXTRAS 100%
B40: FONDO DE RESERVA | C40: 69.42
B41: DECIMO TERCERO | C41: 0
B42: DECIMO CUARTO | C42: 0
B43: TOTAL INGRESOS | C43: =SUM(C32:C42) -> 621.635 | D43: TOTAL EGRESOS | E43: =SUM(E32:E42) -> 78.74874 | G43: 823.99
D44: VALOR NETO A RECIBIR | E44: =+C43-E43 -> 542.88626 | G44: =+G43-E44 -> 281.10374
J45: =100/30 -> 3.3333333
J46: =+J45*11 -> 36.666667

Sheet DEL ROSARIO
B8: Trabajador(a): | C8: LEMA TADAY BRAYAN | F8: Inicio: | G8: 45922
B9: Fecha de ingreso: | C9: 45841 | F9: Fin: | G9: 45930
B10: Sueldo: | C10: 481 | F10: Total de dias | G10: =+_xlfn.DAYS(G9,G8)+1 -> 9
B11: Subsidio: | C11: ENFERMEDAD GENERAL
B13: Calculo para el Pago:
B14: Sueldo Promedio Diario: | D14: =+C10/30 -> 16.033333 | E14: (1-3 dias) | F14: =+C10/30 -> 16.033333
B15: Promedio Diario (25%): | D15: =+D14*25% -> 4.0083333 | E15: (4-70 dias) | F15: =+F14*25% -> 4.0083333 | G15: =+F14*75% -> 12.025
I16: =+G15*18 -> 216.45
B17: Nº | C17: Periodo | E17: Pocentaje | F17: Num. Dias | G17: Valor
C18: Desde | D18: Hasta | I18: =+G27+I16 -> 841.75
B19: 1 | C19: 45922 | D19: 45930 | E19: 100 | F19: =+D19-C19+1 -> 9 | G19: =IF(E19=100,$F$14*F19,$F$15*F19) -> 144.3
B20: 2 | C20: 45931 | D20: 45944 | E20: 100 | F20: =+D20-C20+1 -> 14 | G20: =IF(E20=100,$F$14*F20,$F$15*F20) -> 224.46667
B21: 3 | C21: 45945 | D21: 45961 | E21: 100 | F21: =+D21-C21 -> 16 | G21: =IF(E21=100,$F$14*F21,$F$15*F21) -> 256.53333
B22: 4
B23: 5
B24: 6
B25: 7
B26: 8
B27: TOTAL | F27: =SUM(F19:F22) -> 39 | G27: =SUM(G19:G26) -> 625.3
B29: ROL PROPORCIONAL FEBRERO 2025
B31: INGRESOS | C31: VALOR | D31: EGRESOS | E31: VALOR
B32: SUELDO BÁSICO COOPERATIVA | C32: =+G19 -> 144.3 | D32: APORTE INDIVIDUAL AL IESS 9.45 | E32: =+((C10+C33+C39)*9.45%) -> 45.4545
B33: BONO MOVILIZACION | C33: 0 | D33: CUENTAS POR COBRAR | E33: 0 | H33: =100/30 -> 3.3333333
B34: BONO CUMPLIMIENTO | C34: 0 | D34: anticipo de sueldo | H34: =+H33*F19 -> 30
B35: COMISION POR SUPERAR LA META | C35: 0
B36: COMISION POR PLAZOS FIJOS
B37: COMISION POR SOCIOS NUEVOS
B38: HORAS EXTRAS 50%
B39: HORAS EXTRAS 100%
B40: FONDO DE RESERVA | C40: 0
B41: DECIMO TERCERO | C41: 0
B42: DECIMO CUARTO | C42: 0
B43: TOTAL INGRESOS | C43: =SUM(C32:C42) -> 144.3 | D43: TOTAL EGRESOS | E43: =SUM(E32:E42) -> 45.4545 | G43: 469.84584
D44: VALOR NETO A RECIBIR | E44: =+C43-E43 -> 98.8455 | G44: =+G43-E44 -> 371.00034

Sheet CHIMBOLEMA KEVIN
B8: Trabajador(a): | C8: LEMA TADAY BRAYAN | F8: Inicio: | G8: 45922
B9: Fecha de ingreso: | C9: 45841 | F9: Fin: | G9: 45930
B10: Sueldo: | C10: 481 | F10: Total de dias | G10: =+_xlfn.DAYS(G9,G8)+1 -> 9
B11: Subsidio: | C11: ENFERMEDAD GENERAL
B13: Calculo para el Pago:
B14: Sueldo Promedio Diario: | D14: =+C10/30 -> 16.033333 | E14: (1-3 dias) | F14: =+C10/30 -> 16.033333
B15: Promedio Diario (25%): | D15: =+D14*25% -> 4.0083333 | E15: (4-70 dias) | F15: =+F14*25% -> 4.0083333 | G15: =+F14*75% -> 12.025
I16: =+G15*18 -> 216.45
B17: Nº | C17: Periodo | E17: Pocentaje | F17: Num. Dias | G17: Valor
C18: Desde | D18: Hasta | I18: =+G27+I16 -> 841.75
B19: 1 | C19: 45922 | D19: 45930 | E19: 100 | F19: =+D19-C19+1 -> 9 | G19: =IF(E19=100,$F$14*F19,$F$15*F19) -> 144.3
B20: 2 | C20: 45931 | D20: 45944 | E20: 100 | F20: =+D20-C20+1 -> 14 | G20: =IF(E20=100,$F$14*F20,$F$15*F20) -> 224.46667
B21: 3 | C21: 45945 | D21: 45961 | E21: 100 | F21: =+D21-C21 -> 16 | G21: =IF(E21=100,$F$14*F21,$F$15*F21) -> 256.53333
B22: 4
B23: 5
B24: 6
B25: 7
B26: 8
B27: TOTAL | F27: =SUM(F19:F22) -> 39 | G27: =SUM(G19:G26) -> 625.3
B29: ROL PROPORCIONAL FEBRERO 2025
B31: INGRESOS | C31: VALOR | D31: EGRESOS | E31: VALOR
B32: SUELDO BÁSICO COOPERATIVA | C32: =+G19 -> 144.3 | D32: APORTE INDIVIDUAL AL IESS 9.45 | E32: =+((C10+C33+C39)*9.45%) -> 45.4545
B33: BONO MOVILIZACION | C33: 0 | D33: CUENTAS POR COBRAR | E33: 0 | H33: =100/30 -> 3.3333333
B34: BONO CUMPLIMIENTO | C34: 0 | D34: anticipo de sueldo | H34: =+H33*F19 -> 30
B35: COMISION POR SUPERAR LA META | C35: 0
B36: COMISION POR PLAZOS FIJOS
B37: COMISION POR SOCIOS NUEVOS
B38: HORAS EXTRAS 50%
B39: HORAS EXTRAS 100%
B40: FONDO DE RESERVA | C40: 0
B41: DECIMO TERCERO | C41: 0
B42: DECIMO CUARTO | C42: 0
B43: TOTAL INGRESOS | C43: =SUM(C32:C42) -> 144.3 | D43: TOTAL EGRESOS | E43: =SUM(E32:E42) -> 45.4545 | G43: 469.84584
D44: VALOR NETO A RECIBIR | E44: =+C43-E43 -> 98.8455 | G44: =+G43-E44 -> 371.00034

Sheet OTRAS COMISIONES
B2: CÁLCULO DE COMISIONES (METAS, BONOS,ETC)
B3: NÓMINA OCTUBRE 2025
H5: COMISIONES | K5: TOTAL COMISIÓN
J6: CRÉD-INV
B7: NO | C7: CEDULA | D7: NOMBRE | E7: CARGO | F7: Agencia | G7: SUELDO | H7: BONO BOLETOS | I7: COM. POR CARGO | J7: BONO CUMP | K7: US$,,
B8: 1 | C8: 925813685 | D8: =+VLOOKUP(Tabla335[[#This Row],[CEDULA ]],'OCTUBRE 2025'!$C$8:$J$57,2,0) -> ASITIMBAY CRIOLLO JOHN ANDERSON | E8: =+VLOOKUP(Tabla335[[#This Row],[CEDULA ]],'OCTUBRE 2025'!$C$8:$J$57,4,0) -> JEFE DE MARKETING | F8: =+VLOOKUP(Tabla335[[#This Row],[CEDULA ]],'OCTUBRE 2025'!$C$8:$J$57,6,0) -> Matriz | G8: =+VLOOKUP(Tabla335[[#This Row],[CEDULA ]],'OCTUBRE 2025'!$C$8:$J$57,8,0) -> 817.76 | K8: =+Tabla335[[#This Row],[BONO BOLETOS]]+Tabla335[[#This Row],[COM. POR CARGO]]+Tabla335[[#This Row],[BONO CUMP]] -> 0
B9: 2 | C9: 944405737 | D9: =+VLOOKUP(Tabla335[[#This Row],[CEDULA ]],'OCTUBRE 2025'!$C$8:$J$57,2,0) -> BARAHONA ZAMBRANO DAYANA NICOLE | E9: =+VLOOKUP(Tabla335[[#This Row],[CEDULA ]],'OCTUBRE 2025'!$C$8:$J$57,4,0) -> CAJERO FINANCIERO | F9: =+VLOOKUP(Tabla335[[#This Row],[CEDULA ]],'OCTUBRE 2025'!$C$8:$J$57,6,0) -> Matriz | G9: =+VLOOKUP(Tabla335[[#This Row],[CEDULA ]],'OCTUBRE 2025'!$C$8:$J$57,8,0) -> 15.86 | K9: =+Tabla335[[#This Row],[BONO BOLETOS]]+Tabla335[[#This Row],[COM. POR CARGO]]+Tabla335[[#This Row],[BONO CUMP]] -> 0
B10: 3 | C10: 604394502 | D10: =+VLOOKUP(Tabla335[[#This Row],[CEDULA ]],'OCTUBRE 2025'!$C$8:$J$57,2,0) -> BETUN CHAFLA JULIO CESAR | E10: =+VLOOKUP(Tabla335[[#This Row],[CEDULA ]],'OCTUBRE 2025'!$C$8:$J$57,4,0) -> ASESOR DE NEGOCIOS | F10: =+VLOOKUP(Tabla335[[#This Row],[CEDULA ]],'OCTUBRE 2025'!$C$8:$J$57,6,0) -> Matriz | G10: =+VLOOKUP(Tabla335[[#This Row],[CEDULA ]],'OCTUBRE 2025'!$C$8:$J$57,8,0) -> 613.32 | J10: 0 | K10: =+Tabla335[[#This Row],[BONO BOLETOS]]+Tabla335[[#This Row],[COM. POR CARGO]]+Tabla335[[#This Row],[BONO CUMP]] -> 0
B11: 4 | C11: 955741970 | D11: =+VLOOKUP(Tabla335[[#This Row],[CEDULA ]],'OCTUBRE 2025'!$C$8:$J$57,2,0) -> CHACAGUASAY CHACAGUASAY ROBERTH CRISTHIAN | E11: =+VLOOKUP(Tabla335[[#This Row],[CEDULA ]],'OCTUBRE 2025'!$C$8:$J$57,4,0) -> OFICIAL DE RECAUDACIONES | F11: =+VLOOKUP(Tabla335[[#This Row],[CEDULA ]],'OCTUBRE 2025'!$C$8:$J$57,6,0) -> Matriz | G11: =+VLOOKUP(Tabla335[[#This Row],[CEDULA ]],'OCTUBRE 2025'!$C$8:$J$57,8,0) -> 473.88 | K11: =+Tabla335[[#This Row],[BONO BOLETOS]]+Tabla335[[#This Row],[COM. POR CARGO]]+Tabla335[[#This Row],[BONO CUMP]] -> 0
B12: 5 | C12: 0943964973 | D12: =+VLOOKUP(Tabla335[[#This Row],[CEDULA ]],'OCTUBRE 2025'!$C$8:$J$57,2,0) -> CHACAGUASAY GUAMAN KEVIN NEHEMIAS | E12: =+VLOOKUP(Tabla335[[#This Row],[CEDULA ]],'OCTUBRE 2025'!$C$8:$J$57,4,0) -> ASESOR DE NEGOCIOS | F12: =+VLOOKUP(Tabla335[[#This Row],[CEDULA ]],'OCTUBRE 2025'!$C$8:$J$57,6,0) -> Matriz | G12: =+VLOOKUP(Tabla335[[#This Row],[CEDULA ]],'OCTUBRE 2025'!$C$8:$J$57,8,0) -> 256.53 | J12: 368.77 | K12: =+Tabla335[[#This Row],[BONO BOLETOS]]+Tabla335[[#This Row],[COM. POR CARGO]]+Tabla335[[#This Row],[BONO CUMP]] -> 368.77
B13: 6 | C13: 944143148 | D13: =+VLOOKUP(Tabla335[[#This Row],[CEDULA ]],'OCTUBRE 2025'!$C$8:$J$57,2,0) -> CHIMBOLEMA YUNGAN MARIO EFRAIN | E13: =+VLOOKUP(Tabla335[[#This Row],[CEDULA ]],'OCTUBRE 2025'!$C$8:$J$57,4,0) -> OFICIAL DE RECAUDACIONES | F13: =+VLOOKUP(Tabla335[[#This Row],[CEDULA ]],'OCTUBRE 2025'!$C$8:$J$57,6,0) -> Durán | G13: =+VLOOKUP(Tabla335[[#This Row],[CEDULA ]],'OCTUBRE 2025'!$C$8:$J$57,8,0) -> 142.16 | K13: =+Tabla335[[#This Row],[BONO BOLETOS]]+Tabla335[[#This Row],[COM. POR CARGO]]+Tabla335[[#This Row],[BONO CUMP]] -> 0
B14: 7 | C14: 955325238 | D14: =+VLOOKUP(Tabla335[[#This Row],[CEDULA ]],'OCTUBRE 2025'!$C$8:$J$57,2,0) -> CHOCA CEPEDA INES VIVIANA | E14: =+VLOOKUP(Tabla335[[#This Row],[CEDULA ]],'OCTUBRE 2025'!$C$8:$J$57,4,0) -> CAJERA FINANCIERA | F14: =+VLOOKUP(Tabla335[[#This Row],[CEDULA ]],'OCTUBRE 2025'!$C$8:$J$57,6,0) -> Matriz | G14: =+VLOOKUP(Tabla335[[#This Row],[CEDULA ]],'OCTUBRE 2025'!$C$8:$J$57,8,0) -> 256.53 | K14: =+Tabla335[[#This Row],[BONO BOLETOS]]+Tabla335[[#This Row],[COM. POR CARGO]]+Tabla335[[#This Row],[BONO CUMP]] -> 0
B15: 8 | C15: 914163654 | D15: =+VLOOKUP(Tabla335[[#This Row],[CEDULA ]],'OCTUBRE 2025'!$C$8:$J$57,2,0) -> COCA BENITEZ JORGE MANUEL | E15: =+VLOOKUP(Tabla335[[#This Row],[CEDULA ]],'OCTUBRE 2025'!$C$8:$J$57,4,0) -> ANALISTA DE RIESGO | F15: =+VLOOKUP(Tabla335[[#This Row],[CEDULA ]],'OCTUBRE 2025'!$C$8:$J$57,6,0) -> Matriz | G15: =+VLOOKUP(Tabla335[[#This Row],[CEDULA ]],'OCTUBRE 2025'!$C$8:$J$57,8,0) -> 1200 | K15: =+Tabla335[[#This Row],[BONO BOLETOS]]+Tabla335[[#This Row],[COM. POR CARGO]]+Tabla335[[#This Row],[BONO CUMP]] -> 0
B16: 9 | C16: 956668305 | D16: =+VLOOKUP(Tabla335[[#This Row],[CEDULA ]],'OCTUBRE 2025'!$C$8:$J$57,2,0) -> CORO YUQUILEMA RUTH NOEMI | E16: =+VLOOKUP(Tabla335[[#This Row],[CEDULA ]],'OCTUBRE 2025'!$C$8:$J$57,4,0) -> OFICIAL DE RECAUDACIONES | F16: =+VLOOKUP(Tabla335[[#This Row],[CEDULA ]],'OCTUBRE 2025'!$C$8:$J$57,6,0) -> Matriz | G16: =+VLOOKUP(Tabla335[[#This Row],[CEDULA ]],'OCTUBRE 2025'!$C$8:$J$57,8,0) -> 252.74 | J16: 0 | K16: =+Tabla335[[#This Row],[BONO BOLETOS]]+Tabla335[[#This Row],[COM. POR CARGO]]+Tabla335[[#This Row],[BONO CUMP]] -> 0
B17: 10 | C17: 0918741448 | D17: =+VLOOKUP(Tabla335[[#This Row],[CEDULA ]],'OCTUBRE 2025'!$C$8:$J$57,2,0) -> DEFAS CHICAIZA JOEL ALBERTO | E17: =+VLOOKUP(Tabla335[[#This Row],[CEDULA ]],'OCTUBRE 2025'!$C$8:$J$57,4,0) -> ASESOR DE NEGOCIOS | F17: =+VLOOKUP(Tabla335[[#This Row],[CEDULA ]],'OCTUBRE 2025'!$C$8:$J$57,6,0) -> Norte | G17: =+VLOOKUP(Tabla335[[#This Row],[CEDULA ]],'OCTUBRE 2025'!$C$8:$J$57,8,0) -> 626.65 | K17: =+Tabla335[[#This Row],[BONO BOLETOS]]+Tabla335[[#This Row],[COM. POR CARGO]]+Tabla335[[#This Row],[BONO CUMP]] -> 0
B18: 11 | C18: 931097620 | D18: =+VLOOKUP(Tabla335[[#This Row],[CEDULA ]],'OCTUBRE 2025'!$C$8:$J$57,2,0) -> DEL ROSARIO RODRIGUEZ JUDY ANGELICA | E18: =+VLOOKUP(Tabla335[[#This Row],[CEDULA ]],'OCTUBRE 2025'!$C$8:$J$57,4,0) -> CAJERA FINANCIERA | F18: =+VLOOKUP(Tabla335[[#This Row],[CEDULA ]],'OCTUBRE 2025'!$C$8:$J$57,6,0) -> Norte | G18: =+VLOOKUP(Tabla335[[#This Row],[CEDULA ]],'OCTUBRE 2025'!$C$8:$J$57,8,0) -> 256.53 | J18: 368.77 | K18: =+Tabla335[[#This Row],[BONO BOLETOS]]+Tabla335[[#This Row],[COM. POR CARGO]]+Tabla335[[#This Row],[BONO CUMP]] -> 368.77
B19: 12 | C19: 1105483422 | D19: =+VLOOKUP(Tabla335[[#This Row],[CEDULA ]],'OCTUBRE 2025'!$C$8:$J$57,2,0) -> FLORES HERRERA WENDY DEL CISNE | E19: =+VLOOKUP(Tabla335[[#This Row],[CEDULA ]],'OCTUBRE 2025'!$C$8:$J$57,4,0) -> CAJERO FINANCIERO | F19: =+VLOOKUP(Tabla335[[#This Row],[CEDULA ]],'OCTUBRE 2025'!$C$8:$J$57,6,0) -> Durán | G19: =+VLOOKUP(Tabla335[[#This Row],[CEDULA ]],'OCTUBRE 2025'!$C$8:$J$57,8,0) -> 650 | K19: =+Tabla335[[#This Row],[BONO BOLETOS]]+Tabla335[[#This Row],[COM. POR CARGO]]+Tabla335[[#This Row],[BONO CUMP]] -> 0
B20: 13 | C20: 942614645 | D20: =+VLOOKUP(Tabla335[[#This Row],[CEDULA ]],'OCTUBRE 2025'!$C$8:$J$57,2,0) -> FUELA TOABANDA JOSUE CHRISTIAN | E20: =+VLOOKUP(Tabla335[[#This Row],[CEDULA ]],'OCTUBRE 2025'!$C$8:$J$57,4,0) -> ASISTENTE CONTABLE | F20: =+VLOOKUP(Tabla335[[#This Row],[CEDULA ]],'OCTUBRE 2025'!$C$8:$J$57,6,0) -> Matriz | G20: =+VLOOKUP(Tabla335[[#This Row],[CEDULA ]],'OCTUBRE 2025'!$C$8:$J$57,8,0) -> 481 | K20: =+Tabla335[[#This Row],[BONO BOLETOS]]+Tabla335[[#This Row],[COM. POR CARGO]]+Tabla335[[#This Row],[BONO CUMP]] -> 0
B21: 14 | C21: 951200062 | D21: =+VLOOKUP(Tabla335[[#This Row],[CEDULA ]],'OCTUBRE 2025'!$C$8:$J$57,2,0) -> GALAN LEMACHE INGRID GISELA | E21: =+VLOOKUP(Tabla335[[#This Row],[CEDULA ]],'OCTUBRE 2025'!$C$8:$J$57,4,0) -> BACK UP ADMINISTRATIVO FINANCIERO | F21: =+VLOOKUP(Tabla335[[#This Row],[CEDULA ]],'OCTUBRE 2025'!$C$8:$J$57,6,0) -> Norte | G21: =+VLOOKUP(Tabla335[[#This Row],[CEDULA ]],'OCTUBRE 2025'!$C$8:$J$57,8,0) -> 473.88 | K21: =+Tabla335[[#This Row],[BONO BOLETOS]]+Tabla335[[#This Row],[COM. POR CARGO]]+Tabla335[[#This Row],[BONO CUMP]] -> 0
B22: 15 | C22: 950929232 | D22: =+VLOOKUP(Tabla335[[#This Row],[CEDULA ]],'OCTUBRE 2025'!$C$8:$J$57,2,0) -> GARCIA VERA HENRY LUIS | E22: =+VLOOKUP(Tabla335[[#This Row],[CEDULA ]],'OCTUBRE 2025'!$C$8:$J$57,4,0) -> OFICIAL DE RECAUDACIONES | F22: =+VLOOKUP(Tabla335[[#This Row],[CEDULA ]],'OCTUBRE 2025'!$C$8:$J$57,6,0) -> Norte | G22: =+VLOOKUP(Tabla335[[#This Row],[CEDULA ]],'OCTUBRE 2025'!$C$8:$J$57,8,0) -> 715.54 | K22: =+Tabla335[[#This Row],[BONO BOLETOS]]+Tabla335[[#This Row],[COM. POR CARGO]]+Tabla335[[#This Row],[BONO CUMP]] -> 0
B23: 16 | C23: 953819646 | D23: =+VLOOKUP(Tabla335[[#This Row],[CEDULA ]],'OCTUBRE 2025'!$C$8:$J$57,2,0) -> GUALACEO ÑAMO JONATHAN IVÁN | E23: =+VLOOKUP(Tabla335[[#This Row],[CEDULA ]],'OCTUBRE 2025'!$C$8:$J$57,4,0) -> OFICIAL DE RECAUDACIONES | F23: =+VLOOKUP(Tabla335[[#This Row],[CEDULA ]],'OCTUBRE 2025'!$C$8:$J$57,6,0) -> Matriz | G23: =+VLOOKUP(Tabla335[[#This Row],[CEDULA ]],'OCTUBRE 2025'!$C$8:$J$57,8,0) -> 511.1 | K23: =+Tabla335[[#This Row],[BONO BOLETOS]]+Tabla335[[#This Row],[COM. POR CARGO]]+Tabla335[[#This Row],[BONO CUMP]] -> 0
B24: 17 | C24: 956953392 | D24: =+VLOOKUP(Tabla335[[#This Row],[CEDULA ]],'OCTUBRE 2025'!$C$8:$J$57,2,0) -> GUAPI YUMAGLLA OSCAR EDUARDO | E24: =+VLOOKUP(Tabla335[[#This Row],[CEDULA ]],'OCTUBRE 2025'!$C$8:$J$57,4,0) -> OFICIAL DE RECAUDACIONES | F24: =+VLOOKUP(Tabla335[[#This Row],[CEDULA ]],'OCTUBRE 2025'!$C$8:$J$57,6,0) -> Matriz | G24: =+VLOOKUP(Tabla335[[#This Row],[CEDULA ]],'OCTUBRE 2025'!$C$8:$J$57,8,0) -> 473.88 | K24: =+Tabla335[[#This Row],[BONO BOLETOS]]+Tabla335[[#This Row],[COM. POR CARGO]]+Tabla335[[#This Row],[BONO CUMP]] -> 0
B25: 18 | C25: 956796767 | D25: =+VLOOKUP(Tabla335[[#This Row],[CEDULA ]],'OCTUBRE 2025'!$C$8:$J$57,2,0) -> GUAYANLEMA RUIZ EDINSON DAVID | E25: =+VLOOKUP(Tabla335[[#This Row],[CEDULA ]],'OCTUBRE 2025'!$C$8:$J$57,4,0) -> OFICIAL DE RECAUDACIONES | F25: =+VLOOKUP(Tabla335[[#This Row],[CEDULA ]],'OCTUBRE 2025'!$C$8:$J$57,6,0) -> Norte | G25: =+VLOOKUP(Tabla335[[#This Row],[CEDULA ]],'OCTUBRE 2025'!$C$8:$J$57,8,0) -> 473.88 | K25: =+Tabla335[[#This Row],[BONO BOLETOS]]+Tabla335[[#This Row],[COM. POR CARGO]]+Tabla335[[#This Row],[BONO CUMP]] -> 0
B26: 19 | C26: 0932036049 | D26: =+VLOOKUP(Tabla335[[#This Row],[CEDULA ]],'OCTUBRE 2025'!$C$8:$J$57,2,0) -> HERRERA JIMENEZ CAROLINA ADELIHER | E26: =+VLOOKUP(Tabla335[[#This Row],[CEDULA ]],'OCTUBRE 2025'!$C$8:$J$57,4,0) -> ASISTENTE DE OPERACIONES | F26: =+VLOOKUP(Tabla335[[#This Row],[CEDULA ]],'OCTUBRE 2025'!$C$8:$J$57,6,0) -> Matriz | G26: =+VLOOKUP(Tabla335[[#This Row],[CEDULA ]],'OCTUBRE 2025'!$C$8:$J$57,8,0) -> 481 | K26: =+Tabla335[[#This Row],[BONO BOLETOS]]+Tabla335[[#This Row],[COM. POR CARGO]]+Tabla335[[#This Row],[BONO CUMP]] -> 0
B27: 20 | C27: 1724102940 | D27: =+VLOOKUP(Tabla335[[#This Row],[CEDULA ]],'OCTUBRE 2025'!$C$8:$J$57,2,0) -> HIDALGO CHERRES NESTOR VLADIMIR | E27: =+VLOOKUP(Tabla335[[#This Row],[CEDULA ]],'OCTUBRE 2025'!$C$8:$J$57,4,0) -> JEFE DE CREDITO | F27: =+VLOOKUP(Tabla335[[#This Row],[CEDULA ]],'OCTUBRE 2025'!$C$8:$J$57,6,0) -> Durán | G27: =+VLOOKUP(Tabla335[[#This Row],[CEDULA ]],'OCTUBRE 2025'!$C$8:$J$57,8,0) -> 817.76 | J27: 0 | K27: =+Tabla335[[#This Row],[BONO BOLETOS]]+Tabla335[[#This Row],[COM. POR CARGO]]+Tabla335[[#This Row],[BONO CUMP]] -> 0
B28: 21 | C28: 943322974 | D28: =+VLOOKUP(Tabla335[[#This Row],[CEDULA ]],'OCTUBRE 2025'!$C$8:$J$57,2,0) -> JANETA RUIZ ALEXANDRA DEL ROCIO | E28: =+VLOOKUP(Tabla335[[#This Row],[CEDULA ]],'OCTUBRE 2025'!$C$8:$J$57,4,0) -> OFICIAL DE RECAUDACIONES | F28: =+VLOOKUP(Tabla335[[#This Row],[CEDULA ]],'OCTUBRE 2025'!$C$8:$J$57,6,0) -> Norte | G28: =+VLOOKUP(Tabla335[[#This Row],[CEDULA ]],'OCTUBRE 2025'!$C$8:$J$57,8,0) -> 473.88 | K28: =+Tabla335[[#This Row],[BONO BOLETOS]]+Tabla335[[#This Row],[COM. POR CARGO]]+Tabla335[[#This Row],[BONO CUMP]] -> 0
B29: 22 | C29: 941096851 | D29: =+VLOOKUP(Tabla335[[#This Row],[CEDULA ]],'OCTUBRE 2025'!$C$8:$J$57,2,0) -> LEMA CHIRAU RAMONA MARIA | E29: =+VLOOKUP(Tabla335[[#This Row],[CEDULA ]],'OCTUBRE 2025'!$C$8:$J$57,4,0) -> ASESOR DE CAPTACIONES | F29: =+VLOOKUP(Tabla335[[#This Row],[CEDULA ]],'OCTUBRE 2025'!$C$8:$J$57,6,0) -> Durán | G29: =+VLOOKUP(Tabla335[[#This Row],[CEDULA ]],'OCTUBRE 2025'!$C$8:$J$57,8,0) -> 700 | J29: 0 | K29: =+Tabla335[[#This Row],[BONO BOLETOS]]+Tabla335[[#This Row],[COM. POR CARGO]]+Tabla335[[#This Row],[BONO CUMP]] -> 0
B30: 23 | C30: 957093800 | D30: =+VLOOKUP(Tabla335[[#This Row],[CEDULA ]],'OCTUBRE 2025'!$C$8:$J$57,2,0) -> LEMA TADAY BRAYAN WIDINSON | E30: =+VLOOKUP(Tabla335[[#This Row],[CEDULA ]],'OCTUBRE 2025'!$C$8:$J$57,4,0) -> OFICIAL DE RECAUDACIONES | F30: =+VLOOKUP(Tabla335[[#This Row],[CEDULA ]],'OCTUBRE 2025'!$C$8:$J$57,6,0) -> Durán | G30: =+VLOOKUP(Tabla335[[#This Row],[CEDULA ]],'OCTUBRE 2025'!$C$8:$J$57,8,0) -> 473.88 | K30: =+Tabla335[[#This Row],[BONO BOLETOS]]+Tabla335[[#This Row],[COM. POR CARGO]]+Tabla335[[#This Row],[BONO CUMP]] -> 0
B31: 24 | C31: 957924350 | D31: =+VLOOKUP(Tabla335[[#This Row],[CEDULA ]],'OCTUBRE 2025'!$C$8:$J$57,2,0) -> LLUMI YUQUILEMA MAYCOOL DANNY | E31: =+VLOOKUP(Tabla335[[#This Row],[CEDULA ]],'OCTUBRE 2025'!$C$8:$J$57,4,0) -> ASESOR DE NEGOCIOS | F31: =+VLOOKUP(Tabla335[[#This Row],[CEDULA ]],'OCTUBRE 2025'!$C$8:$J$57,6,0) -> Matriz | G31: =+VLOOKUP(Tabla335[[#This Row],[CEDULA ]],'OCTUBRE 2025'!$C$8:$J$57,8,0) -> 481 | K31: =+Tabla335[[#This Row],[BONO BOLETOS]]+Tabla335[[#This Row],[COM. POR CARGO]]+Tabla335[[#This Row],[BONO CUMP]] -> 0
B32: 25 | C32: 603838657 | D32: =+VLOOKUP(Tabla335[[#This Row],[CEDULA ]],'OCTUBRE 2025'!$C$8:$J$57,2,0) -> MALAN DELGADO JOSE ALBERTO | E32: =+VLOOKUP(Tabla335[[#This Row],[CEDULA ]],'OCTUBRE 2025'!$C$8:$J$57,4,0) -> OFICIAL DE RECAUDACIONES | F32: =+VLOOKUP(Tabla335[[#This Row],[CEDULA ]],'OCTUBRE 2025'!$C$8:$J$57,6,0) -> Durán | G32: =+VLOOKUP(Tabla335[[#This Row],[CEDULA ]],'OCTUBRE 2025'!$C$8:$J$57,8,0) -> 473.88 | K32: =+Tabla335[[#This Row],[BONO BOLETOS]]+Tabla335[[#This Row],[COM. POR CARGO]]+Tabla335[[#This Row],[BONO CUMP]] -> 0
B33: 26 | C33: 925240525 | D33: =+VLOOKUP(Tabla335[[#This Row],[CEDULA ]],'OCTUBRE 2025'!$C$8:$J$57,2,0) -> MALAN YUQUILEMA RAUL ALBERTO | E33: =+VLOOKUP(Tabla335[[#This Row],[CEDULA ]],'OCTUBRE 2025'!$C$8:$J$57,4,0) -> ASESOR LEGAL | F33: =+VLOOKUP(Tabla335[[#This Row],[CEDULA ]],'OCTUBRE 2025'!$C$8:$J$57,6,0) -> Matriz | G33: =+VLOOKUP(Tabla335[[#This Row],[CEDULA ]],'OCTUBRE 2025'!$C$8:$J$57,8,0) -> 2700 | K33: =+Tabla335[[#This Row],[BONO BOLETOS]]+Tabla335[[#This Row],[COM. POR CARGO]]+Tabla335[[#This Row],[BONO CUMP]] -> 0
B34: 27 | C34: 954520599 | D34: =+VLOOKUP(Tabla335[[#This Row],[CEDULA ]],'OCTUBRE 2025'!$C$8:$J$57,2,0) -> MARSHALL VEGA YULIANA LISSETT | E34: =+VLOOKUP(Tabla335[[#This Row],[CEDULA ]],'OCTUBRE 2025'!$C$8:$J$57,4,0) -> ASESOR DE NEGOCIOS | F34: =+VLOOKUP(Tabla335[[#This Row],[CEDULA ]],'OCTUBRE 2025'!$C$8:$J$57,6,0) -> Durán | G34: =+VLOOKUP(Tabla335[[#This Row],[CEDULA ]],'OCTUBRE 2025'!$C$8:$J$57,8,0) -> 613.32 | J34: 0 | K34: =+Tabla335[[#This Row],[BONO BOLETOS]]+Tabla335[[#This Row],[COM. POR CARGO]]+Tabla335[[#This Row],[BONO CUMP]] -> 0
B35: 28 | C35: 0943906032 | D35: =+VLOOKUP(Tabla335[[#This Row],[CEDULA ]],'OCTUBRE 2025'!$C$8:$J$57,2,0) -> MEZA RODRIGUEZ MICHAEL FERNANDO | E35: =+VLOOKUP(Tabla335[[#This Row],[CEDULA ]],'OCTUBRE 2025'!$C$8:$J$57,4,0) -> OFICIAL DE RECAUDACIONES | F35: =+VLOOKUP(Tabla335[[#This Row],[CEDULA ]],'OCTUBRE 2025'!$C$8:$J$57,6,0) -> Norte | G35: =+VLOOKUP(Tabla335[[#This Row],[CEDULA ]],'OCTUBRE 2025'!$C$8:$J$57,8,0) -> 473.88 | K35: =+Tabla335[[#This Row],[BONO BOLETOS]]+Tabla335[[#This Row],[COM. POR CARGO]]+Tabla335[[#This Row],[BONO CUMP]] -> 0
B36: 29 | C36: 0919306050 | D36: =+VLOOKUP(Tabla335[[#This Row],[CEDULA ]],'OCTUBRE 2025'!$C$8:$J$57,2,0) -> MORAN GARCIA DANNY FAVIAN | E36: =+VLOOKUP(Tabla335[[#This Row],[CEDULA ]],'OCTUBRE 2025'!$C$8:$J$57,4,0) -> OFICIAL DE CUMPLIMIENTO | F36: =+VLOOKUP(Tabla335[[#This Row],[CEDULA ]],'OCTUBRE 2025'!$C$8:$J$57,6,0) -> Matriz | G36: =+VLOOKUP(Tabla335[[#This Row],[CEDULA ]],'OCTUBRE 2025'!$C$8:$J$57,8,0) -> 600 | K36: =+Tabla335[[#This Row],[BONO BOLETOS]]+Tabla335[[#This Row],[COM. POR CARGO]]+Tabla335[[#This Row],[BONO CUMP]] -> 0
B37: 30 | C37: 0941235376 | D37: =+VLOOKUP(Tabla335[[#This Row],[CEDULA ]],'OCTUBRE 2025'!$C$8:$J$57,2,0) -> MOREIRA ESPINOZA LINDA ELIZABETH | E37: =+VLOOKUP(Tabla335[[#This Row],[CEDULA ]],'OCTUBRE 2025'!$C$8:$J$57,4,0) -> CAJERO FINANCIERO | F37: =+VLOOKUP(Tabla335[[#This Row],[CEDULA ]],'OCTUBRE 2025'!$C$8:$J$57,6,0) -> Durán | G37: =+VLOOKUP(Tabla335[[#This Row],[CEDULA ]],'OCTUBRE 2025'!$C$8:$J$57,8,0) -> 481 | K37: =+Tabla335[[#This Row],[BONO BOLETOS]]+Tabla335[[#This Row],[COM. POR CARGO]]+Tabla335[[#This Row],[BONO CUMP]] -> 0
B38: 31 | C38: 955395686 | D38: =+VLOOKUP(Tabla335[[#This Row],[CEDULA ]],'OCTUBRE 2025'!$C$8:$J$57,2,0) -> MOROCHO DUCHI SANDRA STEPHANIE | E38: =+VLOOKUP(Tabla335[[#This Row],[CEDULA ]],'OCTUBRE 2025'!$C$8:$J$57,4,0) -> ASESOR DE NEGOCIOS | F38: =+VLOOKUP(Tabla335[[#This Row],[CEDULA ]],'OCTUBRE 2025'!$C$8:$J$57,6,0) -> Norte | G38: =+VLOOKUP(Tabla335[[#This Row],[CEDULA ]],'OCTUBRE 2025'!$C$8:$J$57,8,0) -> 613.32 | H38: 0 | J38: 0 | K38: =+Tabla335[[#This Row],[BONO BOLETOS]]+Tabla335[[#This Row],[COM. POR CARGO]]+Tabla335[[#This Row],[BONO CUMP]] -> 0
B39: 32 | C39: 940991987 | D39: =+VLOOKUP(Tabla335[[#This Row],[CEDULA ]],'OCTUBRE 2025'!$C$8:$J$57,2,0) -> MOROCHO YANTALEMA DINA MAGALY | E39: =+VLOOKUP(Tabla335[[#This Row],[CEDULA ]],'OCTUBRE 2025'!$C$8:$J$57,4,0) -> TALENTO HUMANO | F39: =+VLOOKUP(Tabla335[[#This Row],[CEDULA ]],'OCTUBRE 2025'!$C$8:$J$57,6,0) -> Matriz | G39: =+VLOOKUP(Tabla335[[#This Row],[CEDULA ]],'OCTUBRE 2025'!$C$8:$J$57,8,0) -> 766.65 | K39: =+Tabla335[[#This Row],[BONO BOLETOS]]+Tabla335[[#This Row],[COM. POR CARGO]]+Tabla335[[#This Row],[BONO CUMP]] -> 0
B40: 33 | C40: 956929277 | D40: =+VLOOKUP(Tabla335[[#This Row],[CEDULA ]],'OCTUBRE 2025'!$C$8:$J$57,2,0) -> NAULA CRIOLLO CINTHYA ABIGAIL | E40: =+VLOOKUP(Tabla335[[#This Row],[CEDULA ]],'OCTUBRE 2025'!$C$8:$J$57,4,0) -> CAJERO FINANCIERO | F40: =+VLOOKUP(Tabla335[[#This Row],[CEDULA ]],'OCTUBRE 2025'!$C$8:$J$57,6,0) -> Matriz | G40: =+VLOOKUP(Tabla335[[#This Row],[CEDULA ]],'OCTUBRE 2025'!$C$8:$J$57,8,0) -> 481 | K40: =+Tabla335[[#This Row],[BONO BOLETOS]]+Tabla335[[#This Row],[COM. POR CARGO]]+Tabla335[[#This Row],[BONO CUMP]] -> 0
B41: 34 | C41: 951763994 | D41: =+VLOOKUP(Tabla335[[#This Row],[CEDULA ]],'OCTUBRE 2025'!$C$8:$J$57,2,0) -> NEVAREZ PEÑAFIEL EVELYN JULEXY | E41: =+VLOOKUP(Tabla335[[#This Row],[CEDULA ]],'OCTUBRE 2025'!$C$8:$J$57,4,0) -> ASESOR DE CAPTACIONES | F41: =+VLOOKUP(Tabla335[[#This Row],[CEDULA ]],'OCTUBRE 2025'!$C$8:$J$57,6,0) -> Norte | G41: =+VLOOKUP(Tabla335[[#This Row],[CEDULA ]],'OCTUBRE 2025'!$C$8:$J$57,8,0) -> 475.85 | K41: =+Tabla335[[#This Row],[BONO BOLETOS]]+Tabla335[[#This Row],[COM. POR CARGO]]+Tabla335[[#This Row],[BONO CUMP]] -> 0
B42: 35 | C42: 950703199 | D42: =+VLOOKUP(Tabla335[[#This Row],[CEDULA ]],'OCTUBRE 2025'!$C$8:$J$57,2,0) -> ÑAMO GUALACEO BRYAN JAVIER | E42: =+VLOOKUP(Tabla335[[#This Row],[CEDULA ]],'OCTUBRE 2025'!$C$8:$J$57,4,0) -> OFICIAL DE RECAUDACIONES | F42: =+VLOOKUP(Tabla335[[#This Row],[CEDULA ]],'OCTUBRE 2025'!$C$8:$J$57,6,0) -> Matriz | G42: =+VLOOKUP(Tabla335[[#This Row],[CEDULA ]],'OCTUBRE 2025'!$C$8:$J$57,8,0) -> 473.88 | K42: =+Tabla335[[#This Row],[BONO BOLETOS]]+Tabla335[[#This Row],[COM. POR CARGO]]+Tabla335[[#This Row],[BONO CUMP]] -> 0
B43: 36 | C43: 0923715692 | D43: =+VLOOKUP(Tabla335[[#This Row],[CEDULA ]],'OCTUBRE 2025'!$C$8:$J$57,2,0) -> ORELLANA MANZO WHITNEY YAILYN | E43: =+VLOOKUP(Tabla335[[#This Row],[CEDULA ]],'OCTUBRE 2025'!$C$8:$J$57,4,0) -> OFICIAL DE SEGURIDAD DE LA INFORMACIÓN | F43: =+VLOOKUP(Tabla335[[#This Row],[CEDULA ]],'OCTUBRE 2025'!$C$8:$J$57,6,0) -> Matriz | G43: =+VLOOKUP(Tabla335[[#This Row],[CEDULA ]],'OCTUBRE 2025'!$C$8:$J$57,8,0) -> 600 | K43: =+Tabla335[[#This Row],[BONO BOLETOS]]+Tabla335[[#This Row],[COM. POR CARGO]]+Tabla335[[#This Row],[BONO CUMP]] -> 0
B44: 37 | C44: 925830689 | D44: =+VLOOKUP(Tabla335[[#This Row],[CEDULA ]],'OCTUBRE 2025'!$C$8:$J$57,2,0) -> PERALTA MENDEZ LINA LISSETTE | E44: =+VLOOKUP(Tabla335[[#This Row],[CEDULA ]],'OCTUBRE 2025'!$C$8:$J$57,4,0) -> JEFE DE CRÉDITO | F44: =+VLOOKUP(Tabla335[[#This Row],[CEDULA ]],'OCTUBRE 2025'!$C$8:$J$57,6,0) -> Matriz | G44: =+VLOOKUP(Tabla335[[#This Row],[CEDULA ]],'OCTUBRE 2025'!$C$8:$J$57,8,0) -> 1022.2 | K44: =+Tabla335[[#This Row],[BONO BOLETOS]]+Tabla335[[#This Row],[COM. POR CARGO]]+Tabla335[[#This Row],[BONO CUMP]] -> 0
B45: 38 | C45: 944034842 | D45: =+VLOOKUP(Tabla335[[#This Row],[CEDULA ]],'OCTUBRE 2025'!$C$8:$J$57,2,0) -> PEREZ ZAMORA ANA DE LOS ANGELES | E45: =+VLOOKUP(Tabla335[[#This Row],[CEDULA ]],'OCTUBRE 2025'!$C$8:$J$57,4,0) -> CAJERO FINANCIERO | F45: =+VLOOKUP(Tabla335[[#This Row],[CEDULA ]],'OCTUBRE 2025'!$C$8:$J$57,6,0) -> Matriz | G45: =+VLOOKUP(Tabla335[[#This Row],[CEDULA ]],'OCTUBRE 2025'!$C$8:$J$57,8,0) -> 256.53 | K45: =+Tabla335[[#This Row],[BONO BOLETOS]]+Tabla335[[#This Row],[COM. POR CARGO]]+Tabla335[[#This Row],[BONO CUMP]] -> 0
B46: 39 | C46: 951340702 | D46: =+VLOOKUP(Tabla335[[#This Row],[CEDULA ]],'OCTUBRE 2025'!$C$8:$J$57,2,0) -> QUITO CALDERON JONATHAN ENRIQUE | E46: =+VLOOKUP(Tabla335[[#This Row],[CEDULA ]],'OCTUBRE 2025'!$C$8:$J$57,4,0) -> JEFE DE COBRANZAS | F46: =+VLOOKUP(Tabla335[[#This Row],[CEDULA ]],'OCTUBRE 2025'!$C$8:$J$57,6,0) -> Matriz | G46: =+VLOOKUP(Tabla335[[#This Row],[CEDULA ]],'OCTUBRE 2025'!$C$8:$J$57,8,0) -> 817.76 | K46: =+Tabla335[[#This Row],[BONO BOLETOS]]+Tabla335[[#This Row],[COM. POR CARGO]]+Tabla335[[#This Row],[BONO CUMP]] -> 0
B47: 40 | C47: 650112949 | D47: =+VLOOKUP(Tabla335[[#This Row],[CEDULA ]],'OCTUBRE 2025'!$C$8:$J$57,2,0) -> QUITO UCHUBANDA JANETH ALEXANDRA | E47: =+VLOOKUP(Tabla335[[#This Row],[CEDULA ]],'OCTUBRE 2025'!$C$8:$J$57,4,0) -> OFICIAL DE RECAUDACIONES | F47: =+VLOOKUP(Tabla335[[#This Row],[CEDULA ]],'OCTUBRE 2025'!$C$8:$J$57,6,0) -> Norte | G47: =+VLOOKUP(Tabla335[[#This Row],[CEDULA ]],'OCTUBRE 2025'!$C$8:$J$57,8,0) -> 473.88 | K47: =+Tabla335[[#This Row],[BONO BOLETOS]]+Tabla335[[#This Row],[COM. POR CARGO]]+Tabla335[[#This Row],[BONO CUMP]] -> 0
B48: 41 | C48: 924232804 | D48: =+VLOOKUP(Tabla335[[#This Row],[CEDULA ]],'OCTUBRE 2025'!$C$8:$J$57,2,0) -> RECALDE NARANJO ANGEL ALEXIS | E48: =+VLOOKUP(Tabla335[[#This Row],[CEDULA ]],'OCTUBRE 2025'!$C$8:$J$57,4,0) -> JEFE TI | F48: =+VLOOKUP(Tabla335[[#This Row],[CEDULA ]],'OCTUBRE 2025'!$C$8:$J$57,6,0) -> Matriz | G48: =+VLOOKUP(Tabla335[[#This Row],[CEDULA ]],'OCTUBRE 2025'!$C$8:$J$57,8,0) -> 1022.2 | K48: =+Tabla335[[#This Row],[BONO BOLETOS]]+Tabla335[[#This Row],[COM. POR CARGO]]+Tabla335[[#This Row],[BONO CUMP]] -> 0
B49: 42 | C49: 605031145 | D49: =+VLOOKUP(Tabla335[[#This Row],[CEDULA ]],'OCTUBRE 2025'!$C$8:$J$57,2,0) -> SALAO PEREZ GERMAN FABRICIO | E49: =+VLOOKUP(Tabla335[[#This Row],[CEDULA ]],'OCTUBRE 2025'!$C$8:$J$57,4,0) -> ASESOR DE NEGOCIOS | F49: =+VLOOKUP(Tabla335[[#This Row],[CEDULA ]],'OCTUBRE 2025'!$C$8:$J$57,6,0) -> Durán | G49: =+VLOOKUP(Tabla335[[#This Row],[CEDULA ]],'OCTUBRE 2025'!$C$8:$J$57,8,0) -> 613.32 | J49: 0 | K49: =+Tabla335[[#This Row],[BONO BOLETOS]]+Tabla335[[#This Row],[COM. POR CARGO]]+Tabla335[[#This Row],[BONO CUMP]] -> 0
B50: 43 | C50: 927257576 | D50: =+VLOOKUP(Tabla335[[#This Row],[CEDULA ]],'OCTUBRE 2025'!$C$8:$J$57,2,0) -> SANISACA MITE ISRAEL BENJAMIN | E50: =+VLOOKUP(Tabla335[[#This Row],[CEDULA ]],'OCTUBRE 2025'!$C$8:$J$57,4,0) -> JEFE DE CRÉDITO | F50: =+VLOOKUP(Tabla335[[#This Row],[CEDULA ]],'OCTUBRE 2025'!$C$8:$J$57,6,0) -> Norte | G50: =+VLOOKUP(Tabla335[[#This Row],[CEDULA ]],'OCTUBRE 2025'!$C$8:$J$57,8,0) -> 1022.2 | K50: =+Tabla335[[#This Row],[BONO BOLETOS]]+Tabla335[[#This Row],[COM. POR CARGO]]+Tabla335[[#This Row],[BONO CUMP]] -> 0
B51: 44 | C51: 928901800 | D51: =+VLOOKUP(Tabla335[[#This Row],[CEDULA ]],'OCTUBRE 2025'!$C$8:$J$57,2,0) -> TADAY GUAMAN NÉSTOR ALONSO | E51: =+VLOOKUP(Tabla335[[#This Row],[CEDULA ]],'OCTUBRE 2025'!$C$8:$J$57,4,0) -> JEFE DE BOVEDA | F51: =+VLOOKUP(Tabla335[[#This Row],[CEDULA ]],'OCTUBRE 2025'!$C$8:$J$57,6,0) -> Matriz | G51: =+VLOOKUP(Tabla335[[#This Row],[CEDULA ]],'OCTUBRE 2025'!$C$8:$J$57,8,0) -> 511.1 | K51: =+Tabla335[[#This Row],[BONO BOLETOS]]+Tabla335[[#This Row],[COM. POR CARGO]]+Tabla335[[#This Row],[BONO CUMP]] -> 0
B52: 45 | C52: 951315746 | D52: =+VLOOKUP(Tabla335[[#This Row],[CEDULA ]],'OCTUBRE 2025'!$C$8:$J$57,2,0) -> TIGUA MONTERO KAREN LISBETH | E52: =+VLOOKUP(Tabla335[[#This Row],[CEDULA ]],'OCTUBRE 2025'!$C$8:$J$57,4,0) -> ASESOR DE NEGOCIOS | F52: =+VLOOKUP(Tabla335[[#This Row],[CEDULA ]],'OCTUBRE 2025'!$C$8:$J$57,6,0) -> Matriz | G52: =+VLOOKUP(Tabla335[[#This Row],[CEDULA ]],'OCTUBRE 2025'!$C$8:$J$57,8,0) -> 613.32 | J52: 0 | K52: =+Tabla335[[#This Row],[BONO BOLETOS]]+Tabla335[[#This Row],[COM. POR CARGO]]+Tabla335[[#This Row],[BONO CUMP]] -> 0
B53: 46 | C53: 954184321 | D53: =+VLOOKUP(Tabla335[[#This Row],[CEDULA ]],'OCTUBRE 2025'!$C$8:$J$57,2,0) -> URQUIZO GUARANGA ALEX EFRAIN | E53: =+VLOOKUP(Tabla335[[#This Row],[CEDULA ]],'OCTUBRE 2025'!$C$8:$J$57,4,0) -> OFICIAL DE RECAUDACIONES | F53: =+VLOOKUP(Tabla335[[#This Row],[CEDULA ]],'OCTUBRE 2025'!$C$8:$J$57,6,0) -> Matriz | G53: =+VLOOKUP(Tabla335[[#This Row],[CEDULA ]],'OCTUBRE 2025'!$C$8:$J$57,8,0) -> 511.1 | K53: =+Tabla335[[#This Row],[BONO BOLETOS]]+Tabla335[[#This Row],[COM. POR CARGO]]+Tabla335[[#This Row],[BONO CUMP]] -> 0
B54: 47 | C54: 922034772 | D54: =+VLOOKUP(Tabla335[[#This Row],[CEDULA ]],'OCTUBRE 2025'!$C$8:$J$57,2,0) -> VERA GUEVARA PAOLA KARINA | E54: =+VLOOKUP(Tabla335[[#This Row],[CEDULA ]],'OCTUBRE 2025'!$C$8:$J$57,4,0) -> ASESOR DE CAPTACIONES | F54: =+VLOOKUP(Tabla335[[#This Row],[CEDULA ]],'OCTUBRE 2025'!$C$8:$J$57,6,0) -> Matriz | G54: =+VLOOKUP(Tabla335[[#This Row],[CEDULA ]],'OCTUBRE 2025'!$C$8:$J$57,8,0) -> 700 | J54: 0 | K54: =+Tabla335[[#This Row],[BONO BOLETOS]]+Tabla335[[#This Row],[COM. POR CARGO]]+Tabla335[[#This Row],[BONO CUMP]] -> 0
B55: 48 | C55: 923837991 | D55: =+VLOOKUP(Tabla335[[#This Row],[CEDULA ]],'OCTUBRE 2025'!$C$8:$J$57,2,0) -> YUNDA CUJILEMA MARIA TERESA | E55: =+VLOOKUP(Tabla335[[#This Row],[CEDULA ]],'OCTUBRE 2025'!$C$8:$J$57,4,0) -> CONTADOR GENERAL | F55: =+VLOOKUP(Tabla335[[#This Row],[CEDULA ]],'OCTUBRE 2025'!$C$8:$J$57,6,0) -> Matriz | G55: =+VLOOKUP(Tabla335[[#This Row],[CEDULA ]],'OCTUBRE 2025'!$C$8:$J$57,8,0) -> 1022.2 | K55: =+Tabla335[[#This Row],[BONO BOLETOS]]+Tabla335[[#This Row],[COM. POR CARGO]]+Tabla335[[#This Row],[BONO CUMP]] -> 0
B56: 49 | C56: 941508905 | D56: =+VLOOKUP(Tabla335[[#This Row],[CEDULA ]],'OCTUBRE 2025'!$C$8:$J$57,2,0) -> YUQUILEMA CACUANGO ANGEL JOSE | E56: =+VLOOKUP(Tabla335[[#This Row],[CEDULA ]],'OCTUBRE 2025'!$C$8:$J$57,4,0) -> OFICIAL DE RECAUDACIONES | F56: =+VLOOKUP(Tabla335[[#This Row],[CEDULA ]],'OCTUBRE 2025'!$C$8:$J$57,6,0) -> Matriz | G56: =+VLOOKUP(Tabla335[[#This Row],[CEDULA ]],'OCTUBRE 2025'!$C$8:$J$57,8,0) -> 511.1 | K56: =+Tabla335[[#This Row],[BONO BOLETOS]]+Tabla335[[#This Row],[COM. POR CARGO]]+Tabla335[[#This Row],[BONO CUMP]] -> 0
B57: 50 | C57: 604154575 | D57: =+VLOOKUP(Tabla335[[#This Row],[CEDULA ]],'OCTUBRE 2025'!$C$8:$J$57,2,0) -> YUQUILEMA DELGADO PEDRO ANTONIO | E57: =+VLOOKUP(Tabla335[[#This Row],[CEDULA ]],'OCTUBRE 2025'!$C$8:$J$57,4,0) -> JEFE DE CRÉDITO | F57: =+VLOOKUP(Tabla335[[#This Row],[CEDULA ]],'OCTUBRE 2025'!$C$8:$J$57,6,0) -> Durán | G57: =+VLOOKUP(Tabla335[[#This Row],[CEDULA ]],'OCTUBRE 2025'!$C$8:$J$57,8,0) -> 1022.2 | K57: =+Tabla335[[#This Row],[BONO BOLETOS]]+Tabla335[[#This Row],[COM. POR CARGO]]+Tabla335[[#This Row],[BONO CUMP]] -> 0
J58: 0 | K58: =+Tabla335[[#This Row],[BONO BOLETOS]]+Tabla335[[#This Row],[COM. POR CARGO]]+Tabla335[[#This Row],[BONO CUMP]] -> 0
D59: TOTALES | G59: =SUBTOTAL(109,Tabla335[SUELDO]) -> 30990.65 | H59: =SUBTOTAL(109,Tabla335[BONO BOLETOS]) -> 0 | I59: =SUBTOTAL(109,Tabla335[COM. POR CARGO]) -> 0 | J59: =SUBTOTAL(109,Tabla335[BONO CUMP]) -> 737.54 | K59: =SUBTOTAL(109,Tabla335[US$,,]) -> 737.54

Sheet COMISIONES-SOCIOS
B2: CÁLCULO DE COMISIONES POR APERTURA
B3: NÓMINA SEPTIEMBRE 2025
H5: SOCIOS NUEVOS | J5: VALOR | L5: TOTAL COMISIÓN
H6: APERTURA | I6: APERT+CRÉD | J6: 5 | K6: 10
B7: NO | C7: CEDULA | D7: NOMBRE | E7: CARGO | F7: Agencia | G7: SUELDO | H7: Cantidad | I7: Cantidad2 | J7: US$ | K7: US$, | L7: US$,,
B8: 1 | C8: 925813685 | D8: =+VLOOKUP(Tabla33[[#This Row],[CEDULA ]],'OCTUBRE 2025'!$C$8:$J$57,2,0) -> ASITIMBAY CRIOLLO JOHN ANDERSON | E8: =+VLOOKUP(Tabla33[[#This Row],[CEDULA ]],'OCTUBRE 2025'!$C$8:$J$57,4,0) -> JEFE DE MARKETING | F8: =+VLOOKUP(Tabla33[[#This Row],[CEDULA ]],'OCTUBRE 2025'!$C$8:$J$57,6,0) -> Matriz | G8: =+VLOOKUP(Tabla33[[#This Row],[CEDULA ]],'OCTUBRE 2025'!$C$8:$J$57,8,0) -> 817.76 | J8: =+Tabla33[[#This Row],[Cantidad]]*$J$6 -> 0 | K8: =+Tabla33[[#This Row],[Cantidad2]]*$K$6 -> 0 | L8: =+Tabla33[[#This Row],[US$]]+Tabla33[[#This Row],[US$,]] -> 0
B9: 2 | C9: 944405737 | D9: =+VLOOKUP(Tabla33[[#This Row],[CEDULA ]],'OCTUBRE 2025'!$C$8:$J$57,2,0) -> BARAHONA ZAMBRANO DAYANA NICOLE | E9: =+VLOOKUP(Tabla33[[#This Row],[CEDULA ]],'OCTUBRE 2025'!$C$8:$J$57,4,0) -> CAJERO FINANCIERO | F9: =+VLOOKUP(Tabla33[[#This Row],[CEDULA ]],'OCTUBRE 2025'!$C$8:$J$57,6,0) -> Matriz | G9: =+VLOOKUP(Tabla33[[#This Row],[CEDULA ]],'OCTUBRE 2025'!$C$8:$J$57,8,0) -> 15.86 | J9: =+Tabla33[[#This Row],[Cantidad]]*$J$6 -> 0 | K9: =+Tabla33[[#This Row],[Cantidad2]]*$K$6 -> 0 | L9: =+Tabla33[[#This Row],[US$]]+Tabla33[[#This Row],[US$,]] -> 0
B10: 3 | C10: 604394502 | D10: =+VLOOKUP(Tabla33[[#This Row],[CEDULA ]],'OCTUBRE 2025'!$C$8:$J$57,2,0) -> BETUN CHAFLA JULIO CESAR | E10: =+VLOOKUP(Tabla33[[#This Row],[CEDULA ]],'OCTUBRE 2025'!$C$8:$J$57,4,0) -> ASESOR DE NEGOCIOS | F10: =+VLOOKUP(Tabla33[[#This Row],[CEDULA ]],'OCTUBRE 2025'!$C$8:$J$57,6,0) -> Matriz | G10: =+VLOOKUP(Tabla33[[#This Row],[CEDULA ]],'OCTUBRE 2025'!$C$8:$J$57,8,0) -> 613.32 | J10: =+Tabla33[[#This Row],[Cantidad]]*$J$6 -> 0 | K10: =+Tabla33[[#This Row],[Cantidad2]]*$K$6 -> 0 | L10: =+Tabla33[[#This Row],[US$]]+Tabla33[[#This Row],[US$,]] -> 0
B11: 4 | C11: 955741970 | D11: =+VLOOKUP(Tabla33[[#This Row],[CEDULA ]],'OCTUBRE 2025'!$C$8:$J$57,2,0) -> CHACAGUASAY CHACAGUASAY ROBERTH CRISTHIAN | E11: =+VLOOKUP(Tabla33[[#This Row],[CEDULA ]],'OCTUBRE 2025'!$C$8:$J$57,4,0) -> OFICIAL DE RECAUDACIONES | F11: =+VLOOKUP(Tabla33[[#This Row],[CEDULA ]],'OCTUBRE 2025'!$C$8:$J$57,6,0) -> Matriz | G11: =+VLOOKUP(Tabla33[[#This Row],[CEDULA ]],'OCTUBRE 2025'!$C$8:$J$57,8,0) -> 473.88 | J11: =+Tabla33[[#This Row],[Cantidad]]*$J$6 -> 0 | K11: =+Tabla33[[#This Row],[Cantidad2]]*$K$6 -> 0 | L11: =+Tabla33[[#This Row],[US$]]+Tabla33[[#This Row],[US$,]] -> 0
B12: 5 | C12: 0943964973 | D12: =+VLOOKUP(Tabla33[[#This Row],[CEDULA ]],'OCTUBRE 2025'!$C$8:$J$57,2,0) -> CHACAGUASAY GUAMAN KEVIN NEHEMIAS | E12: =+VLOOKUP(Tabla33[[#This Row],[CEDULA ]],'OCTUBRE 2025'!$C$8:$J$57,4,0) -> ASESOR DE NEGOCIOS | F12: =+VLOOKUP(Tabla33[[#This Row],[CEDULA ]],'OCTUBRE 2025'!$C$8:$J$57,6,0) -> Matriz | G12: =+VLOOKUP(Tabla33[[#This Row],[CEDULA ]],'OCTUBRE 2025'!$C$8:$J$57,8,0) -> 256.53 | J12: =+Tabla33[[#This Row],[Cantidad]]*$J$6 -> 0 | K12: =+Tabla33[[#This Row],[Cantidad2]]*$K$6 -> 0 | L12: =+Tabla33[[#This Row],[US$]]+Tabla33[[#This Row],[US$,]] -> 0
B13: 6 | C13: 944143148 | D13: =+VLOOKUP(Tabla33[[#This Row],[CEDULA ]],'OCTUBRE 2025'!$C$8:$J$57,2,0) -> CHIMBOLEMA YUNGAN MARIO EFRAIN | E13: =+VLOOKUP(Tabla33[[#This Row],[CEDULA ]],'OCTUBRE 2025'!$C$8:$J$57,4,0) -> OFICIAL DE RECAUDACIONES | F13: =+VLOOKUP(Tabla33[[#This Row],[CEDULA ]],'OCTUBRE 2025'!$C$8:$J$57,6,0) -> Durán | G13: =+VLOOKUP(Tabla33[[#This Row],[CEDULA ]],'OCTUBRE 2025'!$C$8:$J$57,8,0) -> 142.16 | J13: =+Tabla33[[#This Row],[Cantidad]]*$J$6 -> 0 | K13: =+Tabla33[[#This Row],[Cantidad2]]*$K$6 -> 0 | L13: =+Tabla33[[#This Row],[US$]]+Tabla33[[#This Row],[US$,]] -> 0
B14: 7 | C14: 955325238 | D14: =+VLOOKUP(Tabla33[[#This Row],[CEDULA ]],'OCTUBRE 2025'!$C$8:$J$57,2,0) -> CHOCA CEPEDA INES VIVIANA | E14: =+VLOOKUP(Tabla33[[#This Row],[CEDULA ]],'OCTUBRE 2025'!$C$8:$J$57,4,0) -> CAJERA FINANCIERA | F14: =+VLOOKUP(Tabla33[[#This Row],[CEDULA ]],'OCTUBRE 2025'!$C$8:$J$57,6,0) -> Matriz | G14: =+VLOOKUP(Tabla33[[#This Row],[CEDULA ]],'OCTUBRE 2025'!$C$8:$J$57,8,0) -> 256.53 | J14: =+Tabla33[[#This Row],[Cantidad]]*$J$6 -> 0 | K14: =+Tabla33[[#This Row],[Cantidad2]]*$K$6 -> 0 | L14: =+Tabla33[[#This Row],[US$]]+Tabla33[[#This Row],[US$,]] -> 0
B15: 8 | C15: 914163654 | D15: =+VLOOKUP(Tabla33[[#This Row],[CEDULA ]],'OCTUBRE 2025'!$C$8:$J$57,2,0) -> COCA BENITEZ JORGE MANUEL | E15: =+VLOOKUP(Tabla33[[#This Row],[CEDULA ]],'OCTUBRE 2025'!$C$8:$J$57,4,0) -> ANALISTA DE RIESGO | F15: =+VLOOKUP(Tabla33[[#This Row],[CEDULA ]],'OCTUBRE 2025'!$C$8:$J$57,6,0) -> Matriz | G15: =+VLOOKUP(Tabla33[[#This Row],[CEDULA ]],'OCTUBRE 2025'!$C$8:$J$57,8,0) -> 1200 | J15: =+Tabla33[[#This Row],[Cantidad]]*$J$6 -> 0 | K15: =+Tabla33[[#This Row],[Cantidad2]]*$K$6 -> 0 | L15: =+Tabla33[[#This Row],[US$]]+Tabla33[[#This Row],[US$,]] -> 0
B16: 9 | C16: 956668305 | D16: =+VLOOKUP(Tabla33[[#This Row],[CEDULA ]],'OCTUBRE 2025'!$C$8:$J$57,2,0) -> CORO YUQUILEMA RUTH NOEMI | E16: =+VLOOKUP(Tabla33[[#This Row],[CEDULA ]],'OCTUBRE 2025'!$C$8:$J$57,4,0) -> OFICIAL DE RECAUDACIONES | F16: =+VLOOKUP(Tabla33[[#This Row],[CEDULA ]],'OCTUBRE 2025'!$C$8:$J$57,6,0) -> Matriz | G16: =+VLOOKUP(Tabla33[[#This Row],[CEDULA ]],'OCTUBRE 2025'!$C$8:$J$57,8,0) -> 252.74 | J16: =+Tabla33[[#This Row],[Cantidad]]*$J$6 -> 0 | K16: =+Tabla33[[#This Row],[Cantidad2]]*$K$6 -> 0 | L16: =+Tabla33[[#This Row],[US$]]+Tabla33[[#This Row],[US$,]] -> 0
B17: 10 | C17: 0918741448 | D17: =+VLOOKUP(Tabla33[[#This Row],[CEDULA ]],'OCTUBRE 2025'!$C$8:$J$57,2,0) -> DEFAS CHICAIZA JOEL ALBERTO | E17: =+VLOOKUP(Tabla33[[#This Row],[CEDULA ]],'OCTUBRE 2025'!$C$8:$J$57,4,0) -> ASESOR DE NEGOCIOS | F17: =+VLOOKUP(Tabla33[[#This Row],[CEDULA ]],'OCTUBRE 2025'!$C$8:$J$57,6,0) -> Norte | G17: =+VLOOKUP(Tabla33[[#This Row],[CEDULA ]],'OCTUBRE 2025'!$C$8:$J$57,8,0) -> 626.65 | J17: =+Tabla33[[#This Row],[Cantidad]]*$J$6 -> 0 | K17: =+Tabla33[[#This Row],[Cantidad2]]*$K$6 -> 0 | L17: =+Tabla33[[#This Row],[US$]]+Tabla33[[#This Row],[US$,]] -> 0
B18: 11 | C18: 931097620 | D18: =+VLOOKUP(Tabla33[[#This Row],[CEDULA ]],'OCTUBRE 2025'!$C$8:$J$57,2,0) -> DEL ROSARIO RODRIGUEZ JUDY ANGELICA | E18: =+VLOOKUP(Tabla33[[#This Row],[CEDULA ]],'OCTUBRE 2025'!$C$8:$J$57,4,0) -> CAJERA FINANCIERA | F18: =+VLOOKUP(Tabla33[[#This Row],[CEDULA ]],'OCTUBRE 2025'!$C$8:$J$57,6,0) -> Norte | G18: =+VLOOKUP(Tabla33[[#This Row],[CEDULA ]],'OCTUBRE 2025'!$C$8:$J$57,8,0) -> 256.53 | J18: =+Tabla33[[#This Row],[Cantidad]]*$J$6 -> 0 | K18: =+Tabla33[[#This Row],[Cantidad2]]*$K$6 -> 0 | L18: =+Tabla33[[#This Row],[US$]]+Tabla33[[#This Row],[US$,]] -> 0
B19: 12 | C19: 1105483422 | D19: =+VLOOKUP(Tabla33[[#This Row],[CEDULA ]],'OCTUBRE 2025'!$C$8:$J$57,2,0) -> FLORES HERRERA WENDY DEL CISNE | E19: =+VLOOKUP(Tabla33[[#This Row],[CEDULA ]],'OCTUBRE 2025'!$C$8:$J$57,4,0) -> CAJERO FINANCIERO | F19: =+VLOOKUP(Tabla33[[#This Row],[CEDULA ]],'OCTUBRE 2025'!$C$8:$J$57,6,0) -> Durán | G19: =+VLOOKUP(Tabla33[[#This Row],[CEDULA ]],'OCTUBRE 2025'!$C$8:$J$57,8,0) -> 650 | J19: =+Tabla33[[#This Row],[Cantidad]]*$J$6 -> 0 | K19: =+Tabla33[[#This Row],[Cantidad2]]*$K$6 -> 0 | L19: =+Tabla33[[#This Row],[US$]]+Tabla33[[#This Row],[US$,]] -> 0
B20: 13 | C20: 942614645 | D20: =+VLOOKUP(Tabla33[[#This Row],[CEDULA ]],'OCTUBRE 2025'!$C$8:$J$57,2,0) -> FUELA TOABANDA JOSUE CHRISTIAN | E20: =+VLOOKUP(Tabla33[[#This Row],[CEDULA ]],'OCTUBRE 2025'!$C$8:$J$57,4,0) -> ASISTENTE CONTABLE | F20: =+VLOOKUP(Tabla33[[#This Row],[CEDULA ]],'OCTUBRE 2025'!$C$8:$J$57,6,0) -> Matriz | G20: =+VLOOKUP(Tabla33[[#This Row],[CEDULA ]],'OCTUBRE 2025'!$C$8:$J$57,8,0) -> 481 | J20: =+Tabla33[[#This Row],[Cantidad]]*$J$6 -> 0 | K20: =+Tabla33[[#This Row],[Cantidad2]]*$K$6 -> 0 | L20: =+Tabla33[[#This Row],[US$]]+Tabla33[[#This Row],[US$,]] -> 0
B21: 14 | C21: 951200062 | D21: =+VLOOKUP(Tabla33[[#This Row],[CEDULA ]],'OCTUBRE 2025'!$C$8:$J$57,2,0) -> GALAN LEMACHE INGRID GISELA | E21: =+VLOOKUP(Tabla33[[#This Row],[CEDULA ]],'OCTUBRE 2025'!$C$8:$J$57,4,0) -> BACK UP ADMINISTRATIVO FINANCIERO | F21: =+VLOOKUP(Tabla33[[#This Row],[CEDULA ]],'OCTUBRE 2025'!$C$8:$J$57,6,0) -> Norte | G21: =+VLOOKUP(Tabla33[[#This Row],[CEDULA ]],'OCTUBRE 2025'!$C$8:$J$57,8,0) -> 473.88 | J21: =+Tabla33[[#This Row],[Cantidad]]*$J$6 -> 0 | K21: =+Tabla33[[#This Row],[Cantidad2]]*$K$6 -> 0 | L21: =+Tabla33[[#This Row],[US$]]+Tabla33[[#This Row],[US$,]] -> 0
B22: 15 | C22: 950929232 | D22: =+VLOOKUP(Tabla33[[#This Row],[CEDULA ]],'OCTUBRE 2025'!$C$8:$J$57,2,0) -> GARCIA VERA HENRY LUIS | E22: =+VLOOKUP(Tabla33[[#This Row],[CEDULA ]],'OCTUBRE 2025'!$C$8:$J$57,4,0) -> OFICIAL DE RECAUDACIONES | F22: =+VLOOKUP(Tabla33[[#This Row],[CEDULA ]],'OCTUBRE 2025'!$C$8:$J$57,6,0) -> Norte | G22: =+VLOOKUP(Tabla33[[#This Row],[CEDULA ]],'OCTUBRE 2025'!$C$8:$J$57,8,0) -> 715.54 | J22: =+Tabla33[[#This Row],[Cantidad]]*$J$6 -> 0 | K22: =+Tabla33[[#This Row],[Cantidad2]]*$K$6 -> 0 | L22: =+Tabla33[[#This Row],[US$]]+Tabla33[[#This Row],[US$,]] -> 0
B23: 16 | C23: 953819646 | D23: =+VLOOKUP(Tabla33[[#This Row],[CEDULA ]],'OCTUBRE 2025'!$C$8:$J$57,2,0) -> GUALACEO ÑAMO JONATHAN IVÁN | E23: =+VLOOKUP(Tabla33[[#This Row],[CEDULA ]],'OCTUBRE 2025'!$C$8:$J$57,4,0) -> OFICIAL DE RECAUDACIONES | F23: =+VLOOKUP(Tabla33[[#This Row],[CEDULA ]],'OCTUBRE 2025'!$C$8:$J$57,6,0) -> Matriz | G23: =+VLOOKUP(Tabla33[[#This Row],[CEDULA ]],'OCTUBRE 2025'!$C$8:$J$57,8,0) -> 511.1 | J23: =+Tabla33[[#This Row],[Cantidad]]*$J$6 -> 0 | K23: =+Tabla33[[#This Row],[Cantidad2]]*$K$6 -> 0 | L23: =+Tabla33[[#This Row],[US$]]+Tabla33[[#This Row],[US$,]] -> 0
B24: 17 | C24: 956953392 | D24: =+VLOOKUP(Tabla33[[#This Row],[CEDULA ]],'OCTUBRE 2025'!$C$8:$J$57,2,0) -> GUAPI YUMAGLLA OSCAR EDUARDO | E24: =+VLOOKUP(Tabla33[[#This Row],[CEDULA ]],'OCTUBRE 2025'!$C$8:$J$57,4,0) -> OFICIAL DE RECAUDACIONES | F24: =+VLOOKUP(Tabla33[[#This Row],[CEDULA ]],'OCTUBRE 2025'!$C$8:$J$57,6,0) -> Matriz | G24: =+VLOOKUP(Tabla33[[#This Row],[CEDULA ]],'OCTUBRE 2025'!$C$8:$J$57,8,0) -> 473.88 | J24: =+Tabla33[[#This Row],[Cantidad]]*$J$6 -> 0 | K24: =+Tabla33[[#This Row],[Cantidad2]]*$K$6 -> 0 | L24: =+Tabla33[[#This Row],[US$]]+Tabla33[[#This Row],[US$,]] -> 0
B25: 18 | C25: 956796767 | D25: =+VLOOKUP(Tabla33[[#This Row],[CEDULA ]],'OCTUBRE 2025'!$C$8:$J$57,2,0) -> GUAYANLEMA RUIZ EDINSON DAVID | E25: =+VLOOKUP(Tabla33[[#This Row],[CEDULA ]],'OCTUBRE 2025'!$C$8:$J$57,4,0) -> OFICIAL DE RECAUDACIONES | F25: =+VLOOKUP(Tabla33[[#This Row],[CEDULA ]],'OCTUBRE 2025'!$C$8:$J$57,6,0) -> Norte | G25: =+VLOOKUP(Tabla33[[#This Row],[CEDULA ]],'OCTUBRE 2025'!$C$8:$J$57,8,0) -> 473.88 | J25: =+Tabla33[[#This Row],[Cantidad]]*$J$6 -> 0 | K25: =+Tabla33[[#This Row],[Cantidad2]]*$K$6 -> 0 | L25: =+Tabla33[[#This Row],[US$]]+Tabla33[[#This Row],[US$,]] -> 0
B26: 19 | C26: 0932036049 | D26: =+VLOOKUP(Tabla33[[#This Row],[CEDULA ]],'OCTUBRE 2025'!$C$8:$J$57,2,0) -> HERRERA JIMENEZ CAROLINA ADELIHER | E26: =+VLOOKUP(Tabla33[[#This Row],[CEDULA ]],'OCTUBRE 2025'!$C$8:$J$57,4,0) -> ASISTENTE DE OPERACIONES | F26: =+VLOOKUP(Tabla33[[#This Row],[CEDULA ]],'OCTUBRE 2025'!$C$8:$J$57,6,0) -> Matriz | G26: =+VLOOKUP(Tabla33[[#This Row],[CEDULA ]],'OCTUBRE 2025'!$C$8:$J$57,8,0) -> 481 | J26: =+Tabla33[[#This Row],[Cantidad]]*$J$6 -> 0 | K26: =+Tabla33[[#This Row],[Cantidad2]]*$K$6 -> 0 | L26: =+Tabla33[[#This Row],[US$]]+Tabla33[[#This Row],[US$,]] -> 0
B27: 20 | C27: 1724102940 | D27: =+VLOOKUP(Tabla33[[#This Row],[CEDULA ]],'OCTUBRE 2025'!$C$8:$J$57,2,0) -> HIDALGO CHERRES NESTOR VLADIMIR | E27: =+VLOOKUP(Tabla33[[#This Row],[CEDULA ]],'OCTUBRE 2025'!$C$8:$J$57,4,0) -> JEFE DE CREDITO | F27: =+VLOOKUP(Tabla33[[#This Row],[CEDULA ]],'OCTUBRE 2025'!$C$8:$J$57,6,0) -> Durán | G27: =+VLOOKUP(Tabla33[[#This Row],[CEDULA ]],'OCTUBRE 2025'!$C$8:$J$57,8,0) -> 817.76 | J27: =+Tabla33[[#This Row],[Cantidad]]*$J$6 -> 0 | K27: =+Tabla33[[#This Row],[Cantidad2]]*$K$6 -> 0 | L27: =+Tabla33[[#This Row],[US$]]+Tabla33[[#This Row],[US$,]] -> 0
B28: 21 | C28: 943322974 | D28: =+VLOOKUP(Tabla33[[#This Row],[CEDULA ]],'OCTUBRE 2025'!$C$8:$J$57,2,0) -> JANETA RUIZ ALEXANDRA DEL ROCIO | E28: =+VLOOKUP(Tabla33[[#This Row],[CEDULA ]],'OCTUBRE 2025'!$C$8:$J$57,4,0) -> OFICIAL DE RECAUDACIONES | F28: =+VLOOKUP(Tabla33[[#This Row],[CEDULA ]],'OCTUBRE 2025'!$C$8:$J$57,6,0) -> Norte | G28: =+VLOOKUP(Tabla33[[#This Row],[CEDULA ]],'OCTUBRE 2025'!$C$8:$J$57,8,0) -> 473.88 | J28: =+Tabla33[[#This Row],[Cantidad]]*$J$6 -> 0 | K28: =+Tabla33[[#This Row],[Cantidad2]]*$K$6 -> 0 | L28: =+Tabla33[[#This Row],[US$]]+Tabla33[[#This Row],[US$,]] -> 0
B29: 22 | C29: 941096851 | D29: =+VLOOKUP(Tabla33[[#This Row],[CEDULA ]],'OCTUBRE 2025'!$C$8:$J$57,2,0) -> LEMA CHIRAU RAMONA MARIA | E29: =+VLOOKUP(Tabla33[[#This Row],[CEDULA ]],'OCTUBRE 2025'!$C$8:$J$57,4,0) -> ASESOR DE CAPTACIONES | F29: =+VLOOKUP(Tabla33[[#This Row],[CEDULA ]],'OCTUBRE 2025'!$C$8:$J$57,6,0) -> Durán | G29: =+VLOOKUP(Tabla33[[#This Row],[CEDULA ]],'OCTUBRE 2025'!$C$8:$J$57,8,0) -> 700 | J29: =+Tabla33[[#This Row],[Cantidad]]*$J$6 -> 0 | K29: =+Tabla33[[#This Row],[Cantidad2]]*$K$6 -> 0 | L29: =+Tabla33[[#This Row],[US$]]+Tabla33[[#This Row],[US$,]] -> 0
B30: 23 | C30: 957093800 | D30: =+VLOOKUP(Tabla33[[#This Row],[CEDULA ]],'OCTUBRE 2025'!$C$8:$J$57,2,0) -> LEMA TADAY BRAYAN WIDINSON | E30: =+VLOOKUP(Tabla33[[#This Row],[CEDULA ]],'OCTUBRE 2025'!$C$8:$J$57,4,0) -> OFICIAL DE RECAUDACIONES | F30: =+VLOOKUP(Tabla33[[#This Row],[CEDULA ]],'OCTUBRE 2025'!$C$8:$J$57,6,0) -> Durán | G30: =+VLOOKUP(Tabla33[[#This Row],[CEDULA ]],'OCTUBRE 2025'!$C$8:$J$57,8,0) -> 473.88 | J30: =+Tabla33[[#This Row],[Cantidad]]*$J$6 -> 0 | K30: =+Tabla33[[#This Row],[Cantidad2]]*$K$6 -> 0 | L30: =+Tabla33[[#This Row],[US$]]+Tabla33[[#This Row],[US$,]] -> 0
B31: 24 | C31: 957924350 | D31: =+VLOOKUP(Tabla33[[#This Row],[CEDULA ]],'OCTUBRE 2025'!$C$8:$J$57,2,0) -> LLUMI YUQUILEMA MAYCOOL DANNY | E31: =+VLOOKUP(Tabla33[[#This Row],[CEDULA ]],'OCTUBRE 2025'!$C$8:$J$57,4,0) -> ASESOR DE NEGOCIOS | F31: =+VLOOKUP(Tabla33[[#This Row],[CEDULA ]],'OCTUBRE 2025'!$C$8:$J$57,6,0) -> Matriz | G31: =+VLOOKUP(Tabla33[[#This Row],[CEDULA ]],'OCTUBRE 2025'!$C$8:$J$57,8,0) -> 481 | J31: =+Tabla33[[#This Row],[Cantidad]]*$J$6 -> 0 | K31: =+Tabla33[[#This Row],[Cantidad2]]*$K$6 -> 0 | L31: =+Tabla33[[#This Row],[US$]]+Tabla33[[#This Row],[US$,]] -> 0
B32: 25 | C32: 603838657 | D32: =+VLOOKUP(Tabla33[[#This Row],[CEDULA ]],'OCTUBRE 2025'!$C$8:$J$57,2,0) -> MALAN DELGADO JOSE ALBERTO | E32: =+VLOOKUP(Tabla33[[#This Row],[CEDULA ]],'OCTUBRE 2025'!$C$8:$J$57,4,0) -> OFICIAL DE RECAUDACIONES | F32: =+VLOOKUP(Tabla33[[#This Row],[CEDULA ]],'OCTUBRE 2025'!$C$8:$J$57,6,0) -> Durán | G32: =+VLOOKUP(Tabla33[[#This Row],[CEDULA ]],'OCTUBRE 2025'!$C$8:$J$57,8,0) -> 473.88 | J32: =+Tabla33[[#This Row],[Cantidad]]*$J$6 -> 0 | K32: =+Tabla33[[#This Row],[Cantidad2]]*$K$6 -> 0 | L32: =+Tabla33[[#This Row],[US$]]+Tabla33[[#This Row],[US$,]] -> 0
B33: 26 | C33: 925240525 | D33: =+VLOOKUP(Tabla33[[#This Row],[CEDULA ]],'OCTUBRE 2025'!$C$8:$J$57,2,0) -> MALAN YUQUILEMA RAUL ALBERTO | E33: =+VLOOKUP(Tabla33[[#This Row],[CEDULA ]],'OCTUBRE 2025'!$C$8:$J$57,4,0) -> ASESOR LEGAL | F33: =+VLOOKUP(Tabla33[[#This Row],[CEDULA ]],'OCTUBRE 2025'!$C$8:$J$57,6,0) -> Matriz | G33: =+VLOOKUP(Tabla33[[#This Row],[CEDULA ]],'OCTUBRE 2025'!$C$8:$J$57,8,0) -> 2700 | J33: =+Tabla33[[#This Row],[Cantidad]]*$J$6 -> 0 | K33: =+Tabla33[[#This Row],[Cantidad2]]*$K$6 -> 0 | L33: =+Tabla33[[#This Row],[US$]]+Tabla33[[#This Row],[US$,]] -> 0
B34: 27 | C34: 954520599 | D34: =+VLOOKUP(Tabla33[[#This Row],[CEDULA ]],'OCTUBRE 2025'!$C$8:$J$57,2,0) -> MARSHALL VEGA YULIANA LISSETT | E34: =+VLOOKUP(Tabla33[[#This Row],[CEDULA ]],'OCTUBRE 2025'!$C$8:$J$57,4,0) -> ASESOR DE NEGOCIOS | F34: =+VLOOKUP(Tabla33[[#This Row],[CEDULA ]],'OCTUBRE 2025'!$C$8:$J$57,6,0) -> Durán | G34: =+VLOOKUP(Tabla33[[#This Row],[CEDULA ]],'OCTUBRE 2025'!$C$8:$J$57,8,0) -> 613.32 | J34: =+Tabla33[[#This Row],[Cantidad]]*$J$6 -> 0 | K34: =+Tabla33[[#This Row],[Cantidad2]]*$K$6 -> 0 | L34: =+Tabla33[[#This Row],[US$]]+Tabla33[[#This Row],[US$,]] -> 0
B35: 28 | C35: 0943906032 | D35: =+VLOOKUP(Tabla33[[#This Row],[CEDULA ]],'OCTUBRE 2025'!$C$8:$J$57,2,0) -> MEZA RODRIGUEZ MICHAEL FERNANDO | E35: =+VLOOKUP(Tabla33[[#This Row],[CEDULA ]],'OCTUBRE 2025'!$C$8:$J$57,4,0) -> OFICIAL DE RECAUDACIONES | F35: =+VLOOKUP(Tabla33[[#This Row],[CEDULA ]],'OCTUBRE 2025'!$C$8:$J$57,6,0) -> Norte | G35: =+VLOOKUP(Tabla33[[#This Row],[CEDULA ]],'OCTUBRE 2025'!$C$8:$J$57,8,0) -> 473.88 | J35: =+Tabla33[[#This Row],[Cantidad]]*$J$6 -> 0 | K35: =+Tabla33[[#This Row],[Cantidad2]]*$K$6 -> 0 | L35: =+Tabla33[[#This Row],[US$]]+Tabla33[[#This Row],[US$,]] -> 0
B36: 29 | C36: 0919306050 | D36: =+VLOOKUP(Tabla33[[#This Row],[CEDULA ]],'OCTUBRE 2025'!$C$8:$J$57,2,0) -> MORAN GARCIA DANNY FAVIAN | E36: =+VLOOKUP(Tabla33[[#This Row],[CEDULA ]],'OCTUBRE 2025'!$C$8:$J$57,4,0) -> OFICIAL DE CUMPLIMIENTO | F36: =+VLOOKUP(Tabla33[[#This Row],[CEDULA ]],'OCTUBRE 2025'!$C$8:$J$57,6,0) -> Matriz | G36: =+VLOOKUP(Tabla33[[#This Row],[CEDULA ]],'OCTUBRE 2025'!$C$8:$J$57,8,0) -> 600 | J36: =+Tabla33[[#This Row],[Cantidad]]*$J$6 -> 0 | K36: =+Tabla33[[#This Row],[Cantidad2]]*$K$6 -> 0 | L36: =+Tabla33[[#This Row],[US$]]+Tabla33[[#This Row],[US$,]] -> 0
B37: 30 | C37: 0941235376 | D37: =+VLOOKUP(Tabla33[[#This Row],[CEDULA ]],'OCTUBRE 2025'!$C$8:$J$57,2,0) -> MOREIRA ESPINOZA LINDA ELIZABETH | E37: =+VLOOKUP(Tabla33[[#This Row],[CEDULA ]],'OCTUBRE 2025'!$C$8:$J$57,4,0) -> CAJERO FINANCIERO | F37: =+VLOOKUP(Tabla33[[#This Row],[CEDULA ]],'OCTUBRE 2025'!$C$8:$J$57,6,0) -> Durán | G37: =+VLOOKUP(Tabla33[[#This Row],[CEDULA ]],'OCTUBRE 2025'!$C$8:$J$57,8,0) -> 481 | J37: =+Tabla33[[#This Row],[Cantidad]]*$J$6 -> 0 | K37: =+Tabla33[[#This Row],[Cantidad2]]*$K$6 -> 0 | L37: =+Tabla33[[#This Row],[US$]]+Tabla33[[#This Row],[US$,]] -> 0
B38: 31 | C38: 955395686 | D38: =+VLOOKUP(Tabla33[[#This Row],[CEDULA ]],'OCTUBRE 2025'!$C$8:$J$57,2,0) -> MOROCHO DUCHI SANDRA STEPHANIE | E38: =+VLOOKUP(Tabla33[[#This Row],[CEDULA ]],'OCTUBRE 2025'!$C$8:$J$57,4,0) -> ASESOR DE NEGOCIOS | F38: =+VLOOKUP(Tabla33[[#This Row],[CEDULA ]],'OCTUBRE 2025'!$C$8:$J$57,6,0) -> Norte | G38: =+VLOOKUP(Tabla33[[#This Row],[CEDULA ]],'OCTUBRE 2025'!$C$8:$J$57,8,0) -> 613.32 | J38: =+Tabla33[[#This Row],[Cantidad]]*$J$6 -> 0 | K38: =+Tabla33[[#This Row],[Cantidad2]]*$K$6 -> 0 | L38: =+Tabla33[[#This Row],[US$]]+Tabla33[[#This Row],[US$,]] -> 0
B39: 32 | C39: 940991987 | D39: =+VLOOKUP(Tabla33[[#This Row],[CEDULA ]],'OCTUBRE 2025'!$C$8:$J$57,2,0) -> MOROCHO YANTALEMA DINA MAGALY | E39: =+VLOOKUP(Tabla33[[#This Row],[CEDULA ]],'OCTUBRE 2025'!$C$8:$J$57,4,0) -> TALENTO HUMANO | F39: =+VLOOKUP(Tabla33[[#This Row],[CEDULA ]],'OCTUBRE 2025'!$C$8:$J$57,6,0) -> Matriz | G39: =+VLOOKUP(Tabla33[[#This Row],[CEDULA ]],'OCTUBRE 2025'!$C$8:$J$57,8,0) -> 766.65 | J39: =+Tabla33[[#This Row],[Cantidad]]*$J$6 -> 0 | K39: =+Tabla33[[#This Row],[Cantidad2]]*$K$6 -> 0 | L39: =+Tabla33[[#This Row],[US$]]+Tabla33[[#This Row],[US$,]] -> 0
B40: 33 | C40: 956929277 | D40: =+VLOOKUP(Tabla33[[#This Row],[CEDULA ]],'OCTUBRE 2025'!$C$8:$J$57,2,0) -> NAULA CRIOLLO CINTHYA ABIGAIL | E40: =+VLOOKUP(Tabla33[[#This Row],[CEDULA ]],'OCTUBRE 2025'!$C$8:$J$57,4,0) -> CAJERO FINANCIERO | F40: =+VLOOKUP(Tabla33[[#This Row],[CEDULA ]],'OCTUBRE 2025'!$C$8:$J$57,6,0) -> Matriz | G40: =+VLOOKUP(Tabla33[[#This Row],[CEDULA ]],'OCTUBRE 2025'!$C$8:$J$57,8,0) -> 481 | J40: =+Tabla33[[#This Row],[Cantidad]]*$J$6 -> 0 | K40: =+Tabla33[[#This Row],[Cantidad2]]*$K$6 -> 0 | L40: =+Tabla33[[#This Row],[US$]]+Tabla33[[#This Row],[US$,]] -> 0
B41: 34 | C41: 951763994 | D41: =+VLOOKUP(Tabla33[[#This Row],[CEDULA ]],'OCTUBRE 2025'!$C$8:$J$57,2,0) -> NEVAREZ PEÑAFIEL EVELYN JULEXY | E41: =+VLOOKUP(Tabla33[[#This Row],[CEDULA ]],'OCTUBRE 2025'!$C$8:$J$57,4,0) -> ASESOR DE CAPTACIONES | F41: =+VLOOKUP(Tabla33[[#This Row],[CEDULA ]],'OCTUBRE 2025'!$C$8:$J$57,6,0) -> Norte | G41: =+VLOOKUP(Tabla33[[#This Row],[CEDULA ]],'OCTUBRE 2025'!$C$8:$J$57,8,0) -> 475.85 | J41: =+Tabla33[[#This Row],[Cantidad]]*$J$6 -> 0 | K41: =+Tabla33[[#This Row],[Cantidad2]]*$K$6 -> 0 | L41: =+Tabla33[[#This Row],[US$]]+Tabla33[[#This Row],[US$,]] -> 0
B42: 35 | C42: 950703199 | D42: =+VLOOKUP(Tabla33[[#This Row],[CEDULA ]],'OCTUBRE 2025'!$C$8:$J$57,2,0) -> ÑAMO GUALACEO BRYAN JAVIER | E42: =+VLOOKUP(Tabla33[[#This Row],[CEDULA ]],'OCTUBRE 2025'!$C$8:$J$57,4,0) -> OFICIAL DE RECAUDACIONES | F42: =+VLOOKUP(Tabla33[[#This Row],[CEDULA ]],'OCTUBRE 2025'!$C$8:$J$57,6,0) -> Matriz | G42: =+VLOOKUP(Tabla33[[#This Row],[CEDULA ]],'OCTUBRE 2025'!$C$8:$J$57,8,0) -> 473.88 | J42: =+Tabla33[[#This Row],[Cantidad]]*$J$6 -> 0 | K42: =+Tabla33[[#This Row],[Cantidad2]]*$K$6 -> 0 | L42: =+Tabla33[[#This Row],[US$]]+Tabla33[[#This Row],[US$,]] -> 0
B43: 36 | C43: 0923715692 | D43: =+VLOOKUP(Tabla33[[#This Row],[CEDULA ]],'OCTUBRE 2025'!$C$8:$J$57,2,0) -> ORELLANA MANZO WHITNEY YAILYN | E43: =+VLOOKUP(Tabla33[[#This Row],[CEDULA ]],'OCTUBRE 2025'!$C$8:$J$57,4,0) -> OFICIAL DE SEGURIDAD DE LA INFORMACIÓN | F43: =+VLOOKUP(Tabla33[[#This Row],[CEDULA ]],'OCTUBRE 2025'!$C$8:$J$57,6,0) -> Matriz | G43: =+VLOOKUP(Tabla33[[#This Row],[CEDULA ]],'OCTUBRE 2025'!$C$8:$J$57,8,0) -> 600 | J43: =+Tabla33[[#This Row],[Cantidad]]*$J$6 -> 0 | K43: =+Tabla33[[#This Row],[Cantidad2]]*$K$6 -> 0 | L43: =+Tabla33[[#This Row],[US$]]+Tabla33[[#This Row],[US$,]] -> 0
B44: 37 | C44: 925830689 | D44: =+VLOOKUP(Tabla33[[#This Row],[CEDULA ]],'OCTUBRE 2025'!$C$8:$J$57,2,0) -> PERALTA MENDEZ LINA LISSETTE | E44: =+VLOOKUP(Tabla33[[#This Row],[CEDULA ]],'OCTUBRE 2025'!$C$8:$J$57,4,0) -> JEFE DE CRÉDITO | F44: =+VLOOKUP(Tabla33[[#This Row],[CEDULA ]],'OCTUBRE 2025'!$C$8:$J$57,6,0) -> Matriz | G44: =+VLOOKUP(Tabla33[[#This Row],[CEDULA ]],'OCTUBRE 2025'!$C$8:$J$57,8,0) -> 1022.2 | J44: =+Tabla33[[#This Row],[Cantidad]]*$J$6 -> 0 | K44: =+Tabla33[[#This Row],[Cantidad2]]*$K$6 -> 0 | L44: =+Tabla33[[#This Row],[US$]]+Tabla33[[#This Row],[US$,]] -> 0
B45: 38 | C45: 944034842 | D45: =+VLOOKUP(Tabla33[[#This Row],[CEDULA ]],'OCTUBRE 2025'!$C$8:$J$57,2,0) -> PEREZ ZAMORA ANA DE LOS ANGELES | E45: =+VLOOKUP(Tabla33[[#This Row],[CEDULA ]],'OCTUBRE 2025'!$C$8:$J$57,4,0) -> CAJERO FINANCIERO | F45: =+VLOOKUP(Tabla33[[#This Row],[CEDULA ]],'OCTUBRE 2025'!$C$8:$J$57,6,0) -> Matriz | G45: =+VLOOKUP(Tabla33[[#This Row],[CEDULA ]],'OCTUBRE 2025'!$C$8:$J$57,8,0) -> 256.53 | J45: =+Tabla33[[#This Row],[Cantidad]]*$J$6 -> 0 | K45: =+Tabla33[[#This Row],[Cantidad2]]*$K$6 -> 0 | L45: =+Tabla33[[#This Row],[US$]]+Tabla33[[#This Row],[US$,]] -> 0
B46: 39 | C46: 951340702 | D46: =+VLOOKUP(Tabla33[[#This Row],[CEDULA ]],'OCTUBRE 2025'!$C$8:$J$57,2,0) -> QUITO CALDERON JONATHAN ENRIQUE | E46: =+VLOOKUP(Tabla33[[#This Row],[CEDULA ]],'OCTUBRE 2025'!$C$8:$J$57,4,0) -> JEFE DE COBRANZAS | F46: =+VLOOKUP(Tabla33[[#This Row],[CEDULA ]],'OCTUBRE 2025'!$C$8:$J$57,6,0) -> Matriz | G46: =+VLOOKUP(Tabla33[[#This Row],[CEDULA ]],'OCTUBRE 2025'!$C$8:$J$57,8,0) -> 817.76 | J46: =+Tabla33[[#This Row],[Cantidad]]*$J$6 -> 0 | K46: =+Tabla33[[#This Row],[Cantidad2]]*$K$6 -> 0 | L46: =+Tabla33[[#This Row],[US$]]+Tabla33[[#This Row],[US$,]] -> 0
B47: 40 | C47: 650112949 | D47: =+VLOOKUP(Tabla33[[#This Row],[CEDULA ]],'OCTUBRE 2025'!$C$8:$J$57,2,0) -> QUITO UCHUBANDA JANETH ALEXANDRA | E47: =+VLOOKUP(Tabla33[[#This Row],[CEDULA ]],'OCTUBRE 2025'!$C$8:$J$57,4,0) -> OFICIAL DE RECAUDACIONES | F47: =+VLOOKUP(Tabla33[[#This Row],[CEDULA ]],'OCTUBRE 2025'!$C$8:$J$57,6,0) -> Norte | G47: =+VLOOKUP(Tabla33[[#This Row],[CEDULA ]],'OCTUBRE 2025'!$C$8:$J$57,8,0) -> 473.88 | J47: =+Tabla33[[#This Row],[Cantidad]]*$J$6 -> 0 | K47: =+Tabla33[[#This Row],[Cantidad2]]*$K$6 -> 0 | L47: =+Tabla33[[#This Row],[US$]]+Tabla33[[#This Row],[US$,]] -> 0
B48: 41 | C48: 924232804 | D48: =+VLOOKUP(Tabla33[[#This Row],[CEDULA ]],'OCTUBRE 2025'!$C$8:$J$57,2,0) -> RECALDE NARANJO ANGEL ALEXIS | E48: =+VLOOKUP(Tabla33[[#This Row],[CEDULA ]],'OCTUBRE 2025'!$C$8:$J$57,4,0) -> JEFE TI | F48: =+VLOOKUP(Tabla33[[#This Row],[CEDULA ]],'OCTUBRE 2025'!$C$8:$J$57,6,0) -> Matriz | G48: =+VLOOKUP(Tabla33[[#This Row],[CEDULA ]],'OCTUBRE 2025'!$C$8:$J$57,8,0) -> 1022.2 | J48: =+Tabla33[[#This Row],[Cantidad]]*$J$6 -> 0 | K48: =+Tabla33[[#This Row],[Cantidad2]]*$K$6 -> 0 | L48: =+Tabla33[[#This Row],[US$]]+Tabla33[[#This Row],[US$,]] -> 0
B49: 42 | C49: 605031145 | D49: =+VLOOKUP(Tabla33[[#This Row],[CEDULA ]],'OCTUBRE 2025'!$C$8:$J$57,2,0) -> SALAO PEREZ GERMAN FABRICIO | E49: =+VLOOKUP(Tabla33[[#This Row],[CEDULA ]],'OCTUBRE 2025'!$C$8:$J$57,4,0) -> ASESOR DE NEGOCIOS | F49: =+VLOOKUP(Tabla33[[#This Row],[CEDULA ]],'OCTUBRE 2025'!$C$8:$J$57,6,0) -> Durán | G49: =+VLOOKUP(Tabla33[[#This Row],[CEDULA ]],'OCTUBRE 2025'!$C$8:$J$57,8,0) -> 613.32 | J49: =+Tabla33[[#This Row],[Cantidad]]*$J$6 -> 0 | K49: =+Tabla33[[#This Row],[Cantidad2]]*$K$6 -> 0 | L49: =+Tabla33[[#This Row],[US$]]+Tabla33[[#This Row],[US$,]] -> 0
B50: 43 | C50: 927257576 | D50: =+VLOOKUP(Tabla33[[#This Row],[CEDULA ]],'OCTUBRE 2025'!$C$8:$J$57,2,0) -> SANISACA MITE ISRAEL BENJAMIN | E50: =+VLOOKUP(Tabla33[[#This Row],[CEDULA ]],'OCTUBRE 2025'!$C$8:$J$57,4,0) -> JEFE DE CRÉDITO | F50: =+VLOOKUP(Tabla33[[#This Row],[CEDULA ]],'OCTUBRE 2025'!$C$8:$J$57,6,0) -> Norte | G50: =+VLOOKUP(Tabla33[[#This Row],[CEDULA ]],'OCTUBRE 2025'!$C$8:$J$57,8,0) -> 1022.2 | J50: =+Tabla33[[#This Row],[Cantidad]]*$J$6 -> 0 | K50: =+Tabla33[[#This Row],[Cantidad2]]*$K$6 -> 0 | L50: =+Tabla33[[#This Row],[US$]]+Tabla33[[#This Row],[US$,]] -> 0
B51: 44 | C51: 928901800 | D51: =+VLOOKUP(Tabla33[[#This Row],[CEDULA ]],'OCTUBRE 2025'!$C$8:$J$57,2,0) -> TADAY GUAMAN NÉSTOR ALONSO | E51: =+VLOOKUP(Tabla33[[#This Row],[CEDULA ]],'OCTUBRE 2025'!$C$8:$J$57,4,0) -> JEFE DE BOVEDA | F51: =+VLOOKUP(Tabla33[[#This Row],[CEDULA ]],'OCTUBRE 2025'!$C$8:$J$57,6,0) -> Matriz | G51: =+VLOOKUP(Tabla33[[#This Row],[CEDULA ]],'OCTUBRE 2025'!$C$8:$J$57,8,0) -> 511.1 | J51: =+Tabla33[[#This Row],[Cantidad]]*$J$6 -> 0 | K51: =+Tabla33[[#This Row],[Cantidad2]]*$K$6 -> 0 | L51: =+Tabla33[[#This Row],[US$]]+Tabla33[[#This Row],[US$,]] -> 0
B52: 45 | C52: 951315746 | D52: =+VLOOKUP(Tabla33[[#This Row],[CEDULA ]],'OCTUBRE 2025'!$C$8:$J$57,2,0) -> TIGUA MONTERO KAREN LISBETH | E52: =+VLOOKUP(Tabla33[[#This Row],[CEDULA ]],'OCTUBRE 2025'!$C$8:$J$57,4,0) -> ASESOR DE NEGOCIOS | F52: =+VLOOKUP(Tabla33[[#This Row],[CEDULA ]],'OCTUBRE 2025'!$C$8:$J$57,6,0) -> Matriz | G52: =+VLOOKUP(Tabla33[[#This Row],[CEDULA ]],'OCTUBRE 2025'!$C$8:$J$57,8,0) -> 613.32 | J52: =+Tabla33[[#This Row],[Cantidad]]*$J$6 -> 0 | K52: =+Tabla33[[#This Row],[Cantidad2]]*$K$6 -> 0 | L52: =+Tabla33[[#This Row],[US$]]+Tabla33[[#This Row],[US$,]] -> 0
B53: 46 | C53: 954184321 | D53: =+VLOOKUP(Tabla33[[#This Row],[CEDULA ]],'OCTUBRE 2025'!$C$8:$J$57,2,0) -> URQUIZO GUARANGA ALEX EFRAIN | E53: =+VLOOKUP(Tabla33[[#This Row],[CEDULA ]],'OCTUBRE 2025'!$C$8:$J$57,4,0) -> OFICIAL DE RECAUDACIONES | F53: =+VLOOKUP(Tabla33[[#This Row],[CEDULA ]],'OCTUBRE 2025'!$C$8:$J$57,6,0) -> Matriz | G53: =+VLOOKUP(Tabla33[[#This Row],[CEDULA ]],'OCTUBRE 2025'!$C$8:$J$57,8,0) -> 511.1 | J53: =+Tabla33[[#This Row],[Cantidad]]*$J$6 -> 0 | K53: =+Tabla33[[#This Row],[Cantidad2]]*$K$6 -> 0 | L53: =+Tabla33[[#This Row],[US$]]+Tabla33[[#This Row],[US$,]] -> 0
B54: 47 | C54: 922034772 | D54: =+VLOOKUP(Tabla33[[#This Row],[CEDULA ]],'OCTUBRE 2025'!$C$8:$J$57,2,0) -> VERA GUEVARA PAOLA KARINA | E54: =+VLOOKUP(Tabla33[[#This Row],[CEDULA ]],'OCTUBRE 2025'!$C$8:$J$57,4,0) -> ASESOR DE CAPTACIONES | F54: =+VLOOKUP(Tabla33[[#This Row],[CEDULA ]],'OCTUBRE 2025'!$C$8:$J$57,6,0) -> Matriz | G54: =+VLOOKUP(Tabla33[[#This Row],[CEDULA ]],'OCTUBRE 2025'!$C$8:$J$57,8,0) -> 700 | J54: =+Tabla33[[#This Row],[Cantidad]]*$J$6 -> 0 | K54: =+Tabla33[[#This Row],[Cantidad2]]*$K$6 -> 0 | L54: =+Tabla33[[#This Row],[US$]]+Tabla33[[#This Row],[US$,]] -> 0
B55: 48 | C55: 923837991 | D55: =+VLOOKUP(Tabla33[[#This Row],[CEDULA ]],'OCTUBRE 2025'!$C$8:$J$57,2,0) -> YUNDA CUJILEMA MARIA TERESA | E55: =+VLOOKUP(Tabla33[[#This Row],[CEDULA ]],'OCTUBRE 2025'!$C$8:$J$57,4,0) -> CONTADOR GENERAL | F55: =+VLOOKUP(Tabla33[[#This Row],[CEDULA ]],'OCTUBRE 2025'!$C$8:$J$57,6,0) -> Matriz | G55: =+VLOOKUP(Tabla33[[#This Row],[CEDULA ]],'OCTUBRE 2025'!$C$8:$J$57,8,0) -> 1022.2 | J55: =+Tabla33[[#This Row],[Cantidad]]*$J$6 -> 0 | K55: =+Tabla33[[#This Row],[Cantidad2]]*$K$6 -> 0 | L55: =+Tabla33[[#This Row],[US$]]+Tabla33[[#This Row],[US$,]] -> 0
... B57: 50 | C57: 604154575 | D57: =+VLOOKUP(Tabla33[[#This Row],[CEDULA ]],'OCTUBRE 2025'!$C$8:$J$57,2,0) -> YUQUILEMA DELGADO PEDRO ANTONIO | E57: =+VLOOKUP(Tabla33[[#This Row],[CEDULA ]],'OCTUBRE 2025'!$C$8:$J$57,4,0) -> JEFE DE CRÉDITO | F57: =+VLOOKUP(Tabla33[[#This Row],[CEDULA ]],'OCTUBRE 2025'!$C$8:$J$57,6,0) -> Durán | G57: =+VLOOKUP(Tabla33[[#This Row],[CEDULA ]],'OCTUBRE 2025'!$C$8:$J$57,8,0) -> 1022.2 | J57: =+Tabla33[[#This Row],[Cantidad]]*$J$6 -> 0 | K57: =+Tabla33[[#This Row],[Cantidad2]]*$K$6 -> 0 | L57: =+Tabla33[[#This Row],[US$]]+Tabla33[[#This Row],[US$,]] -> 0
J58: =+Tabla33[[#This Row],[Cantidad]]*$J$6 -> 0 | K58: =+Tabla33[[#This Row],[Cantidad2]]*$K$6 -> 0 | L58: =+Tabla33[[#This Row],[US$]]+Tabla33[[#This Row],[US$,]] -> 0
D59: TOTALES | G59: =SUBTOTAL(109,Tabla33[SUELDO]) -> 30990.65 | J59: =SUBTOTAL(109,Tabla33[US$]) -> 0 | K59: =SUBTOTAL(109,Tabla33[US$,]) -> 0 | L59: =SUBTOTAL(109,Tabla33[US$,,]) -> 0

Sheet CTAS POR COBRAR-GUAPI
C4: CUENTAS POR COBRAR A EMPLEADO
C7: FECHA: | E7: =TODAY()-8 -> 45982 | G7: NOMBRE: | H7: GUAPI YUMAGLLA OSCAR EDUARDO
C8: SUELDO: | E8: 473.88 | G8: CARGO: | H8: OFICIAL DE COBRANZAS
C9: FECHA DE INGRESO: | E9: 06-03-2024 | G9: AGENCIA: | H9: Matriz
C11: TIPO DE SOLICITUD:
J12: TABLA - FORMA DE PAGO
D13: ANTICIPO | J13: # CUOTA | K13: FECHA | L13: VALOR
D14: PRESTAMO | H14: 149.35 | J14: 1 | K14: 45597 | L14: =+H17 -> 74.675
D15: SOLICITUD DE # CUOTAS A DESCONTAR | H15: 2 | J15: 2 | K15: 45627 | L15: =+H17 -> 74.675
J16: 3
D17: VALOR | H17: =+H14/H15 -> 74.675 | J17: 4
J18: 5
J19: 6
J20: 7
J21: 8
J22: 9
J23: 10
J24: TOTAL | L24: =SUM(L14:L23) -> 149.35
C28: OBSERVACIONES
C30: DESCUENTO POR PÉRDIDA DE EQUIPO MÓVIL
C33: FIRMAS Y/O AUTORIZACIÓN
C35: Autorizo a la empresa Coac Los Andes Latinos LTDA., a descontar mediante mi rol de pago mensual o en mi liquidación de haberes de ser el caso
D43: FIRMA DEL SOLICITANTE | I43: ELABORADO POR
D44: C.I. | I44: DEPARTAMENTO DE RRHH
G56: APROBADO POR
G57: GERENCIA

Sheet H.EXTRAS
B2: CÁLCULO DE HORAS EXTRAS
B3: NÓMINA SEPTIEMBRE 2025
H5: HORAS TRABAJADAS | J5: VALOR | L5: TOTAL SOBRETIEMPO
H6: 0.5 | I6: 1 | J6: 0.5 | K6: 1
B7: NO | C7: CEDULA | D7: NOMBRE | E7: CARGO | F7: Agencia | G7: SUELDO | H7: Cantidad | I7: Cantidad2 | J7: US$ | K7: US$, | L7: US$,,
B8: 1 | C8: 925813685 | D8: =+VLOOKUP(Tabla3[[#This Row],[CEDULA ]],'OCTUBRE 2025'!$C$8:$J$57,2,0) -> ASITIMBAY CRIOLLO JOHN ANDERSON | E8: =+VLOOKUP(Tabla3[[#This Row],[CEDULA ]],'OCTUBRE 2025'!$C$8:$J$57,4,0) -> JEFE DE MARKETING | F8: =+VLOOKUP(Tabla3[[#This Row],[CEDULA ]],'OCTUBRE 2025'!$C$8:$J$57,6,0) -> Matriz | G8: =+VLOOKUP(Tabla3[[#This Row],[CEDULA ]],'OCTUBRE 2025'!$C$8:$J$57,8,0) -> 817.76 | H8: =+VLOOKUP(Tabla3[[#This Row],[CEDULA ]],'Conversión-HE'!$C$20:$I$70,6,0) -> 0 | I8: =+VLOOKUP(Tabla3[[#This Row],[CEDULA ]],'Conversión-HE'!$C$20:$I$70,7,0) -> 0 | J8: =((G8/240)*1.5)*H8 -> 0 | K8: =+((G8/240)*2)*I8 -> 0 | L8: =+Tabla3[[#This Row],[US$]]+Tabla3[[#This Row],[US$,]] -> 0
B9: 2 | C9: 944405737 | D9: =+VLOOKUP(Tabla3[[#This Row],[CEDULA ]],'OCTUBRE 2025'!$C$8:$J$57,2,0) -> BARAHONA ZAMBRANO DAYANA NICOLE | E9: =+VLOOKUP(Tabla3[[#This Row],[CEDULA ]],'OCTUBRE 2025'!$C$8:$J$57,4,0) -> CAJERO FINANCIERO | F9: =+VLOOKUP(Tabla3[[#This Row],[CEDULA ]],'OCTUBRE 2025'!$C$8:$J$57,6,0) -> Matriz | G9: =+VLOOKUP(Tabla3[[#This Row],[CEDULA ]],'OCTUBRE 2025'!$C$8:$J$57,8,0) -> 15.86 | H9: =+VLOOKUP(Tabla3[[#This Row],[CEDULA ]],'Conversión-HE'!$C$20:$I$70,6,0) -> 0 | I9: =+VLOOKUP(Tabla3[[#This Row],[CEDULA ]],'Conversión-HE'!$C$20:$I$70,7,0) -> 0 | J9: =((G9/240)*1.5)*H9 -> 0 | K9: =+((G9/240)*2)*I9 -> 0 | L9: =+Tabla3[[#This Row],[US$]]+Tabla3[[#This Row],[US$,]] -> 0
B10: 3 | C10: 604394502 | D10: =+VLOOKUP(Tabla3[[#This Row],[CEDULA ]],'OCTUBRE 2025'!$C$8:$J$57,2,0) -> BETUN CHAFLA JULIO CESAR | E10: =+VLOOKUP(Tabla3[[#This Row],[CEDULA ]],'OCTUBRE 2025'!$C$8:$J$57,4,0) -> ASESOR DE NEGOCIOS | F10: =+VLOOKUP(Tabla3[[#This Row],[CEDULA ]],'OCTUBRE 2025'!$C$8:$J$57,6,0) -> Matriz | G10: =+VLOOKUP(Tabla3[[#This Row],[CEDULA ]],'OCTUBRE 2025'!$C$8:$J$57,8,0) -> 613.32 | H10: =+VLOOKUP(Tabla3[[#This Row],[CEDULA ]],'Conversión-HE'!$C$20:$I$70,6,0) -> 0 | I10: =+VLOOKUP(Tabla3[[#This Row],[CEDULA ]],'Conversión-HE'!$C$20:$I$70,7,0) -> 0 | J10: =((G10/240)*1.5)*H10 -> 0 | K10: =+((G10/240)*2)*I10 -> 0 | L10: =+Tabla3[[#This Row],[US$]]+Tabla3[[#This Row],[US$,]] -> 0
B11: 4 | C11: 955741970 | D11: =+VLOOKUP(Tabla3[[#This Row],[CEDULA ]],'OCTUBRE 2025'!$C$8:$J$57,2,0) -> CHACAGUASAY CHACAGUASAY ROBERTH CRISTHIAN | E11: =+VLOOKUP(Tabla3[[#This Row],[CEDULA ]],'OCTUBRE 2025'!$C$8:$J$57,4,0) -> OFICIAL DE RECAUDACIONES | F11: =+VLOOKUP(Tabla3[[#This Row],[CEDULA ]],'OCTUBRE 2025'!$C$8:$J$57,6,0) -> Matriz | G11: =+VLOOKUP(Tabla3[[#This Row],[CEDULA ]],'OCTUBRE 2025'!$C$8:$J$57,8,0) -> 473.88 | H11: =+VLOOKUP(Tabla3[[#This Row],[CEDULA ]],'Conversión-HE'!$C$20:$I$70,6,0) -> 0 | I11: =+VLOOKUP(Tabla3[[#This Row],[CEDULA ]],'Conversión-HE'!$C$20:$I$70,7,0) -> 0 | J11: =((G11/240)*1.5)*H11 -> 0 | K11: =+((G11/240)*2)*I11 -> 0 | L11: =+Tabla3[[#This Row],[US$]]+Tabla3[[#This Row],[US$,]] -> 0
B12: 5 | C12: 0943964973 | D12: =+VLOOKUP(Tabla3[[#This Row],[CEDULA ]],'OCTUBRE 2025'!$C$8:$J$57,2,0) -> CHACAGUASAY GUAMAN KEVIN NEHEMIAS | E12: =+VLOOKUP(Tabla3[[#This Row],[CEDULA ]],'OCTUBRE 2025'!$C$8:$J$57,4,0) -> ASESOR DE NEGOCIOS | F12: =+VLOOKUP(Tabla3[[#This Row],[CEDULA ]],'OCTUBRE 2025'!$C$8:$J$57,6,0) -> Matriz | G12: =+VLOOKUP(Tabla3[[#This Row],[CEDULA ]],'OCTUBRE 2025'!$C$8:$J$57,8,0) -> 256.53 | H12: =+VLOOKUP(Tabla3[[#This Row],[CEDULA ]],'Conversión-HE'!$C$20:$I$70,6,0) -> 0 | I12: =+VLOOKUP(Tabla3[[#This Row],[CEDULA ]],'Conversión-HE'!$C$20:$I$70,7,0) -> 0 | J12: =((G12/240)*1.5)*H12 -> 0 | K12: =+((G12/240)*2)*I12 -> 0 | L12: =+Tabla3[[#This Row],[US$]]+Tabla3[[#This Row],[US$,]] -> 0
B13: 6 | C13: 944143148 | D13: =+VLOOKUP(Tabla3[[#This Row],[CEDULA ]],'OCTUBRE 2025'!$C$8:$J$57,2,0) -> CHIMBOLEMA YUNGAN MARIO EFRAIN | E13: =+VLOOKUP(Tabla3[[#This Row],[CEDULA ]],'OCTUBRE 2025'!$C$8:$J$57,4,0) -> OFICIAL DE RECAUDACIONES | F13: =+VLOOKUP(Tabla3[[#This Row],[CEDULA ]],'OCTUBRE 2025'!$C$8:$J$57,6,0) -> Durán | G13: =+VLOOKUP(Tabla3[[#This Row],[CEDULA ]],'OCTUBRE 2025'!$C$8:$J$57,8,0) -> 142.16 | H13: =+VLOOKUP(Tabla3[[#This Row],[CEDULA ]],'Conversión-HE'!$C$20:$I$70,6,0) -> 0 | I13: =+VLOOKUP(Tabla3[[#This Row],[CEDULA ]],'Conversión-HE'!$C$20:$I$70,7,0) -> 0 | J13: =((G13/240)*1.5)*H13 -> 0 | K13: =+((G13/240)*2)*I13 -> 0 | L13: =+Tabla3[[#This Row],[US$]]+Tabla3[[#This Row],[US$,]] -> 0
B14: 7 | C14: 955325238 | D14: =+VLOOKUP(Tabla3[[#This Row],[CEDULA ]],'OCTUBRE 2025'!$C$8:$J$57,2,0) -> CHOCA CEPEDA INES VIVIANA | E14: =+VLOOKUP(Tabla3[[#This Row],[CEDULA ]],'OCTUBRE 2025'!$C$8:$J$57,4,0) -> CAJERA FINANCIERA | F14: =+VLOOKUP(Tabla3[[#This Row],[CEDULA ]],'OCTUBRE 2025'!$C$8:$J$57,6,0) -> Matriz | G14: =+VLOOKUP(Tabla3[[#This Row],[CEDULA ]],'OCTUBRE 2025'!$C$8:$J$57,8,0) -> 256.53 | H14: =+VLOOKUP(Tabla3[[#This Row],[CEDULA ]],'Conversión-HE'!$C$20:$I$70,6,0) -> 0 | I14: =+VLOOKUP(Tabla3[[#This Row],[CEDULA ]],'Conversión-HE'!$C$20:$I$70,7,0) -> 0 | J14: =((G14/240)*1.5)*H14 -> 0 | K14: =+((G14/240)*2)*I14 -> 0 | L14: =+Tabla3[[#This Row],[US$]]+Tabla3[[#This Row],[US$,]] -> 0
B15: 8 | C15: 914163654 | D15: =+VLOOKUP(Tabla3[[#This Row],[CEDULA ]],'OCTUBRE 2025'!$C$8:$J$57,2,0) -> COCA BENITEZ JORGE MANUEL | E15: =+VLOOKUP(Tabla3[[#This Row],[CEDULA ]],'OCTUBRE 2025'!$C$8:$J$57,4,0) -> ANALISTA DE RIESGO | F15: =+VLOOKUP(Tabla3[[#This Row],[CEDULA ]],'OCTUBRE 2025'!$C$8:$J$57,6,0) -> Matriz | G15: =+VLOOKUP(Tabla3[[#This Row],[CEDULA ]],'OCTUBRE 2025'!$C$8:$J$57,8,0) -> 1200 | H15: =+VLOOKUP(Tabla3[[#This Row],[CEDULA ]],'Conversión-HE'!$C$20:$I$70,6,0) -> 0 | I15: =+VLOOKUP(Tabla3[[#This Row],[CEDULA ]],'Conversión-HE'!$C$20:$I$70,7,0) -> 0 | J15: =((G15/240)*1.5)*H15 -> 0 | K15: =+((G15/240)*2)*I15 -> 0 | L15: =+Tabla3[[#This Row],[US$]]+Tabla3[[#This Row],[US$,]] -> 0
B16: 9 | C16: 956668305 | D16: =+VLOOKUP(Tabla3[[#This Row],[CEDULA ]],'OCTUBRE 2025'!$C$8:$J$57,2,0) -> CORO YUQUILEMA RUTH NOEMI | E16: =+VLOOKUP(Tabla3[[#This Row],[CEDULA ]],'OCTUBRE 2025'!$C$8:$J$57,4,0) -> OFICIAL DE RECAUDACIONES | F16: =+VLOOKUP(Tabla3[[#This Row],[CEDULA ]],'OCTUBRE 2025'!$C$8:$J$57,6,0) -> Matriz | G16: =+VLOOKUP(Tabla3[[#This Row],[CEDULA ]],'OCTUBRE 2025'!$C$8:$J$57,8,0) -> 252.74 | H16: =+VLOOKUP(Tabla3[[#This Row],[CEDULA ]],'Conversión-HE'!$C$20:$I$70,6,0) -> 0 | I16: =+VLOOKUP(Tabla3[[#This Row],[CEDULA ]],'Conversión-HE'!$C$20:$I$70,7,0) -> 0 | J16: =((G16/240)*1.5)*H16 -> 0 | K16: =+((G16/240)*2)*I16 -> 0 | L16: =+Tabla3[[#This Row],[US$]]+Tabla3[[#This Row],[US$,]] -> 0
B17: 10 | C17: 0918741448 | D17: =+VLOOKUP(Tabla3[[#This Row],[CEDULA ]],'OCTUBRE 2025'!$C$8:$J$57,2,0) -> DEFAS CHICAIZA JOEL ALBERTO | E17: =+VLOOKUP(Tabla3[[#This Row],[CEDULA ]],'OCTUBRE 2025'!$C$8:$J$57,4,0) -> ASESOR DE NEGOCIOS | F17: =+VLOOKUP(Tabla3[[#This Row],[CEDULA ]],'OCTUBRE 2025'!$C$8:$J$57,6,0) -> Norte | G17: =+VLOOKUP(Tabla3[[#This Row],[CEDULA ]],'OCTUBRE 2025'!$C$8:$J$57,8,0) -> 626.65 | H17: =+VLOOKUP(Tabla3[[#This Row],[CEDULA ]],'Conversión-HE'!$C$20:$I$70,6,0) -> 0 | I17: =+VLOOKUP(Tabla3[[#This Row],[CEDULA ]],'Conversión-HE'!$C$20:$I$70,7,0) -> 0 | J17: =((G17/240)*1.5)*H17 -> 0 | K17: =+((G17/240)*2)*I17 -> 0 | L17: =+Tabla3[[#This Row],[US$]]+Tabla3[[#This Row],[US$,]] -> 0
B18: 11 | C18: 931097620 | D18: =+VLOOKUP(Tabla3[[#This Row],[CEDULA ]],'OCTUBRE 2025'!$C$8:$J$57,2,0) -> DEL ROSARIO RODRIGUEZ JUDY ANGELICA | E18: =+VLOOKUP(Tabla3[[#This Row],[CEDULA ]],'OCTUBRE 2025'!$C$8:$J$57,4,0) -> CAJERA FINANCIERA | F18: =+VLOOKUP(Tabla3[[#This Row],[CEDULA ]],'OCTUBRE 2025'!$C$8:$J$57,6,0) -> Norte | G18: =+VLOOKUP(Tabla3[[#This Row],[CEDULA ]],'OCTUBRE 2025'!$C$8:$J$57,8,0) -> 256.53 | H18: =+VLOOKUP(Tabla3[[#This Row],[CEDULA ]],'Conversión-HE'!$C$20:$I$70,6,0) -> 0 | I18: =+VLOOKUP(Tabla3[[#This Row],[CEDULA ]],'Conversión-HE'!$C$20:$I$70,7,0) -> 0 | J18: =((G18/240)*1.5)*H18 -> 0 | K18: =+((G18/240)*2)*I18 -> 0 | L18: =+Tabla3[[#This Row],[US$]]+Tabla3[[#This Row],[US$,]] -> 0
B19: 12 | C19: 1105483422 | D19: =+VLOOKUP(Tabla3[[#This Row],[CEDULA ]],'OCTUBRE 2025'!$C$8:$J$57,2,0) -> FLORES HERRERA WENDY DEL CISNE | E19: =+VLOOKUP(Tabla3[[#This Row],[CEDULA ]],'OCTUBRE 2025'!$C$8:$J$57,4,0) -> CAJERO FINANCIERO | F19: =+VLOOKUP(Tabla3[[#This Row],[CEDULA ]],'OCTUBRE 2025'!$C$8:$J$57,6,0) -> Durán | G19: =+VLOOKUP(Tabla3[[#This Row],[CEDULA ]],'OCTUBRE 2025'!$C$8:$J$57,8,0) -> 650 | H19: =+VLOOKUP(Tabla3[[#This Row],[CEDULA ]],'Conversión-HE'!$C$20:$I$70,6,0) -> 0 | I19: =+VLOOKUP(Tabla3[[#This Row],[CEDULA ]],'Conversión-HE'!$C$20:$I$70,7,0) -> 0 | J19: =((G19/240)*1.5)*H19 -> 0 | K19: =+((G19/240)*2)*I19 -> 0 | L19: =+Tabla3[[#This Row],[US$]]+Tabla3[[#This Row],[US$,]] -> 0
B20: 13 | C20: 942614645 | D20: =+VLOOKUP(Tabla3[[#This Row],[CEDULA ]],'OCTUBRE 2025'!$C$8:$J$57,2,0) -> FUELA TOABANDA JOSUE CHRISTIAN | E20: =+VLOOKUP(Tabla3[[#This Row],[CEDULA ]],'OCTUBRE 2025'!$C$8:$J$57,4,0) -> ASISTENTE CONTABLE | F20: =+VLOOKUP(Tabla3[[#This Row],[CEDULA ]],'OCTUBRE 2025'!$C$8:$J$57,6,0) -> Matriz | G20: =+VLOOKUP(Tabla3[[#This Row],[CEDULA ]],'OCTUBRE 2025'!$C$8:$J$57,8,0) -> 481 | H20: =+VLOOKUP(Tabla3[[#This Row],[CEDULA ]],'Conversión-HE'!$C$20:$I$70,6,0) -> 0 | I20: =+VLOOKUP(Tabla3[[#This Row],[CEDULA ]],'Conversión-HE'!$C$20:$I$70,7,0) -> 0 | J20: =((G20/240)*1.5)*H20 -> 0 | K20: =+((G20/240)*2)*I20 -> 0 | L20: =+Tabla3[[#This Row],[US$]]+Tabla3[[#This Row],[US$,]] -> 0
B21: 14 | C21: 951200062 | D21: =+VLOOKUP(Tabla3[[#This Row],[CEDULA ]],'OCTUBRE 2025'!$C$8:$J$57,2,0) -> GALAN LEMACHE INGRID GISELA | E21: =+VLOOKUP(Tabla3[[#This Row],[CEDULA ]],'OCTUBRE 2025'!$C$8:$J$57,4,0) -> BACK UP ADMINISTRATIVO FINANCIERO | F21: =+VLOOKUP(Tabla3[[#This Row],[CEDULA ]],'OCTUBRE 2025'!$C$8:$J$57,6,0) -> Norte | G21: =+VLOOKUP(Tabla3[[#This Row],[CEDULA ]],'OCTUBRE 2025'!$C$8:$J$57,8,0) -> 473.88 | H21: =+VLOOKUP(Tabla3[[#This Row],[CEDULA ]],'Conversión-HE'!$C$20:$I$70,6,0) -> 0 | I21: =+VLOOKUP(Tabla3[[#This Row],[CEDULA ]],'Conversión-HE'!$C$20:$I$70,7,0) -> 0 | J21: =((G21/240)*1.5)*H21 -> 0 | K21: =+((G21/240)*2)*I21 -> 0 | L21: =+Tabla3[[#This Row],[US$]]+Tabla3[[#This Row],[US$,]] -> 0
B22: 15 | C22: 950929232 | D22: =+VLOOKUP(Tabla3[[#This Row],[CEDULA ]],'OCTUBRE 2025'!$C$8:$J$57,2,0) -> GARCIA VERA HENRY LUIS | E22: =+VLOOKUP(Tabla3[[#This Row],[CEDULA ]],'OCTUBRE 2025'!$C$8:$J$57,4,0) -> OFICIAL DE RECAUDACIONES | F22: =+VLOOKUP(Tabla3[[#This Row],[CEDULA ]],'OCTUBRE 2025'!$C$8:$J$57,6,0) -> Norte | G22: =+VLOOKUP(Tabla3[[#This Row],[CEDULA ]],'OCTUBRE 2025'!$C$8:$J$57,8,0) -> 715.54 | H22: =+VLOOKUP(Tabla3[[#This Row],[CEDULA ]],'Conversión-HE'!$C$20:$I$70,6,0) -> 0 | I22: =+VLOOKUP(Tabla3[[#This Row],[CEDULA ]],'Conversión-HE'!$C$20:$I$70,7,0) -> 0 | J22: =((G22/240)*1.5)*H22 -> 0 | K22: =+((G22/240)*2)*I22 -> 0 | L22: =+Tabla3[[#This Row],[US$]]+Tabla3[[#This Row],[US$,]] -> 0
B23: 16 | C23: 953819646 | D23: =+VLOOKUP(Tabla3[[#This Row],[CEDULA ]],'OCTUBRE 2025'!$C$8:$J$57,2,0) -> GUALACEO ÑAMO JONATHAN IVÁN | E23: =+VLOOKUP(Tabla3[[#This Row],[CEDULA ]],'OCTUBRE 2025'!$C$8:$J$57,4,0) -> OFICIAL DE RECAUDACIONES | F23: =+VLOOKUP(Tabla3[[#This Row],[CEDULA ]],'OCTUBRE 2025'!$C$8:$J$57,6,0) -> Matriz | G23: =+VLOOKUP(Tabla3[[#This Row],[CEDULA ]],'OCTUBRE 2025'!$C$8:$J$57,8,0) -> 511.1 | H23: =+VLOOKUP(Tabla3[[#This Row],[CEDULA ]],'Conversión-HE'!$C$20:$I$70,6,0) -> 0 | I23: =+VLOOKUP(Tabla3[[#This Row],[CEDULA ]],'Conversión-HE'!$C$20:$I$70,7,0) -> 0 | J23: =((G23/240)*1.5)*H23 -> 0 | K23: =+((G23/240)*2)*I23 -> 0 | L23: =+Tabla3[[#This Row],[US$]]+Tabla3[[#This Row],[US$,]] -> 0
B24: 17 | C24: 956953392 | D24: =+VLOOKUP(Tabla3[[#This Row],[CEDULA ]],'OCTUBRE 2025'!$C$8:$J$57,2,0) -> GUAPI YUMAGLLA OSCAR EDUARDO | E24: =+VLOOKUP(Tabla3[[#This Row],[CEDULA ]],'OCTUBRE 2025'!$C$8:$J$57,4,0) -> OFICIAL DE RECAUDACIONES | F24: =+VLOOKUP(Tabla3[[#This Row],[CEDULA ]],'OCTUBRE 2025'!$C$8:$J$57,6,0) -> Matriz | G24: =+VLOOKUP(Tabla3[[#This Row],[CEDULA ]],'OCTUBRE 2025'!$C$8:$J$57,8,0) -> 473.88 | H24: =+VLOOKUP(Tabla3[[#This Row],[CEDULA ]],'Conversión-HE'!$C$20:$I$70,6,0) -> 0 | I24: =+VLOOKUP(Tabla3[[#This Row],[CEDULA ]],'Conversión-HE'!$C$20:$I$70,7,0) -> 0 | J24: =((G24/240)*1.5)*H24 -> 0 | K24: =+((G24/240)*2)*I24 -> 0 | L24: =+Tabla3[[#This Row],[US$]]+Tabla3[[#This Row],[US$,]] -> 0
B25: 18 | C25: 956796767 | D25: =+VLOOKUP(Tabla3[[#This Row],[CEDULA ]],'OCTUBRE 2025'!$C$8:$J$57,2,0) -> GUAYANLEMA RUIZ EDINSON DAVID | E25: =+VLOOKUP(Tabla3[[#This Row],[CEDULA ]],'OCTUBRE 2025'!$C$8:$J$57,4,0) -> OFICIAL DE RECAUDACIONES | F25: =+VLOOKUP(Tabla3[[#This Row],[CEDULA ]],'OCTUBRE 2025'!$C$8:$J$57,6,0) -> Norte | G25: =+VLOOKUP(Tabla3[[#This Row],[CEDULA ]],'OCTUBRE 2025'!$C$8:$J$57,8,0) -> 473.88 | H25: =+VLOOKUP(Tabla3[[#This Row],[CEDULA ]],'Conversión-HE'!$C$20:$I$70,6,0) -> 0 | I25: =+VLOOKUP(Tabla3[[#This Row],[CEDULA ]],'Conversión-HE'!$C$20:$I$70,7,0) -> 0 | J25: =((G25/240)*1.5)*H25 -> 0 | K25: =+((G25/240)*2)*I25 -> 0 | L25: =+Tabla3[[#This Row],[US$]]+Tabla3[[#This Row],[US$,]] -> 0
B26: 19 | C26: 0932036049 | D26: =+VLOOKUP(Tabla3[[#This Row],[CEDULA ]],'OCTUBRE 2025'!$C$8:$J$57,2,0) -> HERRERA JIMENEZ CAROLINA ADELIHER | E26: =+VLOOKUP(Tabla3[[#This Row],[CEDULA ]],'OCTUBRE 2025'!$C$8:$J$57,4,0) -> ASISTENTE DE OPERACIONES | F26: =+VLOOKUP(Tabla3[[#This Row],[CEDULA ]],'OCTUBRE 2025'!$C$8:$J$57,6,0) -> Matriz | G26: =+VLOOKUP(Tabla3[[#This Row],[CEDULA ]],'OCTUBRE 2025'!$C$8:$J$57,8,0) -> 481 | H26: =+VLOOKUP(Tabla3[[#This Row],[CEDULA ]],'Conversión-HE'!$C$20:$I$70,6,0) -> 0 | I26: =+VLOOKUP(Tabla3[[#This Row],[CEDULA ]],'Conversión-HE'!$C$20:$I$70,7,0) -> 0 | J26: =((G26/240)*1.5)*H26 -> 0 | K26: =+((G26/240)*2)*I26 -> 0 | L26: =+Tabla3[[#This Row],[US$]]+Tabla3[[#This Row],[US$,]] -> 0
B27: 20 | C27: 1724102940 | D27: =+VLOOKUP(Tabla3[[#This Row],[CEDULA ]],'OCTUBRE 2025'!$C$8:$J$57,2,0) -> HIDALGO CHERRES NESTOR VLADIMIR | E27: =+VLOOKUP(Tabla3[[#This Row],[CEDULA ]],'OCTUBRE 2025'!$C$8:$J$57,4,0) -> JEFE DE CREDITO | F27: =+VLOOKUP(Tabla3[[#This Row],[CEDULA ]],'OCTUBRE 2025'!$C$8:$J$57,6,0) -> Durán | G27: =+VLOOKUP(Tabla3[[#This Row],[CEDULA ]],'OCTUBRE 2025'!$C$8:$J$57,8,0) -> 817.76 | H27: =+VLOOKUP(Tabla3[[#This Row],[CEDULA ]],'Conversión-HE'!$C$20:$I$70,6,0) -> 0 | I27: =+VLOOKUP(Tabla3[[#This Row],[CEDULA ]],'Conversión-HE'!$C$20:$I$70,7,0) -> 0 | J27: =((G27/240)*1.5)*H27 -> 0 | K27: =+((G27/240)*2)*I27 -> 0 | L27: =+Tabla3[[#This Row],[US$]]+Tabla3[[#This Row],[US$,]] -> 0
B28: 21 | C28: 943322974 | D28: =+VLOOKUP(Tabla3[[#This Row],[CEDULA ]],'OCTUBRE 2025'!$C$8:$J$57,2,0) -> JANETA RUIZ ALEXANDRA DEL ROCIO | E28: =+VLOOKUP(Tabla3[[#This Row],[CEDULA ]],'OCTUBRE 2025'!$C$8:$J$57,4,0) -> OFICIAL DE RECAUDACIONES | F28: =+VLOOKUP(Tabla3[[#This Row],[CEDULA ]],'OCTUBRE 2025'!$C$8:$J$57,6,0) -> Norte | G28: =+VLOOKUP(Tabla3[[#This Row],[CEDULA ]],'OCTUBRE 2025'!$C$8:$J$57,8,0) -> 473.88 | H28: =+VLOOKUP(Tabla3[[#This Row],[CEDULA ]],'Conversión-HE'!$C$20:$I$70,6,0) -> 0 | I28: =+VLOOKUP(Tabla3[[#This Row],[CEDULA ]],'Conversión-HE'!$C$20:$I$70,7,0) -> 0 | J28: =((G28/240)*1.5)*H28 -> 0 | K28: =+((G28/240)*2)*I28 -> 0 | L28: =+Tabla3[[#This Row],[US$]]+Tabla3[[#This Row],[US$,]] -> 0
B29: 22 | C29: 941096851 | D29: =+VLOOKUP(Tabla3[[#This Row],[CEDULA ]],'OCTUBRE 2025'!$C$8:$J$57,2,0) -> LEMA CHIRAU RAMONA MARIA | E29: =+VLOOKUP(Tabla3[[#This Row],[CEDULA ]],'OCTUBRE 2025'!$C$8:$J$57,4,0) -> ASESOR DE CAPTACIONES | F29: =+VLOOKUP(Tabla3[[#This Row],[CEDULA ]],'OCTUBRE 2025'!$C$8:$J$57,6,0) -> Durán | G29: =+VLOOKUP(Tabla3[[#This Row],[CEDULA ]],'OCTUBRE 2025'!$C$8:$J$57,8,0) -> 700 | H29: =+VLOOKUP(Tabla3[[#This Row],[CEDULA ]],'Conversión-HE'!$C$20:$I$70,6,0) -> 0 | I29: =+VLOOKUP(Tabla3[[#This Row],[CEDULA ]],'Conversión-HE'!$C$20:$I$70,7,0) -> 0 | J29: =((G29/240)*1.5)*H29 -> 0 | K29: =+((G29/240)*2)*I29 -> 0 | L29: =+Tabla3[[#This Row],[US$]]+Tabla3[[#This Row],[US$,]] -> 0
B30: 23 | C30: 957093800 | D30: =+VLOOKUP(Tabla3[[#This Row],[CEDULA ]],'OCTUBRE 2025'!$C$8:$J$57,2,0) -> LEMA TADAY BRAYAN WIDINSON | E30: =+VLOOKUP(Tabla3[[#This Row],[CEDULA ]],'OCTUBRE 2025'!$C$8:$J$57,4,0) -> OFICIAL DE RECAUDACIONES | F30: =+VLOOKUP(Tabla3[[#This Row],[CEDULA ]],'OCTUBRE 2025'!$C$8:$J$57,6,0) -> Durán | G30: =+VLOOKUP(Tabla3[[#This Row],[CEDULA ]],'OCTUBRE 2025'!$C$8:$J$57,8,0) -> 473.88 | H30: =+VLOOKUP(Tabla3[[#This Row],[CEDULA ]],'Conversión-HE'!$C$20:$I$70,6,0) -> 0 | I30: =+VLOOKUP(Tabla3[[#This Row],[CEDULA ]],'Conversión-HE'!$C$20:$I$70,7,0) -> 0 | J30: =((G30/240)*1.5)*H30 -> 0 | K30: =+((G30/240)*2)*I30 -> 0 | L30: =+Tabla3[[#This Row],[US$]]+Tabla3[[#This Row],[US$,]] -> 0
B31: 24 | C31: 957924350 | D31: =+VLOOKUP(Tabla3[[#This Row],[CEDULA ]],'OCTUBRE 2025'!$C$8:$J$57,2,0) -> LLUMI YUQUILEMA MAYCOOL DANNY | E31: =+VLOOKUP(Tabla3[[#This Row],[CEDULA ]],'OCTUBRE 2025'!$C$8:$J$57,4,0) -> ASESOR DE NEGOCIOS | F31: =+VLOOKUP(Tabla3[[#This Row],[CEDULA ]],'OCTUBRE 2025'!$C$8:$J$57,6,0) -> Matriz | G31: =+VLOOKUP(Tabla3[[#This Row],[CEDULA ]],'OCTUBRE 2025'!$C$8:$J$57,8,0) -> 481 | H31: =+VLOOKUP(Tabla3[[#This Row],[CEDULA ]],'Conversión-HE'!$C$20:$I$70,6,0) -> 0 | I31: =+VLOOKUP(Tabla3[[#This Row],[CEDULA ]],'Conversión-HE'!$C$20:$I$70,7,0) -> 0 | J31: =((G31/240)*1.5)*H31 -> 0 | K31: =+((G31/240)*2)*I31 -> 0 | L31: =+Tabla3[[#This Row],[US$]]+Tabla3[[#This Row],[US$,]] -> 0
B32: 25 | C32: 603838657 | D32: =+VLOOKUP(Tabla3[[#This Row],[CEDULA ]],'OCTUBRE 2025'!$C$8:$J$57,2,0) -> MALAN DELGADO JOSE ALBERTO | E32: =+VLOOKUP(Tabla3[[#This Row],[CEDULA ]],'OCTUBRE 2025'!$C$8:$J$57,4,0) -> OFICIAL DE RECAUDACIONES | F32: =+VLOOKUP(Tabla3[[#This Row],[CEDULA ]],'OCTUBRE 2025'!$C$8:$J$57,6,0) -> Durán | G32: =+VLOOKUP(Tabla3[[#This Row],[CEDULA ]],'OCTUBRE 2025'!$C$8:$J$57,8,0) -> 473.88 | H32: =+VLOOKUP(Tabla3[[#This Row],[CEDULA ]],'Conversión-HE'!$C$20:$I$70,6,0) -> 0 | I32: =+VLOOKUP(Tabla3[[#This Row],[CEDULA ]],'Conversión-HE'!$C$20:$I$70,7,0) -> 0 | J32: =((G32/240)*1.5)*H32 -> 0 | K32: =+((G32/240)*2)*I32 -> 0 | L32: =+Tabla3[[#This Row],[US$]]+Tabla3[[#This Row],[US$,]] -> 0
B33: 26 | C33: 925240525 | D33: =+VLOOKUP(Tabla3[[#This Row],[CEDULA ]],'OCTUBRE 2025'!$C$8:$J$57,2,0) -> MALAN YUQUILEMA RAUL ALBERTO | E33: =+VLOOKUP(Tabla3[[#This Row],[CEDULA ]],'OCTUBRE 2025'!$C$8:$J$57,4,0) -> ASESOR LEGAL | F33: =+VLOOKUP(Tabla3[[#This Row],[CEDULA ]],'OCTUBRE 2025'!$C$8:$J$57,6,0) -> Matriz | G33: =+VLOOKUP(Tabla3[[#This Row],[CEDULA ]],'OCTUBRE 2025'!$C$8:$J$57,8,0) -> 2700 | H33: =+VLOOKUP(Tabla3[[#This Row],[CEDULA ]],'Conversión-HE'!$C$20:$I$70,6,0) -> 0 | I33: =+VLOOKUP(Tabla3[[#This Row],[CEDULA ]],'Conversión-HE'!$C$20:$I$70,7,0) -> 0 | J33: =((G33/240)*1.5)*H33 -> 0 | K33: =+((G33/240)*2)*I33 -> 0 | L33: =+Tabla3[[#This Row],[US$]]+Tabla3[[#This Row],[US$,]] -> 0
B34: 27 | C34: 954520599 | D34: =+VLOOKUP(Tabla3[[#This Row],[CEDULA ]],'OCTUBRE 2025'!$C$8:$J$57,2,0) -> MARSHALL VEGA YULIANA LISSETT | E34: =+VLOOKUP(Tabla3[[#This Row],[CEDULA ]],'OCTUBRE 2025'!$C$8:$J$57,4,0) -> ASESOR DE NEGOCIOS | F34: =+VLOOKUP(Tabla3[[#This Row],[CEDULA ]],'OCTUBRE 2025'!$C$8:$J$57,6,0) -> Durán | G34: =+VLOOKUP(Tabla3[[#This Row],[CEDULA ]],'OCTUBRE 2025'!$C$8:$J$57,8,0) -> 613.32 | H34: =+VLOOKUP(Tabla3[[#This Row],[CEDULA ]],'Conversión-HE'!$C$20:$I$70,6,0) -> 0 | I34: =+VLOOKUP(Tabla3[[#This Row],[CEDULA ]],'Conversión-HE'!$C$20:$I$70,7,0) -> 0 | J34: =((G34/240)*1.5)*H34 -> 0 | K34: =+((G34/240)*2)*I34 -> 0 | L34: =+Tabla3[[#This Row],[US$]]+Tabla3[[#This Row],[US$,]] -> 0
B35: 28 | C35: 0943906032 | D35: =+VLOOKUP(Tabla3[[#This Row],[CEDULA ]],'OCTUBRE 2025'!$C$8:$J$57,2,0) -> MEZA RODRIGUEZ MICHAEL FERNANDO | E35: =+VLOOKUP(Tabla3[[#This Row],[CEDULA ]],'OCTUBRE 2025'!$C$8:$J$57,4,0) -> OFICIAL DE RECAUDACIONES | F35: =+VLOOKUP(Tabla3[[#This Row],[CEDULA ]],'OCTUBRE 2025'!$C$8:$J$57,6,0) -> Norte | G35: =+VLOOKUP(Tabla3[[#This Row],[CEDULA ]],'OCTUBRE 2025'!$C$8:$J$57,8,0) -> 473.88 | H35: =+VLOOKUP(Tabla3[[#This Row],[CEDULA ]],'Conversión-HE'!$C$20:$I$70,6,0) -> 0 | I35: =+VLOOKUP(Tabla3[[#This Row],[CEDULA ]],'Conversión-HE'!$C$20:$I$70,7,0) -> 0 | J35: =((G35/240)*1.5)*H35 -> 0 | K35: =+((G35/240)*2)*I35 -> 0 | L35: =+Tabla3[[#This Row],[US$]]+Tabla3[[#This Row],[US$,]] -> 0
B36: 29 | C36: 0919306050 | D36: =+VLOOKUP(Tabla3[[#This Row],[CEDULA ]],'OCTUBRE 2025'!$C$8:$J$57,2,0) -> MORAN GARCIA DANNY FAVIAN | E36: =+VLOOKUP(Tabla3[[#This Row],[CEDULA ]],'OCTUBRE 2025'!$C$8:$J$57,4,0) -> OFICIAL DE CUMPLIMIENTO | F36: =+VLOOKUP(Tabla3[[#This Row],[CEDULA ]],'OCTUBRE 2025'!$C$8:$J$57,6,0) -> Matriz | G36: =+VLOOKUP(Tabla3[[#This Row],[CEDULA ]],'OCTUBRE 2025'!$C$8:$J$57,8,0) -> 600 | H36: =+VLOOKUP(Tabla3[[#This Row],[CEDULA ]],'Conversión-HE'!$C$20:$I$70,6,0) -> 0 | I36: =+VLOOKUP(Tabla3[[#This Row],[CEDULA ]],'Conversión-HE'!$C$20:$I$70,7,0) -> 0 | J36: =((G36/240)*1.5)*H36 -> 0 | K36: =+((G36/240)*2)*I36 -> 0 | L36: =+Tabla3[[#This Row],[US$]]+Tabla3[[#This Row],[US$,]] -> 0
B37: 30 | C37: 0941235376 | D37: =+VLOOKUP(Tabla3[[#This Row],[CEDULA ]],'OCTUBRE 2025'!$C$8:$J$57,2,0) -> MOREIRA ESPINOZA LINDA ELIZABETH | E37: =+VLOOKUP(Tabla3[[#This Row],[CEDULA ]],'OCTUBRE 2025'!$C$8:$J$57,4,0) -> CAJERO FINANCIERO | F37: =+VLOOKUP(Tabla3[[#This Row],[CEDULA ]],'OCTUBRE 2025'!$C$8:$J$57,6,0) -> Durán | G37: =+VLOOKUP(Tabla3[[#This Row],[CEDULA ]],'OCTUBRE 2025'!$C$8:$J$57,8,0) -> 481 | H37: =+VLOOKUP(Tabla3[[#This Row],[CEDULA ]],'Conversión-HE'!$C$20:$I$70,6,0) -> 0 | I37: =+VLOOKUP(Tabla3[[#This Row],[CEDULA ]],'Conversión-HE'!$C$20:$I$70,7,0) -> 0 | J37: =((G37/240)*1.5)*H37 -> 0 | K37: =+((G37/240)*2)*I37 -> 0 | L37: =+Tabla3[[#This Row],[US$]]+Tabla3[[#This Row],[US$,]] -> 0
B38: 31 | C38: 955395686 | D38: =+VLOOKUP(Tabla3[[#This Row],[CEDULA ]],'OCTUBRE 2025'!$C$8:$J$57,2,0) -> MOROCHO DUCHI SANDRA STEPHANIE | E38: =+VLOOKUP(Tabla3[[#This Row],[CEDULA ]],'OCTUBRE 2025'!$C$8:$J$57,4,0) -> ASESOR DE NEGOCIOS | F38: =+VLOOKUP(Tabla3[[#This Row],[CEDULA ]],'OCTUBRE 2025'!$C$8:$J$57,6,0) -> Norte | G38: =+VLOOKUP(Tabla3[[#This Row],[CEDULA ]],'OCTUBRE 2025'!$C$8:$J$57,8,0) -> 613.32 | H38: =+VLOOKUP(Tabla3[[#This Row],[CEDULA ]],'Conversión-HE'!$C$20:$I$70,6,0) -> 0 | I38: =+VLOOKUP(Tabla3[[#This Row],[CEDULA ]],'Conversión-HE'!$C$20:$I$70,7,0) -> 0 | J38: =((G38/240)*1.5)*H38 -> 0 | K38: =+((G38/240)*2)*I38 -> 0 | L38: =+Tabla3[[#This Row],[US$]]+Tabla3[[#This Row],[US$,]] -> 0
B39: 32 | C39: 940991987 | D39: =+VLOOKUP(Tabla3[[#This Row],[CEDULA ]],'OCTUBRE 2025'!$C$8:$J$57,2,0) -> MOROCHO YANTALEMA DINA MAGALY | E39: =+VLOOKUP(Tabla3[[#This Row],[CEDULA ]],'OCTUBRE 2025'!$C$8:$J$57,4,0) -> TALENTO HUMANO | F39: =+VLOOKUP(Tabla3[[#This Row],[CEDULA ]],'OCTUBRE 2025'!$C$8:$J$57,6,0) -> Matriz | G39: =+VLOOKUP(Tabla3[[#This Row],[CEDULA ]],'OCTUBRE 2025'!$C$8:$J$57,8,0) -> 766.65 | H39: =+VLOOKUP(Tabla3[[#This Row],[CEDULA ]],'Conversión-HE'!$C$20:$I$70,6,0) -> 0 | I39: =+VLOOKUP(Tabla3[[#This Row],[CEDULA ]],'Conversión-HE'!$C$20:$I$70,7,0) -> 0 | J39: =((G39/240)*1.5)*H39 -> 0 | K39: =+((G39/240)*2)*I39 -> 0 | L39: =+Tabla3[[#This Row],[US$]]+Tabla3[[#This Row],[US$,]] -> 0
B40: 33 | C40: 956929277 | D40: =+VLOOKUP(Tabla3[[#This Row],[CEDULA ]],'OCTUBRE 2025'!$C$8:$J$57,2,0) -> NAULA CRIOLLO CINTHYA ABIGAIL | E40: =+VLOOKUP(Tabla3[[#This Row],[CEDULA ]],'OCTUBRE 2025'!$C$8:$J$57,4,0) -> CAJERO FINANCIERO | F40: =+VLOOKUP(Tabla3[[#This Row],[CEDULA ]],'OCTUBRE 2025'!$C$8:$J$57,6,0) -> Matriz | G40: =+VLOOKUP(Tabla3[[#This Row],[CEDULA ]],'OCTUBRE 2025'!$C$8:$J$57,8,0) -> 481 | H40: =+VLOOKUP(Tabla3[[#This Row],[CEDULA ]],'Conversión-HE'!$C$20:$I$70,6,0) -> 0 | I40: =+VLOOKUP(Tabla3[[#This Row],[CEDULA ]],'Conversión-HE'!$C$20:$I$70,7,0) -> 0 | J40: =((G40/240)*1.5)*H40 -> 0 | K40: =+((G40/240)*2)*I40 -> 0 | L40: =+Tabla3[[#This Row],[US$]]+Tabla3[[#This Row],[US$,]] -> 0
B41: 34 | C41: 951763994 | D41: =+VLOOKUP(Tabla3[[#This Row],[CEDULA ]],'OCTUBRE 2025'!$C$8:$J$57,2,0) -> NEVAREZ PEÑAFIEL EVELYN JULEXY | E41: =+VLOOKUP(Tabla3[[#This Row],[CEDULA ]],'OCTUBRE 2025'!$C$8:$J$57,4,0) -> ASESOR DE CAPTACIONES | F41: =+VLOOKUP(Tabla3[[#This Row],[CEDULA ]],'OCTUBRE 2025'!$C$8:$J$57,6,0) -> Norte | G41: =+VLOOKUP(Tabla3[[#This Row],[CEDULA ]],'OCTUBRE 2025'!$C$8:$J$57,8,0) -> 475.85 | H41: =+VLOOKUP(Tabla3[[#This Row],[CEDULA ]],'Conversión-HE'!$C$20:$I$70,6,0) -> 0 | I41: =+VLOOKUP(Tabla3[[#This Row],[CEDULA ]],'Conversión-HE'!$C$20:$I$70,7,0) -> 0 | J41: =((G41/240)*1.5)*H41 -> 0 | K41: =+((G41/240)*2)*I41 -> 0 | L41: =+Tabla3[[#This Row],[US$]]+Tabla3[[#This Row],[US$,]] -> 0
B42: 35 | C42: 950703199 | D42: =+VLOOKUP(Tabla3[[#This Row],[CEDULA ]],'OCTUBRE 2025'!$C$8:$J$57,2,0) -> ÑAMO GUALACEO BRYAN JAVIER | E42: =+VLOOKUP(Tabla3[[#This Row],[CEDULA ]],'OCTUBRE 2025'!$C$8:$J$57,4,0) -> OFICIAL DE RECAUDACIONES | F42: =+VLOOKUP(Tabla3[[#This Row],[CEDULA ]],'OCTUBRE 2025'!$C$8:$J$57,6,0) -> Matriz | G42: =+VLOOKUP(Tabla3[[#This Row],[CEDULA ]],'OCTUBRE 2025'!$C$8:$J$57,8,0) -> 473.88 | H42: =+VLOOKUP(Tabla3[[#This Row],[CEDULA ]],'Conversión-HE'!$C$20:$I$70,6,0) -> 0 | I42: =+VLOOKUP(Tabla3[[#This Row],[CEDULA ]],'Conversión-HE'!$C$20:$I$70,7,0) -> 0 | J42: =((G42/240)*1.5)*H42 -> 0 | K42: =+((G42/240)*2)*I42 -> 0 | L42: =+Tabla3[[#This Row],[US$]]+Tabla3[[#This Row],[US$,]] -> 0
B43: 36 | C43: 0923715692 | D43: =+VLOOKUP(Tabla3[[#This Row],[CEDULA ]],'OCTUBRE 2025'!$C$8:$J$57,2,0) -> ORELLANA MANZO WHITNEY YAILYN | E43: =+VLOOKUP(Tabla3[[#This Row],[CEDULA ]],'OCTUBRE 2025'!$C$8:$J$57,4,0) -> OFICIAL DE SEGURIDAD DE LA INFORMACIÓN | F43: =+VLOOKUP(Tabla3[[#This Row],[CEDULA ]],'OCTUBRE 2025'!$C$8:$J$57,6,0) -> Matriz | G43: =+VLOOKUP(Tabla3[[#This Row],[CEDULA ]],'OCTUBRE 2025'!$C$8:$J$57,8,0) -> 600 | H43: =+VLOOKUP(Tabla3[[#This Row],[CEDULA ]],'Conversión-HE'!$C$20:$I$70,6,0) -> 0 | I43: =+VLOOKUP(Tabla3[[#This Row],[CEDULA ]],'Conversión-HE'!$C$20:$I$70,7,0) -> 0 | J43: =((G43/240)*1.5)*H43 -> 0 | K43: =+((G43/240)*2)*I43 -> 0 | L43: =+Tabla3[[#This Row],[US$]]+Tabla3[[#This Row],[US$,]] -> 0
B44: 37 | C44: 925830689 | D44: =+VLOOKUP(Tabla3[[#This Row],[CEDULA ]],'OCTUBRE 2025'!$C$8:$J$57,2,0) -> PERALTA MENDEZ LINA LISSETTE | E44: =+VLOOKUP(Tabla3[[#This Row],[CEDULA ]],'OCTUBRE 2025'!$C$8:$J$57,4,0) -> JEFE DE CRÉDITO | F44: =+VLOOKUP(Tabla3[[#This Row],[CEDULA ]],'OCTUBRE 2025'!$C$8:$J$57,6,0) -> Matriz | G44: =+VLOOKUP(Tabla3[[#This Row],[CEDULA ]],'OCTUBRE 2025'!$C$8:$J$57,8,0) -> 1022.2 | H44: =+VLOOKUP(Tabla3[[#This Row],[CEDULA ]],'Conversión-HE'!$C$20:$I$70,6,0) -> 0 | I44: =+VLOOKUP(Tabla3[[#This Row],[CEDULA ]],'Conversión-HE'!$C$20:$I$70,7,0) -> 0 | J44: =((G44/240)*1.5)*H44 -> 0 | K44: =+((G44/240)*2)*I44 -> 0 | L44: =+Tabla3[[#This Row],[US$]]+Tabla3[[#This Row],[US$,]] -> 0
B45: 38 | C45: 944034842 | D45: =+VLOOKUP(Tabla3[[#This Row],[CEDULA ]],'OCTUBRE 2025'!$C$8:$J$57,2,0) -> PEREZ ZAMORA ANA DE LOS ANGELES | E45: =+VLOOKUP(Tabla3[[#This Row],[CEDULA ]],'OCTUBRE 2025'!$C$8:$J$57,4,0) -> CAJERO FINANCIERO | F45: =+VLOOKUP(Tabla3[[#This Row],[CEDULA ]],'OCTUBRE 2025'!$C$8:$J$57,6,0) -> Matriz | G45: =+VLOOKUP(Tabla3[[#This Row],[CEDULA ]],'OCTUBRE 2025'!$C$8:$J$57,8,0) -> 256.53 | H45: =+VLOOKUP(Tabla3[[#This Row],[CEDULA ]],'Conversión-HE'!$C$20:$I$70,6,0) -> 0 | I45: =+VLOOKUP(Tabla3[[#This Row],[CEDULA ]],'Conversión-HE'!$C$20:$I$70,7,0) -> 0 | J45: =((G45/240)*1.5)*H45 -> 0 | K45: =+((G45/240)*2)*I45 -> 0 | L45: =+Tabla3[[#This Row],[US$]]+Tabla3[[#This Row],[US$,]] -> 0
B46: 39 | C46: 951340702 | D46: =+VLOOKUP(Tabla3[[#This Row],[CEDULA ]],'OCTUBRE 2025'!$C$8:$J$57,2,0) -> QUITO CALDERON JONATHAN ENRIQUE | E46: =+VLOOKUP(Tabla3[[#This Row],[CEDULA ]],'OCTUBRE 2025'!$C$8:$J$57,4,0) -> JEFE DE COBRANZAS | F46: =+VLOOKUP(Tabla3[[#This Row],[CEDULA ]],'OCTUBRE 2025'!$C$8:$J$57,6,0) -> Matriz | G46: =+VLOOKUP(Tabla3[[#This Row],[CEDULA ]],'OCTUBRE 2025'!$C$8:$J$57,8,0) -> 817.76 | H46: =+VLOOKUP(Tabla3[[#This Row],[CEDULA ]],'Conversión-HE'!$C$20:$I$70,6,0) -> 0 | I46: =+VLOOKUP(Tabla3[[#This Row],[CEDULA ]],'Conversión-HE'!$C$20:$I$70,7,0) -> 0 | J46: =((G46/240)*1.5)*H46 -> 0 | K46: =+((G46/240)*2)*I46 -> 0 | L46: =+Tabla3[[#This Row],[US$]]+Tabla3[[#This Row],[US$,]] -> 0
B47: 40 | C47: 650112949 | D47: =+VLOOKUP(Tabla3[[#This Row],[CEDULA ]],'OCTUBRE 2025'!$C$8:$J$57,2,0) -> QUITO UCHUBANDA JANETH ALEXANDRA | E47: =+VLOOKUP(Tabla3[[#This Row],[CEDULA ]],'OCTUBRE 2025'!$C$8:$J$57,4,0) -> OFICIAL DE RECAUDACIONES | F47: =+VLOOKUP(Tabla3[[#This Row],[CEDULA ]],'OCTUBRE 2025'!$C$8:$J$57,6,0) -> Norte | G47: =+VLOOKUP(Tabla3[[#This Row],[CEDULA ]],'OCTUBRE 2025'!$C$8:$J$57,8,0) -> 473.88 | H47: =+VLOOKUP(Tabla3[[#This Row],[CEDULA ]],'Conversión-HE'!$C$20:$I$70,6,0) -> 0 | I47: =+VLOOKUP(Tabla3[[#This Row],[CEDULA ]],'Conversión-HE'!$C$20:$I$70,7,0) -> 0 | J47: =((G47/240)*1.5)*H47 -> 0 | K47: =+((G47/240)*2)*I47 -> 0 | L47: =+Tabla3[[#This Row],[US$]]+Tabla3[[#This Row],[US$,]] -> 0
B48: 41 | C48: 924232804 | D48: =+VLOOKUP(Tabla3[[#This Row],[CEDULA ]],'OCTUBRE 2025'!$C$8:$J$57,2,0) -> RECALDE NARANJO ANGEL ALEXIS | E48: =+VLOOKUP(Tabla3[[#This Row],[CEDULA ]],'OCTUBRE 2025'!$C$8:$J$57,4,0) -> JEFE TI | F48: =+VLOOKUP(Tabla3[[#This Row],[CEDULA ]],'OCTUBRE 2025'!$C$8:$J$57,6,0) -> Matriz | G48: =+VLOOKUP(Tabla3[[#This Row],[CEDULA ]],'OCTUBRE 2025'!$C$8:$J$57,8,0) -> 1022.2 | H48: =+VLOOKUP(Tabla3[[#This Row],[CEDULA ]],'Conversión-HE'!$C$20:$I$70,6,0) -> 0 | I48: =+VLOOKUP(Tabla3[[#This Row],[CEDULA ]],'Conversión-HE'!$C$20:$I$70,7,0) -> 0 | J48: =((G48/240)*1.5)*H48 -> 0 | K48: =+((G48/240)*2)*I48 -> 0 | L48: =+Tabla3[[#This Row],[US$]]+Tabla3[[#This Row],[US$,]] -> 0
B49: 42 | C49: 605031145 | D49: =+VLOOKUP(Tabla3[[#This Row],[CEDULA ]],'OCTUBRE 2025'!$C$8:$J$57,2,0) -> SALAO PEREZ GERMAN FABRICIO | E49: =+VLOOKUP(Tabla3[[#This Row],[CEDULA ]],'OCTUBRE 2025'!$C$8:$J$57,4,0) -> ASESOR DE NEGOCIOS | F49: =+VLOOKUP(Tabla3[[#This Row],[CEDULA ]],'OCTUBRE 2025'!$C$8:$J$57,6,0) -> Durán | G49: =+VLOOKUP(Tabla3[[#This Row],[CEDULA ]],'OCTUBRE 2025'!$C$8:$J$57,8,0) -> 613.32 | H49: =+VLOOKUP(Tabla3[[#This Row],[CEDULA ]],'Conversión-HE'!$C$20:$I$70,6,0) -> 0 | I49: =+VLOOKUP(Tabla3[[#This Row],[CEDULA ]],'Conversión-HE'!$C$20:$I$70,7,0) -> 0 | J49: =((G49/240)*1.5)*H49 -> 0 | K49: =+((G49/240)*2)*I49 -> 0 | L49: =+Tabla3[[#This Row],[US$]]+Tabla3[[#This Row],[US$,]] -> 0
B50: 43 | C50: 927257576 | D50: =+VLOOKUP(Tabla3[[#This Row],[CEDULA ]],'OCTUBRE 2025'!$C$8:$J$57,2,0) -> SANISACA MITE ISRAEL BENJAMIN | E50: =+VLOOKUP(Tabla3[[#This Row],[CEDULA ]],'OCTUBRE 2025'!$C$8:$J$57,4,0) -> JEFE DE CRÉDITO | F50: =+VLOOKUP(Tabla3[[#This Row],[CEDULA ]],'OCTUBRE 2025'!$C$8:$J$57,6,0) -> Norte | G50: =+VLOOKUP(Tabla3[[#This Row],[CEDULA ]],'OCTUBRE 2025'!$C$8:$J$57,8,0) -> 1022.2 | H50: =+VLOOKUP(Tabla3[[#This Row],[CEDULA ]],'Conversión-HE'!$C$20:$I$70,6,0) -> 0 | I50: =+VLOOKUP(Tabla3[[#This Row],[CEDULA ]],'Conversión-HE'!$C$20:$I$70,7,0) -> 0 | J50: =((G50/240)*1.5)*H50 -> 0 | K50: =+((G50/240)*2)*I50 -> 0 | L50: =+Tabla3[[#This Row],[US$]]+Tabla3[[#This Row],[US$,]] -> 0
B51: 44 | C51: 928901800 | D51: =+VLOOKUP(Tabla3[[#This Row],[CEDULA ]],'OCTUBRE 2025'!$C$8:$J$57,2,0) -> TADAY GUAMAN NÉSTOR ALONSO | E51: =+VLOOKUP(Tabla3[[#This Row],[CEDULA ]],'OCTUBRE 2025'!$C$8:$J$57,4,0) -> JEFE DE BOVEDA | F51: =+VLOOKUP(Tabla3[[#This Row],[CEDULA ]],'OCTUBRE 2025'!$C$8:$J$57,6,0) -> Matriz | G51: =+VLOOKUP(Tabla3[[#This Row],[CEDULA ]],'OCTUBRE 2025'!$C$8:$J$57,8,0) -> 511.1 | H51: =+VLOOKUP(Tabla3[[#This Row],[CEDULA ]],'Conversión-HE'!$C$20:$I$70,6,0) -> 0 | I51: =+VLOOKUP(Tabla3[[#This Row],[CEDULA ]],'Conversión-HE'!$C$20:$I$70,7,0) -> 0 | J51: =((G51/240)*1.5)*H51 -> 0 | K51: =+((G51/240)*2)*I51 -> 0 | L51: =+Tabla3[[#This Row],[US$]]+Tabla3[[#This Row],[US$,]] -> 0
B52: 45 | C52: 951315746 | D52: =+VLOOKUP(Tabla3[[#This Row],[CEDULA ]],'OCTUBRE 2025'!$C$8:$J$57,2,0) -> TIGUA MONTERO KAREN LISBETH | E52: =+VLOOKUP(Tabla3[[#This Row],[CEDULA ]],'OCTUBRE 2025'!$C$8:$J$57,4,0) -> ASESOR DE NEGOCIOS | F52: =+VLOOKUP(Tabla3[[#This Row],[CEDULA ]],'OCTUBRE 2025'!$C$8:$J$57,6,0) -> Matriz | G52: =+VLOOKUP(Tabla3[[#This Row],[CEDULA ]],'OCTUBRE 2025'!$C$8:$J$57,8,0) -> 613.32 | H52: =+VLOOKUP(Tabla3[[#This Row],[CEDULA ]],'Conversión-HE'!$C$20:$I$70,6,0) -> 0 | I52: =+VLOOKUP(Tabla3[[#This Row],[CEDULA ]],'Conversión-HE'!$C$20:$I$70,7,0) -> 0 | J52: =((G52/240)*1.5)*H52 -> 0 | K52: =+((G52/240)*2)*I52 -> 0 | L52: =+Tabla3[[#This Row],[US$]]+Tabla3[[#This Row],[US$,]] -> 0
B53: 46 | C53: 954184321 | D53: =+VLOOKUP(Tabla3[[#This Row],[CEDULA ]],'OCTUBRE 2025'!$C$8:$J$57,2,0) -> URQUIZO GUARANGA ALEX EFRAIN | E53: =+VLOOKUP(Tabla3[[#This Row],[CEDULA ]],'OCTUBRE 2025'!$C$8:$J$57,4,0) -> OFICIAL DE RECAUDACIONES | F53: =+VLOOKUP(Tabla3[[#This Row],[CEDULA ]],'OCTUBRE 2025'!$C$8:$J$57,6,0) -> Matriz | G53: =+VLOOKUP(Tabla3[[#This Row],[CEDULA ]],'OCTUBRE 2025'!$C$8:$J$57,8,0) -> 511.1 | H53: =+VLOOKUP(Tabla3[[#This Row],[CEDULA ]],'Conversión-HE'!$C$20:$I$70,6,0) -> 0 | I53: =+VLOOKUP(Tabla3[[#This Row],[CEDULA ]],'Conversión-HE'!$C$20:$I$70,7,0) -> 0 | J53: =((G53/240)*1.5)*H53 -> 0 | K53: =+((G53/240)*2)*I53 -> 0 | L53: =+Tabla3[[#This Row],[US$]]+Tabla3[[#This Row],[US$,]] -> 0
B54: 47 | C54: 922034772 | D54: =+VLOOKUP(Tabla3[[#This Row],[CEDULA ]],'OCTUBRE 2025'!$C$8:$J$57,2,0) -> VERA GUEVARA PAOLA KARINA | E54: =+VLOOKUP(Tabla3[[#This Row],[CEDULA ]],'OCTUBRE 2025'!$C$8:$J$57,4,0) -> ASESOR DE CAPTACIONES | F54: =+VLOOKUP(Tabla3[[#This Row],[CEDULA ]],'OCTUBRE 2025'!$C$8:$J$57,6,0) -> Matriz | G54: =+VLOOKUP(Tabla3[[#This Row],[CEDULA ]],'OCTUBRE 2025'!$C$8:$J$57,8,0) -> 700 | H54: =+VLOOKUP(Tabla3[[#This Row],[CEDULA ]],'Conversión-HE'!$C$20:$I$70,6,0) -> 0 | I54: =+VLOOKUP(Tabla3[[#This Row],[CEDULA ]],'Conversión-HE'!$C$20:$I$70,7,0) -> 0 | J54: =((G54/240)*1.5)*H54 -> 0 | K54: =+((G54/240)*2)*I54 -> 0 | L54: =+Tabla3[[#This Row],[US$]]+Tabla3[[#This Row],[US$,]] -> 0
B55: 48 | C55: 923837991 | D55: =+VLOOKUP(Tabla3[[#This Row],[CEDULA ]],'OCTUBRE 2025'!$C$8:$J$57,2,0) -> YUNDA CUJILEMA MARIA TERESA | E55: =+VLOOKUP(Tabla3[[#This Row],[CEDULA ]],'OCTUBRE 2025'!$C$8:$J$57,4,0) -> CONTADOR GENERAL | F55: =+VLOOKUP(Tabla3[[#This Row],[CEDULA ]],'OCTUBRE 2025'!$C$8:$J$57,6,0) -> Matriz | G55: =+VLOOKUP(Tabla3[[#This Row],[CEDULA ]],'OCTUBRE 2025'!$C$8:$J$57,8,0) -> 1022.2 | H55: =+VLOOKUP(Tabla3[[#This Row],[CEDULA ]],'Conversión-HE'!$C$20:$I$70,6,0) -> 0 | I55: =+VLOOKUP(Tabla3[[#This Row],[CEDULA ]],'Conversión-HE'!$C$20:$I$70,7,0) -> 0 | J55: =((G55/240)*1.5)*H55 -> 0 | K55: =+((G55/240)*2)*I55 -> 0 | L55: =+Tabla3[[#This Row],[US$]]+Tabla3[[#This Row],[US$,]] -> 0
... B57: 50 | C57: 604154575 | D57: =+VLOOKUP(Tabla3[[#This Row],[CEDULA ]],'OCTUBRE 2025'!$C$8:$J$57,2,0) -> YUQUILEMA DELGADO PEDRO ANTONIO | E57: =+VLOOKUP(Tabla3[[#This Row],[CEDULA ]],'OCTUBRE 2025'!$C$8:$J$57,4,0) -> JEFE DE CRÉDITO | F57: =+VLOOKUP(Tabla3[[#This Row],[CEDULA ]],'OCTUBRE 2025'!$C$8:$J$57,6,0) -> Durán | G57: =+VLOOKUP(Tabla3[[#This Row],[CEDULA ]],'OCTUBRE 2025'!$C$8:$J$57,8,0) -> 1022.2 | H57: =+VLOOKUP(Tabla3[[#This Row],[CEDULA ]],'Conversión-HE'!$C$20:$I$70,6,0) -> 0 | I57: =+VLOOKUP(Tabla3[[#This Row],[CEDULA ]],'Conversión-HE'!$C$20:$I$70,7,0) -> 0 | J57: =((G57/240)*1.5)*H57 -> 0 | K57: =+((G57/240)*2)*I57 -> 0 | L57: =+Tabla3[[#This Row],[US$]]+Tabla3[[#This Row],[US$,]] -> 0
J58: =((G58/240)*1.5)*H58 -> 0 | K58: =+((G58/240)*2)*I58 -> 0 | L58: =+Tabla3[[#This Row],[US$]]+Tabla3[[#This Row],[US$,]] -> 0
D59: TOTALES | G59: =SUBTOTAL(109,Tabla3[SUELDO]) -> 30990.65 | H59: =SUBTOTAL(109,Tabla3[Cantidad]) -> 0 | I59: =SUBTOTAL(109,Tabla3[Cantidad2]) -> 0 | J59: =SUBTOTAL(109,Tabla3[US$]) -> 0 | K59: =SUBTOTAL(109,Tabla3[US$,]) -> 0 | L59: =SUBTOTAL(109,Tabla3[US$,,]) -> 0

Sheet Conversión-HE
D2: REPORTE FEBRERO
D3: DIA REPORTADO | H3: HORA SALIDA
D4: 4 | H4: 0.33333333
D5: 5 | H5: 0.33333333
D6: 6 | H6: 0.8125
D7: 7 | H7: -
D8: 8 | H8: 0.33333333
D9: 9 | H9: 0.33333333
D10: 10 | H10: 0.33333333
D11: 11 | H11: 0.33333333
D12: 12 | H12: 0.13541667
D13: 13 | H13: 0.79166667
B19: N° | C19: CI | D19: PERSONAL | E19: AGENCIA | F19: SUPL | G19: EXTRAORD | H19: CONVERSION 50% | I19: CONVERSION 100%
B20: 1 | C20: 925813685 | D20: =+VLOOKUP($C20,'OCTUBRE 2025'!$C$8:$J$57,2,0) -> ASITIMBAY CRIOLLO JOHN ANDERSON | E20: =+VLOOKUP($C20,'OCTUBRE 2025'!$C$8:$J$57,6,0) -> Matriz | H20: =+F20*24 -> 0 | I20: =+G20*24 -> 0
B21: =+B20+1 -> 2 | C21: 944405737 | D21: =+VLOOKUP($C21,'OCTUBRE 2025'!$C$8:$J$57,2,0) -> BARAHONA ZAMBRANO DAYANA NICOLE | E21: =+VLOOKUP($C21,'OCTUBRE 2025'!$C$8:$J$57,6,0) -> Matriz | H21: =+F21*24 -> 0 | I21: =+G21*24 -> 0
B22: =+B21+1 -> 3 | C22: 604394502 | D22: =+VLOOKUP($C22,'OCTUBRE 2025'!$C$8:$J$57,2,0) -> BETUN CHAFLA JULIO CESAR | E22: =+VLOOKUP($C22,'OCTUBRE 2025'!$C$8:$J$57,6,0) -> Matriz | H22: =+F22*24 -> 0 | I22: =+G22*24 -> 0
B23: =+B22+1 -> 4 | C23: 955741970 | D23: =+VLOOKUP($C23,'OCTUBRE 2025'!$C$8:$J$57,2,0) -> CHACAGUASAY CHACAGUASAY ROBERTH CRISTHIAN | E23: =+VLOOKUP($C23,'OCTUBRE 2025'!$C$8:$J$57,6,0) -> Matriz | H23: =+F23*24 -> 0 | I23: =+G23*24 -> 0
B24: =+B23+1 -> 5 | C24: 0943964973 | D24: =+VLOOKUP($C24,'OCTUBRE 2025'!$C$8:$J$57,2,0) -> CHACAGUASAY GUAMAN KEVIN NEHEMIAS | E24: =+VLOOKUP($C24,'OCTUBRE 2025'!$C$8:$J$57,6,0) -> Matriz | H24: =+F24*24 -> 0 | I24: =+G24*24 -> 0
B25: =+B24+1 -> 6 | C25: 944143148 | D25: =+VLOOKUP($C25,'OCTUBRE 2025'!$C$8:$J$57,2,0) -> CHIMBOLEMA YUNGAN MARIO EFRAIN | E25: =+VLOOKUP($C25,'OCTUBRE 2025'!$C$8:$J$57,6,0) -> Durán | H25: =+F25*24 -> 0 | I25: =+G25*24 -> 0
B26: =+B25+1 -> 7 | C26: 955325238 | D26: =+VLOOKUP($C26,'OCTUBRE 2025'!$C$8:$J$57,2,0) -> CHOCA CEPEDA INES VIVIANA | E26: =+VLOOKUP($C26,'OCTUBRE 2025'!$C$8:$J$57,6,0) -> Matriz | H26: =+F26*24 -> 0 | I26: =+G26*24 -> 0
B27: =+B26+1 -> 8 | C27: 914163654 | D27: =+VLOOKUP($C27,'OCTUBRE 2025'!$C$8:$J$57,2,0) -> COCA BENITEZ JORGE MANUEL | E27: =+VLOOKUP($C27,'OCTUBRE 2025'!$C$8:$J$57,6,0) -> Matriz | H27: =+F27*24 -> 0 | I27: =+G27*24 -> 0
B28: =+B27+1 -> 9 | C28: 956668305 | D28: =+VLOOKUP($C28,'OCTUBRE 2025'!$C$8:$J$57,2,0) -> CORO YUQUILEMA RUTH NOEMI | E28: =+VLOOKUP($C28,'OCTUBRE 2025'!$C$8:$J$57,6,0) -> Matriz | H28: =+F28*24 -> 0 | I28: =+G28*24 -> 0
B29: =+B28+1 -> 10 | C29: 0918741448 | D29: =+VLOOKUP($C29,'OCTUBRE 2025'!$C$8:$J$57,2,0) -> DEFAS CHICAIZA JOEL ALBERTO | E29: =+VLOOKUP($C29,'OCTUBRE 2025'!$C$8:$J$57,6,0) -> Norte | H29: =+F29*24 -> 0 | I29: =+G29*24 -> 0
B30: =+B29+1 -> 11 | C30: 931097620 | D30: =+VLOOKUP($C30,'OCTUBRE 2025'!$C$8:$J$57,2,0) -> DEL ROSARIO RODRIGUEZ JUDY ANGELICA | E30: =+VLOOKUP($C30,'OCTUBRE 2025'!$C$8:$J$57,6,0) -> Norte | H30: =+F30*24 -> 0 | I30: =+G30*24 -> 0
B31: =+B30+1 -> 12 | C31: 1105483422 | D31: =+VLOOKUP($C31,'OCTUBRE 2025'!$C$8:$J$57,2,0) -> FLORES HERRERA WENDY DEL CISNE | E31: =+VLOOKUP($C31,'OCTUBRE 2025'!$C$8:$J$57,6,0) -> Durán | H31: =+F31*24 -> 0 | I31: =+G31*24 -> 0
B32: =+B31+1 -> 13 | C32: 942614645 | D32: =+VLOOKUP($C32,'OCTUBRE 2025'!$C$8:$J$57,2,0) -> FUELA TOABANDA JOSUE CHRISTIAN | E32: =+VLOOKUP($C32,'OCTUBRE 2025'!$C$8:$J$57,6,0) -> Matriz | H32: =+F32*24 -> 0 | I32: =+G32*24 -> 0
