Workbook
Name CANTIDAD_POR_DEPARTAMENTO: #REF!
Name SUELDOS_POR_DEPARTAMENTO: #REF!

Sheet OCTUBRE 2025
B2: COOPERATIVA DE AHORRO Y CRÉDITO "LOS ANDES LATINOS" LTDA. | AN2: COOPERATIVA DE AHORRO Y CRÉDITO "LOS ANDES LATINOS" LTDA.
B3: ROL DE PAGOS | R3: MES DE OCTUBRE 2025 | AN3: BENEFICIOS SOCIALES | AU3: =+R3 -> MES DE OCTUBRE 2025
C4: 1 | D4: 2 | E4: 3 | F4: 4 | G4: 5 | H4: 6 | I4: 7 | J4: 8 | K4: 9 | L4: 10 | M4: 11 | N4: 12 | O4: 13 | P4: 14 | Q4: 15 | R4: 16 | S4: 17 | T4: 18 | U4: 19 | V4: 20 | W4: 21 | X4: 22 | Y4: 23 | Z4: 24 | AA4: 25 | AB4: 26 | AC4: 27 | AD4: 28 | AE4: 29 | AF4: 30 | AG4: 31 | AH4: 32 | AI4: 33
J5: INGRESOS | Z5: EGRESOS
B6: No. | C6: CEDULA | D6: NOMBRE | E6: FECHA DE INGRESO | F6: CARGO | G6: GÉNERO | H6: AGENCIA | I6: DIAS TRABAJADOS | J6: SUELDO BRUTO | K6: BONO VEHICULAR | L6: Bono General Mensual | M6: BONO CUMPLIMIENTO | N6: COMISIÓN SUP. META | O6: COMISION POR PLAZOS FIJOS | P6: COM. SOCIOS NUEVOS Y COLOCACION | Q6: VALOR EN HORAS EXTRAS | S6: TOTAL POR VARIACION | T6: INGRESOS APORTE AL IESS | U6: FONDO RESERVAS | V6: FONDO DE RESERVA (BONO NAVIDEÑO) | W6: DECIMO TERCERO | X6: DECIMO CUARTO | Y6: TOTAL DE Ingresos | Z6: IESS | AA6: RET IMP A LA RENTA | AB6: DSCTOS | AC6: PRESTAMO PQ- HIP | AD6: SUBSIDIOS MONETARIO | AE6: EXT. SALUD | AF6: PENSION ALIMENTICIA | AG6: C*C | AH6: ANTICP. SUELD. | AI6: TOTAL DESCTS. | AJ6: NETO | AK6: RECIBI CONFORME | AN6: No. | AO6: NOMBRE | AP6: FECHA DE INGRESO. | AQ6: DIAS TRABAJADOS | AR6: AGENCIA | AS6: TOTAL GANADO EN EL MES GRAVABLE | AT6: 13ER. SUELDO | AU6: FONDO DE RESERVA | AV6: 14TO. SUELDO | AW6: 14TO. SUELDO | AX6: VACACIONES | AY6: TOTAL SUELDO + B.SOCIAL | AZ6: APORTE AL IESS
Q7: 0.5 | R7: 1 | Z7: 0.0945 | AT7: 12 | AU7: 0.0833 | AV7: AJUSTE | AW7: 470 | AX7: 24 | AZ7: Patronal 11,15% | BA7: CCC 1% | BB7: TOTAL
B8: =+#REF!+1 -> #REF! | C8: 923837991 | D8: YUNDA CUJILEMA MARIA TERESA | E8: 41426 | F8: CONTADOR GENERAL | G8: F | H8: Matriz | I8: 30 | J8: 1022.2 | K8: =IFERROR(VLOOKUP(C8,Tabla15[[CEDULA]:[BONO VEHICULAR]],8,0),0) -> 0 | L8: 100 | M8: =+VLOOKUP(C8,Tabla335[[CEDULA ]:[US$,,]],9,0) -> 0 | P8: =+VLOOKUP(C8,'COMISIONES-SOCIOS'!$C$8:$L$57,10,0) -> 0 | Q8: =+VLOOKUP(C8,Tabla3[[CEDULA ]:[US$,]],8,0) -> 0 | R8: =+VLOOKUP($C8,Tabla3[[CEDULA ]:[US$,]],9,0) -> 0 | S8: =SUM(K8:R8) -> 100 | T8: =+J8+S8 -> 1122.2 | U8: =VLOOKUP(C8,FR!$C$6:$M$55,11,0) -> 93.47926 | Y8: =SUM(T8:X8) -> 1215.6793 | Z8: =T8*9.45% -> 106.0479 | AC8: =IFERROR(+VLOOKUP(D8,PQ!$D$35:$E$45,2,0),0) -> 0 | AD8: 0 | AH8: 850 | AI8: =SUM(Z8:AH8) -> 956.0479 | AJ8: =+Y8-AI8 -> 259.63136 | AK8: 600101004961 | AN8: =+#REF!+1 -> #REF! | AO8: =+D8 -> YUNDA CUJILEMA MARIA TERESA | AP8: =+E8 -> 41426 | AQ8: =+I8 -> 30 | AR8: =+H8 -> Matriz | AS8: =T8 -> 1122.2 | AT8: =+AS8/12 -> 93.516667 | AU8: 0 | AW8: =($AW$7/360)*AQ8 -> 39.166667 | AX8: =+AS8/24 -> 46.758333 | AY8: =SUM(AS8:AX8) -> 1301.6417 | AZ8: =+AS8*11.15% -> 125.1253 | BA8: =+AS8*1% -> 11.222 | BB8: =SUM(AZ8:BA8) -> 136.3473
B9: =+B8+1 -> #REF! | C9: 941508905 | D9: YUQUILEMA CACUANGO ANGEL JOSE | E9: 43567 | F9: OFICIAL DE RECAUDACIONES | G9: M | H9: Matriz | I9: 30 | J9: 511.1 | K9: =IFERROR(VLOOKUP(C9,Tabla15[[CEDULA]:[BONO VEHICULAR]],8,0),0) -> 100 | L9: 11.11 | M9: =+VLOOKUP(C9,Tabla335[[CEDULA ]:[US$,,]],9,0) -> 0 | P9: =+VLOOKUP(C9,'COMISIONES-SOCIOS'!$C$8:$L$57,10,0) -> 0 | Q9: =+VLOOKUP(C9,Tabla3[[CEDULA ]:[US$,]],8,0) -> 0 | R9: =+VLOOKUP($C9,Tabla3[[CEDULA ]:[US$,]],9,0) -> 0 | S9: =SUM(K9:R9) -> 111.11 | T9: =+J9+S9 -> 622.21 | U9: =VLOOKUP(C9,FR!$C$6:$M$55,11,0) -> 51.830093 | Y9: =SUM(T9:X9) -> 674.04009 | Z9: =T9*9.45% -> 58.798845 | AC9: =IFERROR(+VLOOKUP(D9,PQ!$D$35:$E$45,2,0),0) -> 0 | AH9: 500 | AI9: =SUM(Z9:AH9) -> 558.79885 | AJ9: =+Y9-AI9 -> 115.24125 | AK9: 600101008981 | AN9: =+AN8+1 -> #REF! | AO9: =+D9 -> YUQUILEMA CACUANGO ANGEL JOSE | AP9: =+E9 -> 43567 | AQ9: =+I9 -> 30 | AR9: =+H9 -> Matriz | AS9: =T9 -> 622.21 | AT9: =+AS9/12 -> 51.850833 | AU9: 0 | AW9: =($AW$7/360)*AQ9 -> 39.166667 | AX9: =+AS9/24 -> 25.925417 | AY9: =SUM(AS9:AX9) -> 739.15292 | AZ9: =+AS9*11.15% -> 69.376415 | BA9: =+AS9*1% -> 6.2221 | BB9: =SUM(AZ9:BA9) -> 75.598515
B10: =+B9+1 -> #REF! | C10: 604154575 | D10: YUQUILEMA DELGADO PEDRO ANTONIO | E10: 43379 | F10: JEFE DE CRÉDITO | G10: M | H10: Durán | I10: 30 | J10: 1022.2 | K10: =IFERROR(VLOOKUP(C10,Tabla15[[CEDULA]:[BONO VEHICULAR]],8,0),0) -> 0 | L10: 0 | M10: =+VLOOKUP(C10,Tabla335[[CEDULA ]:[US$,,]],9,0) -> 0 | P10: =+VLOOKUP(C10,'COMISIONES-SOCIOS'!$C$8:$L$57,10,0) -> 0 | Q10: =+VLOOKUP(C10,Tabla3[[CEDULA ]:[US$,]],8,0) -> 0 | R10: =+VLOOKUP($C10,Tabla3[[CEDULA ]:[US$,]],9,0) -> 0 | S10: =SUM(K10:R10) -> 0 | T10: =+J10+S10 -> 1022.2 | U10: =VLOOKUP(C10,FR!$C$6:$M$55,11,0) -> 85.14926 | Y10: =SUM(T10:X10) -> 1107.3493 | Z10: =T10*9.45% -> 96.5979 | AB10: 0 | AC10: =IFERROR(+VLOOKUP(D10,PQ!$D$35:$E$45,2,0),0) -> 0 | AG10: 0 | AH10: 800 | AI10: =SUM(Z10:AH10) -> 896.5979 | AJ10: =+Y10-AI10 -> 210.75136 | AK10: 600101003932 | AN10: =+AN9+1 -> #REF! | AO10: =+D10 -> YUQUILEMA DELGADO PEDRO ANTONIO | AP10: =+E10 -> 43379 | AQ10: =+I10 -> 30 | AR10: =+H10 -> Durán | AS10: =T10 -> 1022.2 | AT10: =+AS10/12 -> 85.183333 | AU10: 0 | AW10: =($AW$7/360)*AQ10 -> 39.166667 | AX10: =+AS10/24 -> 42.591667 | AY10: =SUM(AS10:AX10) -> 1189.1417 | AZ10: =+AS10*11.15% -> 113.9753 | BA10: =+AS10*1% -> 10.222 | BB10: =SUM(AZ10:BA10) -> 124.1973
D11: TOTALES | J11: =SUBTOTAL(9,J8:J10) -> 2555.5 | K11: =SUBTOTAL(9,K8:K10) -> 100 | L11: =SUBTOTAL(9,L8:L10) -> 111.11 | M11: =SUBTOTAL(9,M8:M10) -> 0 | N11: =SUBTOTAL(9,N8:N10) -> 0 | O11: =SUBTOTAL(9,O8:O10) -> 0 | P11: =SUBTOTAL(9,P8:P10) -> 0 | Q11: =SUBTOTAL(9,Q8:Q10) -> 0 | ... Y11: =SUBTOTAL(9,Y8:Y10) -> 2997.0686 | Z11: =T11*9.45% -> 261.44464 | AA11: =+SUBTOTAL(9,AA8:AA10) -> 0 | AB11: =SUBTOTAL(9,AB8:AB10) -> 0 | AC11: =SUBTOTAL(9,AC8:AC10) -> 0 | AD11: =SUBTOTAL(9,AD8:AD10) -> 0 | AE11: =SUBTOTAL(9,AE8:AE10) -> 0 | AF11: =SUBTOTAL(9,AF8:AF10) -> 0 | AG11: =SUBTOTAL(9,AG8:AG10) -> 0 | AH11: =SUBTOTAL(9,AH8:AH10) -> 2150 | AI11: =SUBTOTAL(9,AI8:AI10) -> 2411.4446 | AJ11: =SUBTOTAL(9,AJ8:AJ10) -> 585.62397 | AO11: =+D11 -> TOTALES | AS11: =SUBTOTAL(9,AS8:AS10) -> 2766.61 | AT11: =SUBTOTAL(9,AT8:AT10) -> 230.55083 | AU11: =SUBTOTAL(9,AU8:AU10) -> 0 | AV11: =SUBTOTAL(9,AV8:AV10) -> 0 | AW11: =SUBTOTAL(9,AW8:AW10) -> 117.5 | AX11: =SUBTOTAL(9,AX8:AX10) -> 115.27542 | AY11: =SUM(AS11:AX11) -> 3229.9363 | AZ11: =+AS11*11.15% -> 308.47701 | BA11: =+AS11*1% -> 27.6661 | BB11: =SUM(AZ11:BA11) -> 336.14311
AT12: 45011005 | AU12: 450135 | AW12: 45011010 | AX12: 45019020 | AZ12: 45012005 | BA12: 45012015
J13: 45010505 | K13: 45019005 | Q13: 45019015 | U13: 450135 | W13: 45011005 | X13: 45011010 | Z13: 25031505 | AA13: 25040505 | AC13: 25039001 | AD13: 45010505 | AE13: 25039002 | AF13: 25039003 | AG13: 16909005 | AH13: 169005 | AJ13: 250305 | AT13: 25031005 | AU13: 250320 | AW13: 25031010 | AX13: 25031025 | AZ13: 25031510 | BA13: 25031510
I27: NORMAL: | J27: =J11 -> 2555.5 | O27: AJUSTE: | P27: =+S11 -> 211.11
I28: 0.0945 | J28: =+J27*I28 -> 241.49475 | O28: 0.0945 | P28: =+P27*O28 -> 19.949895
I29: 0.1215 | J29: =+J27*I29 -> 310.49325 | O29: 0.1215 | P29: =+P27*O29 -> 25.649865 | AT29: 45011005 | AU29: 13° | AV29: =+#REF! -> #REF! | AW29: =+AT11 -> 230.55083
I30: TOTAL | J30: =SUM(J28:J29) -> 551.988 | O30: TOTAL | P30: =SUM(P28:P29) -> 45.59976 | AT30: 450135 | AU30: FR | AW30: =+AU11 -> 0
AT31: 45011010 | AU31: 14° | AV31: =SUM(#REF!) -> #REF! | AW31: =+AW11 -> 117.5
AT32: 45019020 | AU32: Vacaciones | AV32: =SUM(#REF!) -> #REF! | AW32: =+AX11 -> 115.27542
AT33: 45012005 | AU33: Aporte 11.15% | AV33: =+#REF! -> #REF! | AW33: =+AZ11 -> 308.47701
I34: 25031505 | J34: Personal IESS | K34: 2910.88 | O34: 25031505 | P34: Personal IESS | Q34: 657.98 | S34: =+K34+Q34 -> 3568.86 | W34: Cuadre | X34: Personal | Y34: Patronal | Z34: Remuneración | AT34: 45012015 | AU34: Aporte 1% | AV34: =+#REF! -> #REF! | AW34: =+BA11 -> 27.6661
I35: 25031510 | J35: Patronal IESS | K35: 3742.58 | O35: 25031510 | P35: Patronal IESS | Q35: 845.91 | S35: =+K35+Q35 -> 4588.49 | X35: 25031505 | Y35: 25031510 | Z35: 250305 | AT35: 25031005 | AU35: 13° | AX35: =+AT11 -> 230.55083
I36: 45039005 | J36: Gtos Banca | K36: 0 | O36: 45039005 | P36: Gtos Banca | Q36: 0 | W36: Consolidado | X36: =+S34 -> 3568.86 | Y36: =+S35 -> 4588.49 | Z36: 22934.41 | AT36: 250320 | AU36: FR | AX36: =+AU11 -> 0
I37: 25031505 | J37: Personal IESS | M37: 0 | O37: 11031020 | P37: Produbanco | R37: 1503.89 | W37: Matriz | X37: 2129.96 | Y37: 2674.74 | Z37: 13492.95 | AT37: 25031010 | AU37: 14° | AX37: =+AW11 -> 117.5
I38: 25031510 | J38: Patronal IESS | M38: 0 | Q38: =SUM(Q34:Q37) -> 1503.89 | R38: =SUM(R34:R37) -> 1503.89 | W38: Norte | X38: 866.39 | Y38: 1102.87 | Z38: 5495.22 | AT38: 25031025 | AU38: Vacaciones | AX38: =+AX11 -> 115.27542
I39: 11031020 | J39: Produbanco | M39: 6653.46 | R39: =+Q38-R38 -> 0 | W39: Durán | X39: 572.51 | Y39: 783.26 | Z39: 3946.23 | AT39: 25031510 | AU39: Aporte 11.15% | AX39: =+AZ11 -> 308.47701
K40: =SUM(K34:K39) -> 6653.46 | M40: =SUM(M34:M39) -> 6653.46 | W40: Diferencia | X40: =+X36-X37-X38-X39 -> 0 | Y40: =+Y36-Y37-Y38-Y39 -> 27.62 | Z40: =+Z36-Z37-Z38-Z39 -> 0.01 | AT40: 25031510 | AU40: Aporte 1% | AX40: =+BA11 -> 27.6661
M41: =+K40-M40 -> 0 | AW41: =SUM(AW29:AW40) -> 799.46937 | AX41: =SUM(AX29:AX40) -> 799.46937 | AY41: =+AW41-AX41 -> 0
I44: NOTAS DE CRÉDITO IESS
I45: Colaborador | J45: Sueldo | K45: Personal | M45: Patronal
K46: 0.0945 | M46: 0.1115
I47: …... | J47: 0 | K47: =+J47*K46 -> 0 | M47: =+J47*M46 -> 0
I51: 45010505 | J51: Sueldo | K51: =+J11 -> 2555.5
I52: 45019005 | J52: Comisiones | K52: =SUM(K11:P11) -> 211.11
I53: 45019015 | J53: Horas Extras | K53: =SUM(Q11:R11) -> 0
I54: 450135 | J54: FR | K54: =+U11 -> 230.45861
I55: 45011005 | J55: 13° | K55: =+W11 -> 0
I56: 45011010 | J56: 14° | K56: =+X11 -> 0
I57: 25031505 | J57: Apor Personal | M57: =+Z11 -> 261.44464
I58: 25040505 | J58: Retención del Personal | M58: =+AA11 -> 0
I59: 25039001 | J59: Prestamos Q/H | M59: =+AC11 -> 0
I60: 45010505 | J60: Subsidios | M60: =+AD11 -> 0
I61: 25039002 | J61: Ext Salud | M61: =+AE11 -> 0
I62: 25039003 | J62: Pens Alimen | M62: =+AF11 -> 0
I63: 16909005 | J63: Ctas x Cobrar | M63: =+AG11 -> 0
I64: 169005 | J64: Anticipo | M64: =+AH11 -> 2150
I65: 250305 | J65: Remunerac | M65: =+AJ11 -> 585.62397
K66: =SUM(K51:K56) -> 2997.0686 | M66: =SUM(M57:M65) -> 2997.0686 | N66: =+K66-M66 -> 0

Sheet BONO vehicular
B2: CALCULO BONO VEHICULAR
B3: NOMINA SEPTIEMBRE 2025
B6: No. | C6: CEDULA | D6: NOMBRE | E6: FECHA DE INGRESO | F6: CARGO | G6: AGENCIA | H6: DIAS TRABAJADOS | I6: SUELDO | J6: BONO VEHICULAR | K6: Columna1 | N6: DEPARTAMENTOS RECIBEN BONO | O6: BONOS
B7: 1 | C7: 955741970 | D7: =+VLOOKUP(Tabla15[[#This Row],[CEDULA]],'OCTUBRE 2025'!$C$8:$J$10,2,0) -> #N/A | E7: 01/MARZO/2023 | F7: =+VLOOKUP(Tabla15[[#This Row],[CEDULA]],'OCTUBRE 2025'!$C$8:$J$10,4,0) -> #N/A | G7: Matriz | H7: =+VLOOKUP(Tabla15[[#This Row],[CEDULA]],'OCTUBRE 2025'!$C$8:$J$10,7,0) -> #N/A | I7: =+VLOOKUP(Tabla15[[#This Row],[CEDULA]],'OCTUBRE 2025'!$C$8:$J$10,8,0) -> #N/A | J7: =100 -> 100 | N7: EJECUTIVO DE CAPTACIONES | O7: 100
B8: 2 | C8: 944143148 | D8: =+VLOOKUP(Tabla15[[#This Row],[CEDULA]],'OCTUBRE 2025'!$C$8:$J$10,2,0) -> #N/A | E8: 27/ABRIL/2023 | F8: EJECUTIVO DE RECAUDACION | G8: Matriz | H8: =+VLOOKUP(Tabla15[[#This Row],[CEDULA]],'OCTUBRE 2025'!$C$8:$J$10,7,0) -> #N/A | I8: =+VLOOKUP(Tabla15[[#This Row],[CEDULA]],'OCTUBRE 2025'!$C$8:$J$10,8,0) -> #N/A | J8: =+(3.33333333333333)*Tabla15[[#This Row],[DIAS TRABAJADOS]] -> #N/A | N8: ASESOR LEGAL | O8: 200
B9: 3 | C9: 950929232 | D9: =+VLOOKUP(Tabla15[[#This Row],[CEDULA]],'OCTUBRE 2025'!$C$8:$J$10,2,0) -> #N/A | E9: 14/JUNIO/2022 | F9: EJECUTIVO DE RECAUDACION | G9: Norte | H9: =+VLOOKUP(Tabla15[[#This Row],[CEDULA]],'OCTUBRE 2025'!$C$8:$J$10,7,0) -> #N/A | I9: =+VLOOKUP(Tabla15[[#This Row],[CEDULA]],'OCTUBRE 2025'!$C$8:$J$10,8,0) -> #N/A | J9: 0 | N9: JEFE DE AGENCIA | O9: 200
B10: 4 | C10: 953819646 | D10: =+VLOOKUP(Tabla15[[#This Row],[CEDULA]],'OCTUBRE 2025'!$C$8:$J$10,2,0) -> #N/A | E10: 17/MARZO/2022 | F10: EJECUTIVO DE RECAUDACION | G10: Matriz | H10: =+VLOOKUP(Tabla15[[#This Row],[CEDULA]],'OCTUBRE 2025'!$C$8:$J$10,7,0) -> #N/A | I10: =+VLOOKUP(Tabla15[[#This Row],[CEDULA]],'OCTUBRE 2025'!$C$8:$J$10,8,0) -> #N/A | J10: =100 -> 100 | N10: JEFE DE BOVEDA | O10: 300
B11: 5 | C11: 956796767 | D11: =+VLOOKUP(Tabla15[[#This Row],[CEDULA]],'OCTUBRE 2025'!$C$8:$J$10,2,0) -> #N/A | E11: 21/JULIO/2022 | F11: EJECUTIVO DE RECAUDACION | G11: Norte | H11: =+VLOOKUP(Tabla15[[#This Row],[CEDULA]],'OCTUBRE 2025'!$C$8:$J$10,7,0) -> #N/A | I11: =+VLOOKUP(Tabla15[[#This Row],[CEDULA]],'OCTUBRE 2025'!$C$8:$J$10,8,0) -> #N/A | J11: =100 -> 100 | N11: JEFE DE RECAUDACIÓN | O11: 200
B12: 6 | C12: 957093800 | D12: =+VLOOKUP(Tabla15[[#This Row],[CEDULA]],'OCTUBRE 2025'!$C$8:$J$10,2,0) -> #N/A | E12: 01/MAYO/2023 | F12: EJECUTIVO DE RECAUDACION | G12: Durán | H12: =+VLOOKUP(Tabla15[[#This Row],[CEDULA]],'OCTUBRE 2025'!$C$8:$J$10,7,0) -> #N/A | I12: =+VLOOKUP(Tabla15[[#This Row],[CEDULA]],'OCTUBRE 2025'!$C$8:$J$10,8,0) -> #N/A | J12: =+(3.33333333333333)*Tabla15[[#This Row],[DIAS TRABAJADOS]]-60 -> #N/A
B13: 7 | C13: 603838657 | D13: =+VLOOKUP(Tabla15[[#This Row],[CEDULA]],'OCTUBRE 2025'!$C$8:$J$10,2,0) -> #N/A | E13: 01/OCTUBRE/2022 | F13: EJECUTIVO DE RECAUDACION | G13: Durán | H13: =+VLOOKUP(Tabla15[[#This Row],[CEDULA]],'OCTUBRE 2025'!$C$8:$J$10,7,0) -> #N/A | I13: =+VLOOKUP(Tabla15[[#This Row],[CEDULA]],'OCTUBRE 2025'!$C$8:$J$10,8,0) -> #N/A | J13: 200
B14: 8 | C14: 925240525 | D14: =+VLOOKUP(Tabla15[[#This Row],[CEDULA]],'OCTUBRE 2025'!$C$8:$J$10,2,0) -> #N/A | E14: 01/JUNIO/2006 | F14: ASESOR LEGAL | G14: Matriz | H14: =+VLOOKUP(Tabla15[[#This Row],[CEDULA]],'OCTUBRE 2025'!$C$8:$J$10,7,0) -> #N/A | I14: =+VLOOKUP(Tabla15[[#This Row],[CEDULA]],'OCTUBRE 2025'!$C$8:$J$10,8,0) -> #N/A | J14: =200-200 -> 0
C15: 0943906032 | D15: =+VLOOKUP(Tabla15[[#This Row],[CEDULA]],'OCTUBRE 2025'!$C$8:$J$10,2,0) -> #N/A | F15: EJECUTIVO DE RECAUDACION | G15: Norte | H15: 30 | I15: 473.88 | J15: =100 -> 100
B16: 9 | C16: 950703199 | D16: =+VLOOKUP(Tabla15[[#This Row],[CEDULA]],'OCTUBRE 2025'!$C$8:$J$10,2,0) -> #N/A | E16: 13/OCTUBRE/2022 | F16: EJECUTIVO DE RECAUDACION | G16: Matriz | H16: =+VLOOKUP(Tabla15[[#This Row],[CEDULA]],'OCTUBRE 2025'!$C$8:$J$10,7,0) -> #N/A | I16: =+VLOOKUP(Tabla15[[#This Row],[CEDULA]],'OCTUBRE 2025'!$C$8:$J$10,8,0) -> #N/A | J16: =100 -> 100
B17: 10 | C17: 925830689 | D17: =+VLOOKUP(Tabla15[[#This Row],[CEDULA]],'OCTUBRE 2025'!$C$8:$J$10,2,0) -> #N/A | E17: 01/AGOSTO/2019 | F17: JEFE DE AGENCIA | G17: Matriz | H17: =+VLOOKUP(Tabla15[[#This Row],[CEDULA]],'OCTUBRE 2025'!$C$8:$J$10,7,0) -> #N/A | I17: =+VLOOKUP(Tabla15[[#This Row],[CEDULA]],'OCTUBRE 2025'!$C$8:$J$10,8,0) -> #N/A | J17: 0
B18: 12 | C18: 951340702 | D18: =+VLOOKUP(Tabla15[[#This Row],[CEDULA]],'OCTUBRE 2025'!$C$8:$J$10,2,0) -> #N/A | E18: 18/ENERO/2022 | F18: JEFE DE CAPTACIONES | G18: Matriz | H18: =+VLOOKUP(Tabla15[[#This Row],[CEDULA]],'OCTUBRE 2025'!$C$8:$J$10,7,0) -> #N/A | I18: =+VLOOKUP(Tabla15[[#This Row],[CEDULA]],'OCTUBRE 2025'!$C$8:$J$10,8,0) -> #N/A | J18: 0
B19: 13 | C19: 927257576 | D19: =+VLOOKUP(Tabla15[[#This Row],[CEDULA]],'OCTUBRE 2025'!$C$8:$J$10,2,0) -> #N/A | E19: 04/NOVIEMBRE/2020 | F19: JEFE DE AGENCIA | G19: Norte | H19: =+VLOOKUP(Tabla15[[#This Row],[CEDULA]],'OCTUBRE 2025'!$C$8:$J$10,7,0) -> #N/A | I19: =+VLOOKUP(Tabla15[[#This Row],[CEDULA]],'OCTUBRE 2025'!$C$8:$J$10,8,0) -> #N/A | J19: =200-200 -> 0
B20: 14 | C20: 928901800 | D20: =+VLOOKUP(Tabla15[[#This Row],[CEDULA]],'OCTUBRE 2025'!$C$8:$J$10,2,0) -> #N/A | E20: 01/MAYO/2017 | F20: JEFE DE BOVEDA | G20: Matriz | H20: =+VLOOKUP(Tabla15[[#This Row],[CEDULA]],'OCTUBRE 2025'!$C$8:$J$10,7,0) -> #N/A | I20: =+VLOOKUP(Tabla15[[#This Row],[CEDULA]],'OCTUBRE 2025'!$C$8:$J$10,8,0) -> #N/A | J20: =300-100-100 -> 100
B21: 15 | C21: 954184321 | D21: =+VLOOKUP(Tabla15[[#This Row],[CEDULA]],'OCTUBRE 2025'!$C$8:$J$10,2,0) -> #N/A | E21: 01/JULIO/2021 | F21: EJECUTIVO DE RECAUDACION | G21: Matriz | H21: =+VLOOKUP(Tabla15[[#This Row],[CEDULA]],'OCTUBRE 2025'!$C$8:$J$10,7,0) -> #N/A | I21: =+VLOOKUP(Tabla15[[#This Row],[CEDULA]],'OCTUBRE 2025'!$C$8:$J$10,8,0) -> #N/A | J21: =100 -> 100
B22: 16 | C22: 941508905 | D22: =+VLOOKUP(Tabla15[[#This Row],[CEDULA]],'OCTUBRE 2025'!$C$8:$J$10,2,0) -> YUQUILEMA CACUANGO ANGEL JOSE | E22: 12/ABRIL/2019 | F22: EJECUTIVO DE RECAUDACION | G22: Matriz | H22: =+VLOOKUP(Tabla15[[#This Row],[CEDULA]],'OCTUBRE 2025'!$C$8:$J$10,7,0) -> 30 | I22: =+VLOOKUP(Tabla15[[#This Row],[CEDULA]],'OCTUBRE 2025'!$C$8:$J$10,8,0) -> 511.1 | J22: =(100/30)*Tabla15[[#This Row],[DIAS TRABAJADOS]] -> 100
B23: 18 | C23: 604154575 | D23: =+VLOOKUP(Tabla15[[#This Row],[CEDULA]],'OCTUBRE 2025'!$C$8:$J$10,2,0) -> YUQUILEMA DELGADO PEDRO ANTONIO | E23: 06/OCTUBRE/2018 | F23: JEFE DE AGENCIA | G23: Durán | H23: =+VLOOKUP(Tabla15[[#This Row],[CEDULA]],'OCTUBRE 2025'!$C$8:$J$10,7,0) -> 30 | I23: =+VLOOKUP(Tabla15[[#This Row],[CEDULA]],'OCTUBRE 2025'!$C$8:$J$10,8,0) -> 1022.2 | J23: =200-200 -> 0
D25: TOTALES | J25: =SUM(Tabla15[BONO VEHICULAR]) -> #N/A
B44: 4

Sheet COMISIONES
B2: CALCULO DE APERTURA CUENTA- COLOCACIONES - PLAZO FIJO
B3: NOMINA AGOSTO 2023
B4: DEL CORTE DEL 01 DE AGOSTO AL 31 DE AGOSTO DEL 2023
B6: No. | C6: CEDULA | D6: NOMBRE | E6: BONO POR CUMPLIMIENTO | F6: COMISIÓN META | G6: COMISION POR PLAZOS FIJOS | H6: COM. SOCIOS NUEVOS Y COLOCACION | I6: ANTICIPO A SUELDO
B8: 1 | C8: =+'OCTUBRE 2025'!#REF! -> #REF! | D8: =+VLOOKUP(C8,'OCTUBRE 2025'!$C$8:$F$10,2,0) -> #REF!
B9: 2 | C9: =+'OCTUBRE 2025'!#REF! -> #REF! | D9: =+VLOOKUP(C9,'OCTUBRE 2025'!$C$8:$F$10,2,0) -> #REF!
B10: 3 | C10: =+'OCTUBRE 2025'!#REF! -> #REF! | D10: =+VLOOKUP(C10,'OCTUBRE 2025'!$C$8:$F$10,2,0) -> #REF!
B11: 4 | C11: =+'OCTUBRE 2025'!#REF! -> #REF! | D11: =+VLOOKUP(C11,'OCTUBRE 2025'!$C$8:$F$10,2,0) -> #REF! | E11: 100 | F11: 236.65 | H11: 30
B12: 5 | C12: =+'OCTUBRE 2025'!#REF! -> #REF! | D12: =+VLOOKUP(C12,'OCTUBRE 2025'!$C$8:$F$10,2,0) -> #REF! | E12: 100 | F12: 99.5
B13: 6 | C13: =+'OCTUBRE 2025'!#REF! -> #REF! | D13: =+VLOOKUP(C13,'OCTUBRE 2025'!$C$8:$F$10,2,0) -> #REF!
B14: 7 | C14: =+'OCTUBRE 2025'!#REF! -> #REF! | D14: =+VLOOKUP(C14,'OCTUBRE 2025'!$C$8:$F$10,2,0) -> #REF!
B15: 8 | C15: =+'OCTUBRE 2025'!#REF! -> #REF! | D15: =+VLOOKUP(C15,'OCTUBRE 2025'!$C$8:$F$10,2,0) -> #REF!
B16: 9 | C16: =+'OCTUBRE 2025'!#REF! -> #REF! | D16: =+VLOOKUP(C16,'OCTUBRE 2025'!$C$8:$F$10,2,0) -> #REF!
B17: 10 | C17: =+'OCTUBRE 2025'!#REF! -> #REF! | D17: =+VLOOKUP(C17,'OCTUBRE 2025'!$C$8:$F$10,2,0) -> #REF!
B18: 11 | C18: =+'OCTUBRE 2025'!#REF! -> #REF! | D18: =+VLOOKUP(C18,'OCTUBRE 2025'!$C$8:$F$10,2,0) -> #REF!
B19: 12 | C19: =+'OCTUBRE 2025'!#REF! -> #REF! | D19: =+VLOOKUP(C19,'OCTUBRE 2025'!$C$8:$F$10,2,0) -> #REF!
B20: 13 | C20: =+'OCTUBRE 2025'!#REF! -> #REF! | D20: =+VLOOKUP(C20,'OCTUBRE 2025'!$C$8:$F$10,2,0) -> #REF!
B21: 14 | C21: =+'OCTUBRE 2025'!#REF! -> #REF! | D21: =+VLOOKUP(C21,'OCTUBRE 2025'!$C$8:$F$10,2,0) -> #REF!
B22: 15 | C22: =+'OCTUBRE 2025'!#REF! -> #REF! | D22: =+VLOOKUP(C22,'OCTUBRE 2025'!$C$8:$F$10,2,0) -> #REF! | F22: 7.31
B23: 16 | C23: =+'OCTUBRE 2025'!#REF! -> #REF! | D23: =+VLOOKUP(C23,'OCTUBRE 2025'!$C$8:$F$10,2,0) -> #REF!
B24: 17 | C24: =+'OCTUBRE 2025'!#REF! -> #REF! | D24: =+VLOOKUP(C24,'OCTUBRE 2025'!$C$8:$F$10,2,0) -> #REF! | F24: 10.84
B25: 18 | C25: =+'OCTUBRE 2025'!#REF! -> #REF! | D25: =+VLOOKUP(C25,'OCTUBRE 2025'!$C$8:$F$10,2,0) -> #REF!
B26: 19 | C26: =+'OCTUBRE 2025'!#REF! -> #REF! | D26: =+VLOOKUP(C26,'OCTUBRE 2025'!$C$8:$F$10,2,0) -> #REF!
B27: 20 | C27: =+'OCTUBRE 2025'!#REF! -> #REF! | D27: =+VLOOKUP(C27,'OCTUBRE 2025'!$C$8:$F$10,2,0) -> #REF!
B28: 21 | C28: =+'OCTUBRE 2025'!#REF! -> #REF! | D28: =+VLOOKUP(C28,'OCTUBRE 2025'!$C$8:$F$10,2,0) -> #REF!
B29: 22 | C29: =+'OCTUBRE 2025'!#REF! -> #REF! | D29: =+VLOOKUP(C29,'OCTUBRE 2025'!$C$8:$F$10,2,0) -> #REF!
B30: 23 | C30: =+'OCTUBRE 2025'!#REF! -> #REF! | D30: =+VLOOKUP(C30,'OCTUBRE 2025'!$C$8:$F$10,2,0) -> #REF! | E30: 100 | F30: 518.5
B31: 24 | C31: =+'OCTUBRE 2025'!#REF! -> #REF! | D31: =+VLOOKUP(C31,'OCTUBRE 2025'!$C$8:$F$10,2,0) -> #REF!
B32: 25 | C32: =+'OCTUBRE 2025'!#REF! -> #REF! | D32: =+VLOOKUP(C32,'OCTUBRE 2025'!$C$8:$F$10,2,0) -> #REF!
B33: 26 | C33: =+'OCTUBRE 2025'!#REF! -> #REF! | D33: =+VLOOKUP(C33,'OCTUBRE 2025'!$C$8:$F$10,2,0) -> #REF!
B34: 27 | C34: =+'OCTUBRE 2025'!#REF! -> #REF! | D34: =+VLOOKUP(C34,'OCTUBRE 2025'!$C$8:$F$10,2,0) -> #REF!
B35: 28 | C35: =+'OCTUBRE 2025'!#REF! -> #REF! | D35: =+VLOOKUP(C35,'OCTUBRE 2025'!$C$8:$F$10,2,0) -> #REF!
B36: 29 | C36: =+'OCTUBRE 2025'!#REF! -> #REF! | D36: =+VLOOKUP(C36,'OCTUBRE 2025'!$C$8:$F$10,2,0) -> #REF!
B37: 30 | C37: =+'OCTUBRE 2025'!#REF! -> #REF! | D37: =+VLOOKUP(C37,'OCTUBRE 2025'!$C$8:$F$10,2,0) -> #REF!
B38: 31 | C38: =+'OCTUBRE 2025'!#REF! -> #REF! | D38: =+VLOOKUP(C38,'OCTUBRE 2025'!$C$8:$F$10,2,0) -> #REF! | F38: 60.37
B39: 32 | C39: =+'OCTUBRE 2025'!#REF! -> #REF! | D39: =+VLOOKUP(C39,'OCTUBRE 2025'!$C$8:$F$10,2,0) -> #REF!
B40: 33 | C40: =+'OCTUBRE 2025'!#REF! -> #REF! | D40: =+VLOOKUP(C40,'OCTUBRE 2025'!$C$8:$F$10,2,0) -> #REF! | E40: 100 | F40: 75
B41: 34 | C41: =+'OCTUBRE 2025'!#REF! -> #REF! | D41: =+VLOOKUP(C41,'OCTUBRE 2025'!$C$8:$F$10,2,0) -> #REF!
B42: 35 | C42: =+'OCTUBRE 2025'!#REF! -> #REF! | D42: =+VLOOKUP(C42,'OCTUBRE 2025'!$C$8:$F$10,2,0) -> #REF!
B43: 36 | C43: =+'OCTUBRE 2025'!#REF! -> #REF! | D43: =+VLOOKUP(C43,'OCTUBRE 2025'!$C$8:$F$10,2,0) -> #REF!
B44: 37 | C44: =+'OCTUBRE 2025'!#REF! -> #REF! | D44: =+VLOOKUP(C44,'OCTUBRE 2025'!$C$8:$F$10,2,0) -> #REF!
B45: 38 | C45: =+'OCTUBRE 2025'!#REF! -> #REF! | D45: =+VLOOKUP(C45,'OCTUBRE 2025'!$C$8:$F$10,2,0) -> #REF! | E45: 100 | F45: 222.5
B46: 39 | C46: =+'OCTUBRE 2025'!#REF! -> #REF! | D46: =+VLOOKUP(C46,'OCTUBRE 2025'!$C$8:$F$10,2,0) -> #REF! | F46: 203.97
B47: 40 | C47: =+'OCTUBRE 2025'!#REF! -> #REF! | D47: =+VLOOKUP(C47,'OCTUBRE 2025'!$C$8:$F$10,2,0) -> #REF!
B48: 41 | C48: =+'OCTUBRE 2025'!#REF! -> #REF! | D48: =+VLOOKUP(C48,'OCTUBRE 2025'!$C$8:$F$10,2,0) -> #REF!
B49: 42 | C49: =+'OCTUBRE 2025'!#REF! -> #REF! | D49: =+VLOOKUP(C49,'OCTUBRE 2025'!$C$8:$F$10,2,0) -> #REF!
B50: 43 | C50: =+'OCTUBRE 2025'!#REF! -> #REF! | D50: =+VLOOKUP(C50,'OCTUBRE 2025'!$C$8:$F$10,2,0) -> #REF! | F50: 50.03
B51: 44 | C51: =+'OCTUBRE 2025'!#REF! -> #REF! | D51: =+VLOOKUP(C51,'OCTUBRE 2025'!$C$8:$F$10,2,0) -> #REF!
B52: 45 | C52: =+'OCTUBRE 2025'!C8 -> 923837991 | D52: =+VLOOKUP(C52,'OCTUBRE 2025'!$C$8:$F$10,2,0) -> YUNDA CUJILEMA MARIA TERESA
D54: TOTALES | E54: =SUM(E8:E52) -> 500 | F54: =SUM(F8:F50) -> 1484.67 | G54: =SUM(G8:G50) -> 0 | H54: =SUM(H8:H52) -> 30 | I54: =SUM(I8:I52) -> 0

Sheet ROL INDIVIDUAL
F5: ROL INDIVIDUAL | H5: 45931
C7: Identificación: | D7: 923837991 | F7: Oficina: | G7: =VLOOKUP($D$7,'OCTUBRE 2025'!$C$8:$AJ$10,6,0) -> Matriz
C8: Nombres: | D8: =VLOOKUP($D$7,'OCTUBRE 2025'!$C$8:$AJ$10,2,0) -> YUNDA CUJILEMA MARIA TERESA | F8: No. días: | G8: =VLOOKUP($D$7,'OCTUBRE 2025'!$C$8:$AJ$10,7,0) -> 30
C9: Cargo: | D9: =VLOOKUP($D$7,'OCTUBRE 2025'!$C$8:$AJ$10,4,0) -> CONTADOR GENERAL
C11: INGRESOS | E11: VALOR | F11: EGRESOS | H11: VALOR
C12: Sueldo básico cooperativa | E12: =VLOOKUP($D$7,'OCTUBRE 2025'!$C$8:$AJ$10,8,0) -> 1022.2 | F12: Aporte Individual IESS 9.45% | H12: =VLOOKUP($D$7,'OCTUBRE 2025'!$C$8:$AJ$10,24,0) -> 106.0479
C13: Bono Movilización | E13: =VLOOKUP($D$7,'OCTUBRE 2025'!$C$8:$AJ$10,9,0) -> 0 | F13: Préstamos Quirografarios o Hipotecarios | H13: =VLOOKUP($D$7,'OCTUBRE 2025'!$C$8:$AJ$10,27,0) -> 0
C14: Bono mensual (2.174%) | E14: =VLOOKUP($D$7,'OCTUBRE 2025'!$C$8:$AJ$10,10,0) -> 100 | F14: Subsidio Monetario | H14: =VLOOKUP($D$7,'OCTUBRE 2025'!$C$8:$AJ$10,28,0) -> 0
C15: Bono cumplimiento | E15: =VLOOKUP($D$7,'OCTUBRE 2025'!$C$8:$AJ$10,11,0) -> 0 | F15: Extensión de Salud | H15: =VLOOKUP($D$7,'OCTUBRE 2025'!$C$8:$AJ$10,29,0) -> 0
C16: Comisión por superación de meta | E16: =VLOOKUP($D$7,'OCTUBRE 2025'!$C$8:$AJ$10,12,0) -> 0 | F16: Pensión alimenticia | H16: =VLOOKUP($D$7,'OCTUBRE 2025'!$C$8:$AJ$10,30,0) -> 0
C17: Comisión por Depósito a Plazo Fijo | E17: =VLOOKUP($D$7,'OCTUBRE 2025'!$C$8:$AJ$10,13,0) -> 0 | F17: Cuentas por cobrar | H17: =VLOOKUP($D$7,'OCTUBRE 2025'!$C$8:$AJ$10,31,0) -> 0
C18: Comisión socios nuevos | E18: =VLOOKUP($D$7,'OCTUBRE 2025'!$C$8:$AJ$10,14,0) -> 0 | F18: Anticipo de Sueldo | H18: =VLOOKUP($D$7,'OCTUBRE 2025'!$C$8:$AJ$10,32,0) -> 850
C19: Horas Extras 50% | E19: =VLOOKUP($D$7,'OCTUBRE 2025'!$C$8:$AJ$10,15,0) -> 0 | F19: Ret Imp. A la Renta | H19: =VLOOKUP($D$7,'OCTUBRE 2025'!$C$8:$AJ$10,25,0) -> 0
C20: Horas Extras 100% | E20: =VLOOKUP($D$7,'OCTUBRE 2025'!$C$8:$AJ$10,16,0) -> 0 | F20: Descuentos | H20: =VLOOKUP($D$7,'OCTUBRE 2025'!$C$8:$AJ$10,26,0) -> 0
C21: Fondo de Reserva | E21: =VLOOKUP($D$7,'OCTUBRE 2025'!$C$8:$AJ$10,19,0) -> 93.47926
C22: Fondo de Reserva (ajustes) | E22: =VLOOKUP($D$7,'OCTUBRE 2025'!$C$8:$AJ$10,20,0) -> 0
C23: Décimo Tercero | E23: =VLOOKUP($D$7,'OCTUBRE 2025'!$C$8:$AJ$10,21,0) -> 0
C24: Décimo Cuarto | E24: =VLOOKUP($D$7,'OCTUBRE 2025'!$C$8:$AJ$10,22,0) -> 0
C25: TOTAL DE INGRESOS | E25: =SUM(E12:E24) -> 1215.6793 | F25: TOTAL EGRESOS | H25: =SUM(H12:H23) -> 956.0479
F26: VALOR NETO A RECIBIR | H26: =+E25-H25 -> 259.63136
C28: Elaborado por: | G28: Recibí Conforme:
C31: Ing. Magaly Morocho | G31: =+$D$8 -> YUNDA CUJILEMA MARIA TERESA
C32: Talento Humano | G32: Funcionario

Sheet ROL INDIVIDUAL (2)
F5: ROL INDIVIDUAL | H5: 45839
C7: Identificación: | D7: 0943906032 | F7: Oficina: | G7: =VLOOKUP($D$7,'OCTUBRE 2025'!$C$8:$AJ$10,6,0) -> #N/A
C8: Nombres: | D8: =VLOOKUP($D$7,'OCTUBRE 2025'!$C$8:$AJ$10,2,0) -> #N/A | F8: No. días: | G8: =VLOOKUP($D$7,'OCTUBRE 2025'!$C$8:$AJ$10,7,0) -> #N/A
C9: Cargo: | D9: =VLOOKUP($D$7,'OCTUBRE 2025'!$C$8:$AJ$10,4,0) -> #N/A
C11: INGRESOS | E11: VALOR | F11: EGRESOS | H11: VALOR
C12: Sueldo básico cooperativa | E12: =VLOOKUP($D$7,'OCTUBRE 2025'!$C$8:$AJ$10,8,0) -> #N/A | F12: Aporte Individual IESS 9.45% | H12: =VLOOKUP($D$7,'OCTUBRE 2025'!$C$8:$AJ$10,24,0) -> #N/A
C13: Bono Movilización | E13: =VLOOKUP($D$7,'OCTUBRE 2025'!$C$8:$AJ$10,9,0) -> #N/A | F13: Préstamos Quirografarios o Hipotecarios | H13: =VLOOKUP($D$7,'OCTUBRE 2025'!$C$8:$AJ$10,27,0) -> #N/A
C14: Bono mensual (2.174%) | E14: =VLOOKUP($D$7,'OCTUBRE 2025'!$C$8:$AJ$10,10,0) -> #N/A | F14: Subsidio Monetario | H14: =VLOOKUP($D$7,'OCTUBRE 2025'!$C$8:$AJ$10,28,0) -> #N/A
C15: Bono cumplimiento | E15: =VLOOKUP($D$7,'OCTUBRE 2025'!$C$8:$AJ$10,11,0) -> #N/A | F15: Extensión de Salud | H15: =VLOOKUP($D$7,'OCTUBRE 2025'!$C$8:$AJ$10,29,0) -> #N/A
C16: Comisión por cumplimiento de meta | E16: =VLOOKUP($D$7,'OCTUBRE 2025'!$C$8:$AJ$10,12,0) -> #N/A | F16: Pensión alimenticia | H16: =VLOOKUP($D$7,'OCTUBRE 2025'!$C$8:$AJ$10,30,0) -> #N/A
C17: Comisión por Depósito a Plazo Fijo | E17: =VLOOKUP($D$7,'OCTUBRE 2025'!$C$8:$AJ$10,13,0) -> #N/A | F17: Cuentas por cobrar | H17: =VLOOKUP($D$7,'OCTUBRE 2025'!$C$8:$AJ$10,31,0) -> #N/A
C18: Comisión socios nuevos | E18: =VLOOKUP($D$7,'OCTUBRE 2025'!$C$8:$AJ$10,14,0) -> #N/A | F18: Anticipo de Sueldo | H18: 0
C19: Horas Extras 50% | E19: =VLOOKUP($D$7,'OCTUBRE 2025'!$C$8:$AJ$10,15,0) -> #N/A | F19: Ret Imp. A la Renta | H19: =VLOOKUP($D$7,'OCTUBRE 2025'!$C$8:$AJ$10,25,0) -> #N/A
C20: Horas Extras 100% | E20: =VLOOKUP($D$7,'OCTUBRE 2025'!$C$8:$AJ$10,16,0) -> #N/A | F20: Descuentos | H20: =VLOOKUP($D$7,'OCTUBRE 2025'!$C$8:$AJ$10,26,0) -> #N/A
C21: Fondo de Reserva | E21: =VLOOKUP($D$7,'OCTUBRE 2025'!$C$8:$AJ$10,19,0) -> #N/A
C22: Fondo de Reserva (ajustes) | E22: =VLOOKUP($D$7,'OCTUBRE 2025'!$C$8:$AJ$10,20,0) -> #N/A
C23: Décimo Tercero | E23: =VLOOKUP($D$7,'OCTUBRE 2025'!$C$8:$AJ$10,21,0) -> #N/A
C24: Décimo Cuarto | E24: =VLOOKUP($D$7,'OCTUBRE 2025'!$C$8:$AJ$10,22,0) -> #N/A
C25: TOTAL DE INGRESOS | E25: =SUM(E12:E24) -> #N/A | F25: TOTAL EGRESOS | H25: =SUM(H12:H23) -> #N/A
F26: VALOR NETO A RECIBIR | H26: =+E25-H25 -> #N/A
C28: Elaborado por: | G28: Recibí Conforme:
C31: Ing. Magaly Morocho | G31: =+$D$8 -> #N/A
C32: Talento Humano | G32: Funcionario

Sheet CHIMBOLEMA
B8: Trabajador(a): | C8: CHIMBOLEMA YUNGAN MARIO EFRAIN | F8: Inicio: | G8: 45884
B9: Fecha de ingreso: | C9: 45884 | F9: Fin: | G9: 45681
B10: Sueldo: | C10: 473.88 | F10: Total de dias | G10: =+_xlfn.DAYS(G9,G8) -> -203
B11: Subsidio: | C11: MATERNIDAD
B13: Calculo para el Pago:
B14: Sueldo Promedio Diario: | D14: =+C10/30 -> 15.796 | E14: (1-3 dias) | F14: =+C10/30 -> 15.796
B15: Promedio Diario (25%): | D15: =+D14*25% -> 3.949 | E15: (4-70 dias) | F15: =+F14*25% -> 3.949
B17: Nº | C17: Periodo | E17: Pocentaje | F17: Num. Dias | G17: Valor | M17: Nº | N17: Periodo | P17: Pocentaje | Q17: Num. Dias | R17: Valor
C18: Desde | D18: Hasta | N18: Desde | O18: Hasta
B19: 1 | C19: 45931 | D19: 45939 | E19: 100 | F19: =+D19-C19+1 -> 9 | G19: =+F14*F19 -> 142.164 | M19: 1 | N19: 45593 | O19: 45596 | P19: 25 | Q19: 4 | R19: =+Q15*Q19 -> 0
B20: 2 | M20: 2 | N20: 45597 | O20: 45626 | P20: 25 | Q20: 30 | R20: =+Q15*Q20 -> 0
B21: 3 | M21: 3 | N21: 45992 | O21: 45657 | P21: 25 | Q21: 31 | R21: =+Q21*Q15 -> 0
B22: 4 | M22: 4 | N22: 45658 | O22: 45676 | P22: 25 | Q22: 19 | R22: =+Q22*Q14 -> 0
B27: TOTAL | F27: =SUM(F19:F22) -> 9 | G27: =SUM(G19:G26) -> 142.164 | M27: TOTAL | Q27: =SUM(Q19:Q24) -> 84 | R27: =SUM(R19:R26) -> 0
B29: ROL PROPORCIONAL OCTUBRE 2024
B31: INGRESOS | C31: VALOR | D31: EGRESOS | E31: VALOR
B32: SUELDO BÁSICO COOPERATIVA | C32: =+G19 -> 142.164 | D32: APORTE INDIVIDUAL AL IESS 9.45 | E32: =+((C32+C33+C34+C39)*9.45%) -> 16.269498
B33: BONO MOVILIZACION | C33: =+(3.33333333333333)*9 -> 30 | D33: CUENTAS POR COBRAR | E33: 0
B34: BONO CUMPLIMIENTO | C34: 0
B35: COMISION POR SUPERAR LA META | C35: 0
B36: COMISION POR PLAZOS FIJOS | C36: 0 | D36: anticipo | E36: 0
B37: COMISION POR SOCIOS NUEVOS | C37: 0
B38: HORAS EXTRAS 50% | C38: 0
B39: HORAS EXTRAS 100% | C39: 0
B40: FONDO DE RESERVA | C40: 0
B41: DECIMO TERCERO | C41: 0
B42: DECIMO CUARTO | C42: 0
B43: TOTAL INGRESOS | C43: =SUM(C32:C42) -> 172.164 | D43: TOTAL EGRESOS | E43: =SUM(E32:E42) -> 16.269498
D44: VALOR NETO A RECIBIR | E44: =+C43-E43 -> 155.8945
E48: 645.95749

Sheet coca
B8: Trabajador(a): | C8: COCA BENITEZ JORGE | F8: Inicio:
B9: Fecha de ingreso: | C9: 45762 | F9: Fin:
B10: Sueldo: | C10: 715.54 | F10: Total de dias | G10: =+_xlfn.DAYS(G9,G8)+1 -> 1
B11: Subsidio: | C11: MATERNIDAD
B13: Calculo para el Pago: | H13: =+C10/30 -> 23.851333
B14: Sueldo Promedio Diario: | D14: =+C10/30 -> 23.851333 | E14: (1-3 dias) | F14: =+C10/30 -> 23.851333
B15: Promedio Diario (25%): | D15: =+D14*25% -> 5.9628333 | E15: (4-70 dias) | F15: =+F14*25% -> 5.9628333
B17: Nº | C17: Periodo | E17: Pocentaje | F17: Num. Dias | G17: Valor | M17: Nº | N17: Periodo | P17: Pocentaje | Q17: Num. Dias | R17: Valor
C18: Desde | D18: Hasta | N18: Desde | O18: Hasta
B19: 1 | C19: 45658 | D19: 45674 | E19: 100 | F19: 17 | G19: =+F14*F19 -> 405.47267 | M19: 1 | N19: 45593 | O19: 45596 | P19: 25 | Q19: 4 | R19: =+Q15*Q19 -> 0
B20: 2 | C20: 45675 | D20: 45688 | E20: 25 | F20: 14 | G20: =+F15*F20 -> 83.479667 | M20: 2 | N20: 45597 | O20: 45626 | P20: 25 | Q20: 30 | R20: =+Q15*Q20 -> 0
B21: 3 | G21: =+F21*F15 -> 0 | M21: 3 | N21: 45992 | O21: 45657 | P21: 25 | Q21: 31 | R21: =+Q21*Q15 -> 0
B22: 4 | G22: =+F22*F14 -> 0 | M22: 4 | N22: 45658 | O22: 45676 | P22: 25 | Q22: 19 | R22: =+Q22*Q14 -> 0
B27: TOTAL | F27: =SUM(F19:F22) -> 31 | G27: =SUM(G19:G26) -> 488.95233 | M27: TOTAL | Q27: =SUM(Q19:Q24) -> 84 | R27: =SUM(R19:R26) -> 0
B29: ROL PROPORCIONAL JUNIO 2024
B31: INGRESOS | C31: VALOR | D31: EGRESOS | E31: VALOR
B32: SUELDO BÁSICO COOPERATIVA | C32: 715.54 | D32: APORTE INDIVIDUAL AL IESS 9.45 | E32: =+((C10*9.45%)) -> 67.61853
B33: BONO MOVILIZACION | C33: 0 | D33: descuento | E33: 0 | H33: =1200-C32 -> 484.46
B34: BONO CUMPLIMIENTO | C34: 0 | E34: 145 | H34: =+ROUND(H33*9.45%,2) -> 45.78
B35: COMISION POR SUPERAR LA META | C35: 0 | H35: =+ROUND(H33*12.15%,2) -> 58.86
B36: COMISION POR PLAZOS FIJOS | C36: 0 | H36: =+H33*8.33% -> 40.355518
B37: COMISION POR SOCIOS NUEVOS | C37: 0
B38: HORAS EXTRAS 50% | C38: 0 | H38: =+SUM(H34:H36) -> 144.99552
B39: HORAS EXTRAS 100% | C39: 0
B40: FONDO DE RESERVA | C40: =+(C32*8.33%) -> 59.604482
B41: DECIMO TERCERO | C41: 0
B42: DECIMO CUARTO | C42: 0
B43: TOTAL INGRESOS | C43: =SUM(C32:C42) -> 775.14448 | D43: TOTAL EGRESOS | E43: =SUM(E32:E42) -> 212.61853 | G43: 1186.55
D44: VALOR NETO A RECIBIR | E44: =+C43-E43 -> 562.52595 | G44: =+G43-E44 -> 624.02405
K47: 602.89
B50: INGRESOS | C50: VALOR | D50: EGRESOS | E50: VALOR
B51: SUELDO BÁSICO COOPERATIVA | C51: 1200 | D51: APORTE INDIVIDUAL AL IESS 9.45 | E51: =+((C51*9.45%)) -> 113.4
B52: BONO MOVILIZACION | C52: 0 | D52: descuento | E52: 36
B53: BONO CUMPLIMIENTO | C53: 0 | E53: 0
B54: COMISION POR SUPERAR LA META | C54: 0
B55: COMISION POR PLAZOS FIJOS | C55: 0
B56: COMISION POR SOCIOS NUEVOS | C56: 0
B57: HORAS EXTRAS 50% | C57: 0
B58: HORAS EXTRAS 100% | C58: 0
B59: FONDO DE RESERVA | C59: =+(C51*8.33%) -> 99.96
B60: DECIMO TERCERO | C60: 0
B61: DECIMO CUARTO | C61: 0
B62: TOTAL INGRESOS | C62: =SUM(C51:C61) -> 1299.96 | D62: TOTAL EGRESOS | E62: =SUM(E51:E61) -> 149.4
D63: VALOR NETO A RECIBIR | E63: =+C62-E62 -> 1150.56 | I63: =+E63-E44 -> 588.03405

Sheet coca (2)
B8: Trabajador(a): | C8: COCA BENITEZ JORGE | F8: Inicio:
B9: Fecha de ingreso: | C9: 45762 | F9: Fin:
B10: Sueldo: | C10: 715.54 | F10: Total de dias | G10: =+_xlfn.DAYS(G9,G8)+1 -> 1
B11: Subsidio: | C11: MATERNIDAD
B13: Calculo para el Pago: | H13: =+C10/30 -> 23.851333
B14: Sueldo Promedio Diario: | D14: =+C10/30 -> 23.851333 | E14: (1-3 dias) | F14: =+C10/30 -> 23.851333
B15: Promedio Diario (25%): | D15: =+D14*25% -> 5.9628333 | E15: (4-70 dias) | F15: =+F14*25% -> 5.9628333
B17: Nº | C17: Periodo | E17: Pocentaje | F17: Num. Dias | G17: Valor | M17: Nº | N17: Periodo | P17: Pocentaje | Q17: Num. Dias | R17: Valor
C18: Desde | D18: Hasta | N18: Desde | O18: Hasta
B19: 1 | C19: 45658 | D19: 45674 | E19: 100 | F19: 17 | G19: =+F14*F19 -> 405.47267 | M19: 1 | N19: 45593 | O19: 45596 | P19: 25 | Q19: 4 | R19: =+Q15*Q19 -> 0
B20: 2 | C20: 45675 | D20: 45688 | E20: 25 | F20: 14 | G20: =+F15*F20 -> 83.479667 | M20: 2 | N20: 45597 | O20: 45626 | P20: 25 | Q20: 30 | R20: =+Q15*Q20 -> 0
B21: 3 | G21: =+F21*F15 -> 0 | M21: 3 | N21: 45992 | O21: 45657 | P21: 25 | Q21: 31 | R21: =+Q21*Q15 -> 0
B22: 4 | G22: =+F22*F14 -> 0 | M22: 4 | N22: 45658 | O22: 45676 | P22: 25 | Q22: 19 | R22: =+Q22*Q14 -> 0
B27: TOTAL | F27: =SUM(F19:F22) -> 31 | G27: =SUM(G19:G26) -> 488.95233 | M27: TOTAL | Q27: =SUM(Q19:Q24) -> 84 | R27: =SUM(R19:R26) -> 0
B29: ROL PROPORCIONAL JUNIO 2024
B31: INGRESOS | C31: VALOR | D31: EGRESOS | E31: VALOR
B32: SUELDO BÁSICO COOPERATIVA | C32: 700 | D32: APORTE INDIVIDUAL AL IESS 9.45 | E32: =+SUM(C32:C34)*9.45% -> 115.46766
B33: BONO MOVILIZACION | C33: 21.88 | D33: descuento | E33: 0 | H33: =1200-C32 -> 500 | J33: =+SUM(C32:C34) -> 1221.88
B34: BONO CUMPLIMIENTO | C34: 500 | E34: 360 | H34: =+ROUND(H33*9.45%,2) -> 47.25 | J34: =+J33*9.45% -> 115.46766
B35: COMISION POR SUPERAR LA META | C35: 0 | H35: =+ROUND(H33*12.15%,2) -> 60.75
B36: COMISION POR PLAZOS FIJOS | C36: 0 | H36: =+H33*8.33% -> 41.65
B37: COMISION POR SOCIOS NUEVOS | C37: 0
B38: HORAS EXTRAS 50% | C38: 0 | H38: =+SUM(H34:H36) -> 149.65
B39: HORAS EXTRAS 100% | C39: 0
B40: FONDO DE RESERVA | C40: =+((C32+C33+C34)*8.33%) -> 101.7826
B41: DECIMO TERCERO | C41: 0
B42: DECIMO CUARTO | C42: 0
B43: TOTAL INGRESOS | C43: =SUM(C32:C42) -> 1323.6626 | D43: TOTAL EGRESOS | E43: =SUM(E32:E42) -> 475.46766 | G43: 1186.55
D44: VALOR NETO A RECIBIR | E44: =+C43-E43 -> 848.19494 | G44: =+G43-E44 -> 338.35506
K47: 602.89
B50: INGRESOS | C50: VALOR | D50: EGRESOS | E50: VALOR
B51: SUELDO BÁSICO COOPERATIVA | C51: 1200 | D51: APORTE INDIVIDUAL AL IESS 9.45 | E51: =+((C51*9.45%)) -> 113.4
B52: BONO MOVILIZACION | C52: 0 | D52: descuento | E52: 36
B53: BONO CUMPLIMIENTO | C53: 0 | E53: 0
B54: COMISION POR SUPERAR LA META | C54: 0
B55: COMISION POR PLAZOS FIJOS | C55: 0
B56: COMISION POR SOCIOS NUEVOS | C56: 0
B57: HORAS EXTRAS 50% | C57: 0
B58: HORAS EXTRAS 100% | C58: 0
B59: FONDO DE RESERVA | C59: =+(C51*8.33%) -> 99.96
B60: DECIMO TERCERO | C60: 0
B61: DECIMO CUARTO | C61: 0
B62: TOTAL INGRESOS | C62: =SUM(C51:C61) -> 1299.96 | D62: TOTAL EGRESOS | E62: =SUM(E51:E61) -> 149.4
D63: VALOR NETO A RECIBIR | E63: =+C62-E62 -> 1150.56 | I63: =+E63-E44 -> 302.36506

Sheet Enfermedad-Meza)
B8: Trabajador(a): | C8: MEZA RODRIGUEZ MICHAEL FERNANDO | F8: Inicio: | G8: 45850
B9: Fecha de ingreso: | C9: 45762 | F9: Fin: | G9: 45869
B10: Sueldo: | C10: 473.88 | F10: Total de dias | G10: =+_xlfn.DAYS(G9,G8)+1 -> 20
B11: Subsidio: | C11: ENFERMEDAD GENERAL
B13: Calculo para el Pago:
B14: Sueldo Promedio Diario: | D14: =+C10/30 -> 15.796 | E14: (1-3 dias) | F14: =+C10/30 -> 15.796
B15: Promedio Diario (25%): | D15: =+D14*25% -> 3.949 | E15: (4-70 dias) | F15: =+F14*25% -> 3.949 | G15: =+F14*75% -> 11.847
B17: Nº | C17: Periodo | E17: Pocentaje | F17: Num. Dias | G17: Valor | M17: Nº | N17: Periodo | P17: Pocentaje | Q17: Num. Dias | R17: Valor
C18: Desde | D18: Hasta | N18: Desde | O18: Hasta
B19: 1 | C19: 45839 | D19: 45849 | E19: 100 | F19: 11 | G19: =IF(E19=100,$F$14*F19,$F$15*F19) -> 173.756 | M19: 1 | N19: 45593 | O19: 45596 | P19: 25 | Q19: 4 | R19: =+Q15*Q19 -> 0
B20: 2 | C20: 45850 | D20: 45852 | E20: 100 | F20: 19 | G20: =IF(E20=100,$F$14*F20,$F$15*F20) -> 300.124 | M20: 2 | N20: 45597 | O20: 45626 | P20: 25 | Q20: 30 | R20: =+Q15*Q20 -> 0
B21: 3 | E21: 0 | F21: 0 | G21: =IF(E21=100,$F$14*F21,$F$15*F21) -> 0 | M21: 3 | N21: 45992 | O21: 45657 | P21: 25 | Q21: 31 | R21: =+Q21*Q15 -> 0
B22: 4 | M22: 4 | N22: 45658 | O22: 45676 | P22: 25 | Q22: 19 | R22: =+Q22*Q14 -> 0
B23: 5
B24: 6
B25: 7
B26: 8
B27: TOTAL | F27: =SUM(F19:F22) -> 30 | G27: =SUM(G19:G26) -> 473.88 | M27: TOTAL | Q27: =SUM(Q19:Q24) -> 84 | R27: =SUM(R19:R26) -> 0
B29: ROL PROPORCIONAL FEBRERO 2025
B31: INGRESOS | C31: VALOR | D31: EGRESOS | E31: VALOR
B32: SUELDO BÁSICO COOPERATIVA | C32: =+G19 -> 173.756 | D32: APORTE INDIVIDUAL AL IESS 9.45 | E32: =+((C10+C34+C33+C37+C39)*9.45%) -> 51.596055
B33: BONO MOVILIZACION | C33: 36.67 | D33: CUENTAS POR COBRAR | E33: 0
B34: BONO CUMPLIMIENTO | C34: 10.3 | D34: anticipo de sueldo
B35: COMISION POR SUPERAR LA META | C35: 0
B36: COMISION POR PLAZOS FIJOS | C36: 0
B37: COMISION POR SOCIOS NUEVOS | C37: 5
B38: HORAS EXTRAS 50% | C38: 0
B39: HORAS EXTRAS 100% | C39: 20.14
B40: FONDO DE RESERVA | C40: 0
B41: DECIMO TERCERO | C41: 0
B42: DECIMO CUARTO | C42: 0
B43: TOTAL INGRESOS | C43: =SUM(C32:C42) -> 245.866 | D43: TOTAL EGRESOS | E43: =SUM(E32:E42) -> 51.596055 | G43: 494.39385
D44: VALOR NETO A RECIBIR | E44: =+C43-E43 -> 194.26995 | G44: =+G43-E44 -> 300.12391
J45: =100/30 -> 3.3333333
J46: =+J45*11 -> 36.666667

Sheet Cálculo Morocho
B8: Trabajador(a): | C8: MOROCHO YANTALEMA DINA | F8: Inicio: | G8: 45850
B9: Fecha de ingreso: | C9: 43074 | F9: Fin: | G9: 45869
B10: Sueldo: | C10: 766.65 | F10: Total de dias | G10: =+_xlfn.DAYS(G9,G8)+1 -> 20
B11: Subsidio: | C11: ENFERMEDAD GENERAL
B13: Calculo para el Pago:
B14: Sueldo Promedio Diario: | D14: =+C10/30 -> 25.555 | E14: (1-3 dias) | F14: =+C10/30 -> 25.555
B15: Promedio Diario (25%): | D15: =+D14*25% -> 6.38875 | E15: (4-70 dias) | F15: =+F14*25% -> 6.38875 | G15: =+F14*75% -> 19.16625
B17: Nº | C17: Periodo | E17: Pocentaje | F17: Num. Dias | G17: Valor | M17: Nº | N17: Periodo | P17: Pocentaje | Q17: Num. Dias | R17: Valor
C18: Desde | D18: Hasta | N18: Desde | O18: Hasta
B19: 1 | C19: 45839 | D19: 45849 | E19: 100 | F19: 19 | G19: =IF(E19=100,$F$14*F19,$F$15*F19) -> 485.545 | M19: 1 | N19: 45593 | O19: 45596 | P19: 25 | Q19: 4 | R19: =+Q15*Q19 -> 0
B20: 2 | C20: 45850 | D20: 45852 | E20: 0 | F20: 0 | G20: =IF(E20=100,$F$14*F20,$F$15*F20) -> 0 | M20: 2 | N20: 45597 | O20: 45626 | P20: 25 | Q20: 30 | R20: =+Q15*Q20 -> 0
B21: 3 | E21: 0 | F21: 0 | G21: =IF(E21=100,$F$14*F21,$F$15*F21) -> 0 | M21: 3 | N21: 45992 | O21: 45657 | P21: 25 | Q21: 31 | R21: =+Q21*Q15 -> 0
B22: 4 | M22: 4 | N22: 45658 | O22: 45676 | P22: 25 | Q22: 19 | R22: =+Q22*Q14 -> 0
B23: 5
B24: 6
B25: 7
B26: 8
B27: TOTAL | F27: =SUM(F19:F22) -> 19 | G27: =SUM(G19:G26) -> 485.545 | M27: TOTAL | Q27: =SUM(Q19:Q24) -> 84 | R27: =SUM(R19:R26) -> 0
B29: ROL PROPORCIONAL FEBRERO 2025
B31: INGRESOS | C31: VALOR | D31: EGRESOS | E31: VALOR
B32: SUELDO BÁSICO COOPERATIVA | C32: =+G19 -> 485.545 | D32: APORTE INDIVIDUAL AL IESS 9.45 | E32: =+((C10+C34+C33+C37+C39+C35)*9.45%) -> 78.74874
B33: BONO MOVILIZACION | D33: CUENTAS POR COBRAR | E33: 0
B34: BONO CUMPLIMIENTO | C34: 16.67 | D34: anticipo de sueldo
B35: COMISION POR SUPERAR LA META | C35: 50
B36: COMISION POR PLAZOS FIJOS
B37: COMISION POR SOCIOS NUEVOS
B38: HORAS EXTRAS 50%
B39: HORAS EXTRAS 100%
B40: FONDO DE RESERVA | C40: 69.42
B41: DECIMO TERCERO | C41: 0
B42: DECIMO CUARTO | C42: 0
B43: TOTAL INGRESOS | C43: =SUM(C32:C42) -> 621.635 | D43: TOTAL EGRESOS | E43: =SUM(E32:E42) -> 78.74874 | G43: 823.99
D44: VALOR NETO A RECIBIR | E44: =+C43-E43 -> 542.88626 | G44: =+G43-E44 -> 281.10374
J45: =100/30 -> 3.3333333
J46: =+J45*11 -> 36.666667

Sheet DEL ROSARIO
B8: Trabajador(a): | C8: LEMA TADAY BRAYAN | F8: Inicio: | G8: 45922
B9: Fecha de ingreso: | C9: 45841 | F9: Fin: | G9: 45930
B10: Sueldo: | C10: 481 | F10: Total de dias | G10: =+_xlfn.DAYS(G9,G8)+1 -> 9
B11: Subsidio: | C11: ENFERMEDAD GENERAL
B13: Calculo para el Pago:
B14: Sueldo Promedio Diario: | D14: =+C10/30 -> 16.033333 | E14: (1-3 dias) | F14: =+C10/30 -> 16.033333
B15: Promedio Diario (25%): | D15: =+D14*25% -> 4.0083333 | E15: (4-70 dias) | F15: =+F14*25% -> 4.0083333 | G15: =+F14*75% -> 12.025
I16: =+G15*18 -> 216.45
B17: Nº | C17: Periodo | E17: Pocentaje | F17: Num. Dias | G17: Valor
C18: Desde | D18: Hasta | I18: =+G27+I16 -> 841.75
B19: 1 | C19: 45922 | D19: 45930 | E19: 100 | F19: =+D19-C19+1 -> 9 | G19: =IF(E19=100,$F$14*F19,$F$15*F19) -> 144.3
B20: 2 | C20: 45931 | D20: 45944 | E20: 100 | F20: =+D20-C20+1 -> 14 | G20: =IF(E20=100,$F$14*F20,$F$15*F20) -> 224.46667
B21: 3 | C21: 45945 | D21: 45961 | E21: 100 | F21: =+D21-C21 -> 16 | G21: =IF(E21=100,$F$14*F21,$F$15*F21) -> 256.53333
B22: 4
B23: 5
B24: 6
B25: 7
B26: 8
B27: TOTAL | F27: =SUM(F19:F22) -> 39 | G27: =SUM(G19:G26) -> 625.3
B29: ROL PROPORCIONAL FEBRERO 2025
B31: INGRESOS | C31: VALOR | D31: EGRESOS | E31: VALOR
B32: SUELDO BÁSICO COOPERATIVA | C32: =+G19 -> 144.3 | D32: APORTE INDIVIDUAL AL IESS 9.45 | E32: =+((C10+C33+C39)*9.45%) -> 45.4545
B33: BONO MOVILIZACION | C33: 0 | D33: CUENTAS POR COBRAR | E33: 0 | H33: =100/30 -> 3.3333333
B34: BONO CUMPLIMIENTO | C34: 0 | D34: anticipo de sueldo | H34: =+H33*F19 -> 30
B35: COMISION POR SUPERAR LA META | C35: 0
B36: COMISION POR PLAZOS FIJOS
B37: COMISION POR SOCIOS NUEVOS
B38: HORAS EXTRAS 50%
B39: HORAS EXTRAS 100%
B40: FONDO DE RESERVA | C40: 0
B41: DECIMO TERCERO | C41: 0
B42: DECIMO CUARTO | C42: 0
B43: TOTAL INGRESOS | C43: =SUM(C32:C42) -> 144.3 | D43: TOTAL EGRESOS | E43: =SUM(E32:E42) -> 45.4545 | G43: 469.84584
D44: VALOR NETO A RECIBIR | E44: =+C43-E43 -> 98.8455 | G44: =+G43-E44 -> 371.00034

Sheet CHIMBOLEMA KEVIN
B8: Trabajador(a): | C8: LEMA TADAY BRAYAN | F8: Inicio: | G8: 45922
B9: Fecha de ingreso: | C9: 45841 | F9: Fin: | G9: 45930
B10: Sueldo: | C10: 481 | F10: Total de dias | G10: =+_xlfn.DAYS(G9,G8)+1 -> 9
B11: Subsidio: | C11: ENFERMEDAD GENERAL
B13: Calculo para el Pago:
B14: Sueldo Promedio Diario: | D14: =+C10/30 -> 16.033333 | E14: (1-3 dias) | F14: =+C10/30 -> 16.033333
B15: Promedio Diario (25%): | D15: =+D14*25% -> 4.0083333 | E15: (4-70 dias) | F15: =+F14*25% -> 4.0083333 | G15: =+F14*75% -> 12.025
I16: =+G15*18 -> 216.45
B17: Nº | C17: Periodo | E17: Pocentaje | F17: Num. Dias | G17: Valor
C18: Desde | D18: Hasta | I18: =+G27+I16 -> 841.75
B19: 1 | C19: 45922 | D19: 45930 | E19: 100 | F19: =+D19-C19+1 -> 9 | G19: =IF(E19=100,$F$14*F19,$F$15*F19) -> 144.3
B20: 2 | C20: 45931 | D20: 45944 | E20: 100 | F20: =+D20-C20+1 -> 14 | G20: =IF(E20=100,$F$14*F20,$F$15*F20) -> 224.46667
B21: 3 | C21: 45945 | D21: 45961 | E21: 100 | F21: =+D21-C21 -> 16 | G21: =IF(E21=100,$F$14*F21,$F$15*F21) -> 256.53333
B22: 4
B23: 5
B24: 6
B25: 7
B26: 8
B27: TOTAL | F27: =SUM(F19:F22) -> 39 | G27: =SUM(G19:G26) -> 625.3
B29: ROL PROPORCIONAL FEBRERO 2025
B31: INGRESOS | C31: VALOR | D31: EGRESOS | E31: VALOR
B32: SUELDO BÁSICO COOPERATIVA | C32: =+G19 -> 144.3 | D32: APORTE INDIVIDUAL AL IESS 9.45 | E32: =+((C10+C33+C39)*9.45%) -> 45.4545
B33: BONO MOVILIZACION | C33: 0 | D33: CUENTAS POR COBRAR | E33: 0 | H33: =100/30 -> 3.3333333
B34: BONO CUMPLIMIENTO | C34: 0 | D34: anticipo de sueldo | H34: =+H33*F19 -> 30
B35: COMISION POR SUPERAR LA META | C35: 0
B36: COMISION POR PLAZOS FIJOS
B37: COMISION POR SOCIOS NUEVOS
B38: HORAS EXTRAS 50%
B39: HORAS EXTRAS 100%
B40: FONDO DE RESERVA | C40: 0
B41: DECIMO TERCERO | C41: 0
B42: DECIMO CUARTO | C42: 0
B43: TOTAL INGRESOS | C43: =SUM(C32:C42) -> 144.3 | D43: TOTAL EGRESOS | E43: =SUM(E32:E42) -> 45.4545 | G43: 469.84584
D44: VALOR NETO A RECIBIR | E44: =+C43-E43 -> 98.8455 | G44: =+G43-E44 -> 371.00034

Sheet OTRAS COMISIONES
B2: CÁLCULO DE COMISIONES (METAS, BONOS,ETC)
B3: NÓMINA OCTUBRE 2025
H5: COMISIONES | K5: TOTAL COMISIÓN
J6: CRÉD-INV
B7: NO | C7: CEDULA | D7: NOMBRE | E7: CARGO | F7: Agencia | G7: SUELDO | H7: BONO BOLETOS | I7: COM. POR CARGO | J7: BONO CUMP | K7: US$,,
B8: 1 | C8: 925813685 | D8: =+VLOOKUP(Tabla335[[#This Row],[CEDULA ]],'OCTUBRE 2025'!$C$8:$J$10,2,0) -> #N/A | E8: =+VLOOKUP(Tabla335[[#This Row],[CEDULA ]],'OCTUBRE 2025'!$C$8:$J$10,4,0) -> #N/A | F8: =+VLOOKUP(Tabla335[[#This Row],[CEDULA ]],'OCTUBRE 2025'!$C$8:$J$10,6,0) -> #N/A | G8: =+VLOOKUP(Tabla335[[#This Row],[CEDULA ]],'OCTUBRE 2025'!$C$8:$J$10,8,0) -> #N/A | K8: =+Tabla335[[#This Row],[BONO BOLETOS]]+Tabla335[[#This Row],[COM. POR CARGO]]+Tabla335[[#This Row],[BONO CUMP]] -> 0
B9: 2 | C9: 944405737 | D9: =+VLOOKUP(Tabla335[[#This Row],[CEDULA ]],'OCTUBRE 2025'!$C$8:$J$10,2,0) -> #N/A | E9: =+VLOOKUP(Tabla335[[#This Row],[CEDULA ]],'OCTUBRE 2025'!$C$8:$J$10,4,0) -> #N/A | F9: =+VLOOKUP(Tabla335[[#This Row],[CEDULA ]],'OCTUBRE 2025'!$C$8:$J$10,6,0) -> #N/A | G9: =+VLOOKUP(Tabla335[[#This Row],[CEDULA ]],'OCTUBRE 2025'!$C$8:$J$10,8,0) -> #N/A | K9: =+Tabla335[[#This Row],[BONO BOLETOS]]+Tabla335[[#This Row],[COM. POR CARGO]]+Tabla335[[#This Row],[BONO CUMP]] -> 0
B10: 3 | C10: 604394502 | D10: =+VLOOKUP(Tabla335[[#This Row],[CEDULA ]],'OCTUBRE 2025'!$C$8:$J$10,2,0) -> #N/A | E10: =+VLOOKUP(Tabla335[[#This Row],[CEDULA ]],'OCTUBRE 2025'!$C$8:$J$10,4,0) -> #N/A | F10: =+VLOOKUP(Tabla335[[#This Row],[CEDULA ]],'OCTUBRE 2025'!$C$8:$J$10,6,0) -> #N/A | G10: =+VLOOKUP(Tabla335[[#This Row],[CEDULA ]],'OCTUBRE 2025'!$C$8:$J$10,8,0) -> #N/A | J10: 0 | K10: =+Tabla335[[#This Row],[BONO BOLETOS]]+Tabla335[[#This Row],[COM. POR CARGO]]+Tabla335[[#This Row],[BONO CUMP]] -> 0
B11: 4 | C11: 955741970 | D11: =+VLOOKUP(Tabla335[[#This Row],[CEDULA ]],'OCTUBRE 2025'!$C$8:$J$10,2,0) -> #N/A | E11: =+VLOOKUP(Tabla335[[#This Row],[CEDULA ]],'OCTUBRE 2025'!$C$8:$J$10,4,0) -> #N/A | F11: =+VLOOKUP(Tabla335[[#This Row],[CEDULA ]],'OCTUBRE 2025'!$C$8:$J$10,6,0) -> #N/A | G11: =+VLOOKUP(Tabla335[[#This Row],[CEDULA ]],'OCTUBRE 2025'!$C$8:$J$10,8,0) -> #N/A | K11: =+Tabla335[[#This Row],[BONO BOLETOS]]+Tabla335[[#This Row],[COM. POR CARGO]]+Tabla335[[#This Row],[BONO CUMP]] -> 0
B12: 5 | C12: 0943964973 | D12: =+VLOOKUP(Tabla335[[#This Row],[CEDULA ]],'OCTUBRE 2025'!$C$8:$J$10,2,0) -> #N/A | E12: =+VLOOKUP(Tabla335[[#This Row],[CEDULA ]],'OCTUBRE 2025'!$C$8:$J$10,4,0) -> #N/A | F12: =+VLOOKUP(Tabla335[[#This Row],[CEDULA ]],'OCTUBRE 2025'!$C$8:$J$10,6,0) -> #N/A | G12: =+VLOOKUP(Tabla335[[#This Row],[CEDULA ]],'OCTUBRE 2025'!$C$8:$J$10,8,0) -> #N/A | J12: 368.77 | K12: =+Tabla335[[#This Row],[BONO BOLETOS]]+Tabla335[[#This Row],[COM. POR CARGO]]+Tabla335[[#This Row],[BONO CUMP]] -> 368.77
B13: 6 | C13: 944143148 | D13: =+VLOOKUP(Tabla335[[#This Row],[CEDULA ]],'OCTUBRE 2025'!$C$8:$J$10,2,0) -> #N/A | E13: =+VLOOKUP(Tabla335[[#This Row],[CEDULA ]],'OCTUBRE 2025'!$C$8:$J$10,4,0) -> #N/A | F13: =+VLOOKUP(Tabla335[[#This Row],[CEDULA ]],'OCTUBRE 2025'!$C$8:$J$10,6,0) -> #N/A | G13: =+VLOOKUP(Tabla335[[#This Row],[CEDULA ]],'OCTUBRE 2025'!$C$8:$J$10,8,0) -> #N/A | K13: =+Tabla335[[#This Row],[BONO BOLETOS]]+Tabla335[[#This Row],[COM. POR CARGO]]+Tabla335[[#This Row],[BONO CUMP]] -> 0
B14: 7 | C14: 955325238 | D14: =+VLOOKUP(Tabla335[[#This Row],[CEDULA ]],'OCTUBRE 2025'!$C$8:$J$10,2,0) -> #N/A | E14: =+VLOOKUP(Tabla335[[#This Row],[CEDULA ]],'OCTUBRE 2025'!$C$8:$J$10,4,0) -> #N/A | F14: =+VLOOKUP(Tabla335[[#This Row],[CEDULA ]],'OCTUBRE 2025'!$C$8:$J$10,6,0) -> #N/A | G14: =+VLOOKUP(Tabla335[[#This Row],[CEDULA ]],'OCTUBRE 2025'!$C$8:$J$10,8,0) -> #N/A | K14: =+Tabla335[[#This Row],[BONO BOLETOS]]+Tabla335[[#This Row],[COM. POR CARGO]]+Tabla335[[#This Row],[BONO CUMP]] -> 0
B15: 8 | C15: 914163654 | D15: =+VLOOKUP(Tabla335[[#This Row],[CEDULA ]],'OCTUBRE 2025'!$C$8:$J$10,2,0) -> #N/A | E15: =+VLOOKUP(Tabla335[[#This Row],[CEDULA ]],'OCTUBRE 2025'!$C$8:$J$10,4,0) -> #N/A | F15: =+VLOOKUP(Tabla335[[#This Row],[CEDULA ]],'OCTUBRE 2025'!$C$8:$J$10,6,0) -> #N/A | G15: =+VLOOKUP(Tabla335[[#This Row],[CEDULA ]],'OCTUBRE 2025'!$C$8:$J$10,8,0) -> #N/A | K15: =+Tabla335[[#This Row],[BONO BOLETOS]]+Tabla335[[#This Row],[COM. POR CARGO]]+Tabla335[[#This Row],[BONO CUMP]] -> 0
B16: 9 | C16: 956668305 | D16: =+VLOOKUP(Tabla335[[#This Row],[CEDULA ]],'OCTUBRE 2025'!$C$8:$J$10,2,0) -> #N/A | E16: =+VLOOKUP(Tabla335[[#This Row],[CEDULA ]],'OCTUBRE 2025'!$C$8:$J$10,4,0) -> #N/A | F16: =+VLOOKUP(Tabla335[[#This Row],[CEDULA ]],'OCTUBRE 2025'!$C$8:$J$10,6,0) -> #N/A | G16: =+VLOOKUP(Tabla335[[#This Row],[CEDULA ]],'OCTUBRE 2025'!$C$8:$J$10,8,0) -> #N/A | J16: 0 | K16: =+Tabla335[[#This Row],[BONO BOLETOS]]+Tabla335[[#This Row],[COM. POR CARGO]]+Tabla335[[#This Row],[BONO CUMP]] -> 0
B17: 10 | C17: 0918741448 | D17: =+VLOOKUP(Tabla335[[#This Row],[CEDULA ]],'OCTUBRE 2025'!$C$8:$J$10,2,0) -> #N/A | E17: =+VLOOKUP(Tabla335[[#This Row],[CEDULA ]],'OCTUBRE 2025'!$C$8:$J$10,4,0) -> #N/A | F17: =+VLOOKUP(Tabla335[[#This Row],[CEDULA ]],'OCTUBRE 2025'!$C$8:$J$10,6,0) -> #N/A | G17: =+VLOOKUP(Tabla335[[#This Row],[CEDULA ]],'OCTUBRE 2025'!$C$8:$J$10,8,0) -> #N/A | K17: =+Tabla335[[#This Row],[BONO BOLETOS]]+Tabla335[[#This Row],[COM. POR CARGO]]+Tabla335[[#This Row],[BONO CUMP]] -> 0
B18: 11 | C18: 931097620 | D18: =+VLOOKUP(Tabla335[[#This Row],[CEDULA ]],'OCTUBRE 2025'!$C$8:$J$10,2,0) -> #N/A | E18: =+VLOOKUP(Tabla335[[#This Row],[CEDULA ]],'OCTUBRE 2025'!$C$8:$J$10,4,0) -> #N/A | F18: =+VLOOKUP(Tabla335[[#This Row],[CEDULA ]],'OCTUBRE 2025'!$C$8:$J$10,6,0) -> #N/A | G18: =+VLOOKUP(Tabla335[[#This Row],[CEDULA ]],'OCTUBRE 2025'!$C$8:$J$10,8,0) -> #N/A | J18: 368.77 | K18: =+Tabla335[[#This Row],[BONO BOLETOS]]+Tabla335[[#This Row],[COM. POR CARGO]]+Tabla335[[#This Row],[BONO CUMP]] -> 368.77
B19: 12 | C19: 1105483422 | D19: =+VLOOKUP(Tabla335[[#This Row],[CEDULA ]],'OCTUBRE 2025'!$C$8:$J$10,2,0) -> #N/A | E19: =+VLOOKUP(Tabla335[[#This Row],[CEDULA ]],'OCTUBRE 2025'!$C$8:$J$10,4,0) -> #N/A | F19: =+VLOOKUP(Tabla335[[#This Row],[CEDULA ]],'OCTUBRE 2025'!$C$8:$J$10,6,0) -> #N/A | G19: =+VLOOKUP(Tabla335[[#This Row],[CEDULA ]],'OCTUBRE 2025'!$C$8:$J$10,8,0) -> #N/A | K19: =+Tabla335[[#This Row],[BONO BOLETOS]]+Tabla335[[#This Row],[COM. POR CARGO]]+Tabla335[[#This Row],[BONO CUMP]] -> 0
B20: 13 | C20: 942614645 | D20: =+VLOOKUP(Tabla335[[#This Row],[CEDULA ]],'OCTUBRE 2025'!$C$8:$J$10,2,0) -> #N/A | E20: =+VLOOKUP(Tabla335[[#This Row],[CEDULA ]],'OCTUBRE 2025'!$C$8:$J$10,4,0) -> #N/A | F20: =+VLOOKUP(Tabla335[[#This Row],[CEDULA ]],'OCTUBRE 2025'!$C$8:$J$10,6,0) -> #N/A | G20: =+VLOOKUP(Tabla335[[#This Row],[CEDULA ]],'OCTUBRE 2025'!$C$8:$J$10,8,0) -> #N/A | K20: =+Tabla335[[#This Row],[BONO BOLETOS]]+Tabla335[[#This Row],[COM. POR CARGO]]+Tabla335[[#This Row],[BONO CUMP]] -> 0
B21: 14 | C21: 951200062 | D21: =+VLOOKUP(Tabla335[[#This Row],[CEDULA ]],'OCTUBRE 2025'!$C$8:$J$10,2,0) -> #N/A | E21: =+VLOOKUP(Tabla335[[#This Row],[CEDULA ]],'OCTUBRE 2025'!$C$8:$J$10,4,0) -> #N/A | F21: =+VLOOKUP(Tabla335[[#This Row],[CEDULA ]],'OCTUBRE 2025'!$C$8:$J$10,6,0) -> #N/A | G21: =+VLOOKUP(Tabla335[[#This Row],[CEDULA ]],'OCTUBRE 2025'!$C$8:$J$10,8,0) -> #N/A | K21: =+Tabla335[[#This Row],[BONO BOLETOS]]+Tabla335[[#This Row],[COM. POR CARGO]]+Tabla335[[#This Row],[BONO CUMP]] -> 0
B22: 15 | C22: 950929232 | D22: =+VLOOKUP(Tabla335[[#This Row],[CEDULA ]],'OCTUBRE 2025'!$C$8:$J$10,2,0) -> #N/A | E22: =+VLOOKUP(Tabla335[[#This Row],[CEDULA ]],'OCTUBRE 2025'!$C$8:$J$10,4,0) -> #N/A | F22: =+VLOOKUP(Tabla335[[#This Row],[CEDULA ]],'OCTUBRE 2025'!$C$8:$J$10,6,0) -> #N/A | G22: =+VLOOKUP(Tabla335[[#This Row],[CEDULA ]],'OCTUBRE 2025'!$C$8:$J$10,8,0) -> #N/A | K22: =+Tabla335[[#This Row],[BONO BOLETOS]]+Tabla335[[#This Row],[COM. POR CARGO]]+Tabla335[[#This Row],[BONO CUMP]] -> 0
B23: 16 | C23: 953819646 | D23: =+VLOOKUP(Tabla335[[#This Row],[CEDULA ]],'OCTUBRE 2025'!$C$8:$J$10,2,0) -> #N/A | E23: =+VLOOKUP(Tabla335[[#This Row],[CEDULA ]],'OCTUBRE 2025'!$C$8:$J$10,4,0) -> #N/A | F23: =+VLOOKUP(Tabla335[[#This Row],[CEDULA ]],'OCTUBRE 2025'!$C$8:$J$10,6,0) -> #N/A | G23: =+VLOOKUP(Tabla335[[#This Row],[CEDULA ]],'OCTUBRE 2025'!$C$8:$J$10,8,0) -> #N/A | K23: =+Tabla335[[#This Row],[BONO BOLETOS]]+Tabla335[[#This Row],[COM. POR CARGO]]+Tabla335[[#This Row],[BONO CUMP]] -> 0
B24: 17 | C24: 956953392 | D24: =+VLOOKUP(Tabla335[[#This Row],[CEDULA ]],'OCTUBRE 2025'!$C$8:$J$10,2,0) -> #N/A | E24: =+VLOOKUP(Tabla335[[#This Row],[CEDULA ]],'OCTUBRE 2025'!$C$8:$J$10,4,0) -> #N/A | F24: =+VLOOKUP(Tabla335[[#This Row],[CEDULA ]],'OCTUBRE 2025'!$C$8:$J$10,6,0) -> #N/A | G24: =+VLOOKUP(Tabla335[[#This Row],[CEDULA ]],'OCTUBRE 2025'!$C$8:$J$10,8,0) -> #N/A | K24: =+Tabla335[[#This Row],[BONO BOLETOS]]+Tabla335[[#This Row],[COM. POR CARGO]]+Tabla335[[#This Row],[BONO CUMP]] -> 0
B25: 18 | C25: 956796767 | D25: =+VLOOKUP(Tabla335[[#This Row],[CEDULA ]],'OCTUBRE 2025'!$C$8:$J$10,2,0) -> #N/A | E25: =+VLOOKUP(Tabla335[[#This Row],[CEDULA ]],'OCTUBRE 2025'!$C$8:$J$10,4,0) -> #N/A | F25: =+VLOOKUP(Tabla335[[#This Row],[CEDULA ]],'OCTUBRE 2025'!$C$8:$J$10,6,0) -> #N/A | G25: =+VLOOKUP(Tabla335[[#This Row],[CEDULA ]],'OCTUBRE 2025'!$C$8:$J$10,8,0) -> #N/A | K25: =+Tabla335[[#This Row],[BONO BOLETOS]]+Tabla335[[#This Row],[COM. POR CARGO]]+Tabla335[[#This Row],[BONO CUMP]] -> 0
B26: 19 | C26: 0932036049 | D26: =+VLOOKUP(Tabla335[[#This Row],[CEDULA ]],'OCTUBRE 2025'!$C$8:$J$10,2,0) -> #N/A | E26: =+VLOOKUP(Tabla335[[#This Row],[CEDULA ]],'OCTUBRE 2025'!$C$8:$J$10,4,0) -> #N/A | F26: =+VLOOKUP(Tabla335[[#This Row],[CEDULA ]],'OCTUBRE 2025'!$C$8:$J$10,6,0) -> #N/A | G26: =+VLOOKUP(Tabla335[[#This Row],[CEDULA ]],'OCTUBRE 2025'!$C$8:$J$10,8,0) -> #N/A | K26: =+Tabla335[[#This Row],[BONO BOLETOS]]+Tabla335[[#This Row],[COM. POR CARGO]]+Tabla335[[#This Row],[BONO CUMP]] -> 0
B27: 20 | C27: 1724102940 | D27: =+VLOOKUP(Tabla335[[#This Row],[CEDULA ]],'OCTUBRE 2025'!$C$8:$J$10,2,0) -> #N/A | E27: =+VLOOKUP(Tabla335[[#This Row],[CEDULA ]],'OCTUBRE 2025'!$C$8:$J$10,4,0) -> #N/A | F27: =+VLOOKUP(Tabla335[[#This Row],[CEDULA ]],'OCTUBRE 2025'!$C$8:$J$10,6,0) -> #N/A | G27: =+VLOOKUP(Tabla335[[#This Row],[CEDULA ]],'OCTUBRE 2025'!$C$8:$J$10,8,0) -> #N/A | J27: 0 | K27: =+Tabla335[[#This Row],[BONO BOLETOS]]+Tabla335[[#This Row],[COM. POR CARGO]]+Tabla335[[#This Row],[BONO CUMP]] -> 0
B28: 21 | C28: 943322974 | D28: =+VLOOKUP(Tabla335[[#This Row],[CEDULA ]],'OCTUBRE 2025'!$C$8:$J$10,2,0) -> #N/A | E28: =+VLOOKUP(Tabla335[[#This Row],[CEDULA ]],'OCTUBRE 2025'!$C$8:$J$10,4,0) -> #N/A | F28: =+VLOOKUP(Tabla335[[#This Row],[CEDULA ]],'OCTUBRE 2025'!$C$8:$J$10,6,0) -> #N/A | G28: =+VLOOKUP(Tabla335[[#This Row],[CEDULA ]],'OCTUBRE 2025'!$C$8:$J$10,8,0) -> #N/A | K28: =+Tabla335[[#This Row],[BONO BOLETOS]]+Tabla335[[#This Row],[COM. POR CARGO]]+Tabla335[[#This Row],[BONO CUMP]] -> 0
B29: 22 | C29: 941096851 | D29: =+VLOOKUP(Tabla335[[#This Row],[CEDULA ]],'OCTUBRE 2025'!$C$8:$J$10,2,0) -> #N/A | E29: =+VLOOKUP(Tabla335[[#This Row],[CEDULA ]],'OCTUBRE 2025'!$C$8:$J$10,4,0) -> #N/A | F29: =+VLOOKUP(Tabla335[[#This Row],[CEDULA ]],'OCTUBRE 2025'!$C$8:$J$10,6,0) -> #N/A | G29: =+VLOOKUP(Tabla335[[#This Row],[CEDULA ]],'OCTUBRE 2025'!$C$8:$J$10,8,0) -> #N/A | J29: 0 | K29: =+Tabla335[[#This Row],[BONO BOLETOS]]+Tabla335[[#This Row],[COM. POR CARGO]]+Tabla335[[#This Row],[BONO CUMP]] -> 0
B30: 23 | C30: 957093800 | D30: =+VLOOKUP(Tabla335[[#This Row],[CEDULA ]],'OCTUBRE 2025'!$C$8:$J$10,2,0) -> #N/A | E30: =+VLOOKUP(Tabla335[[#This Row],[CEDULA ]],'OCTUBRE 2025'!$C$8:$J$10,4,0) -> #N/A | F30: =+VLOOKUP(Tabla335[[#This Row],[CEDULA ]],'OCTUBRE 2025'!$C$8:$J$10,6,0) -> #N/A | G30: =+VLOOKUP(Tabla335[[#This Row],[CEDULA ]],'OCTUBRE 2025'!$C$8:$J$10,8,0) -> #N/A | K30: =+Tabla335[[#This Row],[BONO BOLETOS]]+Tabla335[[#This Row],[COM. POR CARGO]]+Tabla335[[#This Row],[BONO CUMP]] -> 0
B31: 24 | C31: 957924350 | D31: =+VLOOKUP(Tabla335[[#This Row],[CEDULA ]],'OCTUBRE 2025'!$C$8:$J$10,2,0) -> #N/A | E31: =+VLOOKUP(Tabla335[[#This Row],[CEDULA ]],'OCTUBRE 2025'!$C$8:$J$10,4,0) -> #N/A | F31: =+VLOOKUP(Tabla335[[#This Row],[CEDULA ]],'OCTUBRE 2025'!$C$8:$J$10,6,0) -> #N/A | G31: =+VLOOKUP(Tabla335[[#This Row],[CEDULA ]],'OCTUBRE 2025'!$C$8:$J$10,8,0) -> #N/A | K31: =+Tabla335[[#This Row],[BONO BOLETOS]]+Tabla335[[#This Row],[COM. POR CARGO]]+Tabla335[[#This Row],[BONO CUMP]] -> 0
B32: 25 | C32: 603838657 | D32: =+VLOOKUP(Tabla335[[#This Row],[CEDULA ]],'OCTUBRE 2025'!$C$8:$J$10,2,0) -> #N/A | E32: =+VLOOKUP(Tabla335[[#This Row],[CEDULA ]],'OCTUBRE 2025'!$C$8:$J$10,4,0) -> #N/A | F32: =+VLOOKUP(Tabla335[[#This Row],[CEDULA ]],'OCTUBRE 2025'!$C$8:$J$10,6,0) -> #N/A | G32: =+VLOOKUP(Tabla335[[#This Row],[CEDULA ]],'OCTUBRE 2025'!$C$8:$J$10,8,0) -> #N/A | K32: =+Tabla335[[#This Row],[BONO BOLETOS]]+Tabla335[[#This Row],[COM. POR CARGO]]+Tabla335[[#This Row],[BONO CUMP]] -> 0
B33: 26 | C33: 925240525 | D33: =+VLOOKUP(Tabla335[[#This Row],[CEDULA ]],'OCTUBRE 2025'!$C$8:$J$10,2,0) -> #N/A | E33: =+VLOOKUP(Tabla335[[#This Row],[CEDULA ]],'OCTUBRE 2025'!$C$8:$J$10,4,0) -> #N/A | F33: =+VLOOKUP(Tabla335[[#This Row],[CEDULA ]],'OCTUBRE 2025'!$C$8:$J$10,6,0) -> #N/A | G33: =+VLOOKUP(Tabla335[[#This Row],[CEDULA ]],'OCTUBRE 2025'!$C$8:$J$10,8,0) -> #N/A | K33: =+Tabla335[[#This Row],[BONO BOLETOS]]+Tabla335[[#This Row],[COM. POR CARGO]]+Tabla335[[#This Row],[BONO CUMP]] -> 0
B34: 27 | C34: 954520599 | D34: =+VLOOKUP(Tabla335[[#This Row],[CEDULA ]],'OCTUBRE 2025'!$C$8:$J$10,2,0) -> #N/A | E34: =+VLOOKUP(Tabla335[[#This Row],[CEDULA ]],'OCTUBRE 2025'!$C$8:$J$10,4,0) -> #N/A | F34: =+VLOOKUP(Tabla335[[#This Row],[CEDULA ]],'OCTUBRE 2025'!$C$8:$J$10,6,0) -> #N/A | G34: =+VLOOKUP(Tabla335[[#This Row],[CEDULA ]],'OCTUBRE 2025'!$C$8:$J$10,8,0) -> #N/A | J34: 0 | K34: =+Tabla335[[#This Row],[BONO BOLETOS]]+Tabla335[[#This Row],[COM. POR CARGO]]+Tabla335[[#This Row],[BONO CUMP]] -> 0
B35: 28 | C35: 0943906032 | D35: =+VLOOKUP(Tabla335[[#This Row],[CEDULA ]],'OCTUBRE 2025'!$C$8:$J$10,2,0) -> #N/A | E35: =+VLOOKUP(Tabla335[[#This Row],[CEDULA ]],'OCTUBRE 2025'!$C$8:$J$10,4,0) -> #N/A | F35: =+VLOOKUP(Tabla335[[#This Row],[CEDULA ]],'OCTUBRE 2025'!$C$8:$J$10,6,0) -> #N/A | G35: =+VLOOKUP(Tabla335[[#This Row],[CEDULA ]],'OCTUBRE 2025'!$C$8:$J$10,8,0) -> #N/A | K35: =+Tabla335[[#This Row],[BONO BOLETOS]]+Tabla335[[#This Row],[COM. POR CARGO]]+Tabla335[[#This Row],[BONO CUMP]] -> 0
B36: 29 | C36: 0919306050 | D36: =+VLOOKUP(Tabla335[[#This Row],[CEDULA ]],'OCTUBRE 2025'!$C$8:$J$10,2,0) -> #N/A | E36: =+VLOOKUP(Tabla335[[#This Row],[CEDULA ]],'OCTUBRE 2025'!$C$8:$J$10,4,0) -> #N/A | F36: =+VLOOKUP(Tabla335[[#This Row],[CEDULA ]],'OCTUBRE 2025'!$C$8:$J$10,6,0) -> #N/A | G36: =+VLOOKUP(Tabla335[[#This Row],[CEDULA ]],'OCTUBRE 2025'!$C$8:$J$10,8,0) -> #N/A | K36: =+Tabla335[[#This Row],[BONO BOLETOS]]+Tabla335[[#This Row],[COM. POR CARGO]]+Tabla335[[#This Row],[BONO CUMP]] -> 0
B37: 30 | C37: 0941235376 | D37: =+VLOOKUP(Tabla335[[#This Row],[CEDULA ]],'OCTUBRE 2025'!$C$8:$J$10,2,0) -> #N/A | E37: =+VLOOKUP(Tabla335[[#This Row],[CEDULA ]],'OCTUBRE 2025'!$C$8:$J$10,4,0) -> #N/A | F37: =+VLOOKUP(Tabla335[[#This Row],[CEDULA ]],'OCTUBRE 2025'!$C$8:$J$10,6,0) -> #N/A | G37: =+VLOOKUP(Tabla335[[#This Row],[CEDULA ]],'OCTUBRE 2025'!$C$8:$J$10,8,0) -> #N/A | K37: =+Tabla335[[#This Row],[BONO BOLETOS]]+Tabla335[[#This Row],[COM. POR CARGO]]+Tabla335[[#This Row],[BONO CUMP]] -> 0
B38: 31 | C38: 955395686 | D38: =+VLOOKUP(Tabla335[[#This Row],[CEDULA ]],'OCTUBRE 2025'!$C$8:$J$10,2,0) -> #N/A | E38: =+VLOOKUP(Tabla335[[#This Row],[CEDULA ]],'OCTUBRE 2025'!$C$8:$J$10,4,0) -> #N/A | F38: =+VLOOKUP(Tabla335[[#This Row],[CEDULA ]],'OCTUBRE 2025'!$C$8:$J$10,6,0) -> #N/A | G38: =+VLOOKUP(Tabla335[[#This Row],[CEDULA ]],'OCTUBRE 2025'!$C$8:$J$10,8,0) -> #N/A | H38: 0 | J38: 0 | K38: =+Tabla335[[#This Row],[BONO BOLETOS]]+Tabla335[[#This Row],[COM. POR CARGO]]+Tabla335[[#This Row],[BONO CUMP]] -> 0
B39: 32 | C39: 940991987 | D39: =+VLOOKUP(Tabla335[[#This Row],[CEDULA ]],'OCTUBRE 2025'!$C$8:$J$10,2,0) -> #N/A | E39: =+VLOOKUP(Tabla335[[#This Row],[CEDULA ]],'OCTUBRE 2025'!$C$8:$J$10,4,0) -> #N/A | F39: =+VLOOKUP(Tabla335[[#This Row],[CEDULA ]],'OCTUBRE 2025'!$C$8:$J$10,6,0) -> #N/A | G39: =+VLOOKUP(Tabla335[[#This Row],[CEDULA ]],'OCTUBRE 2025'!$C$8:$J$10,8,0) -> #N/A | K39: =+Tabla335[[#This Row],[BONO BOLETOS]]+Tabla335[[#This Row],[COM. POR CARGO]]+Tabla335[[#This Row],[BONO CUMP]] -> 0
B40: 33 | C40: 956929277 | D40: =+VLOOKUP(Tabla335[[#This Row],[CEDULA ]],'OCTUBRE 2025'!$C$8:$J$10,2,0) -> #N/A | E40: =+VLOOKUP(Tabla335[[#This Row],[CEDULA ]],'OCTUBRE 2025'!$C$8:$J$10,4,0) -> #N/A | F40: =+VLOOKUP(Tabla335[[#This Row],[CEDULA ]],'OCTUBRE 2025'!$C$8:$J$10,6,0) -> #N/A | G40: =+VLOOKUP(Tabla335[[#This Row],[CEDULA ]],'OCTUBRE 2025'!$C$8:$J$10,8,0) -> #N/A | K40: =+Tabla335[[#This Row],[BONO BOLETOS]]+Tabla335[[#This Row],[COM. POR CARGO]]+Tabla335[[#This Row],[BONO CUMP]] -> 0
B41: 34 | C41: 951763994 | D41: =+VLOOKUP(Tabla335[[#This Row],[CEDULA ]],'OCTUBRE 2025'!$C$8:$J$10,2,0) -> #N/A | E41: =+VLOOKUP(Tabla335[[#This Row],[CEDULA ]],'OCTUBRE 2025'!$C$8:$J$10,4,0) -> #N/A | F41: =+VLOOKUP(Tabla335[[#This Row],[CEDULA ]],'OCTUBRE 2025'!$C$8:$J$10,6,0) -> #N/A | G41: =+VLOOKUP(Tabla335[[#This Row],[CEDULA ]],'OCTUBRE 2025'!$C$8:$J$10,8,0) -> #N/A | K41: =+Tabla335[[#This Row],[BONO BOLETOS]]+Tabla335[[#This Row],[COM. POR CARGO]]+Tabla335[[#This Row],[BONO CUMP]] -> 0
B42: 35 | C42: 950703199 | D42: =+VLOOKUP(Tabla335[[#This Row],[CEDULA ]],'OCTUBRE 2025'!$C$8:$J$10,2,0) -> #N/A | E42: =+VLOOKUP(Tabla335[[#This Row],[CEDULA ]],'OCTUBRE 2025'!$C$8:$J$10,4,0) -> #N/A | F42: =+VLOOKUP(Tabla335[[#This Row],[CEDULA ]],'OCTUBRE 2025'!$C$8:$J$10,6,0) -> #N/A | G42: =+VLOOKUP(Tabla335[[#This Row],[CEDULA ]],'OCTUBRE 2025'!$C$8:$J$10,8,0) -> #N/A | K42: =+Tabla335[[#This Row],[BONO BOLETOS]]+Tabla335[[#This Row],[COM. POR CARGO]]+Tabla335[[#This Row],[BONO CUMP]] -> 0
B43: 36 | C43: 0923715692 | D43: =+VLOOKUP(Tabla335[[#This Row],[CEDULA ]],'OCTUBRE 2025'!$C$8:$J$10,2,0) -> #N/A | E43: =+VLOOKUP(Tabla335[[#This Row],[CEDULA ]],'OCTUBRE 2025'!$C$8:$J$10,4,0) -> #N/A | F43: =+VLOOKUP(Tabla335[[#This Row],[CEDULA ]],'OCTUBRE 2025'!$C$8:$J$10,6,0) -> #N/A | G43: =+VLOOKUP(Tabla335[[#This Row],[CEDULA ]],'OCTUBRE 2025'!$C$8:$J$10,8,0) -> #N/A | K43: =+Tabla335[[#This Row],[BONO BOLETOS]]+Tabla335[[#This Row],[COM. POR CARGO]]+Tabla335[[#This Row],[BONO CUMP]] -> 0
B44: 37 | C44: 925830689 | D44: =+VLOOKUP(Tabla335[[#This Row],[CEDULA ]],'OCTUBRE 2025'!$C$8:$J$10,2,0) -> #N/A | E44: =+VLOOKUP(Tabla335[[#This Row],[CEDULA ]],'OCTUBRE 2025'!$C$8:$J$10,4,0) -> #N/A | F44: =+VLOOKUP(Tabla335[[#This Row],[CEDULA ]],'OCTUBRE 2025'!$C$8:$J$10,6,0) -> #N/A | G44: =+VLOOKUP(Tabla335[[#This Row],[CEDULA ]],'OCTUBRE 2025'!$C$8:$J$10,8,0) -> #N/A | K44: =+Tabla335[[#This Row],[BONO BOLETOS]]+Tabla335[[#This Row],[COM. POR CARGO]]+Tabla335[[#This Row],[BONO CUMP]] -> 0
B45: 38 | C45: 944034842 | D45: =+VLOOKUP(Tabla335[[#This Row],[CEDULA ]],'OCTUBRE 2025'!$C$8:$J$10,2,0) -> #N/A | E45: =+VLOOKUP(Tabla335[[#This Row],[CEDULA ]],'OCTUBRE 2025'!$C$8:$J$10,4,0) -> #N/A | F45: =+VLOOKUP(Tabla335[[#This Row],[CEDULA ]],'OCTUBRE 2025'!$C$8:$J$10,6,0) -> #N/A | G45: =+VLOOKUP(Tabla335[[#This Row],[CEDULA ]],'OCTUBRE 2025'!$C$8:$J$10,8,0) -> #N/A | K45: =+Tabla335[[#This Row],[BONO BOLETOS]]+Tabla335[[#This Row],[COM. POR CARGO]]+Tabla335[[#This Row],[BONO CUMP]] -> 0
B46: 39 | C46: 951340702 | D46: =+VLOOKUP(Tabla335[[#This Row],[CEDULA ]],'OCTUBRE 2025'!$C$8:$J$10,2,0) -> #N/A | E46: =+VLOOKUP(Tabla335[[#This Row],[CEDULA ]],'OCTUBRE 2025'!$C$8:$J$10,4,0) -> #N/A | F46: =+VLOOKUP(Tabla335[[#This Row],[CEDULA ]],'OCTUBRE 2025'!$C$8:$J$10,6,0) -> #N/A | G46: =+VLOOKUP(Tabla335[[#This Row],[CEDULA ]],'OCTUBRE 2025'!$C$8:$J$10,8,0) -> #N/A | K46: =+Tabla335[[#This Row],[BONO BOLETOS]]+Tabla335[[#This Row],[COM. POR CARGO]]+Tabla335[[#This Row],[BONO CUMP]] -> 0
B47: 40 | C47: 650112949 | D47: =+VLOOKUP(Tabla335[[#This Row],[CEDULA ]],'OCTUBRE 2025'!$C$8:$J$10,2,0) -> #N/A | E47: =+VLOOKUP(Tabla335[[#This Row],[CEDULA ]],'OCTUBRE 2025'!$C$8:$J$10,4,0) -> #N/A | F47: =+VLOOKUP(Tabla335[[#This Row],[CEDULA ]],'OCTUBRE 2025'!$C$8:$J$10,6,0) -> #N/A | G47: =+VLOOKUP(Tabla335[[#This Row],[CEDULA ]],'OCTUBRE 2025'!$C$8:$J$10,8,0) -> #N/A | K47: =+Tabla335[[#This Row],[BONO BOLETOS]]+Tabla335[[#This Row],[COM. POR CARGO]]+Tabla335[[#This Row],[BONO CUMP]] -> 0
B48: 41 | C48: 924232804 | D48: =+VLOOKUP(Tabla335[[#This Row],[CEDULA ]],'OCTUBRE 2025'!$C$8:$J$10,2,0) -> #N/A | E48: =+VLOOKUP(Tabla335[[#This Row],[CEDULA ]],'OCTUBRE 2025'!$C$8:$J$10,4,0) -> #N/A | F48: =+VLOOKUP(Tabla335[[#This Row],[CEDULA ]],'OCTUBRE 2025'!$C$8:$J$10,6,0) -> #N/A | G48: =+VLOOKUP(Tabla335[[#This Row],[CEDULA ]],'OCTUBRE 2025'!$C$8:$J$10,8,0) -> #N/A | K48: =+Tabla335[[#This Row],[BONO BOLETOS]]+Tabla335[[#This Row],[COM. POR CARGO]]+Tabla335[[#This Row],[BONO CUMP]] -> 0
B49: 42 | C49: 605031145 | D49: =+VLOOKUP(Tabla335[[#This Row],[CEDULA ]],'OCTUBRE 2025'!$C$8:$J$10,2,0) -> #N/A | E49: =+VLOOKUP(Tabla335[[#This Row],[CEDULA ]],'OCTUBRE 2025'!$C$8:$J$10,4,0) -> #N/A | F49: =+VLOOKUP(Tabla335[[#This Row],[CEDULA ]],'OCTUBRE 2025'!$C$8:$J$10,6,0) -> #N/A | G49: =+VLOOKUP(Tabla335[[#This Row],[CEDULA ]],'OCTUBRE 2025'!$C$8:$J$10,8,0) -> #N/A | J49: 0 | K49: =+Tabla335[[#This Row],[BONO BOLETOS]]+Tabla335[[#This Row],[COM. POR CARGO]]+Tabla335[[#This Row],[BONO CUMP]] -> 0
B50: 43 | C50: 927257576 | D50: =+VLOOKUP(Tabla335[[#This Row],[CEDULA ]],'OCTUBRE 2025'!$C$8:$J$10,2,0) -> #N/A | E50: =+VLOOKUP(Tabla335[[#This Row],[CEDULA ]],'OCTUBRE 2025'!$C$8:$J$10,4,0) -> #N/A | F50: =+VLOOKUP(Tabla335[[#This Row],[CEDULA ]],'OCTUBRE 2025'!$C$8:$J$10,6,0) -> #N/A | G50: =+VLOOKUP(Tabla335[[#This Row],[CEDULA ]],'OCTUBRE 2025'!$C$8:$J$10,8,0) -> #N/A | K50: =+Tabla335[[#This Row],[BONO BOLETOS]]+Tabla335[[#This Row],[COM. POR CARGO]]+Tabla335[[#This Row],[BONO CUMP]] -> 0
B51: 44 | C51: 928901800 | D51: =+VLOOKUP(Tabla335[[#This Row],[CEDULA ]],'OCTUBRE 2025'!$C$8:$J$10,2,0) -> #N/A | E51: =+VLOOKUP(Tabla335[[#This Row],[CEDULA ]],'OCTUBRE 2025'!$C$8:$J$10,4,0) -> #N/A | F51: =+VLOOKUP(Tabla335[[#This Row],[CEDULA ]],'OCTUBRE 2025'!$C$8:$J$10,6,0) -> #N/A | G51: =+VLOOKUP(Tabla335[[#This Row],[CEDULA ]],'OCTUBRE 2025'!$C$8:$J$10,8,0) -> #N/A | K51: =+Tabla335[[#This Row],[BONO BOLETOS]]+Tabla335[[#This Row],[COM. POR CARGO]]+Tabla335[[#This Row],[BONO CUMP]] -> 0
B52: 45 | C52: 951315746 | D52: =+VLOOKUP(Tabla335[[#This Row],[CEDULA ]],'OCTUBRE 2025'!$C$8:$J$10,2,0) -> #N/A | E52: =+VLOOKUP(Tabla335[[#This Row],[CEDULA ]],'OCTUBRE 2025'!$C$8:$J$10,4,0) -> #N/A | F52: =+VLOOKUP(Tabla335[[#This Row],[CEDULA ]],'OCTUBRE 2025'!$C$8:$J$10,6,0) -> #N/A | G52: =+VLOOKUP(Tabla335[[#This Row],[CEDULA ]],'OCTUBRE 2025'!$C$8:$J$10,8,0) -> #N/A | J52: 0 | K52: =+Tabla335[[#This Row],[BONO BOLETOS]]+Tabla335[[#This Row],[COM. POR CARGO]]+Tabla335[[#This Row],[BONO CUMP]] -> 0
B53: 46 | C53: 954184321 | D53: =+VLOOKUP(Tabla335[[#This Row],[CEDULA ]],'OCTUBRE 2025'!$C$8:$J$10,2,0) -> #N/A | E53: =+VLOOKUP(Tabla335[[#This Row],[CEDULA ]],'OCTUBRE 2025'!$C$8:$J$10,4,0) -> #N/A | F53: =+VLOOKUP(Tabla335[[#This Row],[CEDULA ]],'OCTUBRE 2025'!$C$8:$J$10,6,0) -> #N/A | G53: =+VLOOKUP(Tabla335[[#This Row],[CEDULA ]],'OCTUBRE 2025'!$C$8:$J$10,8,0) -> #N/A | K53: =+Tabla335[[#This Row],[BONO BOLETOS]]+Tabla335[[#This Row],[COM. POR CARGO]]+Tabla335[[#This Row],[BONO CUMP]] -> 0
B54: 47 | C54: 922034772 | D54: =+VLOOKUP(Tabla335[[#This Row],[CEDULA ]],'OCTUBRE 2025'!$C$8:$J$10,2,0) -> #N/A | E54: =+VLOOKUP(Tabla335[[#This Row],[CEDULA ]],'OCTUBRE 2025'!$C$8:$J$10,4,0) -> #N/A | F54: =+VLOOKUP(Tabla335[[#This Row],[CEDULA ]],'OCTUBRE 2025'!$C$8:$J$10,6,0) -> #N/A | G54: =+VLOOKUP(Tabla335[[#This Row],[CEDULA ]],'OCTUBRE 2025'!$C$8:$J$10,8,0) -> #N/A | J54: 0 | K54: =+Tabla335[[#This Row],[BONO BOLETOS]]+Tabla335[[#This Row],[COM. POR CARGO]]+Tabla335[[#This Row],[BONO CUMP]] -> 0
B55: 48 | C55: 923837991 | D55: =+VLOOKUP(Tabla335[[#This Row],[CEDULA ]],'OCTUBRE 2025'!$C$8:$J$10,2,0) -> YUNDA CUJILEMA MARIA TERESA | E55: =+VLOOKUP(Tabla335[[#This Row],[CEDULA ]],'OCTUBRE 2025'!$C$8:$J$10,4,0) -> CONTADOR GENERAL | F55: =+VLOOKUP(Tabla335[[#This Row],[CEDULA ]],'OCTUBRE 2025'!$C$8:$J$10,6,0) -> Matriz | G55: =+VLOOKUP(Tabla335[[#This Row],[CEDULA ]],'OCTUBRE 2025'!$C$8:$J$10,8,0) -> 1022.2 | K55: =+Tabla335[[#This Row],[BONO BOLETOS]]+Tabla335[[#This Row],[COM. POR CARGO]]+Tabla335[[#This Row],[BONO CUMP]] -> 0
B56: 49 | C56: 941508905 | D56: =+VLOOKUP(Tabla335[[#This Row],[CEDULA ]],'OCTUBRE 2025'!$C$8:$J$10,2,0) -> YUQUILEMA CACUANGO ANGEL JOSE | E56: =+VLOOKUP(Tabla335[[#This Row],[CEDULA ]],'OCTUBRE 2025'!$C$8:$J$10,4,0) -> OFICIAL DE RECAUDACIONES | F56: =+VLOOKUP(Tabla335[[#This Row],[CEDULA ]],'OCTUBRE 2025'!$C$8:$J$10,6,0) -> Matriz | G56: =+VLOOKUP(Tabla335[[#This Row],[CEDULA ]],'OCTUBRE 2025'!$C$8:$J$10,8,0) -> 511.1 | K56: =+Tabla335[[#This Row],[BONO BOLETOS]]+Tabla335[[#This Row],[COM. POR CARGO]]+Tabla335[[#This Row],[BONO CUMP]] -> 0
B57: 50 | C57: 604154575 | D57: =+VLOOKUP(Tabla335[[#This Row],[CEDULA ]],'OCTUBRE 2025'!$C$8:$J$10,2,0) -> YUQUILEMA DELGADO PEDRO ANTONIO | E57: =+VLOOKUP(Tabla335[[#This Row],[CEDULA ]],'OCTUBRE 2025'!$C$8:$J$10,4,0) -> JEFE DE CRÉDITO | F57: =+VLOOKUP(Tabla335[[#This Row],[CEDULA ]],'OCTUBRE 2025'!$C$8:$J$10,6,0) -> Durán | G57: =+VLOOKUP(Tabla335[[#This Row],[CEDULA ]],'OCTUBRE 2025'!$C$8:$J$10,8,0) -> 1022.2 | K57: =+Tabla335[[#This Row],[BONO BOLETOS]]+Tabla335[[#This Row],[COM. POR CARGO]]+Tabla335[[#This Row],[BONO CUMP]] -> 0
J58: 0 | K58: =+Tabla335[[#This Row],[BONO BOLETOS]]+Tabla335[[#This Row],[COM. POR CARGO]]+Tabla335[[#This Row],[BONO CUMP]] -> 0
D59: TOTALES | G59: =SUBTOTAL(109,Tabla335[SUELDO]) -> #N/A | H59: =SUBTOTAL(109,Tabla335[BONO BOLETOS]) -> 0 | I59: =SUBTOTAL(109,Tabla335[COM. POR CARGO]) -> 0 | J59: =SUBTOTAL(109,Tabla335[BONO CUMP]) -> 737.54 | K59: =SUBTOTAL(109,Tabla335[US$,,]) -> 737.54

Sheet COMISIONES-SOCIOS
B2: CÁLCULO DE COMISIONES POR APERTURA
B3: NÓMINA SEPTIEMBRE 2025
H5: SOCIOS NUEVOS | J5: VALOR | L5: TOTAL COMISIÓN
H6: APERTURA | I6: APERT+CRÉD | J6: 5 | K6: 10
B7: NO | C7: CEDULA | D7: NOMBRE | E7: CARGO | F7: Agencia | G7: SUELDO | H7: Cantidad | I7: Cantidad2 | J7: US$ | K7: US$, | L7: US$,,
B8: 1 | C8: 925813685 | D8: =+VLOOKUP(Tabla33[[#This Row],[CEDULA ]],'OCTUBRE 2025'!$C$8:$J$10,2,0) -> #N/A | E8: =+VLOOKUP(Tabla33[[#This Row],[CEDULA ]],'OCTUBRE 2025'!$C$8:$J$10,4,0) -> #N/A | F8: =+VLOOKUP(Tabla33[[#This Row],[CEDULA ]],'OCTUBRE 2025'!$C$8:$J$10,6,0) -> #N/A | G8: =+VLOOKUP(Tabla33[[#This Row],[CEDULA ]],'OCTUBRE 2025'!$C$8:$J$10,8,0) -> #N/A | J8: =+Tabla33[[#This Row],[Cantidad]]*$J$6 -> 0 | K8: =+Tabla33[[#This Row],[Cantidad2]]*$K$6 -> 0 | L8: =+Tabla33[[#This Row],[US$]]+Tabla33[[#This Row],[US$,]] -> 0
B9: 2 | C9: 944405737 | D9: =+VLOOKUP(Tabla33[[#This Row],[CEDULA ]],'OCTUBRE 2025'!$C$8:$J$10,2,0) -> #N/A | E9: =+VLOOKUP(Tabla33[[#This Row],[CEDULA ]],'OCTUBRE 2025'!$C$8:$J$10,4,0) -> #N/A | F9: =+VLOOKUP(Tabla33[[#This Row],[CEDULA ]],'OCTUBRE 2025'!$C$8:$J$10,6,0) -> #N/A | G9: =+VLOOKUP(Tabla33[[#This Row],[CEDULA ]],'OCTUBRE 2025'!$C$8:$J$10,8,0) -> #N/A | J9: =+Tabla33[[#This Row],[Cantidad]]*$J$6 -> 0 | K9: =+Tabla33[[#This Row],[Cantidad2]]*$K$6 -> 0 | L9: =+Tabla33[[#This Row],[US$]]+Tabla33[[#This Row],[US$,]] -> 0
B10: 3 | C10: 604394502 | D10: =+VLOOKUP(Tabla33[[#This Row],[CEDULA ]],'OCTUBRE 2025'!$C$8:$J$10,2,0) -> #N/A | E10: =+VLOOKUP(Tabla33[[#This Row],[CEDULA ]],'OCTUBRE 2025'!$C$8:$J$10,4,0) -> #N/A | F10: =+VLOOKUP(Tabla33[[#This Row],[CEDULA ]],'OCTUBRE 2025'!$C$8:$J$10,6,0) -> #N/A | G10: =+VLOOKUP(Tabla33[[#This Row],[CEDULA ]],'OCTUBRE 2025'!$C$8:$J$10,8,0) -> #N/A | J10: =+Tabla33[[#This Row],[Cantidad]]*$J$6 -> 0 | K10: =+Tabla33[[#This Row],[Cantidad2]]*$K$6 -> 0 | L10: =+Tabla33[[#This Row],[US$]]+Tabla33[[#This Row],[US$,]] -> 0
B11: 4 | C11: 955741970 | D11: =+VLOOKUP(Tabla33[[#This Row],[CEDULA ]],'OCTUBRE 2025'!$C$8:$J$10,2,0) -> #N/A | E11: =+VLOOKUP(Tabla33[[#This Row],[CEDULA ]],'OCTUBRE 2025'!$C$8:$J$10,4,0) -> #N/A | F11: =+VLOOKUP(Tabla33[[#This Row],[CEDULA ]],'OCTUBRE 2025'!$C$8:$J$10,6,0) -> #N/A | G11: =+VLOOKUP(Tabla33[[#This Row],[CEDULA ]],'OCTUBRE 2025'!$C$8:$J$10,8,0) -> #N/A | J11: =+Tabla33[[#This Row],[Cantidad]]*$J$6 -> 0 | K11: =+Tabla33[[#This Row],[Cantidad2]]*$K$6 -> 0 | L11: =+Tabla33[[#This Row],[US$]]+Tabla33[[#This Row],[US$,]] -> 0
B12: 5 | C12: 0943964973 | D12: =+VLOOKUP(Tabla33[[#This Row],[CEDULA ]],'OCTUBRE 2025'!$C$8:$J$10,2,0) -> #N/A | E12: =+VLOOKUP(Tabla33[[#This Row],[CEDULA ]],'OCTUBRE 2025'!$C$8:$J$10,4,0) -> #N/A | F12: =+VLOOKUP(Tabla33[[#This Row],[CEDULA ]],'OCTUBRE 2025'!$C$8:$J$10,6,0) -> #N/A | G12: =+VLOOKUP(Tabla33[[#This Row],[CEDULA ]],'OCTUBRE 2025'!$C$8:$J$10,8,0) -> #N/A | J12: =+Tabla33[[#This Row],[Cantidad]]*$J$6 -> 0 | K12: =+Tabla33[[#This Row],[Cantidad2]]*$K$6 -> 0 | L12: =+Tabla33[[#This Row],[US$]]+Tabla33[[#This Row],[US$,]] -> 0
B13: 6 | C13: 944143148 | D13: =+VLOOKUP(Tabla33[[#This Row],[CEDULA ]],'OCTUBRE 2025'!$C$8:$J$10,2,0) -> #N/A | E13: =+VLOOKUP(Tabla33[[#This Row],[CEDULA ]],'OCTUBRE 2025'!$C$8:$J$10,4,0) -> #N/A | F13: =+VLOOKUP(Tabla33[[#This Row],[CEDULA ]],'OCTUBRE 2025'!$C$8:$J$10,6,0) -> #N/A | G13: =+VLOOKUP(Tabla33[[#This Row],[CEDULA ]],'OCTUBRE 2025'!$C$8:$J$10,8,0) -> #N/A | J13: =+Tabla33[[#This Row],[Cantidad]]*$J$6 -> 0 | K13: =+Tabla33[[#This Row],[Cantidad2]]*$K$6 -> 0 | L13: =+Tabla33[[#This Row],[US$]]+Tabla33[[#This Row],[US$,]] -> 0
B14: 7 | C14: 955325238 | D14: =+VLOOKUP(Tabla33[[#This Row],[CEDULA ]],'OCTUBRE 2025'!$C$8:$J$10,2,0) -> #N/A | E14: =+VLOOKUP(Tabla33[[#This Row],[CEDULA ]],'OCTUBRE 2025'!$C$8:$J$10,4,0) -> #N/A | F14: =+VLOOKUP(Tabla33[[#This Row],[CEDULA ]],'OCTUBRE 2025'!$C$8:$J$10,6,0) -> #N/A | G14: =+VLOOKUP(Tabla33[[#This Row],[CEDULA ]],'OCTUBRE 2025'!$C$8:$J$10,8,0) -> #N/A | J14: =+Tabla33[[#This Row],[Cantidad]]*$J$6 -> 0 | K14: =+Tabla33[[#This Row],[Cantidad2]]*$K$6 -> 0 | L14: =+Tabla33[[#This Row],[US$]]+Tabla33[[#This Row],[US$,]] -> 0
B15: 8 | C15: 914163654 | D15: =+VLOOKUP(Tabla33[[#This Row],[CEDULA ]],'OCTUBRE 2025'!$C$8:$J$10,2,0) -> #N/A | E15: =+VLOOKUP(Tabla33[[#This Row],[CEDULA ]],'OCTUBRE 2025'!$C$8:$J$10,4,0) -> #N/A | F15: =+VLOOKUP(Tabla33[[#This Row],[CEDULA ]],'OCTUBRE 2025'!$C$8:$J$10,6,0) -> #N/A | G15: =+VLOOKUP(Tabla33[[#This Row],[CEDULA ]],'OCTUBRE 2025'!$C$8:$J$10,8,0) -> #N/A | J15: =+Tabla33[[#This Row],[Cantidad]]*$J$6 -> 0 | K15: =+Tabla33[[#This Row],[Cantidad2]]*$K$6 -> 0 | L15: =+Tabla33[[#This Row],[US$]]+Tabla33[[#This Row],[US$,]] -> 0
B16: 9 | C16: 956668305 | D16: =+VLOOKUP(Tabla33[[#This Row],[CEDULA ]],'OCTUBRE 2025'!$C$8:$J$10,2,0) -> #N/A | E16: =+VLOOKUP(Tabla33[[#This Row],[CEDULA ]],'OCTUBRE 2025'!$C$8:$J$10,4,0) -> #N/A | F16: =+VLOOKUP(Tabla33[[#This Row],[CEDULA ]],'OCTUBRE 2025'!$C$8:$J$10,6,0) -> #N/A | G16: =+VLOOKUP(Tabla33[[#This Row],[CEDULA ]],'OCTUBRE 2025'!$C$8:$J$10,8,0) -> #N/A | J16: =+Tabla33[[#This Row],[Cantidad]]*$J$6 -> 0 | K16: =+Tabla33[[#This Row],[Cantidad2]]*$K$6 -> 0 | L16: =+Tabla33[[#This Row],[US$]]+Tabla33[[#This Row],[US$,]] -> 0
B17: 10 | C17: 0918741448 | D17: =+VLOOKUP(Tabla33[[#This Row],[CEDULA ]],'OCTUBRE 2025'!$C$8:$J$10,2,0) -> #N/A | E17: =+VLOOKUP(Tabla33[[#This Row],[CEDULA ]],'OCTUBRE 2025'!$C$8:$J$10,4,0) -> #N/A | F17: =+VLOOKUP(Tabla33[[#This Row],[CEDULA ]],'OCTUBRE 2025'!$C$8:$J$10,6,0) -> #N/A | G17: =+VLOOKUP(Tabla33[[#This Row],[CEDULA ]],'OCTUBRE 2025'!$C$8:$J$10,8,0) -> #N/A | J17: =+Tabla33[[#This Row],[Cantidad]]*$J$6 -> 0 | K17: =+Tabla33[[#This Row],[Cantidad2]]*$K$6 -> 0 | L17: =+Tabla33[[#This Row],[US$]]+Tabla33[[#This Row],[US$,]] -> 0
B18: 11 | C18: 931097620 | D18: =+VLOOKUP(Tabla33[[#This Row],[CEDULA ]],'OCTUBRE 2025'!$C$8:$J$10,2,0) -> #N/A | E18: =+VLOOKUP(Tabla33[[#This Row],[CEDULA ]],'OCTUBRE 2025'!$C$8:$J$10,4,0) -> #N/A | F18: =+VLOOKUP(Tabla33[[#This Row],[CEDULA ]],'OCTUBRE 2025'!$C$8:$J$10,6,0) -> #N/A | G18: =+VLOOKUP(Tabla33[[#This Row],[CEDULA ]],'OCTUBRE 2025'!$C$8:$J$10,8,0) -> #N/A | J18: =+Tabla33[[#This Row],[Cantidad]]*$J$6 -> 0 | K18: =+Tabla33[[#This Row],[Cantidad2]]*$K$6 -> 0 | L18: =+Tabla33[[#This Row],[US$]]+Tabla33[[#This Row],[US$,]] -> 0
B19: 12 | C19: 1105483422 | D19: =+VLOOKUP(Tabla33[[#This Row],[CEDULA ]],'OCTUBRE 2025'!$C$8:$J$10,2,0) -> #N/A | E19: =+VLOOKUP(Tabla33[[#This Row],[CEDULA ]],'OCTUBRE 2025'!$C$8:$J$10,4,0) -> #N/A | F19: =+VLOOKUP(Tabla33[[#This Row],[CEDULA ]],'OCTUBRE 2025'!$C$8:$J$10,6,0) -> #N/A | G19: =+VLOOKUP(Tabla33[[#This Row],[CEDULA ]],'OCTUBRE 2025'!$C$8:$J$10,8,0) -> #N/A | J19: =+Tabla33[[#This Row],[Cantidad]]*$J$6 -> 0 | K19: =+Tabla33[[#This Row],[Cantidad2]]*$K$6 -> 0 | L19: =+Tabla33[[#This Row],[US$]]+Tabla33[[#This Row],[US$,]] -> 0
B20: 13 | C20: 942614645 | D20: =+VLOOKUP(Tabla33[[#This Row],[CEDULA ]],'OCTUBRE 2025'!$C$8:$J$10,2,0) -> #N/A | E20: =+VLOOKUP(Tabla33[[#This Row],[CEDULA ]],'OCTUBRE 2025'!$C$8:$J$10,4,0) -> #N/A | F20: =+VLOOKUP(Tabla33[[#This Row],[CEDULA ]],'OCTUBRE 2025'!$C$8:$J$10,6,0) -> #N/A | G20: =+VLOOKUP(Tabla33[[#This Row],[CEDULA ]],'OCTUBRE 2025'!$C$8:$J$10,8,0) -> #N/A | J20: =+Tabla33[[#This Row],[Cantidad]]*$J$6 -> 0 | K20: =+Tabla33[[#This Row],[Cantidad2]]*$K$6 -> 0 | L20: =+Tabla33[[#This Row],[US$]]+Tabla33[[#This Row],[US$,]] -> 0
B21: 14 | C21: 951200062 | D21: =+VLOOKUP(Tabla33[[#This Row],[CEDULA ]],'OCTUBRE 2025'!$C$8:$J$10,2,0) -> #N/A | E21: =+VLOOKUP(Tabla33[[#This Row],[CEDULA ]],'OCTUBRE 2025'!$C$8:$J$10,4,0) -> #N/A | F21: =+VLOOKUP(Tabla33[[#This Row],[CEDULA ]],'OCTUBRE 2025'!$C$8:$J$10,6,0) -> #N/A | G21: =+VLOOKUP(Tabla33[[#This Row],[CEDULA ]],'OCTUBRE 2025'!$C$8:$J$10,8,0) -> #N/A | J21: =+Tabla33[[#This Row],[Cantidad]]*$J$6 -> 0 | K21: =+Tabla33[[#This Row],[Cantidad2]]*$K$6 -> 0 | L21: =+Tabla33[[#This Row],[US$]]+Tabla33[[#This Row],[US$,]] -> 0
B22: 15 | C22: 950929232 | D22: =+VLOOKUP(Tabla33[[#This Row],[CEDULA ]],'OCTUBRE 2025'!$C$8:$J$10,2,0) -> #N/A | E22: =+VLOOKUP(Tabla33[[#This Row],[CEDULA ]],'OCTUBRE 2025'!$C$8:$J$10,4,0) -> #N/A | F22: =+VLOOKUP(Tabla33[[#This Row],[CEDULA ]],'OCTUBRE 2025'!$C$8:$J$10,6,0) -> #N/A | G22: =+VLOOKUP(Tabla33[[#This Row],[CEDULA ]],'OCTUBRE 2025'!$C$8:$J$10,8,0) -> #N/A | J22: =+Tabla33[[#This Row],[Cantidad]]*$J$6 -> 0 | K22: =+Tabla33[[#This Row],[Cantidad2]]*$K$6 -> 0 | L22: =+Tabla33[[#This Row],[US$]]+Tabla33[[#This Row],[US$,]] -> 0
B23: 16 | C23: 953819646 | D23: =+VLOOKUP(Tabla33[[#This Row],[CEDULA ]],'OCTUBRE 2025'!$C$8:$J$10,2,0) -> #N/A | E23: =+VLOOKUP(Tabla33[[#This Row],[CEDULA ]],'OCTUBRE 2025'!$C$8:$J$10,4,0) -> #N/A | F23: =+VLOOKUP(Tabla33[[#This Row],[CEDULA ]],'OCTUBRE 2025'!$C$8:$J$10,6,0) -> #N/A | G23: =+VLOOKUP(Tabla33[[#This Row],[CEDULA ]],'OCTUBRE 2025'!$C$8:$J$10,8,0) -> #N/A | J23: =+Tabla33[[#This Row],[Cantidad]]*$J$6 -> 0 | K23: =+Tabla33[[#This Row],[Cantidad2]]*$K$6 -> 0 | L23: =+Tabla33[[#This Row],[US$]]+Tabla33[[#This Row],[US$,]] -> 0
B24: 17 | C24: 956953392 | D24: =+VLOOKUP(Tabla33[[#This Row],[CEDULA ]],'OCTUBRE 2025'!$C$8:$J$10,2,0) -> #N/A | E24: =+VLOOKUP(Tabla33[[#This Row],[CEDULA ]],'OCTUBRE 2025'!$C$8:$J$10,4,0) -> #N/A | F24: =+VLOOKUP(Tabla33[[#This Row],[CEDULA ]],'OCTUBRE 2025'!$C$8:$J$10,6,0) -> #N/A | G24: =+VLOOKUP(Tabla33[[#This Row],[CEDULA ]],'OCTUBRE 2025'!$C$8:$J$10,8,0) -> #N/A | J24: =+Tabla33[[#This Row],[Cantidad]]*$J$6 -> 0 | K24: =+Tabla33[[#This Row],[Cantidad2]]*$K$6 -> 0 | L24: =+Tabla33[[#This Row],[US$]]+Tabla33[[#This Row],[US$,]] -> 0
B25: 18 | C25: 956796767 | D25: =+VLOOKUP(Tabla33[[#This Row],[CEDULA ]],'OCTUBRE 2025'!$C$8:$J$10,2,0) -> #N/A | E25: =+VLOOKUP(Tabla33[[#This Row],[CEDULA ]],'OCTUBRE 2025'!$C$8:$J$10,4,0) -> #N/A | F25: =+VLOOKUP(Tabla33[[#This Row],[CEDULA ]],'OCTUBRE 2025'!$C$8:$J$10,6,0) -> #N/A | G25: =+VLOOKUP(Tabla33[[#This Row],[CEDULA ]],'OCTUBRE 2025'!$C$8:$J$10,8,0) -> #N/A | J25: =+Tabla33[[#This Row],[Cantidad]]*$J$6 -> 0 | K25: =+Tabla33[[#This Row],[Cantidad2]]*$K$6 -> 0 | L25: =+Tabla33[[#This Row],[US$]]+Tabla33[[#This Row],[US$,]] -> 0
B26: 19 | C26: 0932036049 | D26: =+VLOOKUP(Tabla33[[#This Row],[CEDULA ]],'OCTUBRE 2025'!$C$8:$J$10,2,0) -> #N/A | E26: =+VLOOKUP(Tabla33[[#This Row],[CEDULA ]],'OCTUBRE 2025'!$C$8:$J$10,4,0) -> #N/A | F26: =+VLOOKUP(Tabla33[[#This Row],[CEDULA ]],'OCTUBRE 2025'!$C$8:$J$10,6,0) -> #N/A | G26: =+VLOOKUP(Tabla33[[#This Row],[CEDULA ]],'OCTUBRE 2025'!$C$8:$J$10,8,0) -> #N/A | J26: =+Tabla33[[#This Row],[Cantidad]]*$J$6 -> 0 | K26: =+Tabla33[[#This Row],[Cantidad2]]*$K$6 -> 0 | L26: =+Tabla33[[#This Row],[US$]]+Tabla33[[#This Row],[US$,]] -> 0
B27: 20 | C27: 1724102940 | D27: =+VLOOKUP(Tabla33[[#This Row],[CEDULA ]],'OCTUBRE 2025'!$C$8:$J$10,2,0) -> #N/A | E27: =+VLOOKUP(Tabla33[[#This Row],[CEDULA ]],'OCTUBRE 2025'!$C$8:$J$10,4,0) -> #N/A | F27: =+VLOOKUP(Tabla33[[#This Row],[CEDULA ]],'OCTUBRE 2025'!$C$8:$J$10,6,0) -> #N/A | G27: =+VLOOKUP(Tabla33[[#This Row],[CEDULA ]],'OCTUBRE 2025'!$C$8:$J$10,8,0) -> #N/A | J27: =+Tabla33[[#This Row],[Cantidad]]*$J$6 -> 0 | K27: =+Tabla33[[#This Row],[Cantidad2]]*$K$6 -> 0 | L27: =+Tabla33[[#This Row],[US$]]+Tabla33[[#This Row],[US$,]] -> 0
B28: 21 | C28: 943322974 | D28: =+VLOOKUP(Tabla33[[#This Row],[CEDULA ]],'OCTUBRE 2025'!$C$8:$J$10,2,0) -> #N/A | E28: =+VLOOKUP(Tabla33[[#This Row],[CEDULA ]],'OCTUBRE 2025'!$C$8:$J$10,4,0) -> #N/A | F28: =+VLOOKUP(Tabla33[[#This Row],[CEDULA ]],'OCTUBRE 2025'!$C$8:$J$10,6,0) -> #N/A | G28: =+VLOOKUP(Tabla33[[#This Row],[CEDULA ]],'OCTUBRE 2025'!$C$8:$J$10,8,0) -> #N/A | J28: =+Tabla33[[#This Row],[Cantidad]]*$J$6 -> 0 | K28: =+Tabla33[[#This Row],[Cantidad2]]*$K$6 -> 0 | L28: =+Tabla33[[#This Row],[US$]]+Tabla33[[#This Row],[US$,]] -> 0
B29: 22 | C29: 941096851 | D29: =+VLOOKUP(Tabla33[[#This Row],[CEDULA ]],'OCTUBRE 2025'!$C$8:$J$10,2,0) -> #N/A | E29: =+VLOOKUP(Tabla33[[#This Row],[CEDULA ]],'OCTUBRE 2025'!$C$8:$J$10,4,0) -> #N/A | F29: =+VLOOKUP(Tabla33[[#This Row],[CEDULA ]],'OCTUBRE 2025'!$C$8:$J$10,6,0) -> #N/A | G29: =+VLOOKUP(Tabla33[[#This Row],[CEDULA ]],'OCTUBRE 2025'!$C$8:$J$10,8,0) -> #N/A | J29: =+Tabla33[[#This Row],[Cantidad]]*$J$6 -> 0 | K29: =+Tabla33[[#This Row],[Cantidad2]]*$K$6 -> 0 | L29: =+Tabla33[[#This Row],[US$]]+Tabla33[[#This Row],[US$,]] -> 0
B30: 23 | C30: 957093800 | D30: =+VLOOKUP(Tabla33[[#This Row],[CEDULA ]],'OCTUBRE 2025'!$C$8:$J$10,2,0) -> #N/A | E30: =+VLOOKUP(Tabla33[[#This Row],[CEDULA ]],'OCTUBRE 2025'!$C$8:$J$10,4,0) -> #N/A | F30: =+VLOOKUP(Tabla33[[#This Row],[CEDULA ]],'OCTUBRE 2025'!$C$8:$J$10,6,0) -> #N/A | G30: =+VLOOKUP(Tabla33[[#This Row],[CEDULA ]],'OCTUBRE 2025'!$C$8:$J$10,8,0) -> #N/A | J30: =+Tabla33[[#This Row],[Cantidad]]*$J$6 -> 0 | K30: =+Tabla33[[#This Row],[Cantidad2]]*$K$6 -> 0 | L30: =+Tabla33[[#This Row],[US$]]+Tabla33[[#This Row],[US$,]] -> 0
B31: 24 | C31: 957924350 | D31: =+VLOOKUP(Tabla33[[#This Row],[CEDULA ]],'OCTUBRE 2025'!$C$8:$J$10,2,0) -> #N/A | E31: =+VLOOKUP(Tabla33[[#This Row],[CEDULA ]],'OCTUBRE 2025'!$C$8:$J$10,4,0) -> #N/A | F31: =+VLOOKUP(Tabla33[[#This Row],[CEDULA ]],'OCTUBRE 2025'!$C$8:$J$10,6,0) -> #N/A | G31: =+VLOOKUP(Tabla33[[#This Row],[CEDULA ]],'OCTUBRE 2025'!$C$8:$J$10,8,0) -> #N/A | J31: =+Tabla33[[#This Row],[Cantidad]]*$J$6 -> 0 | K31: =+Tabla33[[#This Row],[Cantidad2]]*$K$6 -> 0 | L31: =+Tabla33[[#This Row],[US$]]+Tabla33[[#This Row],[US$,]] -> 0
B32: 25 | C32: 603838657 | D32: =+VLOOKUP(Tabla33[[#This Row],[CEDULA ]],'OCTUBRE 2025'!$C$8:$J$10,2,0) -> #N/A | E32: =+VLOOKUP(Tabla33[[#This Row],[CEDULA ]],'OCTUBRE 2025'!$C$8:$J$10,4,0) -> #N/A | F32: =+VLOOKUP(Tabla33[[#This Row],[CEDULA ]],'OCTUBRE 2025'!$C$8:$J$10,6,0) -> #N/A | G32: =+VLOOKUP(Tabla33[[#This Row],[CEDULA ]],'OCTUBRE 2025'!$C$8:$J$10,8,0) -> #N/A | J32: =+Tabla33[[#This Row],[Cantidad]]*$J$6 -> 0 | K32: =+Tabla33[[#This Row],[Cantidad2]]*$K$6 -> 0 | L32: =+Tabla33[[#This Row],[US$]]+Tabla33[[#This Row],[US$,]] -> 0
B33: 26 | C33: 925240525 | D33: =+VLOOKUP(Tabla33[[#This Row],[CEDULA ]],'OCTUBRE 2025'!$C$8:$J$10,2,0) -> #N/A | E33: =+VLOOKUP(Tabla33[[#This Row],[CEDULA ]],'OCTUBRE 2025'!$C$8:$J$10,4,0) -> #N/A | F33: =+VLOOKUP(Tabla33[[#This Row],[CEDULA ]],'OCTUBRE 2025'!$C$8:$J$10,6,0) -> #N/A | G33: =+VLOOKUP(Tabla33[[#This Row],[CEDULA ]],'OCTUBRE 2025'!$C$8:$J$10,8,0) -> #N/A | J33: =+Tabla33[[#This Row],[Cantidad]]*$J$6 -> 0 | K33: =+Tabla33[[#This Row],[Cantidad2]]*$K$6 -> 0 | L33: =+Tabla33[[#This Row],[US$]]+Tabla33[[#This Row],[US$,]] -> 0
B34: 27 | C34: 954520599 | D34: =+VLOOKUP(Tabla33[[#This Row],[CEDULA ]],'OCTUBRE 2025'!$C$8:$J$10,2,0) -> #N/A | E34: =+VLOOKUP(Tabla33[[#This Row],[CEDULA ]],'OCTUBRE 2025'!$C$8:$J$10,4,0) -> #N/A | F34: =+VLOOKUP(Tabla33[[#This Row],[CEDULA ]],'OCTUBRE 2025'!$C$8:$J$10,6,0) -> #N/A | G34: =+VLOOKUP(Tabla33[[#This Row],[CEDULA ]],'OCTUBRE 2025'!$C$8:$J$10,8,0) -> #N/A | J34: =+Tabla33[[#This Row],[Cantidad]]*$J$6 -> 0 | K34: =+Tabla33[[#This Row],[Cantidad2]]*$K$6 -> 0 | L34: =+Tabla33[[#This Row],[US$]]+Tabla33[[#This Row],[US$,]] -> 0
B35: 28 | C35: 0943906032 | D35: =+VLOOKUP(Tabla33[[#This Row],[CEDULA ]],'OCTUBRE 2025'!$C$8:$J$10,2,0) -> #N/A | E35: =+VLOOKUP(Tabla33[[#This Row],[CEDULA ]],'OCTUBRE 2025'!$C$8:$J$10,4,0) -> #N/A | F35: =+VLOOKUP(Tabla33[[#This Row],[CEDULA ]],'OCTUBRE 2025'!$C$8:$J$10,6,0) -> #N/A | G35: =+VLOOKUP(Tabla33[[#This Row],[CEDULA ]],'OCTUBRE 2025'!$C$8:$J$10,8,0) -> #N/A | J35: =+Tabla33[[#This Row],[Cantidad]]*$J$6 -> 0 | K35: =+Tabla33[[#This Row],[Cantidad2]]*$K$6 -> 0 | L35: =+Tabla33[[#This Row],[US$]]+Tabla33[[#This Row],[US$,]] -> 0
B36: 29 | C36: 0919306050 | D36: =+VLOOKUP(Tabla33[[#This Row],[CEDULA ]],'OCTUBRE 2025'!$C$8:$J$10,2,0) -> #N/A | E36: =+VLOOKUP(Tabla33[[#This Row],[CEDULA ]],'OCTUBRE 2025'!$C$8:$J$10,4,0) -> #N/A | F36: =+VLOOKUP(Tabla33[[#This Row],[CEDULA ]],'OCTUBRE 2025'!$C$8:$J$10,6,0) -> #N/A | G36: =+VLOOKUP(Tabla33[[#This Row],[CEDULA ]],'OCTUBRE 2025'!$C$8:$J$10,8,0) -> #N/A | J36: =+Tabla33[[#This Row],[Cantidad]]*$J$6 -> 0 | K36: =+Tabla33[[#This Row],[Cantidad2]]*$K$6 -> 0 | L36: =+Tabla33[[#This Row],[US$]]+Tabla33[[#This Row],[US$,]] -> 0
B37: 30 | C37: 0941235376 | D37: =+VLOOKUP(Tabla33[[#This Row],[CEDULA ]],'OCTUBRE 2025'!$C$8:$J$10,2,0) -> #N/A | E37: =+VLOOKUP(Tabla33[[#This Row],[CEDULA ]],'OCTUBRE 2025'!$C$8:$J$10,4,0) -> #N/A | F37: =+VLOOKUP(Tabla33[[#This Row],[CEDULA ]],'OCTUBRE 2025'!$C$8:$J$10,6,0) -> #N/A | G37: =+VLOOKUP(Tabla33[[#This Row],[CEDULA ]],'OCTUBRE 2025'!$C$8:$J$10,8,0) -> #N/A | J37: =+Tabla33[[#This Row],[Cantidad]]*$J$6 -> 0 | K37: =+Tabla33[[#This Row],[Cantidad2]]*$K$6 -> 0 | L37: =+Tabla33[[#This Row],[US$]]+Tabla33[[#This Row],[US$,]] -> 0
B38: 31 | C38: 955395686 | D38: =+VLOOKUP(Tabla33[[#This Row],[CEDULA ]],'OCTUBRE 2025'!$C$8:$J$10,2,0) -> #N/A | E38: =+VLOOKUP(Tabla33[[#This Row],[CEDULA ]],'OCTUBRE 2025'!$C$8:$J$10,4,0) -> #N/A | F38: =+VLOOKUP(Tabla33[[#This Row],[CEDULA ]],'OCTUBRE 2025'!$C$8:$J$10,6,0) -> #N/A | G38: =+VLOOKUP(Tabla33[[#This Row],[CEDULA ]],'OCTUBRE 2025'!$C$8:$J$10,8,0) -> #N/A | J38: =+Tabla33[[#This Row],[Cantidad]]*$J$6 -> 0 | K38: =+Tabla33[[#This Row],[Cantidad2]]*$K$6 -> 0 | L38: =+Tabla33[[#This Row],[US$]]+Tabla33[[#This Row],[US$,]] -> 0
B39: 32 | C39: 940991987 | D39: =+VLOOKUP(Tabla33[[#This Row],[CEDULA ]],'OCTUBRE 2025'!$C$8:$J$10,2,0) -> #N/A | E39: =+VLOOKUP(Tabla33[[#This Row],[CEDULA ]],'OCTUBRE 2025'!$C$8:$J$10,4,0) -> #N/A | F39: =+VLOOKUP(Tabla33[[#This Row],[CEDULA ]],'OCTUBRE 2025'!$C$8:$J$10,6,0) -> #N/A | G39: =+VLOOKUP(Tabla33[[#This Row],[CEDULA ]],'OCTUBRE 2025'!$C$8:$J$10,8,0) -> #N/A | J39: =+Tabla33[[#This Row],[Cantidad]]*$J$6 -> 0 | K39: =+Tabla33[[#This Row],[Cantidad2]]*$K$6 -> 0 | L39: =+Tabla33[[#This Row],[US$]]+Tabla33[[#This Row],[US$,]] -> 0
B40: 33 | C40: 956929277 | D40: =+VLOOKUP(Tabla33[[#This Row],[CEDULA ]],'OCTUBRE 2025'!$C$8:$J$10,2,0) -> #N/A | E40: =+VLOOKUP(Tabla33[[#This Row],[CEDULA ]],'OCTUBRE 2025'!$C$8:$J$10,4,0) -> #N/A | F40: =+VLOOKUP(Tabla33[[#This Row],[CEDULA ]],'OCTUBRE 2025'!$C$8:$J$10,6,0) -> #N/A | G40: =+VLOOKUP(Tabla33[[#This Row],[CEDULA ]],'OCTUBRE 2025'!$C$8:$J$10,8,0) -> #N/A | J40: =+Tabla33[[#This Row],[Cantidad]]*$J$6 -> 0 | K40: =+Tabla33[[#This Row],[Cantidad2]]*$K$6 -> 0 | L40: =+Tabla33[[#This Row],[US$]]+Tabla33[[#This Row],[US$,]] -> 0
B41: 34 | C41: 951763994 | D41: =+VLOOKUP(Tabla33[[#This Row],[CEDULA ]],'OCTUBRE 2025'!$C$8:$J$10,2,0) -> #N/A | E41: =+VLOOKUP(Tabla33[[#This Row],[CEDULA ]],'OCTUBRE 2025'!$C$8:$J$10,4,0) -> #N/A | F41: =+VLOOKUP(Tabla33[[#This Row],[CEDULA ]],'OCTUBRE 2025'!$C$8:$J$10,6,0) -> #N/A | G41: =+VLOOKUP(Tabla33[[#This Row],[CEDULA ]],'OCTUBRE 2025'!$C$8:$J$10,8,0) -> #N/A | J41: =+Tabla33[[#This Row],[Cantidad]]*$J$6 -> 0 | K41: =+Tabla33[[#This Row],[Cantidad2]]*$K$6 -> 0 | L41: =+Tabla33[[#This Row],[US$]]+Tabla33[[#This Row],[US$,]] -> 0
B42: 35 | C42: 950703199 | D42: =+VLOOKUP(Tabla33[[#This Row],[CEDULA ]],'OCTUBRE 2025'!$C$8:$J$10,2,0) -> #N/A | E42: =+VLOOKUP(Tabla33[[#This Row],[CEDULA ]],'OCTUBRE 2025'!$C$8:$J$10,4,0) -> #N/A | F42: =+VLOOKUP(Tabla33[[#This Row],[CEDULA ]],'OCTUBRE 2025'!$C$8:$J$10,6,0) -> #N/A | G42: =+VLOOKUP(Tabla33[[#This Row],[CEDULA ]],'OCTUBRE 2025'!$C$8:$J$10,8,0) -> #N/A | J42: =+Tabla33[[#This Row],[Cantidad]]*$J$6 -> 0 | K42: =+Tabla33[[#This Row],[Cantidad2]]*$K$6 -> 0 | L42: =+Tabla33[[#This Row],[US$]]+Tabla33[[#This Row],[US$,]] -> 0
B43: 36 | C43: 0923715692 | D43: =+VLOOKUP(Tabla33[[#This Row],[CEDULA ]],'OCTUBRE 2025'!$C$8:$J$10,2,0) -> #N/A | E43: =+VLOOKUP(Tabla33[[#This Row],[CEDULA ]],'OCTUBRE 2025'!$C$8:$J$10,4,0) -> #N/A | F43: =+VLOOKUP(Tabla33[[#This Row],[CEDULA ]],'OCTUBRE 2025'!$C$8:$J$10,6,0) -> #N/A | G43: =+VLOOKUP(Tabla33[[#This Row],[CEDULA ]],'OCTUBRE 2025'!$C$8:$J$10,8,0) -> #N/A | J43: =+Tabla33[[#This Row],[Cantidad]]*$J$6 -> 0 | K43: =+Tabla33[[#This Row],[Cantidad2]]*$K$6 -> 0 | L43: =+Tabla33[[#This Row],[US$]]+Tabla33[[#This Row],[US$,]] -> 0
B44: 37 | C44: 925830689 | D44: =+VLOOKUP(Tabla33[[#This Row],[CEDULA ]],'OCTUBRE 2025'!$C$8:$J$10,2,0) -> #N/A | E44: =+VLOOKUP(Tabla33[[#This Row],[CEDULA ]],'OCTUBRE 2025'!$C$8:$J$10,4,0) -> #N/A | F44: =+VLOOKUP(Tabla33[[#This Row],[CEDULA ]],'OCTUBRE 2025'!$C$8:$J$10,6,0) -> #N/A | G44: =+VLOOKUP(Tabla33[[#This Row],[CEDULA ]],'OCTUBRE 2025'!$C$8:$J$10,8,0) -> #N/A | J44: =+Tabla33[[#This Row],[Cantidad]]*$J$6 -> 0 | K44: =+Tabla33[[#This Row],[Cantidad2]]*$K$6 -> 0 | L44: =+Tabla33[[#This Row],[US$]]+Tabla33[[#This Row],[US$,]] -> 0
B45: 38 | C45: 944034842 | D45: =+VLOOKUP(Tabla33[[#This Row],[CEDULA ]],'OCTUBRE 2025'!$C$8:$J$10,2,0) -> #N/A | E45: =+VLOOKUP(Tabla33[[#This Row],[CEDULA ]],'OCTUBRE 2025'!$C$8:$J$10,4,0) -> #N/A | F45: =+VLOOKUP(Tabla33[[#This Row],[CEDULA ]],'OCTUBRE 2025'!$C$8:$J$10,6,0) -> #N/A | G45: =+VLOOKUP(Tabla33[[#This Row],[CEDULA ]],'OCTUBRE 2025'!$C$8:$J$10,8,0) -> #N/A | J45: =+Tabla33[[#This Row],[Cantidad]]*$J$6 -> 0 | K45: =+Tabla33[[#This Row],[Cantidad2]]*$K$6 -> 0 | L45: =+Tabla33[[#This Row],[US$]]+Tabla33[[#This Row],[US$,]] -> 0
B46: 39 | C46: 951340702 | D46: =+VLOOKUP(Tabla33[[#This Row],[CEDULA ]],'OCTUBRE 2025'!$C$8:$J$10,2,0) -> #N/A | E46: =+VLOOKUP(Tabla33[[#This Row],[CEDULA ]],'OCTUBRE 2025'!$C$8:$J$10,4,0) -> #N/A | F46: =+VLOOKUP(Tabla33[[#This Row],[CEDULA ]],'OCTUBRE 2025'!$C$8:$J$10,6,0) -> #N/A | G46: =+VLOOKUP(Tabla33[[#This Row],[CEDULA ]],'OCTUBRE 2025'!$C$8:$J$10,8,0) -> #N/A | J46: =+Tabla33[[#This Row],[Cantidad]]*$J$6 -> 0 | K46: =+Tabla33[[#This Row],[Cantidad2]]*$K$6 -> 0 | L46: =+Tabla33[[#This Row],[US$]]+Tabla33[[#This Row],[US$,]] -> 0
B47: 40 | C47: 650112949 | D47: =+VLOOKUP(Tabla33[[#This Row],[CEDULA ]],'OCTUBRE 2025'!$C$8:$J$10,2,0) -> #N/A | E47: =+VLOOKUP(Tabla33[[#This Row],[CEDULA ]],'OCTUBRE 2025'!$C$8:$J$10,4,0) -> #N/A | F47: =+VLOOKUP(Tabla33[[#This Row],[CEDULA ]],'OCTUBRE 2025'!$C$8:$J$10,6,0) -> #N/A | G47: =+VLOOKUP(Tabla33[[#This Row],[CEDULA ]],'OCTUBRE 2025'!$C$8:$J$10,8,0) -> #N/A | J47: =+Tabla33[[#This Row],[Cantidad]]*$J$6 -> 0 | K47: =+Tabla33[[#This Row],[Cantidad2]]*$K$6 -> 0 | L47: =+Tabla33[[#This Row],[US$]]+Tabla33[[#This Row],[US$,]] -> 0
B48: 41 | C48: 924232804 | D48: =+VLOOKUP(Tabla33[[#This Row],[CEDULA ]],'OCTUBRE 2025'!$C$8:$J$10,2,0) -> #N/A | E48: =+VLOOKUP(Tabla33[[#This Row],[CEDULA ]],'OCTUBRE 2025'!$C$8:$J$10,4,0) -> #N/A | F48: =+VLOOKUP(Tabla33[[#This Row],[CEDULA ]],'OCTUBRE 2025'!$C$8:$J$10,6,0) -> #N/A | G48: =+VLOOKUP(Tabla33[[#This Row],[CEDULA ]],'OCTUBRE 2025'!$C$8:$J$10,8,0) -> #N/A | J48: =+Tabla33[[#This Row],[Cantidad]]*$J$6 -> 0 | K48: =+Tabla33[[#This Row],[Cantidad2]]*$K$6 -> 0 | L48: =+Tabla33[[#This Row],[US$]]+Tabla33[[#This Row],[US$,]] -> 0
B49: 42 | C49: 605031145 | D49: =+VLOOKUP(Tabla33[[#This Row],[CEDULA ]],'OCTUBRE 2025'!$C$8:$J$10,2,0) -> #N/A | E49: =+VLOOKUP(Tabla33[[#This Row],[CEDULA ]],'OCTUBRE 2025'!$C$8:$J$10,4,0) -> #N/A | F49: =+VLOOKUP(Tabla33[[#This Row],[CEDULA ]],'OCTUBRE 2025'!$C$8:$J$10,6,0) -> #N/A | G49: =+VLOOKUP(Tabla33[[#This Row],[CEDULA ]],'OCTUBRE 2025'!$C$8:$J$10,8,0) -> #N/A | J49: =+Tabla33[[#This Row],[Cantidad]]*$J$6 -> 0 | K49: =+Tabla33[[#This Row],[Cantidad2]]*$K$6 -> 0 | L49: =+Tabla33[[#This Row],[US$]]+Tabla33[[#This Row],[US$,]] -> 0
B50: 43 | C50: 927257576 | D50: =+VLOOKUP(Tabla33[[#This Row],[CEDULA ]],'OCTUBRE 2025'!$C$8:$J$10,2,0) -> #N/A | E50: =+VLOOKUP(Tabla33[[#This Row],[CEDULA ]],'OCTUBRE 2025'!$C$8:$J$10,4,0) -> #N/A | F50: =+VLOOKUP(Tabla33[[#This Row],[CEDULA ]],'OCTUBRE 2025'!$C$8:$J$10,6,0) -> #N/A | G50: =+VLOOKUP(Tabla33[[#This Row],[CEDULA ]],'OCTUBRE 2025'!$C$8:$J$10,8,0) -> #N/A | J50: =+Tabla33[[#This Row],[Cantidad]]*$J$6 -> 0 | K50: =+Tabla33[[#This Row],[Cantidad2]]*$K$6 -> 0 | L50: =+Tabla33[[#This Row],[US$]]+Tabla33[[#This Row],[US$,]] -> 0
B51: 44 | C51: 928901800 | D51: =+VLOOKUP(Tabla33[[#This Row],[CEDULA ]],'OCTUBRE 2025'!$C$8:$J$10,2,0) -> #N/A | E51: =+VLOOKUP(Tabla33[[#This Row],[CEDULA ]],'OCTUBRE 2025'!$C$8:$J$10,4,0) -> #N/A | F51: =+VLOOKUP(Tabla33[[#This Row],[CEDULA ]],'OCTUBRE 2025'!$C$8:$J$10,6,0) -> #N/A | G51: =+VLOOKUP(Tabla33[[#This Row],[CEDULA ]],'OCTUBRE 2025'!$C$8:$J$10,8,0) -> #N/A | J51: =+Tabla33[[#This Row],[Cantidad]]*$J$6 -> 0 | K51: =+Tabla33[[#This Row],[Cantidad2]]*$K$6 -> 0 | L51: =+Tabla33[[#This Row],[US$]]+Tabla33[[#This Row],[US$,]] -> 0
B52: 45 | C52: 951315746 | D52: =+VLOOKUP(Tabla33[[#This Row],[CEDULA ]],'OCTUBRE 2025'!$C$8:$J$10,2,0) -> #N/A | E52: =+VLOOKUP(Tabla33[[#This Row],[CEDULA ]],'OCTUBRE 2025'!$C$8:$J$10,4,0) -> #N/A | F52: =+VLOOKUP(Tabla33[[#This Row],[CEDULA ]],'OCTUBRE 2025'!$C$8:$J$10,6,0) -> #N/A | G52: =+VLOOKUP(Tabla33[[#This Row],[CEDULA ]],'OCTUBRE 2025'!$C$8:$J$10,8,0) -> #N/A | J52: =+Tabla33[[#This Row],[Cantidad]]*$J$6 -> 0 | K52: =+Tabla33[[#This Row],[Cantidad2]]*$K$6 -> 0 | L52: =+Tabla33[[#This Row],[US$]]+Tabla33[[#This Row],[US$,]] -> 0
B53: 46 | C53: 954184321 | D53: =+VLOOKUP(Tabla33[[#This Row],[CEDULA ]],'OCTUBRE 2025'!$C$8:$J$10,2,0) -> #N/A | E53: =+VLOOKUP(Tabla33[[#This Row],[CEDULA ]],'OCTUBRE 2025'!$C$8:$J$10,4,0) -> #N/A | F53: =+VLOOKUP(Tabla33[[#This Row],[CEDULA ]],'OCTUBRE 2025'!$C$8:$J$10,6,0) -> #N/A | G53: =+VLOOKUP(Tabla33[[#This Row],[CEDULA ]],'OCTUBRE 2025'!$C$8:$J$10,8,0) -> #N/A | J53: =+Tabla33[[#This Row],[Cantidad]]*$J$6 -> 0 | K53: =+Tabla33[[#This Row],[Cantidad2]]*$K$6 -> 0 | L53: =+Tabla33[[#This Row],[US$]]+Tabla33[[#This Row],[US$,]] -> 0
B54: 47 | C54: 922034772 | D54: =+VLOOKUP(Tabla33[[#This Row],[CEDULA ]],'OCTUBRE 2025'!$C$8:$J$10,2,0) -> #N/A | E54: =+VLOOKUP(Tabla33[[#This Row],[CEDULA ]],'OCTUBRE 2025'!$C$8:$J$10,4,0) -> #N/A | F54: =+VLOOKUP(Tabla33[[#This Row],[CEDULA ]],'OCTUBRE 2025'!$C$8:$J$10,6,0) -> #N/A | G54: =+VLOOKUP(Tabla33[[#This Row],[CEDULA ]],'OCTUBRE 2025'!$C$8:$J$10,8,0) -> #N/A | J54: =+Tabla33[[#This Row],[Cantidad]]*$J$6 -> 0 | K54: =+Tabla33[[#This Row],[Cantidad2]]*$K$6 -> 0 | L54: =+Tabla33[[#This Row],[US$]]+Tabla33[[#This Row],[US$,]] -> 0
B55: 48 | C55: 923837991 | D55: =+VLOOKUP(Tabla33[[#This Row],[CEDULA ]],'OCTUBRE 2025'!$C$8:$J$10,2,0) -> YUNDA CUJILEMA MARIA TERESA | E55: =+VLOOKUP(Tabla33[[#This Row],[CEDULA ]],'OCTUBRE 2025'!$C$8:$J$10,4,0) -> CONTADOR GENERAL | F55: =+VLOOKUP(Tabla33[[#This Row],[CEDULA ]],'OCTUBRE 2025'!$C$8:$J$10,6,0) -> Matriz | G55: =+VLOOKUP(Tabla33[[#This Row],[CEDULA ]],'OCTUBRE 2025'!$C$8:$J$10,8,0) -> 1022.2 | J55: =+Tabla33[[#This Row],[Cantidad]]*$J$6 -> 0 | K55: =+Tabla33[[#This Row],[Cantidad2]]*$K$6 -> 0 | L55: =+Tabla33[[#This Row],[US$]]+Tabla33[[#This Row],[US$,]] -> 0
... B57: 50 | C57: 604154575 | D57: =+VLOOKUP(Tabla33[[#This Row],[CEDULA ]],'OCTUBRE 2025'!$C$8:$J$10,2,0) -> YUQUILEMA DELGADO PEDRO ANTONIO | E57: =+VLOOKUP(Tabla33[[#This Row],[CEDULA ]],'OCTUBRE 2025'!$C$8:$J$10,4,0) -> JEFE DE CRÉDITO | F57: =+VLOOKUP(Tabla33[[#This Row],[CEDULA ]],'OCTUBRE 2025'!$C$8:$J$10,6,0) -> Durán | G57: =+VLOOKUP(Tabla33[[#This Row],[CEDULA ]],'OCTUBRE 2025'!$C$8:$J$10,8,0) -> 1022.2 | J57: =+Tabla33[[#This Row],[Cantidad]]*$J$6 -> 0 | K57: =+Tabla33[[#This Row],[Cantidad2]]*$K$6 -> 0 | L57: =+Tabla33[[#This Row],[US$]]+Tabla33[[#This Row],[US$,]] -> 0
J58: =+Tabla33[[#This Row],[Cantidad]]*$J$6 -> 0 | K58: =+Tabla33[[#This Row],[Cantidad2]]*$K$6 -> 0 | L58: =+Tabla33[[#This Row],[US$]]+Tabla33[[#This Row],[US$,]] -> 0
D59: TOTALES | G59: =SUBTOTAL(109,Tabla33[SUELDO]) -> #N/A | J59: =SUBTOTAL(109,Tabla33[US$]) -> 0 | K59: =SUBTOTAL(109,Tabla33[US$,]) -> 0 | L59: =SUBTOTAL(109,Tabla33[US$,,]) -> 0

Sheet CTAS POR COBRAR-GUAPI
C4: CUENTAS POR COBRAR A EMPLEADO
C7: FECHA: | E7: =TODAY()-8 -> 45982 | G7: NOMBRE: | H7: GUAPI YUMAGLLA OSCAR EDUARDO
C8: SUELDO: | E8: 473.88 | G8: CARGO: | H8: OFICIAL DE COBRANZAS
C9: FECHA DE INGRESO: | E9: 06-03-2024 | G9: AGENCIA: | H9: Matriz
C11: TIPO DE SOLICITUD:
J12: TABLA - FORMA DE PAGO
D13: ANTICIPO | J13: # CUOTA | K13: FECHA | L13: VALOR
D14: PRESTAMO | H14: 149.35 | J14: 1 | K14: 45597 | L14: =+H17 -> 74.675
D15: SOLICITUD DE # CUOTAS A DESCONTAR | H15: 2 | J15: 2 | K15: 45627 | L15: =+H17 -> 74.675
J16: 3
D17: VALOR | H17: =+H14/H15 -> 74.675 | J17: 4
J18: 5
J19: 6
J20: 7
J21: 8
J22: 9
J23: 10
J24: TOTAL | L24: =SUM(L14:L23) -> 149.35
C28: OBSERVACIONES
C30: DESCUENTO POR PÉRDIDA DE EQUIPO MÓVIL
C33: FIRMAS Y/O AUTORIZACIÓN
C35: Autorizo a la empresa Coac Los Andes Latinos LTDA., a descontar mediante mi rol de pago mensual o en mi liquidación de haberes de ser el caso
D43: FIRMA DEL SOLICITANTE | I43: ELABORADO POR
D44: C.I. | I44: DEPARTAMENTO DE RRHH
G56: APROBADO POR
G57: GERENCIA

Sheet H.EXTRAS
B2: CÁLCULO DE HORAS EXTRAS
B3: NÓMINA SEPTIEMBRE 2025
H5: HORAS TRABAJADAS | J5: VALOR | L5: TOTAL SOBRETIEMPO
H6: 0.5 | I6: 1 | J6: 0.5 | K6: 1
B7: NO | C7: CEDULA | D7: NOMBRE | E7: CARGO | F7: Agencia | G7: SUELDO | H7: Cantidad | I7: Cantidad2 | J7: US$ | K7: US$, | L7: US$,,
B8: 1 | C8: 925813685 | D8: =+VLOOKUP(Tabla3[[#This Row],[CEDULA ]],'OCTUBRE 2025'!$C$8:$J$10,2,0) -> #N/A | E8: =+VLOOKUP(Tabla3[[#This Row],[CEDULA ]],'OCTUBRE 2025'!$C$8:$J$10,4,0) -> #N/A | F8: =+VLOOKUP(Tabla3[[#This Row],[CEDULA ]],'OCTUBRE 2025'!$C$8:$J$10,6,0) -> #N/A | G8: =+VLOOKUP(Tabla3[[#This Row],[CEDULA ]],'OCTUBRE 2025'!$C$8:$J$10,8,0) -> #N/A | H8: =+VLOOKUP(Tabla3[[#This Row],[CEDULA ]],'Conversión-HE'!$C$20:$I$70,6,0) -> 0 | I8: =+VLOOKUP(Tabla3[[#This Row],[CEDULA ]],'Conversión-HE'!$C$20:$I$70,7,0) -> 0 | J8: =((G8/240)*1.5)*H8 -> #N/A | K8: =+((G8/240)*2)*I8 -> #N/A | L8: =+Tabla3[[#This Row],[US$]]+Tabla3[[#This Row],[US$,]] -> #N/A
B9: 2 | C9: 944405737 | D9: =+VLOOKUP(Tabla3[[#This Row],[CEDULA ]],'OCTUBRE 2025'!$C$8:$J$10,2,0) -> #N/A | E9: =+VLOOKUP(Tabla3[[#This Row],[CEDULA ]],'OCTUBRE 2025'!$C$8:$J$10,4,0) -> #N/A | F9: =+VLOOKUP(Tabla3[[#This Row],[CEDULA ]],'OCTUBRE 2025'!$C$8:$J$10,6,0) -> #N/A | G9: =+VLOOKUP(Tabla3[[#This Row],[CEDULA ]],'OCTUBRE 2025'!$C$8:$J$10,8,0) -> #N/A | H9: =+VLOOKUP(Tabla3[[#This Row],[CEDULA ]],'Conversión-HE'!$C$20:$I$70,6,0) -> 0 | I9: =+VLOOKUP(Tabla3[[#This Row],[CEDULA ]],'Conversión-HE'!$C$20:$I$70,7,0) -> 0 | J9: =((G9/240)*1.5)*H9 -> #N/A | K9: =+((G9/240)*2)*I9 -> #N/A | L9: =+Tabla3[[#This Row],[US$]]+Tabla3[[#This Row],[US$,]] -> #N/A
B10: 3 | C10: 604394502 | D10: =+VLOOKUP(Tabla3[[#This Row],[CEDULA ]],'OCTUBRE 2025'!$C$8:$J$10,2,0) -> #N/A | E10: =+VLOOKUP(Tabla3[[#This Row],[CEDULA ]],'OCTUBRE 2025'!$C$8:$J$10,4,0) -> #N/A | F10: =+VLOOKUP(Tabla3[[#This Row],[CEDULA ]],'OCTUBRE 2025'!$C$8:$J$10,6,0) -> #N/A | G10: =+VLOOKUP(Tabla3[[#This Row],[CEDULA ]],'OCTUBRE 2025'!$C$8:$J$10,8,0) -> #N/A | H10: =+VLOOKUP(Tabla3[[#This Row],[CEDULA ]],'Conversión-HE'!$C$20:$I$70,6,0) -> 0 | I10: =+VLOOKUP(Tabla3[[#This Row],[CEDULA ]],'Conversión-HE'!$C$20:$I$70,7,0) -> 0 | J10: =((G10/240)*1.5)*H10 -> #N/A | K10: =+((G10/240)*2)*I10 -> #N/A | L10: =+Tabla3[[#This Row],[US$]]+Tabla3[[#This Row],[US$,]] -> #N/A
B11: 4 | C11: 955741970 | D11: =+VLOOKUP(Tabla3[[#This Row],[CEDULA ]],'OCTUBRE 2025'!$C$8:$J$10,2,0) -> #N/A | E11: =+VLOOKUP(Tabla3[[#This Row],[CEDULA ]],'OCTUBRE 2025'!$C$8:$J$10,4,0) -> #N/A | F11: =+VLOOKUP(Tabla3[[#This Row],[CEDULA ]],'OCTUBRE 2025'!$C$8:$J$10,6,0) -> #N/A | G11: =+VLOOKUP(Tabla3[[#This Row],[CEDULA ]],'OCTUBRE 2025'!$C$8:$J$10,8,0) -> #N/A | H11: =+VLOOKUP(Tabla3[[#This Row],[CEDULA ]],'Conversión-HE'!$C$20:$I$70,6,0) -> 0 | I11: =+VLOOKUP(Tabla3[[#This Row],[CEDULA ]],'Conversión-HE'!$C$20:$I$70,7,0) -> 0 | J11: =((G11/240)*1.5)*H11 -> #N/A | K11: =+((G11/240)*2)*I11 -> #N/A | L11: =+Tabla3[[#This Row],[US$]]+Tabla3[[#This Row],[US$,]] -> #N/A
B12: 5 | C12: 0943964973 | D12: =+VLOOKUP(Tabla3[[#This Row],[CEDULA ]],'OCTUBRE 2025'!$C$8:$J$10,2,0) -> #N/A | E12: =+VLOOKUP(Tabla3[[#This Row],[CEDULA ]],'OCTUBRE 2025'!$C$8:$J$10,4,0) -> #N/A | F12: =+VLOOKUP(Tabla3[[#This Row],[CEDULA ]],'OCTUBRE 2025'!$C$8:$J$10,6,0) -> #N/A | G12: =+VLOOKUP(Tabla3[[#This Row],[CEDULA ]],'OCTUBRE 2025'!$C$8:$J$10,8,0) -> #N/A | H12: =+VLOOKUP(Tabla3[[#This Row],[CEDULA ]],'Conversión-HE'!$C$20:$I$70,6,0) -> 0 | I12: =+VLOOKUP(Tabla3[[#This Row],[CEDULA ]],'Conversión-HE'!$C$20:$I$70,7,0) -> 0 | J12: =((G12/240)*1.5)*H12 -> #N/A | K12: =+((G12/240)*2)*I12 -> #N/A | L12: =+Tabla3[[#This Row],[US$]]+Tabla3[[#This Row],[US$,]] -> #N/A
B13: 6 | C13: 944143148 | D13: =+VLOOKUP(Tabla3[[#This Row],[CEDULA ]],'OCTUBRE 2025'!$C$8:$J$10,2,0) -> #N/A | E13: =+VLOOKUP(Tabla3[[#This Row],[CEDULA ]],'OCTUBRE 2025'!$C$8:$J$10,4,0) -> #N/A | F13: =+VLOOKUP(Tabla3[[#This Row],[CEDULA ]],'OCTUBRE 2025'!$C$8:$J$10,6,0) -> #N/A | G13: =+VLOOKUP(Tabla3[[#This Row],[CEDULA ]],'OCTUBRE 2025'!$C$8:$J$10,8,0) -> #N/A | H13: =+VLOOKUP(Tabla3[[#This Row],[CEDULA ]],'Conversión-HE'!$C$20:$I$70,6,0) -> 0 | I13: =+VLOOKUP(Tabla3[[#This Row],[CEDULA ]],'Conversión-HE'!$C$20:$I$70,7,0) -> 0 | J13: =((G13/240)*1.5)*H13 -> #N/A | K13: =+((G13/240)*2)*I13 -> #N/A | L13: =+Tabla3[[#This Row],[US$]]+Tabla3[[#This Row],[US$,]] -> #N/A
B14: 7 | C14: 955325238 | D14: =+VLOOKUP(Tabla3[[#This Row],[CEDULA ]],'OCTUBRE 2025'!$C$8:$J$10,2,0) -> #N/A | E14: =+VLOOKUP(Tabla3[[#This Row],[CEDULA ]],'OCTUBRE 2025'!$C$8:$J$10,4,0) -> #N/A | F14: =+VLOOKUP(Tabla3[[#This Row],[CEDULA ]],'OCTUBRE 2025'!$C$8:$J$10,6,0) -> #N/A | G14: =+VLOOKUP(Tabla3[[#This Row],[CEDULA ]],'OCTUBRE 2025'!$C$8:$J$10,8,0) -> #N/A | H14: =+VLOOKUP(Tabla3[[#This Row],[CEDULA ]],'Conversión-HE'!$C$20:$I$70,6,0) -> 0 | I14: =+VLOOKUP(Tabla3[[#This Row],[CEDULA ]],'Conversión-HE'!$C$20:$I$70,7,0) -> 0 | J14: =((G14/240)*1.5)*H14 -> #N/A | K14: =+((G14/240)*2)*I14 -> #N/A | L14: =+Tabla3[[#This Row],[US$]]+Tabla3[[#This Row],[US$,]] -> #N/A
B15: 8 | C15: 914163654 | D15: =+VLOOKUP(Tabla3[[#This Row],[CEDULA ]],'OCTUBRE 2025'!$C$8:$J$10,2,0) -> #N/A | E15: =+VLOOKUP(Tabla3[[#This Row],[CEDULA ]],'OCTUBRE 2025'!$C$8:$J$10,4,0) -> #N/A | F15: =+VLOOKUP(Tabla3[[#This Row],[CEDULA ]],'OCTUBRE 2025'!$C$8:$J$10,6,0) -> #N/A | G15: =+VLOOKUP(Tabla3[[#This Row],[CEDULA ]],'OCTUBRE 2025'!$C$8:$J$10,8,0) -> #N/A | H15: =+VLOOKUP(Tabla3[[#This Row],[CEDULA ]],'Conversión-HE'!$C$20:$I$70,6,0) -> 0 | I15: =+VLOOKUP(Tabla3[[#This Row],[CEDULA ]],'Conversión-HE'!$C$20:$I$70,7,0) -> 0 | J15: =((G15/240)*1.5)*H15 -> #N/A | K15: =+((G15/240)*2)*I15 -> #N/A | L15: =+Tabla3[[#This Row],[US$]]+Tabla3[[#This Row],[US$,]] -> #N/A
B16: 9 | C16: 956668305 | D16: =+VLOOKUP(Tabla3[[#This Row],[CEDULA ]],'OCTUBRE 2025'!$C$8:$J$10,2,0) -> #N/A | E16: =+VLOOKUP(Tabla3[[#This Row],[CEDULA ]],'OCTUBRE 2025'!$C$8:$J$10,4,0) -> #N/A | F16: =+VLOOKUP(Tabla3[[#This Row],[CEDULA ]],'OCTUBRE 2025'!$C$8:$J$10,6,0) -> #N/A | G16: =+VLOOKUP(Tabla3[[#This Row],[CEDULA ]],'OCTUBRE 2025'!$C$8:$J$10,8,0) -> #N/A | H16: =+VLOOKUP(Tabla3[[#This Row],[CEDULA ]],'Conversión-HE'!$C$20:$I$70,6,0) -> 0 | I16: =+VLOOKUP(Tabla3[[#This Row],[CEDULA ]],'Conversión-HE'!$C$20:$I$70,7,0) -> 0 | J16: =((G16/240)*1.5)*H16 -> #N/A | K16: =+((G16/240)*2)*I16 -> #N/A | L16: =+Tabla3[[#This Row],[US$]]+Tabla3[[#This Row],[US$,]] -> #N/A
B17: 10 | C17: 0918741448 | D17: =+VLOOKUP(Tabla3[[#This Row],[CEDULA ]],'OCTUBRE 2025'!$C$8:$J$10,2,0) -> #N/A | E17: =+VLOOKUP(Tabla3[[#This Row],[CEDULA ]],'OCTUBRE 2025'!$C$8:$J$10,4,0) -> #N/A | F17: =+VLOOKUP(Tabla3[[#This Row],[CEDULA ]],'OCTUBRE 2025'!$C$8:$J$10,6,0) -> #N/A | G17: =+VLOOKUP(Tabla3[[#This Row],[CEDULA ]],'OCTUBRE 2025'!$C$8:$J$10,8,0) -> #N/A | H17: =+VLOOKUP(Tabla3[[#This Row],[CEDULA ]],'Conversión-HE'!$C$20:$I$70,6,0) -> 0 | I17: =+VLOOKUP(Tabla3[[#This Row],[CEDULA ]],'Conversión-HE'!$C$20:$I$70,7,0) -> 0 | J17: =((G17/240)*1.5)*H17 -> #N/A | K17: =+((G17/240)*2)*I17 -> #N/A | L17: =+Tabla3[[#This Row],[US$]]+Tabla3[[#This Row],[US$,]] -> #N/A
B18: 11 | C18: 931097620 | D18: =+VLOOKUP(Tabla3[[#This Row],[CEDULA ]],'OCTUBRE 2025'!$C$8:$J$10,2,0) -> #N/A | E18: =+VLOOKUP(Tabla3[[#This Row],[CEDULA ]],'OCTUBRE 2025'!$C$8:$J$10,4,0) -> #N/A | F18: =+VLOOKUP(Tabla3[[#This Row],[CEDULA ]],'OCTUBRE 2025'!$C$8:$J$10,6,0) -> #N/A | G18: =+VLOOKUP(Tabla3[[#This Row],[CEDULA ]],'OCTUBRE 2025'!$C$8:$J$10,8,0) -> #N/A | H18: =+VLOOKUP(Tabla3[[#This Row],[CEDULA ]],'Conversión-HE'!$C$20:$I$70,6,0) -> 0 | I18: =+VLOOKUP(Tabla3[[#This Row],[CEDULA ]],'Conversión-HE'!$C$20:$I$70,7,0) -> 0 | J18: =((G18/240)*1.5)*H18 -> #N/A | K18: =+((G18/240)*2)*I18 -> #N/A | L18: =+Tabla3[[#This Row],[US$]]+Tabla3[[#This Row],[US$,]] -> #N/A
B19: 12 | C19: 1105483422 | D19: =+VLOOKUP(Tabla3[[#This Row],[CEDULA ]],'OCTUBRE 2025'!$C$8:$J$10,2,0) -> #N/A | E19: =+VLOOKUP(Tabla3[[#This Row],[CEDULA ]],'OCTUBRE 2025'!$C$8:$J$10,4,0) -> #N/A | F19: =+VLOOKUP(Tabla3[[#This Row],[CEDULA ]],'OCTUBRE 2025'!$C$8:$J$10,6,0) -> #N/A | G19: =+VLOOKUP(Tabla3[[#This Row],[CEDULA ]],'OCTUBRE 2025'!$C$8:$J$10,8,0) -> #N/A | H19: =+VLOOKUP(Tabla3[[#This Row],[CEDULA ]],'Conversión-HE'!$C$20:$I$70,6,0) -> 0 | I19: =+VLOOKUP(Tabla3[[#This Row],[CEDULA ]],'Conversión-HE'!$C$20:$I$70,7,0) -> 0 | J19: =((G19/240)*1.5)*H19 -> #N/A | K19: =+((G19/240)*2)*I19 -> #N/A | L19: =+Tabla3[[#This Row],[US$]]+Tabla3[[#This Row],[US$,]] -> #N/A
B20: 13 | C20: 942614645 | D20: =+VLOOKUP(Tabla3[[#This Row],[CEDULA ]],'OCTUBRE 2025'!$C$8:$J$10,2,0) -> #N/A | E20: =+VLOOKUP(Tabla3[[#This Row],[CEDULA ]],'OCTUBRE 2025'!$C$8:$J$10,4,0) -> #N/A | F20: =+VLOOKUP(Tabla3[[#This Row],[CEDULA ]],'OCTUBRE 2025'!$C$8:$J$10,6,0) -> #N/A | G20: =+VLOOKUP(Tabla3[[#This Row],[CEDULA ]],'OCTUBRE 2025'!$C$8:$J$10,8,0) -> #N/A | H20: =+VLOOKUP(Tabla3[[#This Row],[CEDULA ]],'Conversión-HE'!$C$20:$I$70,6,0) -> 0 | I20: =+VLOOKUP(Tabla3[[#This Row],[CEDULA ]],'Conversión-HE'!$C$20:$I$70,7,0) -> 0 | J20: =((G20/240)*1.5)*H20 -> #N/A | K20: =+((G20/240)*2)*I20 -> #N/A | L20: =+Tabla3[[#This Row],[US$]]+Tabla3[[#This Row],[US$,]] -> #N/A
B21: 14 | C21: 951200062 | D21: =+VLOOKUP(Tabla3[[#This Row],[CEDULA ]],'OCTUBRE 2025'!$C$8:$J$10,2,0) -> #N/A | E21: =+VLOOKUP(Tabla3[[#This Row],[CEDULA ]],'OCTUBRE 2025'!$C$8:$J$10,4,0) -> #N/A | F21: =+VLOOKUP(Tabla3[[#This Row],[CEDULA ]],'OCTUBRE 2025'!$C$8:$J$10,6,0) -> #N/A | G21: =+VLOOKUP(Tabla3[[#This Row],[CEDULA ]],'OCTUBRE 2025'!$C$8:$J$10,8,0) -> #N/A | H21: =+VLOOKUP(Tabla3[[#This Row],[CEDULA ]],'Conversión-HE'!$C$20:$I$70,6,0) -> 0 | I21: =+VLOOKUP(Tabla3[[#This Row],[CEDULA ]],'Conversión-HE'!$C$20:$I$70,7,0) -> 0 | J21: =((G21/240)*1.5)*H21 -> #N/A | K21: =+((G21/240)*2)*I21 -> #N/A | L21: =+Tabla3[[#This Row],[US$]]+Tabla3[[#This Row],[US$,]] -> #N/A
B22: 15 | C22: 950929232 | D22: =+VLOOKUP(Tabla3[[#This Row],[CEDULA ]],'OCTUBRE 2025'!$C$8:$J$10,2,0) -> #N/A | E22: =+VLOOKUP(Tabla3[[#This Row],[CEDULA ]],'OCTUBRE 2025'!$C$8:$J$10,4,0) -> #N/A | F22: =+VLOOKUP(Tabla3[[#This Row],[CEDULA ]],'OCTUBRE 2025'!$C$8:$J$10,6,0) -> #N/A | G22: =+VLOOKUP(Tabla3[[#This Row],[CEDULA ]],'OCTUBRE 2025'!$C$8:$J$10,8,0) -> #N/A | H22: =+VLOOKUP(Tabla3[[#This Row],[CEDULA ]],'Conversión-HE'!$C$20:$I$70,6,0) -> 0 | I22: =+VLOOKUP(Tabla3[[#This Row],[CEDULA ]],'Conversión-HE'!$C$20:$I$70,7,0) -> 0 | J22: =((G22/240)*1.5)*H22 -> #N/A | K22: =+((G22/240)*2)*I22 -> #N/A | L22: =+Tabla3[[#This Row],[US$]]+Tabla3[[#This Row],[US$,]] -> #N/A
B23: 16 | C23: 953819646 | D23: =+VLOOKUP(Tabla3[[#This Row],[CEDULA ]],'OCTUBRE 2025'!$C$8:$J$10,2,0) -> #N/A | E23: =+VLOOKUP(Tabla3[[#This Row],[CEDULA ]],'OCTUBRE 2025'!$C$8:$J$10,4,0) -> #N/A | F23: =+VLOOKUP(Tabla3[[#This Row],[CEDULA ]],'OCTUBRE 2025'!$C$8:$J$10,6,0) -> #N/A | G23: =+VLOOKUP(Tabla3[[#This Row],[CEDULA ]],'OCTUBRE 2025'!$C$8:$J$10,8,0) -> #N/A | H23: =+VLOOKUP(Tabla3[[#This Row],[CEDULA ]],'Conversión-HE'!$C$20:$I$70,6,0) -> 0 | I23: =+VLOOKUP(Tabla3[[#This Row],[CEDULA ]],'Conversión-HE'!$C$20:$I$70,7,0) -> 0 | J23: =((G23/240)*1.5)*H23 -> #N/A | K23: =+((G23/240)*2)*I23 -> #N/A | L23: =+Tabla3[[#This Row],[US$]]+Tabla3[[#This Row],[US$,]] -> #N/A
B24: 17 | C24: 956953392 | D24: =+VLOOKUP(Tabla3[[#This Row],[CEDULA ]],'OCTUBRE 2025'!$C$8:$J$10,2,0) -> #N/A | E24: =+VLOOKUP(Tabla3[[#This Row],[CEDULA ]],'OCTUBRE 2025'!$C$8:$J$10,4,0) -> #N/A | F24: =+VLOOKUP(Tabla3[[#This Row],[CEDULA ]],'OCTUBRE 2025'!$C$8:$J$10,6,0) -> #N/A | G24: =+VLOOKUP(Tabla3[[#This Row],[CEDULA ]],'OCTUBRE 2025'!$C$8:$J$10,8,0) -> #N/A | H24: =+VLOOKUP(Tabla3[[#This Row],[CEDULA ]],'Conversión-HE'!$C$20:$I$70,6,0) -> 0 | I24: =+VLOOKUP(Tabla3[[#This Row],[CEDULA ]],'Conversión-HE'!$C$20:$I$70,7,0) -> 0 | J24: =((G24/240)*1.5)*H24 -> #N/A | K24: =+((G24/240)*2)*I24 -> #N/A | L24: =+Tabla3[[#This Row],[US$]]+Tabla3[[#This Row],[US$,]] -> #N/A
B25: 18 | C25: 956796767 | D25: =+VLOOKUP(Tabla3[[#This Row],[CEDULA ]],'OCTUBRE 2025'!$C$8:$J$10,2,0) -> #N/A | E25: =+VLOOKUP(Tabla3[[#This Row],[CEDULA ]],'OCTUBRE 2025'!$C$8:$J$10,4,0) -> #N/A | F25: =+VLOOKUP(Tabla3[[#This Row],[CEDULA ]],'OCTUBRE 2025'!$C$8:$J$10,6,0) -> #N/A | G25: =+VLOOKUP(Tabla3[[#This Row],[CEDULA ]],'OCTUBRE 2025'!$C$8:$J$10,8,0) -> #N/A | H25: =+VLOOKUP(Tabla3[[#This Row],[CEDULA ]],'Conversión-HE'!$C$20:$I$70,6,0) -> 0 | I25: =+VLOOKUP(Tabla3[[#This Row],[CEDULA ]],'Conversión-HE'!$C$20:$I$70,7,0) -> 0 | J25: =((G25/240)*1.5)*H25 -> #N/A | K25: =+((G25/240)*2)*I25 -> #N/A | L25: =+Tabla3[[#This Row],[US$]]+Tabla3[[#This Row],[US$,]] -> #N/A
B26: 19 | C26: 0932036049 | D26: =+VLOOKUP(Tabla3[[#This Row],[CEDULA ]],'OCTUBRE 2025'!$C$8:$J$10,2,0) -> #N/A | E26: =+VLOOKUP(Tabla3[[#This Row],[CEDULA ]],'OCTUBRE 2025'!$C$8:$J$10,4,0) -> #N/A | F26: =+VLOOKUP(Tabla3[[#This Row],[CEDULA ]],'OCTUBRE 2025'!$C$8:$J$10,6,0) -> #N/A | G26: =+VLOOKUP(Tabla3[[#This Row],[CEDULA ]],'OCTUBRE 2025'!$C$8:$J$10,8,0) -> #N/A | H26: =+VLOOKUP(Tabla3[[#This Row],[CEDULA ]],'Conversión-HE'!$C$20:$I$70,6,0) -> 0 | I26: =+VLOOKUP(Tabla3[[#This Row],[CEDULA ]],'Conversión-HE'!$C$20:$I$70,7,0) -> 0 | J26: =((G26/240)*1.5)*H26 -> #N/A | K26: =+((G26/240)*2)*I26 -> #N/A | L26: =+Tabla3[[#This Row],[US$]]+Tabla3[[#This Row],[US$,]] -> #N/A
B27: 20 | C27: 1724102940 | D27: =+VLOOKUP(Tabla3[[#This Row],[CEDULA ]],'OCTUBRE 2025'!$C$8:$J$10,2,0) -> #N/A | E27: =+VLOOKUP(Tabla3[[#This Row],[CEDULA ]],'OCTUBRE 2025'!$C$8:$J$10,4,0) -> #N/A | F27: =+VLOOKUP(Tabla3[[#This Row],[CEDULA ]],'OCTUBRE 2025'!$C$8:$J$10,6,0) -> #N/A | G27: =+VLOOKUP(Tabla3[[#This Row],[CEDULA ]],'OCTUBRE 2025'!$C$8:$J$10,8,0) -> #N/A | H27: =+VLOOKUP(Tabla3[[#This Row],[CEDULA ]],'Conversión-HE'!$C$20:$I$70,6,0) -> 0 | I27: =+VLOOKUP(Tabla3[[#This Row],[CEDULA ]],'Conversión-HE'!$C$20:$I$70,7,0) -> 0 | J27: =((G27/240)*1.5)*H27 -> #N/A | K27: =+((G27/240)*2)*I27 -> #N/A | L27: =+Tabla3[[#This Row],[US$]]+Tabla3[[#This Row],[US$,]] -> #N/A
B28: 21 | C28: 943322974 | D28: =+VLOOKUP(Tabla3[[#This Row],[CEDULA ]],'OCTUBRE 2025'!$C$8:$J$10,2,0) -> #N/A | E28: =+VLOOKUP(Tabla3[[#This Row],[CEDULA ]],'OCTUBRE 2025'!$C$8:$J$10,4,0) -> #N/A | F28: =+VLOOKUP(Tabla3[[#This Row],[CEDULA ]],'OCTUBRE 2025'!$C$8:$J$10,6,0) -> #N/A | G28: =+VLOOKUP(Tabla3[[#This Row],[CEDULA ]],'OCTUBRE 2025'!$C$8:$J$10,8,0) -> #N/A | H28: =+VLOOKUP(Tabla3[[#This Row],[CEDULA ]],'Conversión-HE'!$C$20:$I$70,6,0) -> 0 | I28: =+VLOOKUP(Tabla3[[#This Row],[CEDULA ]],'Conversión-HE'!$C$20:$I$70,7,0) -> 0 | J28: =((G28/240)*1.5)*H28 -> #N/A | K28: =+((G28/240)*2)*I28 -> #N/A | L28: =+Tabla3[[#This Row],[US$]]+Tabla3[[#This Row],[US$,]] -> #N/A
B29: 22 | C29: 941096851 | D29: =+VLOOKUP(Tabla3[[#This Row],[CEDULA ]],'OCTUBRE 2025'!$C$8:$J$10,2,0) -> #N/A | E29: =+VLOOKUP(Tabla3[[#This Row],[CEDULA ]],'OCTUBRE 2025'!$C$8:$J$10,4,0) -> #N/A | F29: =+VLOOKUP(Tabla3[[#This Row],[CEDULA ]],'OCTUBRE 2025'!$C$8:$J$10,6,0) -> #N/A | G29: =+VLOOKUP(Tabla3[[#This Row],[CEDULA ]],'OCTUBRE 2025'!$C$8:$J$10,8,0) -> #N/A | H29: =+VLOOKUP(Tabla3[[#This Row],[CEDULA ]],'Conversión-HE'!$C$20:$I$70,6,0) -> 0 | I29: =+VLOOKUP(Tabla3[[#This Row],[CEDULA ]],'Conversión-HE'!$C$20:$I$70,7,0) -> 0 | J29: =((G29/240)*1.5)*H29 -> #N/A | K29: =+((G29/240)*2)*I29 -> #N/A | L29: =+Tabla3[[#This Row],[US$]]+Tabla3[[#This Row],[US$,]] -> #N/A
B30: 23 | C30: 957093800 | D30: =+VLOOKUP(Tabla3[[#This Row],[CEDULA ]],'OCTUBRE 2025'!$C$8:$J$10,2,0) -> #N/A | E30: =+VLOOKUP(Tabla3[[#This Row],[CEDULA ]],'OCTUBRE 2025'!$C$8:$J$10,4,0) -> #N/A | F30: =+VLOOKUP(Tabla3[[#This Row],[CEDULA ]],'OCTUBRE 2025'!$C$8:$J$10,6,0) -> #N/A | G30: =+VLOOKUP(Tabla3[[#This Row],[CEDULA ]],'OCTUBRE 2025'!$C$8:$J$10,8,0) -> #N/A | H30: =+VLOOKUP(Tabla3[[#This Row],[CEDULA ]],'Conversión-HE'!$C$20:$I$70,6,0) -> 0 | I30: =+VLOOKUP(Tabla3[[#This Row],[CEDULA ]],'Conversión-HE'!$C$20:$I$70,7,0) -> 0 | J30: =((G30/240)*1.5)*H30 -> #N/A | K30: =+((G30/240)*2)*I30 -> #N/A | L30: =+Tabla3[[#This Row],[US$]]+Tabla3[[#This Row],[US$,]] -> #N/A
B31: 24 | C31: 957924350 | D31: =+VLOOKUP(Tabla3[[#This Row],[CEDULA ]],'OCTUBRE 2025'!$C$8:$J$10,2,0) -> #N/A | E31: =+VLOOKUP(Tabla3[[#This Row],[CEDULA ]],'OCTUBRE 2025'!$C$8:$J$10,4,0) -> #N/A | F31: =+VLOOKUP(Tabla3[[#This Row],[CEDULA ]],'OCTUBRE 2025'!$C$8:$J$10,6,0) -> #N/A | G31: =+VLOOKUP(Tabla3[[#This Row],[CEDULA ]],'OCTUBRE 2025'!$C$8:$J$10,8,0) -> #N/A | H31: =+VLOOKUP(Tabla3[[#This Row],[CEDULA ]],'Conversión-HE'!$C$20:$I$70,6,0) -> 0 | I31: =+VLOOKUP(Tabla3[[#This Row],[CEDULA ]],'Conversión-HE'!$C$20:$I$70,7,0) -> 0 | J31: =((G31/240)*1.5)*H31 -> #N/A | K31: =+((G31/240)*2)*I31 -> #N/A | L31: =+Tabla3[[#This Row],[US$]]+Tabla3[[#This Row],[US$,]] -> #N/A
B32: 25 | C32: 603838657 | D32: =+VLOOKUP(Tabla3[[#This Row],[CEDULA ]],'OCTUBRE 2025'!$C$8:$J$10,2,0) -> #N/A | E32: =+VLOOKUP(Tabla3[[#This Row],[CEDULA ]],'OCTUBRE 2025'!$C$8:$J$10,4,0) -> #N/A | F32: =+VLOOKUP(Tabla3[[#This Row],[CEDULA ]],'OCTUBRE 2025'!$C$8:$J$10,6,0) -> #N/A | G32: =+VLOOKUP(Tabla3[[#This Row],[CEDULA ]],'OCTUBRE 2025'!$C$8:$J$10,8,0) -> #N/A | H32: =+VLOOKUP(Tabla3[[#This Row],[CEDULA ]],'Conversión-HE'!$C$20:$I$70,6,0) -> 0 | I32: =+VLOOKUP(Tabla3[[#This Row],[CEDULA ]],'Conversión-HE'!$C$20:$I$70,7,0) -> 0 | J32: =((G32/240)*1.5)*H32 -> #N/A | K32: =+((G32/240)*2)*I32 -> #N/A | L32: =+Tabla3[[#This Row],[US$]]+Tabla3[[#This Row],[US$,]] -> #N/A
B33: 26 | C33: 925240525 | D33: =+VLOOKUP(Tabla3[[#This Row],[CEDULA ]],'OCTUBRE 2025'!$C$8:$J$10,2,0) -> #N/A | E33: =+VLOOKUP(Tabla3[[#This Row],[CEDULA ]],'OCTUBRE 2025'!$C$8:$J$10,4,0) -> #N/A | F33: =+VLOOKUP(Tabla3[[#This Row],[CEDULA ]],'OCTUBRE 2025'!$C$8:$J$10,6,0) -> #N/A | G33: =+VLOOKUP(Tabla3[[#This Row],[CEDULA ]],'OCTUBRE 2025'!$C$8:$J$10,8,0) -> #N/A | H33: =+VLOOKUP(Tabla3[[#This Row],[CEDULA ]],'Conversión-HE'!$C$20:$I$70,6,0) -> 0 | I33: =+VLOOKUP(Tabla3[[#This Row],[CEDULA ]],'Conversión-HE'!$C$20:$I$70,7,0) -> 0 | J33: =((G33/240)*1.5)*H33 -> #N/A | K33: =+((G33/240)*2)*I33 -> #N/A | L33: =+Tabla3[[#This Row],[US$]]+Tabla3[[#This Row],[US$,]] -> #N/A
B34: 27 | C34: 954520599 | D34: =+VLOOKUP(Tabla3[[#This Row],[CEDULA ]],'OCTUBRE 2025'!$C$8:$J$10,2,0) -> #N/A | E34: =+VLOOKUP(Tabla3[[#This Row],[CEDULA ]],'OCTUBRE 2025'!$C$8:$J$10,4,0) -> #N/A | F34: =+VLOOKUP(Tabla3[[#This Row],[CEDULA ]],'OCTUBRE 2025'!$C$8:$J$10,6,0) -> #N/A | G34: =+VLOOKUP(Tabla3[[#This Row],[CEDULA ]],'OCTUBRE 2025'!$C$8:$J$10,8,0) -> #N/A | H34: =+VLOOKUP(Tabla3[[#This Row],[CEDULA ]],'Conversión-HE'!$C$20:$I$70,6,0) -> 0 | I34: =+VLOOKUP(Tabla3[[#This Row],[CEDULA ]],'Conversión-HE'!$C$20:$I$70,7,0) -> 0 | J34: =((G34/240)*1.5)*H34 -> #N/A | K34: =+((G34/240)*2)*I34 -> #N/A | L34: =+Tabla3[[#This Row],[US$]]+Tabla3[[#This Row],[US$,]] -> #N/A
B35: 28 | C35: 0943906032 | D35: =+VLOOKUP(Tabla3[[#This Row],[CEDULA ]],'OCTUBRE 2025'!$C$8:$J$10,2,0) -> #N/A | E35: =+VLOOKUP(Tabla3[[#This Row],[CEDULA ]],'OCTUBRE 2025'!$C$8:$J$10,4,0) -> #N/A | F35: =+VLOOKUP(Tabla3[[#This Row],[CEDULA ]],'OCTUBRE 2025'!$C$8:$J$10,6,0) -> #N/A | G35: =+VLOOKUP(Tabla3[[#This Row],[CEDULA ]],'OCTUBRE 2025'!$C$8:$J$10,8,0) -> #N/A | H35: =+VLOOKUP(Tabla3[[#This Row],[CEDULA ]],'Conversión-HE'!$C$20:$I$70,6,0) -> 0 | I35: =+VLOOKUP(Tabla3[[#This Row],[CEDULA ]],'Conversión-HE'!$C$20:$I$70,7,0) -> 0 | J35: =((G35/240)*1.5)*H35 -> #N/A | K35: =+((G35/240)*2)*I35 -> #N/A | L35: =+Tabla3[[#This Row],[US$]]+Tabla3[[#This Row],[US$,]] -> #N/A
B36: 29 | C36: 0919306050 | D36: =+VLOOKUP(Tabla3[[#This Row],[CEDULA ]],'OCTUBRE 2025'!$C$8:$J$10,2,0) -> #N/A | E36: =+VLOOKUP(Tabla3[[#This Row],[CEDULA ]],'OCTUBRE 2025'!$C$8:$J$10,4,0) -> #N/A | F36: =+VLOOKUP(Tabla3[[#This Row],[CEDULA ]],'OCTUBRE 2025'!$C$8:$J$10,6,0) -> #N/A | G36: =+VLOOKUP(Tabla3[[#This Row],[CEDULA ]],'OCTUBRE 2025'!$C$8:$J$10,8,0) -> #N/A | H36: =+VLOOKUP(Tabla3[[#This Row],[CEDULA ]],'Conversión-HE'!$C$20:$I$70,6,0) -> 0 | I36: =+VLOOKUP(Tabla3[[#This Row],[CEDULA ]],'Conversión-HE'!$C$20:$I$70,7,0) -> 0 | J36: =((G36/240)*1.5)*H36 -> #N/A | K36: =+((G36/240)*2)*I36 -> #N/A | L36: =+Tabla3[[#This Row],[US$]]+Tabla3[[#This Row],[US$,]] -> #N/A
B37: 30 | C37: 0941235376 | D37: =+VLOOKUP(Tabla3[[#This Row],[CEDULA ]],'OCTUBRE 2025'!$C$8:$J$10,2,0) -> #N/A | E37: =+VLOOKUP(Tabla3[[#This Row],[CEDULA ]],'OCTUBRE 2025'!$C$8:$J$10,4,0) -> #N/A | F37: =+VLOOKUP(Tabla3[[#This Row],[CEDULA ]],'OCTUBRE 2025'!$C$8:$J$10,6,0) -> #N/A | G37: =+VLOOKUP(Tabla3[[#This Row],[CEDULA ]],'OCTUBRE 2025'!$C$8:$J$10,8,0) -> #N/A | H37: =+VLOOKUP(Tabla3[[#This Row],[CEDULA ]],'Conversión-HE'!$C$20:$I$70,6,0) -> 0 | I37: =+VLOOKUP(Tabla3[[#This Row],[CEDULA ]],'Conversión-HE'!$C$20:$I$70,7,0) -> 0 | J37: =((G37/240)*1.5)*H37 -> #N/A | K37: =+((G37/240)*2)*I37 -> #N/A | L37: =+Tabla3[[#This Row],[US$]]+Tabla3[[#This Row],[US$,]] -> #N/A
B38: 31 | C38: 955395686 | D38: =+VLOOKUP(Tabla3[[#This Row],[CEDULA ]],'OCTUBRE 2025'!$C$8:$J$10,2,0) -> #N/A | E38: =+VLOOKUP(Tabla3[[#This Row],[CEDULA ]],'OCTUBRE 2025'!$C$8:$J$10,4,0) -> #N/A | F38: =+VLOOKUP(Tabla3[[#This Row],[CEDULA ]],'OCTUBRE 2025'!$C$8:$J$10,6,0) -> #N/A | G38: =+VLOOKUP(Tabla3[[#This Row],[CEDULA ]],'OCTUBRE 2025'!$C$8:$J$10,8,0) -> #N/A | H38: =+VLOOKUP(Tabla3[[#This Row],[CEDULA ]],'Conversión-HE'!$C$20:$I$70,6,0) -> 0 | I38: =+VLOOKUP(Tabla3[[#This Row],[CEDULA ]],'Conversión-HE'!$C$20:$I$70,7,0) -> 0 | J38: =((G38/240)*1.5)*H38 -> #N/A | K38: =+((G38/240)*2)*I38 -> #N/A | L38: =+Tabla3[[#This Row],[US$]]+Tabla3[[#This Row],[US$,]] -> #N/A
B39: 32 | C39: 940991987 | D39: =+VLOOKUP(Tabla3[[#This Row],[CEDULA ]],'OCTUBRE 2025'!$C$8:$J$10,2,0) -> #N/A | E39: =+VLOOKUP(Tabla3[[#This Row],[CEDULA ]],'OCTUBRE 2025'!$C$8:$J$10,4,0) -> #N/A | F39: =+VLOOKUP(Tabla3[[#This Row],[CEDULA ]],'OCTUBRE 2025'!$C$8:$J$10,6,0) -> #N/A | G39: =+VLOOKUP(Tabla3[[#This Row],[CEDULA ]],'OCTUBRE 2025'!$C$8:$J$10,8,0) -> #N/A | H39: =+VLOOKUP(Tabla3[[#This Row],[CEDULA ]],'Conversión-HE'!$C$20:$I$70,6,0) -> 0 | I39: =+VLOOKUP(Tabla3[[#This Row],[CEDULA ]],'Conversión-HE'!$C$20:$I$70,7,0) -> 0 | J39: =((G39/240)*1.5)*H39 -> #N/A | K39: =+((G39/240)*2)*I39 -> #N/A | L39: =+Tabla3[[#This Row],[US$]]+Tabla3[[#This Row],[US$,]] -> #N/A
B40: 33 | C40: 956929277 | D40: =+VLOOKUP(Tabla3[[#This Row],[CEDULA ]],'OCTUBRE 2025'!$C$8:$J$10,2,0) -> #N/A | E40: =+VLOOKUP(Tabla3[[#This Row],[CEDULA ]],'OCTUBRE 2025'!$C$8:$J$10,4,0) -> #N/A | F40: =+VLOOKUP(Tabla3[[#This Row],[CEDULA ]],'OCTUBRE 2025'!$C$8:$J$10,6,0) -> #N/A | G40: =+VLOOKUP(Tabla3[[#This Row],[CEDULA ]],'OCTUBRE 2025'!$C$8:$J$10,8,0) -> #N/A | H40: =+VLOOKUP(Tabla3[[#This Row],[CEDULA ]],'Conversión-HE'!$C$20:$I$70,6,0) -> 0 | I40: =+VLOOKUP(Tabla3[[#This Row],[CEDULA ]],'Conversión-HE'!$C$20:$I$70,7,0) -> 0 | J40: =((G40/240)*1.5)*H40 -> #N/A | K40: =+((G40/240)*2)*I40 -> #N/A | L40: =+Tabla3[[#This Row],[US$]]+Tabla3[[#This Row],[US$,]] -> #N/A
B41: 34 | C41: 951763994 | D41: =+VLOOKUP(Tabla3[[#This Row],[CEDULA ]],'OCTUBRE 2025'!$C$8:$J$10,2,0) -> #N/A | E41: =+VLOOKUP(Tabla3[[#This Row],[CEDULA ]],'OCTUBRE 2025'!$C$8:$J$10,4,0) -> #N/A | F41: =+VLOOKUP(Tabla3[[#This Row],[CEDULA ]],'OCTUBRE 2025'!$C$8:$J$10,6,0) -> #N/A | G41: =+VLOOKUP(Tabla3[[#This Row],[CEDULA ]],'OCTUBRE 2025'!$C$8:$J$10,8,0) -> #N/A | H41: =+VLOOKUP(Tabla3[[#This Row],[CEDULA ]],'Conversión-HE'!$C$20:$I$70,6,0) -> 0 | I41: =+VLOOKUP(Tabla3[[#This Row],[CEDULA ]],'Conversión-HE'!$C$20:$I$70,7,0) -> 0 | J41: =((G41/240)*1.5)*H41 -> #N/A | K41: =+((G41/240)*2)*I41 -> #N/A | L41: =+Tabla3[[#This Row],[US$]]+Tabla3[[#This Row],[US$,]] -> #N/A
B42: 35 | C42: 950703199 | D42: =+VLOOKUP(Tabla3[[#This Row],[CEDULA ]],'OCTUBRE 2025'!$C$8:$J$10,2,0) -> #N/A | E42: =+VLOOKUP(Tabla3[[#This Row],[CEDULA ]],'OCTUBRE 2025'!$C$8:$J$10,4,0) -> #N/A | F42: =+VLOOKUP(Tabla3[[#This Row],[CEDULA ]],'OCTUBRE 2025'!$C$8:$J$10,6,0) -> #N/A | G42: =+VLOOKUP(Tabla3[[#This Row],[CEDULA ]],'OCTUBRE 2025'!$C$8:$J$10,8,0) -> #N/A | H42: =+VLOOKUP(Tabla3[[#This Row],[CEDULA ]],'Conversión-HE'!$C$20:$I$70,6,0) -> 0 | I42: =+VLOOKUP(Tabla3[[#This Row],[CEDULA ]],'Conversión-HE'!$C$20:$I$70,7,0) -> 0 | J42: =((G42/240)*1.5)*H42 -> #N/A | K42: =+((G42/240)*2)*I42 -> #N/A | L42: =+Tabla3[[#This Row],[US$]]+Tabla3[[#This Row],[US$,]] -> #N/A
B43: 36 | C43: 0923715692 | D43: =+VLOOKUP(Tabla3[[#This Row],[CEDULA ]],'OCTUBRE 2025'!$C$8:$J$10,2,0) -> #N/A | E43: =+VLOOKUP(Tabla3[[#This Row],[CEDULA ]],'OCTUBRE 2025'!$C$8:$J$10,4,0) -> #N/A | F43: =+VLOOKUP(Tabla3[[#This Row],[CEDULA ]],'OCTUBRE 2025'!$C$8:$J$10,6,0) -> #N/A | G43: =+VLOOKUP(Tabla3[[#This Row],[CEDULA ]],'OCTUBRE 2025'!$C$8:$J$10,8,0) -> #N/A | H43: =+VLOOKUP(Tabla3[[#This Row],[CEDULA ]],'Conversión-HE'!$C$20:$I$70,6,0) -> 0 | I43: =+VLOOKUP(Tabla3[[#This Row],[CEDULA ]],'Conversión-HE'!$C$20:$I$70,7,0) -> 0 | J43: =((G43/240)*1.5)*H43 -> #N/A | K43: =+((G43/240)*2)*I43 -> #N/A | L43: =+Tabla3[[#This Row],[US$]]+Tabla3[[#This Row],[US$,]] -> #N/A
B44: 37 | C44: 925830689 | D44: =+VLOOKUP(Tabla3[[#This Row],[CEDULA ]],'OCTUBRE 2025'!$C$8:$J$10,2,0) -> #N/A | E44: =+VLOOKUP(Tabla3[[#This Row],[CEDULA ]],'OCTUBRE 2025'!$C$8:$J$10,4,0) -> #N/A | F44: =+VLOOKUP(Tabla3[[#This Row],[CEDULA ]],'OCTUBRE 2025'!$C$8:$J$10,6,0) -> #N/A | G44: =+VLOOKUP(Tabla3[[#This Row],[CEDULA ]],'OCTUBRE 2025'!$C$8:$J$10,8,0) -> #N/A | H44: =+VLOOKUP(Tabla3[[#This Row],[CEDULA ]],'Conversión-HE'!$C$20:$I$70,6,0) -> 0 | I44: =+VLOOKUP(Tabla3[[#This Row],[CEDULA ]],'Conversión-HE'!$C$20:$I$70,7,0) -> 0 | J44: =((G44/240)*1.5)*H44 -> #N/A | K44: =+((G44/240)*2)*I44 -> #N/A | L44: =+Tabla3[[#This Row],[US$]]+Tabla3[[#This Row],[US$,]] -> #N/A
B45: 38 | C45: 944034842 | D45: =+VLOOKUP(Tabla3[[#This Row],[CEDULA ]],'OCTUBRE 2025'!$C$8:$J$10,2,0) -> #N/A | E45: =+VLOOKUP(Tabla3[[#This Row],[CEDULA ]],'OCTUBRE 2025'!$C$8:$J$10,4,0) -> #N/A | F45: =+VLOOKUP(Tabla3[[#This Row],[CEDULA ]],'OCTUBRE 2025'!$C$8:$J$10,6,0) -> #N/A | G45: =+VLOOKUP(Tabla3[[#This Row],[CEDULA ]],'OCTUBRE 2025'!$C$8:$J$10,8,0) -> #N/A | H45: =+VLOOKUP(Tabla3[[#This Row],[CEDULA ]],'Conversión-HE'!$C$20:$I$70,6,0) -> 0 | I45: =+VLOOKUP(Tabla3[[#This Row],[CEDULA ]],'Conversión-HE'!$C$20:$I$70,7,0) -> 0 | J45: =((G45/240)*1.5)*H45 -> #N/A | K45: =+((G45/240)*2)*I45 -> #N/A | L45: =+Tabla3[[#This Row],[US$]]+Tabla3[[#This Row],[US$,]] -> #N/A
B46: 39 | C46: 951340702 | D46: =+VLOOKUP(Tabla3[[#This Row],[CEDULA ]],'OCTUBRE 2025'!$C$8:$J$10,2,0) -> #N/A | E46: =+VLOOKUP(Tabla3[[#This Row],[CEDULA ]],'OCTUBRE 2025'!$C$8:$J$10,4,0) -> #N/A | F46: =+VLOOKUP(Tabla3[[#This Row],[CEDULA ]],'OCTUBRE 2025'!$C$8:$J$10,6,0) -> #N/A | G46: =+VLOOKUP(Tabla3[[#This Row],[CEDULA ]],'OCTUBRE 2025'!$C$8:$J$10,8,0) -> #N/A | H46: =+VLOOKUP(Tabla3[[#This Row],[CEDULA ]],'Conversión-HE'!$C$20:$I$70,6,0) -> 0 | I46: =+VLOOKUP(Tabla3[[#This Row],[CEDULA ]],'Conversión-HE'!$C$20:$I$70,7,0) -> 0 | J46: =((G46/240)*1.5)*H46 -> #N/A | K46: =+((G46/240)*2)*I46 -> #N/A | L46: =+Tabla3[[#This Row],[US$]]+Tabla3[[#This Row],[US$,]] -> #N/A
B47: 40 | C47: 650112949 | D47: =+VLOOKUP(Tabla3[[#This Row],[CEDULA ]],'OCTUBRE 2025'!$C$8:$J$10,2,0) -> #N/A | E47: =+VLOOKUP(Tabla3[[#This Row],[CEDULA ]],'OCTUBRE 2025'!$C$8:$J$10,4,0) -> #N/A | F47: =+VLOOKUP(Tabla3[[#This Row],[CEDULA ]],'OCTUBRE 2025'!$C$8:$J$10,6,0) -> #N/A | G47: =+VLOOKUP(Tabla3[[#This Row],[CEDULA ]],'OCTUBRE 2025'!$C$8:$J$10,8,0) -> #N/A | H47: =+VLOOKUP(Tabla3[[#This Row],[CEDULA ]],'Conversión-HE'!$C$20:$I$70,6,0) -> 0 | I47: =+VLOOKUP(Tabla3[[#This Row],[CEDULA ]],'Conversión-HE'!$C$20:$I$70,7,0) -> 0 | J47: =((G47/240)*1.5)*H47 -> #N/A | K47: =+((G47/240)*2)*I47 -> #N/A | L47: =+Tabla3[[#This Row],[US$]]+Tabla3[[#This Row],[US$,]] -> #N/A
B48: 41 | C48: 924232804 | D48: =+VLOOKUP(Tabla3[[#This Row],[CEDULA ]],'OCTUBRE 2025'!$C$8:$J$10,2,0) -> #N/A | E48: =+VLOOKUP(Tabla3[[#This Row],[CEDULA ]],'OCTUBRE 2025'!$C$8:$J$10,4,0) -> #N/A | F48: =+VLOOKUP(Tabla3[[#This Row],[CEDULA ]],'OCTUBRE 2025'!$C$8:$J$10,6,0) -> #N/A | G48: =+VLOOKUP(Tabla3[[#This Row],[CEDULA ]],'OCTUBRE 2025'!$C$8:$J$10,8,0) -> #N/A | H48: =+VLOOKUP(Tabla3[[#This Row],[CEDULA ]],'Conversión-HE'!$C$20:$I$70,6,0) -> 0 | I48: =+VLOOKUP(Tabla3[[#This Row],[CEDULA ]],'Conversión-HE'!$C$20:$I$70,7,0) -> 0 | J48: =((G48/240)*1.5)*H48 -> #N/A | K48: =+((G48/240)*2)*I48 -> #N/A | L48: =+Tabla3[[#This Row],[US$]]+Tabla3[[#This Row],[US$,]] -> #N/A
B49: 42 | C49: 605031145 | D49: =+VLOOKUP(Tabla3[[#This Row],[CEDULA ]],'OCTUBRE 2025'!$C$8:$J$10,2,0) -> #N/A | E49: =+VLOOKUP(Tabla3[[#This Row],[CEDULA ]],'OCTUBRE 2025'!$C$8:$J$10,4,0) -> #N/A | F49: =+VLOOKUP(Tabla3[[#This Row],[CEDULA ]],'OCTUBRE 2025'!$C$8:$J$10,6,0) -> #N/A | G49: =+VLOOKUP(Tabla3[[#This Row],[CEDULA ]],'OCTUBRE 2025'!$C$8:$J$10,8,0) -> #N/A | H49: =+VLOOKUP(Tabla3[[#This Row],[CEDULA ]],'Conversión-HE'!$C$20:$I$70,6,0) -> 0 | I49: =+VLOOKUP(Tabla3[[#This Row],[CEDULA ]],'Conversión-HE'!$C$20:$I$70,7,0) -> 0 | J49: =((G49/240)*1.5)*H49 -> #N/A | K49: =+((G49/240)*2)*I49 -> #N/A | L49: =+Tabla3[[#This Row],[US$]]+Tabla3[[#This Row],[US$,]] -> #N/A
B50: 43 | C50: 927257576 | D50: =+VLOOKUP(Tabla3[[#This Row],[CEDULA ]],'OCTUBRE 2025'!$C$8:$J$10,2,0) -> #N/A | E50: =+VLOOKUP(Tabla3[[#This Row],[CEDULA ]],'OCTUBRE 2025'!$C$8:$J$10,4,0) -> #N/A | F50: =+VLOOKUP(Tabla3[[#This Row],[CEDULA ]],'OCTUBRE 2025'!$C$8:$J$10,6,0) -> #N/A | G50: =+VLOOKUP(Tabla3[[#This Row],[CEDULA ]],'OCTUBRE 2025'!$C$8:$J$10,8,0) -> #N/A | H50: =+VLOOKUP(Tabla3[[#This Row],[CEDULA ]],'Conversión-HE'!$C$20:$I$70,6,0) -> 0 | I50: =+VLOOKUP(Tabla3[[#This Row],[CEDULA ]],'Conversión-HE'!$C$20:$I$70,7,0) -> 0 | J50: =((G50/240)*1.5)*H50 -> #N/A | K50: =+((G50/240)*2)*I50 -> #N/A | L50: =+Tabla3[[#This Row],[US$]]+Tabla3[[#This Row],[US$,]] -> #N/A
B51: 44 | C51: 928901800 | D51: =+VLOOKUP(Tabla3[[#This Row],[CEDULA ]],'OCTUBRE 2025'!$C$8:$J$10,2,0) -> #N/A | E51: =+VLOOKUP(Tabla3[[#This Row],[CEDULA ]],'OCTUBRE 2025'!$C$8:$J$10,4,0) -> #N/A | F51: =+VLOOKUP(Tabla3[[#This Row],[CEDULA ]],'OCTUBRE 2025'!$C$8:$J$10,6,0) -> #N/A | G51: =+VLOOKUP(Tabla3[[#This Row],[CEDULA ]],'OCTUBRE 2025'!$C$8:$J$10,8,0) -> #N/A | H51: =+VLOOKUP(Tabla3[[#This Row],[CEDULA ]],'Conversión-HE'!$C$20:$I$70,6,0) -> 0 | I51: =+VLOOKUP(Tabla3[[#This Row],[CEDULA ]],'Conversión-HE'!$C$20:$I$70,7,0) -> 0 | J51: =((G51/240)*1.5)*H51 -> #N/A | K51: =+((G51/240)*2)*I51 -> #N/A | L51: =+Tabla3[[#This Row],[US$]]+Tabla3[[#This Row],[US$,]] -> #N/A
B52: 45 | C52: 951315746 | D52: =+VLOOKUP(Tabla3[[#This Row],[CEDULA ]],'OCTUBRE 2025'!$C$8:$J$10,2,0) -> #N/A | E52: =+VLOOKUP(Tabla3[[#This Row],[CEDULA ]],'OCTUBRE 2025'!$C$8:$J$10,4,0) -> #N/A | F52: =+VLOOKUP(Tabla3[[#This Row],[CEDULA ]],'OCTUBRE 2025'!$C$8:$J$10,6,0) -> #N/A | G52: =+VLOOKUP(Tabla3[[#This Row],[CEDULA ]],'OCTUBRE 2025'!$C$8:$J$10,8,0) -> #N/A | H52: =+VLOOKUP(Tabla3[[#This Row],[CEDULA ]],'Conversión-HE'!$C$20:$I$70,6,0) -> 0 | I52: =+VLOOKUP(Tabla3[[#This Row],[CEDULA ]],'Conversión-HE'!$C$20:$I$70,7,0) -> 0 | J52: =((G52/240)*1.5)*H52 -> #N/A | K52: =+((G52/240)*2)*I52 -> #N/A | L52: =+Tabla3[[#This Row],[US$]]+Tabla3[[#This Row],[US$,]] -> #N/A
B53: 46 | C53: 954184321 | D53: =+VLOOKUP(Tabla3[[#This Row],[CEDULA ]],'OCTUBRE 2025'!$C$8:$J$10,2,0) -> #N/A | E53: =+VLOOKUP(Tabla3[[#This Row],[CEDULA ]],'OCTUBRE 2025'!$C$8:$J$10,4,0) -> #N/A | F53: =+VLOOKUP(Tabla3[[#This Row],[CEDULA ]],'OCTUBRE 2025'!$C$8:$J$10,6,0) -> #N/A | G53: =+VLOOKUP(Tabla3[[#This Row],[CEDULA ]],'OCTUBRE 2025'!$C$8:$J$10,8,0) -> #N/A | H53: =+VLOOKUP(Tabla3[[#This Row],[CEDULA ]],'Conversión-HE'!$C$20:$I$70,6,0) -> 0 | I53: =+VLOOKUP(Tabla3[[#This Row],[CEDULA ]],'Conversión-HE'!$C$20:$I$70,7,0) -> 0 | J53: =((G53/240)*1.5)*H53 -> #N/A | K53: =+((G53/240)*2)*I53 -> #N/A | L53: =+Tabla3[[#This Row],[US$]]+Tabla3[[#This Row],[US$,]] -> #N/A
B54: 47 | C54: 922034772 | D54: =+VLOOKUP(Tabla3[[#This Row],[CEDULA ]],'OCTUBRE 2025'!$C$8:$J$10,2,0) -> #N/A | E54: =+VLOOKUP(Tabla3[[#This Row],[CEDULA ]],'OCTUBRE 2025'!$C$8:$J$10,4,0) -> #N/A | F54: =+VLOOKUP(Tabla3[[#This Row],[CEDULA ]],'OCTUBRE 2025'!$C$8:$J$10,6,0) -> #N/A | G54: =+VLOOKUP(Tabla3[[#This Row],[CEDULA ]],'OCTUBRE 2025'!$C$8:$J$10,8,0) -> #N/A | H54: =+VLOOKUP(Tabla3[[#This Row],[CEDULA ]],'Conversión-HE'!$C$20:$I$70,6,0) -> 0 | I54: =+VLOOKUP(Tabla3[[#This Row],[CEDULA ]],'Conversión-HE'!$C$20:$I$70,7,0) -> 0 | J54: =((G54/240)*1.5)*H54 -> #N/A | K54: =+((G54/240)*2)*I54 -> #N/A | L54: =+Tabla3[[#This Row],[US$]]+Tabla3[[#This Row],[US$,]] -> #N/A
B55: 48 | C55: 923837991 | D55: =+VLOOKUP(Tabla3[[#This Row],[CEDULA ]],'OCTUBRE 2025'!$C$8:$J$10,2,0) -> YUNDA CUJILEMA MARIA TERESA | E55: =+VLOOKUP(Tabla3[[#This Row],[CEDULA ]],'OCTUBRE 2025'!$C$8:$J$10,4,0) -> CONTADOR GENERAL | F55: =+VLOOKUP(Tabla3[[#This Row],[CEDULA ]],'OCTUBRE 2025'!$C$8:$J$10,6,0) -> Matriz | G55: =+VLOOKUP(Tabla3[[#This Row],[CEDULA ]],'OCTUBRE 2025'!$C$8:$J$10,8,0) -> 1022.2 | H55: =+VLOOKUP(Tabla3[[#This Row],[CEDULA ]],'Conversión-HE'!$C$20:$I$70,6,0) -> 0 | I55: =+VLOOKUP(Tabla3[[#This Row],[CEDULA ]],'Conversión-HE'!$C$20:$I$70,7,0) -> 0 | J55: =((G55/240)*1.5)*H55 -> 0 | K55: =+((G55/240)*2)*I55 -> 0 | L55: =+Tabla3[[#This Row],[US$]]+Tabla3[[#This Row],[US$,]] -> 0
... B57: 50 | C57: 604154575 | D57: =+VLOOKUP(Tabla3[[#This Row],[CEDULA ]],'OCTUBRE 2025'!$C$8:$J$10,2,0) -> YUQUILEMA DELGADO PEDRO ANTONIO | E57: =+VLOOKUP(Tabla3[[#This Row],[CEDULA ]],'OCTUBRE 2025'!$C$8:$J$10,4,0) -> JEFE DE CRÉDITO | F57: =+VLOOKUP(Tabla3[[#This Row],[CEDULA ]],'OCTUBRE 2025'!$C$8:$J$10,6,0) -> Durán | G57: =+VLOOKUP(Tabla3[[#This Row],[CEDULA ]],'OCTUBRE 2025'!$C$8:$J$10,8,0) -> 1022.2 | H57: =+VLOOKUP(Tabla3[[#This Row],[CEDULA ]],'Conversión-HE'!$C$20:$I$70,6,0) -> 0 | I57: =+VLOOKUP(Tabla3[[#This Row],[CEDULA ]],'Conversión-HE'!$C$20:$I$70,7,0) -> 0 | J57: =((G57/240)*1.5)*H57 -> 0 | K57: =+((G57/240)*2)*I57 -> 0 | L57: =+Tabla3[[#This Row],[US$]]+Tabla3[[#This Row],[US$,]] -> 0
J58: =((G58/240)*1.5)*H58 -> 0 | K58: =+((G58/240)*2)*I58 -> 0 | L58: =+Tabla3[[#This Row],[US$]]+Tabla3[[#This Row],[US$,]] -> 0
D59: TOTALES | G59: =SUBTOTAL(109,Tabla3[SUELDO]) -> #N/A | H59: =SUBTOTAL(109,Tabla3[Cantidad]) -> 0 | I59: =SUBTOTAL(109,Tabla3[Cantidad2]) -> 0 | J59: =SUBTOTAL(109,Tabla3[US$]) -> #N/A | K59: =SUBTOTAL(109,Tabla3[US$,]) -> #N/A | L59: =SUBTOTAL(109,Tabla3[US$,,]) -> #N/A

Sheet Conversión-HE
D2: REPORTE FEBRERO
D3: DIA REPORTADO | H3: HORA SALIDA
D4: 4 | H4: 0.33333333
D5: 5 | H5: 0.33333333
D6: 6 | H6: 0.8125
D7: 7 | H7: -
D8: 8 | H8: 0.33333333
D9: 9 | H9: 0.33333333
D10: 10 | H10: 0.33333333
D11: 11 | H11: 0.33333333
D12: 12 | H12: 0.13541667
D13: 13 | H13: 0.79166667
B19: N° | C19: CI | D19: PERSONAL | E19: AGENCIA | F19: SUPL | G19: EXTRAORD | H19: CONVERSION 50% | I19: CONVERSION 100%
B20: 1 | C20: 925813685 | D20: =+VLOOKUP($C20,'OCTUBRE 2025'!$C$8:$J$10,2,0) -> #N/A | E20: =+VLOOKUP($C20,'OCTUBRE 2025'!$C$8:$J$10,6,0) -> #N/A | H20: =+F20*24 -> 0 | I20: =+G20*24 -> 0
B21: =+B20+1 -> 2 | C21: 944405737 | D21: =+VLOOKUP($C21,'OCTUBRE 2025'!$C$8:$J$10,2,0) -> #N/A | E21: =+VLOOKUP($C21,'OCTUBRE 2025'!$C$8:$J$10,6,0) -> #N/A | H21: =+F21*24 -> 0 | I21: =+G21*24 -> 0
B22: =+B21+1 -> 3 | C22: 604394502 | D22: =+VLOOKUP($C22,'OCTUBRE 2025'!$C$8:$J$10,2,0) -> #N/A | E22: =+VLOOKUP($C22,'OCTUBRE 2025'!$C$8:$J$10,6,0) -> #N/A | H22: =+F22*24 -> 0 | I22: =+G22*24 -> 0
B23: =+B22+1 -> 4 | C23: 955741970 | D23: =+VLOOKUP($C23,'OCTUBRE 2025'!$C$8:$J$10,2,0) -> #N/A | E23: =+VLOOKUP($C23,'OCTUBRE 2025'!$C$8:$J$10,6,0) -> #N/A | H23: =+F23*24 -> 0 | I23: =+G23*24 -> 0
B24: =+B23+1 -> 5 | C24: 0943964973 | D24: =+VLOOKUP($C24,'OCTUBRE 2025'!$C$8:$J$10,2,0) -> #N/A | E24: =+VLOOKUP($C24,'OCTUBRE 2025'!$C$8:$J$10,6,0) -> #N/A | H24: =+F24*24 -> 0 | I24: =+G24*24 -> 0
B25: =+B24+1 -> 6 | C25: 944143148 | D25: =+VLOOKUP($C25,'OCTUBRE 2025'!$C$8:$J$10,2,0) -> #N/A | E25: =+VLOOKUP($C25,'OCTUBRE 2025'!$C$8:$J$10,6,0) -> #N/A | H25: =+F25*24 -> 0 | I25: =+G25*24 -> 0
B26: =+B25+1 -> 7 | C26: 955325238 | D26: =+VLOOKUP($C26,'OCTUBRE 2025'!$C$8:$J$10,2,0) -> #N/A | E26: =+VLOOKUP($C26,'OCTUBRE 2025'!$C$8:$J$10,6,0) -> #N/A | H26: =+F26*24 -> 0 | I26: =+G26*24 -> 0
B27: =+B26+1 -> 8 | C27: 914163654 | D27: =+VLOOKUP($C27,'OCTUBRE 2025'!$C$8:$J$10,2,0) -> #N/A | E27: =+VLOOKUP($C27,'OCTUBRE 2025'!$C$8:$J$10,6,0) -> #N/A | H27: =+F27*24 -> 0 | I27: =+G27*24 -> 0
B28: =+B27+1 -> 9 | C28: 956668305 | D28: =+VLOOKUP($C28,'OCTUBRE 2025'!$C$8:$J$10,2,0) -> #N/A | E28: =+VLOOKUP($C28,'OCTUBRE 2025'!$C$8:$J$10,6,0) -> #N/A | H28: =+F28*24 -> 0 | I28: =+G28*24 -> 0
B29: =+B28+1 -> 10 | C29: 0918741448 | D29: =+VLOOKUP($C29,'OCTUBRE 2025'!$C$8:$J$10,2,0) -> #N/A | E29: =+VLOOKUP($C29,'OCTUBRE 2025'!$C$8:$J$10,6,0) -> #N/A | H29: =+F29*24 -> 0 | I29: =+G29*24 -> 0
B30: =+B29+1 -> 11 | C30: 931097620 | D30: =+VLOOKUP($C30,'OCTUBRE 2025'!$C$8:$J$10,2,0) -> #N/A | E30: =+VLOOKUP($C30,'OCTUBRE 2025'!$C$8:$J$10,6,0) -> #N/A | H30: =+F30*24 -> 0 | I30: =+G30*24 -> 0
B31: =+B30+1 -> 12 | C31: 1105483422 | D31: =+VLOOKUP($C31,'OCTUBRE 2025'!$C$8:$J$10,2,0) -> #N/A | E31: =+VLOOKUP($C31,'OCTUBRE 2025'!$C$8:$J$10,6,0) -> #N/A | H31: =+F31*24 -> 0 | I31: =+G31*24 -> 0
B32: =+B31+1 -> 13 | C32: 942614645 | D32: =+VLOOKUP($C32,'OCTUBRE 2025'!$C$8:$J$10,2,0) -> #N/A | E32: =+VLOOKUP($C32,'OCTUBRE 2025'!$C$8:$J$10,6,0) -> #N/A | H32: =+F32*24 -> 0 | I32: =+G32*24 -> 0
B33: =+B32+1 -> 14 | C33: 951200062 | D33: =+VLOOKUP($C33,'OCTUBRE 2025'!$C$8:$J$10,2,0) -> #N/A | E33: =+VLOOKUP($C33,'OCTUBRE 2025'!$C$8:$J$10,6,0) -> #N/A | H33: =+F33*24 -> 0 | I33: =+G33*24 -> 0
B34: =+B33+1 -> 15 | C34: 950929232 | D34: =+VLOOKUP($C34,'OCTUBRE 2025'!$C$8:$J$10,2,0) -> #N/A | E34: =+VLOOKUP($C34,'OCTUBRE 2025'!$C$8:$J$10,6,0) -> #N/A | H34: =+F34*24 -> 0 | I34: =+G34*24 -> 0
B35: =+B34+1 -> 16 | C35: 953819646 | D35: =+VLOOKUP($C35,'OCTUBRE 2025'!$C$8:$J$10,2,0) -> #N/A | E35: =+VLOOKUP($C35,'OCTUBRE 2025'!$C$8:$J$10,6,0) -> #N/A | H35: =+F35*24 -> 0 | I35: =+G35*24 -> 0
B36: =+B35+1 -> 17 | C36: 956953392 | D36: =+VLOOKUP($C36,'OCTUBRE 2025'!$C$8:$J$10,2,0) -> #N/A | E36: =+VLOOKUP($C36,'OCTUBRE 2025'!$C$8:$J$10,6,0) -> #N/A | H36: =+F36*24 -> 0 | I36: =+G36*24 -> 0
B37: =+B36+1 -> 18 | C37: 956796767 | D37: =+VLOOKUP($C37,'OCTUBRE 2025'!$C$8:$J$10,2,0) -> #N/A | E37: =+VLOOKUP($C37,'OCTUBRE 2025'!$C$8:$J$10,6,0) -> #N/A | H37: =+F37*24 -> 0 | I37: =+G37*24 -> 0
B38: =+B37+1 -> 19 | C38: 0932036049 | D38: =+VLOOKUP($C38,'OCTUBRE 2025'!$C$8:$J$10,2,0) -> #N/A | E38: =+VLOOKUP($C38,'OCTUBRE 2025'!$C$8:$J$10,6,0) -> #N/A | H38: =+F38*24 -> 0 | I38: =+G38*24 -> 0
B39: =+B38+1 -> 20 | C39: 1724102940 | D39: =+VLOOKUP($C39,'OCTUBRE 2025'!$C$8:$J$10,2,0) -> #N/A | E39: =+VLOOKUP($C39,'OCTUBRE 2025'!$C$8:$J$10,6,0) -> #N/A | H39: =+F39*24 -> 0 | I39: =+G39*24 -> 0
B40: =+B39+1 -> 21 | C40: 943322974 | D40: =+VLOOKUP($C40,'OCTUBRE 2025'!$C$8:$J$10,2,0) -> #N/A | E40: =+VLOOKUP($C40,'OCTUBRE 2025'!$C$8:$J$10,6,0) -> #N/A | H40: =+F40*24 -> 0 | I40: =+G40*24 -> 0
B41: =+B40+1 -> 22 | C41: 941096851 | D41: =+VLOOKUP($C41,'OCTUBRE 2025'!$C$8:$J$10,2,0) -> #N/A | E41: =+VLOOKUP($C41,'OCTUBRE 2025'!$C$8:$J$10,6,0) -> #N/A | H41: =+F41*24 -> 0 | I41: =+G41*24 -> 0
B42: =+B41+1 -> 23 | C42: 957093800 | D42: =+VLOOKUP($C42,'OCTUBRE 2025'!$C$8:$J$10,2,0) -> #N/A | E42: =+VLOOKUP($C42,'OCTUBRE 2025'!$C$8:$J$10,6,0) -> #N/A | H42: =+F42*24 -> 0 | I42: =+G42*24 -> 0
B43: =+B42+1 -> 24 | C43: 957924350 | D43: =+VLOOKUP($C43,'OCTUBRE 2025'!$C$8:$J$10,2,0) -> #N/A | E43: =+VLOOKUP($C43,'OCTUBRE 2025'!$C$8:$J$10,6,0) -> #N/A | H43: =+F43*24 -> 0 | I43: =+G43*24 -> 0
B44: =+B43+1 -> 25 | C44: 603838657 | D44: =+VLOOKUP($C44,'OCTUBRE 2025'!$C$8:$J$10,2,0) -> #N/A | E44: =+VLOOKUP($C44,'OCTUBRE 2025'!$C$8:$J$10,6,0) -> #N/A | H44: =+F44*24 -> 0 | I44: =+G44*24 -> 0
B45: =+B44+1 -> 26 | C45: 925240525 | D45: =+VLOOKUP($C45,'OCTUBRE 2025'!$C$8:$J$10,2,0) -> #N/A | E45: =+VLOOKUP($C45,'OCTUBRE 2025'!$C$8:$J$10,6,0) -> #N/A | H45: =+F45*24 -> 0 | I45: =+G45*24 -> 0
B46: =+B45+1 -> 27 | C46: 954520599 | D46: =+VLOOKUP($C46,'OCTUBRE 2025'!$C$8:$J$10,2,0) -> #N/A | E46: =+VLOOKUP($C46,'OCTUBRE 2025'!$C$8:$J$10,6,0) -> #N/A | H46: =+F46*24 -> 0 | I46: =+G46*24 -> 0
B47: =+B46+1 -> 28 | C47: 0943906032 | D47: =+VLOOKUP($C47,'OCTUBRE 2025'!$C$8:$J$10,2,0) -> #N/A | E47: =+VLOOKUP($C47,'OCTUBRE 2025'!$C$8:$J$10,6,0) -> #N/A | H47: =+F47*24 -> 0 | I47: =+G47*24 -> 0
B48: =+B47+1 -> 29 | C48: 0919306050 | D48: =+VLOOKUP($C48,'OCTUBRE 2025'!$C$8:$J$10,2,0) -> #N/A | E48: =+VLOOKUP($C48,'OCTUBRE 2025'!$C$8:$J$10,6,0) -> #N/A | H48: =+F48*24 -> 0 | I48: =+G48*24 -> 0
B49: =+B48+1 -> 30 | C49: 0941235376 | D49: =+VLOOKUP($C49,'OCTUBRE 2025'!$C$8:$J$10,2,0) -> #N/A | E49: =+VLOOKUP($C49,'OCTUBRE 2025'!$C$8:$J$10,6,0) -> #N/A | H49: =+F49*24 -> 0 | I49: =+G49*24 -> 0
B50: =+B49+1 -> 31 | C50: 955395686 | D50: =+VLOOKUP($C50,'OCTUBRE 2025'!$C$8:$J$10,2,0) -> #N/A | E50: =+VLOOKUP($C50,'OCTUBRE 2025'!$C$8:$J$10,6,0) -> #N/A | H50: =+F50*24 -> 0 | I50: =+G50*24 -> 0
B51: =+B50+1 -> 32 | C51: 940991987 | D51: =+VLOOKUP($C51,'OCTUBRE 2025'!$C$8:$J$10,2,0) -> #N/A | E51: =+VLOOKUP($C51,'OCTUBRE 2025'!$C$8:$J$10,6,0) -> #N/A | H51: =+F51*24 -> 0 | I51: =+G51*24 -> 0
B52: =+B51+1 -> 33 | C52: 956929277 | D52: =+VLOOKUP($C52,'OCTUBRE 2025'!$C$8:$J$10,2,0) -> #N/A | E52: =+VLOOKUP($C52,'OCTUBRE 2025'!$C$8:$J$10,6,0) -> #N/A | H52: =+F52*24 -> 0 | I52: =+G52*24 -> 0
B53: =+B52+1 -> 34 | C53: 951763994 | D53: =+VLOOKUP($C53,'OCTUBRE 2025'!$C$8:$J$10,2,0) -> #N/A | E53: =+VLOOKUP($C53,'OCTUBRE 2025'!$C$8:$J$10,6,0) -> #N/A | H53: =+F53*24 -> 0 | I53: =+G53*24 -> 0
B54: =+B53+1 -> 35 | C54: 950703199 | D54: =+VLOOKUP($C54,'OCTUBRE 2025'!$C$8:$J$10,2,0) -> #N/A | E54: =+VLOOKUP($C54,'OCTUBRE 2025'!$C$8:$J$10,6,0) -> #N/A | H54: =+F54*24 -> 0 | I54: =+G54*24 -> 0
B55: =+B54+1 -> 36 | C55: 0923715692 | D55: =+VLOOKUP($C55,'OCTUBRE 2025'!$C$8:$J$10,2,0) -> #N/A | E55: =+VLOOKUP($C55,'OCTUBRE 2025'!$C$8:$J$10,6,0) -> #N/A | H55: =+F55*24 -> 0 | I55: =+G55*24 -> 0
B56: =+B55+1 -> 37 | C56: 925830689 | D56: =+VLOOKUP($C56,'OCTUBRE 2025'!$C$8:$J$10,2,0) -> #N/A | E56: =+VLOOKUP($C56,'OCTUBRE 2025'!$C$8:$J$10,6,0) -> #N/A | H56: =+F56*24 -> 0 | I56: =+G56*24 -> 0
B57: =+B56+1 -> 38 | C57: 944034842 | D57: =+VLOOKUP($C57,'OCTUBRE 2025'!$C$8:$J$10,2,0) -> #N/A | E57: =+VLOOKUP($C57,'OCTUBRE 2025'!$C$8:$J$10,6,0) -> #N/A | H57: =+F57*24 -> 0 | I57: =+G57*24 -> 0
B58: =+B57+1 -> 39 | C58: 951340702 | D58: =+VLOOKUP($C58,'OCTUBRE 2025'!$C$8:$J$10,2,0) -> #N/A | E58: =+VLOOKUP($C58,'OCTUBRE 2025'!$C$8:$J$10,6,0) -> #N/A | H58: =+F58*24 -> 0 | I58: =+G58*24 -> 0
B59: =+B58+1 -> 40 | C59: 650112949 | D59: =+VLOOKUP($C59,'OCTUBRE 2025'!$C$8:$J$10,2,0) -> #N/A | E59: =+VLOOKUP($C59,'OCTUBRE 2025'!$C$8:$J$10,6,0) -> #N/A | H59: =+F59*24 -> 0 | I59: =+G59*24 -> 0
B60: =+B59+1 -> 41 | C60: 924232804 | D60: =+VLOOKUP($C60,'OCTUBRE 2025'!$C$8:$J$10,2,0) -> #N/A | E60: =+VLOOKUP($C60,'OCTUBRE 2025'!$C$8:$J$10,6,0) -> #N/A | H60: =+F60*24 -> 0 | I60: =+G60*24 -> 0
B61: =+B60+1 -> 42 | C61: 605031145 | D61: =+VLOOKUP($C61,'OCTUBRE 2025'!$C$8:$J$10,2,0) -> #N/A | E61: =+VLOOKUP($C61,'OCTUBRE 2025'!$C$8:$J$10,6,0) -> #N/A | H61: =+F61*24 -> 0 | I61: =+G61*24 -> 0
B62: =+B61+1 -> 43 | C62: 927257576 | D62: =+VLOOKUP($C62,'OCTUBRE 2025'!$C$8:$J$10,2,0) -> #N/A | E62: =+VLOOKUP($C62,'OCTUBRE 2025'!$C$8:$J$10,6,0) -> #N/A | H62: =+F62*24 -> 0 | I62: =+G62*24 -> 0
B63: =+B62+1 -> 44 | C63: 928901800 | D63: =+VLOOKUP($C63,'OCTUBRE 2025'!$C$8:$J$10,2,0) -> #N/A | E63: =+VLOOKUP($C63,'OCTUBRE 2025'!$C$8:$J$10,6,0) -> #N/A | H63: =+F63*24 -> 0 | I63: =+G63*24 -> 0
B64: =+B63+1 -> 45 | C64: 951315746 | D64: =+VLOOKUP($C64,'OCTUBRE 2025'!$C$8:$J$10,2,0) -> #N/A | E64: =+VLOOKUP($C64,'OCTUBRE 2025'!$C$8:$J$10,6,0) -> #N/A | H64: =+F64*24 -> 0 | I64: =+G64*24 -> 0
B65: =+B64+1 -> 46 | C65: 954184321 | D65: =+VLOOKUP($C65,'OCTUBRE 2025'!$C$8:$J$10,2,0) -> #N/A | E65: =+VLOOKUP($C65,'OCTUBRE 2025'!$C$8:$J$10,6,0) -> #N/A | H65: =+F65*24 -> 0 | I65: =+G65*24 -> 0
B66: =+B65+1 -> 47 | C66: 922034772 | D66: =+VLOOKUP($C66,'OCTUBRE 2025'!$C$8:$J$10,2,0) -> #N/A | E66: =+VLOOKUP($C66,'OCTUBRE 2025'!$C$8:$J$10,6,0) -> #N/A | H66: =+F66*24 -> 0 | I66: =+G66*24 -> 0
B67: =+B66+1 -> 48 | C67: 923837991 | D67: =+VLOOKUP($C67,'OCTUBRE 2025'!$C$8:$J$10,2,0) -> YUNDA CUJILEMA MARIA TERESA | E67: =+VLOOKUP($C67,'OCTUBRE 2025'!$C$8:$J$10,6,0) -> Matriz | H67: =+F67*24 -> 0 | I67: =+G67*24 -> 0
... B69: =+B68+1 -> 50 | C69: 604154575 | D69: =+VLOOKUP($C69,'OCTUBRE 2025'!$C$8:$J$10,2,0) -> YUQUILEMA DELGADO PEDRO ANTONIO | E69: =+VLOOKUP($C69,'OCTUBRE 2025'!$C$8:$J$10,6,0) -> Durán | H69: =+F69*24 -> 0 | I69: =+G69*24 -> 0
H70: =SUM(H20:H69) -> 0 | I70: =SUM(I20:I69) -> 0

Sheet PQ
C3: PRÉSTAMOS QUIROGRAFARIOS E HIPOTECARIOS
C4: NÓMINA OCTUBRE 2025
B7: NO | C7: CEDULA | D7: NOMBRES Y APELLIDOS | E7: NUT | F7: VALOR
B8: 1 | C8: 0950929232 | D8: GARCIA VERA HENRY LUIS | E8: 15496427 | F8: 13.21
B9: 2 | C9: 0950929232 | D9: GARCIA VERA HENRY LUIS | E9: 17091341 | F9: 25.89
B10: 3 | C10: 0950929232 | D10: GARCIA VERA HENRY LUIS | E10: 18698061 | F10: 59.39 | I10: Etiquetas de fila | J10: Suma de VALOR
B11: 4 | C11: 0950929232 | D11: GARCIA VERA HENRY LUIS | E11: 13715336 | F11: 11.53 | I11: DEFAS CHICAIZA JOEL ALBERTO | J11: 261.63
B12: 5 | C12: 0950929232 | D12: GARCIA VERA HENRY LUIS | E12: 14750228 | F12: 19.83 | I12: GARCIA VERA HENRY LUIS | J12: 87.66
B13: 6 | C13: 0950929232 | D13: GARCIA VERA HENRY LUIS | E13: 16294333 | F13: 16.69 | I13: GUAYANLEMA RUIZ EDINSON DAVID | J13: 20.96
B14: 7 | C14: 0956796767 | D14: GUAYANLEMA RUIZ EDINSON DAVID | E14: 16038686 | F14: 20.96 | I14: MALAN DELGADO JOSE ALBERTO | J14: 36.13
B15: 8 | C15: 0954520599 | D15: MARSHALL VEGA YULIANA LISSETT | E15: 18644981 | F15: 15.48 | I15: MARSHALL VEGA YULIANA LISSETT | J15: 27.17
B16: 9 | C16: 0954520599 | D16: MARSHALL VEGA YULIANA LISSETT | E16: 17678636 | F16: 11.69 | I16: MOREIRA ESPINOZA LINDA ELIZABETH | J16: 35.22
B17: 10 | C17: 0943906032 | D17: MEZA RODRIGUEZ MICHAEL FERNANDO | E17: 18861527 | F17: 58.15 | I17: MUÑOZ MOLINA VERONICA PATRICIA | J17: 161.05
B18: 11 | C18: 0941235376 | D18: MOREIRA ESPINOZA LINDA ELIZABETH | E18: 17447992 | F18: 34.98 | I18: PERALTA MENDEZ LINA LISSETTE | J18: 80.94
B19: 12 | C19: 0925830689 | D19: PERALTA MENDEZ LINA LISSETTE | E19: 18546441 | F19: 80.94 | I19: RECALDE NARANJO ANGEL ALEXIS | J19: 71.05
B20: 13 | C20: 0924232804 | D20: RECALDE NARANJO ANGEL ALEXIS | E20: 18902486 | F20: 37.16 | I20: SANISACA MITE ISRAEL BENJAMIN | J20: 55.57
B21: 14 | C21: 0924232804 | D21: RECALDE NARANJO ANGEL ALEXIS | E21: 18385843 | F21: 37.04 | I21: TADAY GUAMAN NESTOR ALONSO | J21: 84.3
B22: 15 | C22: 0924232804 | D22: RECALDE NARANJO ANGEL ALEXIS | E22: 17552082 | F22: 33.41 | I22: (en blanco)
B23: 16 | C23: 0927257576 | D23: SANISACA MITE ISRAEL BENJAMIN | E23: 16124684 | F23: 22.78 | I23: Total general | J23: 921.68
B24: 17 | C24: 0927257576 | D24: SANISACA MITE ISRAEL BENJAMIN | E24: 14534491 | F24: 10.97
B25: 18 | C25: 0927257576 | D25: SANISACA MITE ISRAEL BENJAMIN | E25: 17321972 | F25: 21.82
B26: 19 | C26: 0928901800 | D26: TADAY GUAMAN NESTOR ALONSO | E26: 14576862 | F26: 84.3
B27: 20 | C27: 918741448 | D27: DEFAS CHICAIZA JOEL ALBERTO | E27: 10070196 | F27: 261.63
B28: 21 | C28: 925240525 | D28: MALAN YUQUILEMA RAUL ALBERTO | E28: 18667642 | F28: 710.01
G32: =+SUM(F8:F28) -> 1587.86
D34: Etiquetas de fila | E34: MONTOS
D35: DEFAS CHICAIZA JOEL ALBERTO | E35: =+GETPIVOTDATA("VALOR",$I$10,"NOMBRES Y APELLIDOS","DEFAS CHICAIZA JOEL ALBERTO") -> 261.63
D36: GARCIA VERA HENRY LUIS | E36: =+GETPIVOTDATA("VALOR",$I$10,"NOMBRES Y APELLIDOS","GARCIA VERA HENRY LUIS") -> 87.66
D37: GUAYANLEMA RUIZ EDINSON DAVID | E37: =+GETPIVOTDATA("VALOR",$I$10,"NOMBRES Y APELLIDOS","GUAYANLEMA RUIZ EDINSON DAVID") -> 20.96
D38: MALAN DELGADO JOSE ALBERTO | E38: =+GETPIVOTDATA("VALOR",$I$10,"NOMBRES Y APELLIDOS","MALAN DELGADO JOSE ALBERTO") -> 36.13
D39: MARSHALL VEGA YULIANA LISSETT | E39: =+GETPIVOTDATA("VALOR",$I$10,"NOMBRES Y APELLIDOS","MARSHALL VEGA YULIANA LISSETT") -> 27.17
D40: MOREIRA ESPINOZA LINDA ELIZABETH | E40: =+GETPIVOTDATA("VALOR",$I$10,"NOMBRES Y APELLIDOS","MOREIRA ESPINOZA LINDA ELIZABETH") -> 35.22
D41: MUÑOZ MOLINA VERONICA PATRICIA | E41: =+GETPIVOTDATA("VALOR",$I$10,"NOMBRES Y APELLIDOS","MUÑOZ MOLINA VERONICA PATRICIA") -> 161.05
D42: PERALTA MENDEZ LINA LISSETTE | E42: 80.94
D43: RECALDE NARANJO ANGEL ALEXIS | E43: =+GETPIVOTDATA("VALOR",$I$10,"NOMBRES Y APELLIDOS","RECALDE NARANJO ANGEL ALEXIS") -> 71.05
D44: SANISACA MITE ISRAEL BENJAMIN | E44: =+GETPIVOTDATA("VALOR",$I$10,"NOMBRES Y APELLIDOS","SANISACA MITE ISRAEL BENJAMIN") -> 55.57
D45: TADAY GUAMAN NÉSTOR ALONSO | E45: =+GETPIVOTDATA("VALOR",$I$10,"NOMBRES Y APELLIDOS","TADAY GUAMAN NESTOR ALONSO") -> 84.3
D47: (en blanco) | E47: =SUM(E35:E46) -> 921.68

Sheet FR
D2: REPORTE DE FONDOS DE RESERVA
D3: NÓMINA OCTUBRE2025
B5: No | C5: cedula | D5: NOMBRES Y APELLIDOS | E5: Sucursal | F5: Tiene Solicitud de Acum. | G5: Fecha de Solicitud | H5: Tiene Derecho | I5: FECHA DE INGRESO | J5: DIAS | K5: INGRESO APORTE AL IESS | L5: ACUMULA | M5: TOTALES | Q5: Fondo de Reserva Bono | R5: Fondo de reserva ajuste
B6: 1 | C6: 925813685 | D6: =+VLOOKUP(C6,'OCTUBRE 2025'!$C$8:$D$10,2,0) -> #N/A | E6: 1 | F6: NO | H6: SI | I6: =+VLOOKUP(C6,'OCTUBRE 2025'!$C$8:$J$10,3,0) -> #N/A | J6: =+VLOOKUP(C6,'OCTUBRE 2025'!$C$8:$J$10,7,0) -> #N/A | K6: =+'OCTUBRE 2025'!#REF! -> #REF! | M6: =+((K6)*8.33%) -> #REF!
B7: =+B6+1 -> 2 | C7: 944405737 | D7: =+VLOOKUP(C7,'OCTUBRE 2025'!$C$8:$D$10,2,0) -> #N/A | E7: 1 | F7: SI | G7: 44998 | H7: SI | I7: =+VLOOKUP(C7,'OCTUBRE 2025'!$C$8:$J$10,3,0) -> #N/A | J7: =+VLOOKUP(C7,'OCTUBRE 2025'!$C$8:$J$10,7,0) -> #N/A | K7: =+'OCTUBRE 2025'!#REF! -> #REF! | M7: ACUMULA
B8: =+B7+1 -> 3 | C8: 604394502 | D8: =+VLOOKUP(C8,'OCTUBRE 2025'!$C$8:$D$10,2,0) -> #N/A | E8: 1 | F8: NO | H8: SI | I8: =+VLOOKUP(C8,'OCTUBRE 2025'!$C$8:$J$10,3,0) -> #N/A | J8: =+VLOOKUP(C8,'OCTUBRE 2025'!$C$8:$J$10,7,0) -> #N/A | K8: =+'OCTUBRE 2025'!#REF! -> #REF! | M8: =(+(K8)*8.33%) -> #REF!
B9: =+B8+1 -> 4 | C9: 955741970 | D9: =+VLOOKUP(C9,'OCTUBRE 2025'!$C$8:$D$10,2,0) -> #N/A | E9: 1 | F9: NO | H9: SI | I9: =+VLOOKUP(C9,'OCTUBRE 2025'!$C$8:$J$10,3,0) -> #N/A | J9: =+VLOOKUP(C9,'OCTUBRE 2025'!$C$8:$J$10,7,0) -> #N/A | K9: =+'OCTUBRE 2025'!#REF! -> #REF! | M9: =(+(K9)*8.33%) -> #REF!
B10: =+B9+1 -> 5 | C10: 0943964973 | D10: =+VLOOKUP(C10,'OCTUBRE 2025'!$C$8:$D$10,2,0) -> #N/A | E10: 2 | F10: NO | H10: NO | I10: =+VLOOKUP(C10,'OCTUBRE 2025'!$C$8:$J$10,3,0) -> #N/A | J10: =+VLOOKUP(C10,'OCTUBRE 2025'!$C$8:$J$10,7,0) -> #N/A | K10: =+'OCTUBRE 2025'!#REF! -> #REF!
B11: =+B10+1 -> 6 | C11: 944143148 | D11: =+VLOOKUP(C11,'OCTUBRE 2025'!$C$8:$D$10,2,0) -> #N/A | E11: 2 | F11: NO | H11: NO | I11: =+VLOOKUP(C11,'OCTUBRE 2025'!$C$8:$J$10,3,0) -> #N/A | J11: =+VLOOKUP(C11,'OCTUBRE 2025'!$C$8:$J$10,7,0) -> #N/A | K11: =+'OCTUBRE 2025'!#REF! -> #REF! | M11: 0
B12: =+B11+1 -> 7 | C12: 955325238 | D12: =+VLOOKUP(C12,'OCTUBRE 2025'!$C$8:$D$10,2,0) -> #N/A | E12: 2 | F12: NO | H12: NO | I12: =+VLOOKUP(C12,'OCTUBRE 2025'!$C$8:$J$10,3,0) -> #N/A | J12: =+VLOOKUP(C12,'OCTUBRE 2025'!$C$8:$J$10,7,0) -> #N/A | K12: =+'OCTUBRE 2025'!#REF! -> #REF!
B13: =+B12+1 -> 8 | C13: 914163654 | D13: =+VLOOKUP(C13,'OCTUBRE 2025'!$C$8:$D$10,2,0) -> #N/A | E13: 1 | F13: NO | H13: SI | I13: =+VLOOKUP(C13,'OCTUBRE 2025'!$C$8:$J$10,3,0) -> #N/A | J13: =+VLOOKUP(C13,'OCTUBRE 2025'!$C$8:$J$10,7,0) -> #N/A | K13: =+'OCTUBRE 2025'!#REF! -> #REF! | M13: =(+(K13)*8.33%) -> #REF!
B14: =+B13+1 -> 9 | C14: 956668305 | D14: =+VLOOKUP(C14,'OCTUBRE 2025'!$C$8:$D$10,2,0) -> #N/A | E14: 2 | F14: NO | H14: NO | I14: =+VLOOKUP(C14,'OCTUBRE 2025'!$C$8:$J$10,3,0) -> #N/A | J14: =+VLOOKUP(C14,'OCTUBRE 2025'!$C$8:$J$10,7,0) -> #N/A | K14: =+'OCTUBRE 2025'!#REF! -> #REF!
B15: =+B14+1 -> 10 | C15: 0918741448 | D15: =+VLOOKUP(C15,'OCTUBRE 2025'!$C$8:$D$10,2,0) -> #N/A | E15: 3 | F15: NO | H15: NO | I15: =+VLOOKUP(C15,'OCTUBRE 2025'!$C$8:$J$10,3,0) -> #N/A | J15: =+VLOOKUP(C15,'OCTUBRE 2025'!$C$8:$J$10,7,0) -> #N/A | K15: =+'OCTUBRE 2025'!#REF! -> #REF!
B16: =+B15+1 -> 11 | C16: 931097620 | D16: =+VLOOKUP(C16,'OCTUBRE 2025'!$C$8:$D$10,2,0) -> #N/A | E16: 4 | F16: NO | H16: NO | I16: =+VLOOKUP(C16,'OCTUBRE 2025'!$C$8:$J$10,3,0) -> #N/A | J16: =+VLOOKUP(C16,'OCTUBRE 2025'!$C$8:$J$10,7,0) -> #N/A | K16: =+'OCTUBRE 2025'!#REF! -> #REF!
B17: =+B16+1 -> 12 | C17: 1105483422 | D17: =+VLOOKUP(C17,'OCTUBRE 2025'!$C$8:$D$10,2,0) -> #N/A | E17: 3 | F17: NO | H17: SI | I17: =+VLOOKUP(C17,'OCTUBRE 2025'!$C$8:$J$10,3,0) -> #N/A | J17: =+VLOOKUP(C17,'OCTUBRE 2025'!$C$8:$J$10,7,0) -> #N/A | K17: =+'OCTUBRE 2025'!#REF! -> #REF! | M17: =(+(K17)*8.33%) -> #REF!
B18: =+B17+1 -> 13 | C18: 942614645 | D18: =+VLOOKUP(C18,'OCTUBRE 2025'!$C$8:$D$10,2,0) -> #N/A | E18: 1 | F18: NO | H18: SI | I18: =+VLOOKUP(C18,'OCTUBRE 2025'!$C$8:$J$10,3,0) -> #N/A | J18: =+VLOOKUP(C18,'OCTUBRE 2025'!$C$8:$J$10,7,0) -> #N/A | K18: =+'OCTUBRE 2025'!#REF! -> #REF! | M18: =(+(K18)*8.33%) -> #REF!
B19: =+B18+1 -> 14 | C19: 951200062 | D19: =+VLOOKUP(C19,'OCTUBRE 2025'!$C$8:$D$10,2,0) -> #N/A | E19: 1 | F19: NO | H19: SI | I19: =+VLOOKUP(C19,'OCTUBRE 2025'!$C$8:$J$10,3,0) -> #N/A | J19: =+VLOOKUP(C19,'OCTUBRE 2025'!$C$8:$J$10,7,0) -> #N/A | K19: =+'OCTUBRE 2025'!#REF! -> #REF! | M19: =(+(K19)*8.33%) -> #REF!
B20: =+B19+1 -> 15 | C20: 950929232 | D20: =+VLOOKUP(C20,'OCTUBRE 2025'!$C$8:$D$10,2,0) -> #N/A | E20: 1 | F20: SI | G20: 45279 | H20: SI | I20: =+VLOOKUP(C20,'OCTUBRE 2025'!$C$8:$J$10,3,0) -> #N/A | J20: =+VLOOKUP(C20,'OCTUBRE 2025'!$C$8:$J$10,7,0) -> #N/A | K20: =+'OCTUBRE 2025'!#REF! -> #REF! | M20: ACUMULA
B21: =+B20+1 -> 16 | C21: 953819646 | D21: =+VLOOKUP(C21,'OCTUBRE 2025'!$C$8:$D$10,2,0) -> #N/A | E21: 1 | F21: NO | H21: SI | I21: =+VLOOKUP(C21,'OCTUBRE 2025'!$C$8:$J$10,3,0) -> #N/A | J21: =+VLOOKUP(C21,'OCTUBRE 2025'!$C$8:$J$10,7,0) -> #N/A | K21: =+'OCTUBRE 2025'!#REF! -> #REF! | M21: =(+(K21)*8.33%) -> #REF!
B22: =+B21+1 -> 17 | C22: 956953392 | D22: =+VLOOKUP(C22,'OCTUBRE 2025'!$C$8:$D$10,2,0) -> #N/A | E22: 1 | F22: NO | H22: SI | I22: =+VLOOKUP(C22,'OCTUBRE 2025'!$C$8:$J$10,3,0) -> #N/A | J22: =+VLOOKUP(C22,'OCTUBRE 2025'!$C$8:$J$10,7,0) -> #N/A | K22: =+'OCTUBRE 2025'!#REF! -> #REF! | M22: =(+(K22)*8.33%) -> #REF!
B23: =+B22+1 -> 18 | C23: 956796767 | D23: =+VLOOKUP(C23,'OCTUBRE 2025'!$C$8:$D$10,2,0) -> #N/A | E23: 1 | F23: NO | H23: SI | I23: =+VLOOKUP(C23,'OCTUBRE 2025'!$C$8:$J$10,3,0) -> #N/A | J23: =+VLOOKUP(C23,'OCTUBRE 2025'!$C$8:$J$10,7,0) -> #N/A | K23: =+'OCTUBRE 2025'!#REF! -> #REF! | M23: =(+(K23)*8.33%)+Q23+R23 -> #REF!
B24: =+B23+1 -> 19 | C24: 0932036049 | D24: =+VLOOKUP(C24,'OCTUBRE 2025'!$C$8:$D$10,2,0) -> #N/A | E24: 2 | F24: NO | H24: NO | I24: =+VLOOKUP(C24,'OCTUBRE 2025'!$C$8:$J$10,3,0) -> #N/A | J24: =+VLOOKUP(C24,'OCTUBRE 2025'!$C$8:$J$10,7,0) -> #N/A | K24: =+'OCTUBRE 2025'!#REF! -> #REF! | M24: 0
B25: =+B24+1 -> 20 | C25: 1724102940 | D25: =+VLOOKUP(C25,'OCTUBRE 2025'!$C$8:$D$10,2,0) -> #N/A | E25: 1 | F25: NO | H25: SI | I25: =+VLOOKUP(C25,'OCTUBRE 2025'!$C$8:$J$10,3,0) -> #N/A | J25: =+VLOOKUP(C25,'OCTUBRE 2025'!$C$8:$J$10,7,0) -> #N/A | K25: =+'OCTUBRE 2025'!#REF! -> #REF! | M25: =(+(K25)*8.33%) -> #REF!
B26: =+B25+1 -> 21 | C26: 943322974 | D26: =+VLOOKUP(C26,'OCTUBRE 2025'!$C$8:$D$10,2,0) -> #N/A | E26: 1 | F26: NO | H26: SI | I26: =+VLOOKUP(C26,'OCTUBRE 2025'!$C$8:$J$10,3,0) -> #N/A | J26: =+VLOOKUP(C26,'OCTUBRE 2025'!$C$8:$J$10,7,0) -> #N/A | K26: =+'OCTUBRE 2025'!#REF! -> #REF! | M26: =(+(K26)*8.33%)+Q26+R26 -> #REF!
B27: =+B26+1 -> 22 | C27: 941096851 | D27: =+VLOOKUP(C27,'OCTUBRE 2025'!$C$8:$D$10,2,0) -> #N/A | E27: 1 | F27: NO | H27: SI | I27: =+VLOOKUP(C27,'OCTUBRE 2025'!$C$8:$J$10,3,0) -> #N/A | J27: =+VLOOKUP(C27,'OCTUBRE 2025'!$C$8:$J$10,7,0) -> #N/A | K27: =+'OCTUBRE 2025'!#REF! -> #REF! | M27: =(+(K27)*8.33%)+Q27+R27 -> #REF!
B28: =+B27+1 -> 23 | C28: 957093800 | D28: =+VLOOKUP(C28,'OCTUBRE 2025'!$C$8:$D$10,2,0) -> #N/A | F28: NO | H28: NO | I28: =+VLOOKUP(C28,'OCTUBRE 2025'!$C$8:$J$10,3,0) -> #N/A | J28: =+VLOOKUP(C28,'OCTUBRE 2025'!$C$8:$J$10,7,0) -> #N/A | K28: =+'OCTUBRE 2025'!#REF! -> #REF! | M28: 0
B29: =+B28+1 -> 24 | C29: 957924350 | D29: =+VLOOKUP(C29,'OCTUBRE 2025'!$C$8:$D$10,2,0) -> #N/A | F29: NO | H29: NO | I29: =+VLOOKUP(C29,'OCTUBRE 2025'!$C$8:$J$10,3,0) -> #N/A | J29: =+VLOOKUP(C29,'OCTUBRE 2025'!$C$8:$J$10,7,0) -> #N/A | K29: =+'OCTUBRE 2025'!#REF! -> #REF! | M29: 0
B30: =+B29+1 -> 25 | C30: 603838657 | D30: =+VLOOKUP(C30,'OCTUBRE 2025'!$C$8:$D$10,2,0) -> #N/A | E30: 1 | F30: NO | H30: SI | I30: =+VLOOKUP(C30,'OCTUBRE 2025'!$C$8:$J$10,3,0) -> #N/A | J30: =+VLOOKUP(C30,'OCTUBRE 2025'!$C$8:$J$10,7,0) -> #N/A | K30: =+'OCTUBRE 2025'!#REF! -> #REF! | M30: =(+(K30)*8.33%)+Q30+R30 -> #REF!
B31: =+B30+1 -> 26 | C31: 925240525 | D31: =+VLOOKUP(C31,'OCTUBRE 2025'!$C$8:$D$10,2,0) -> #N/A | E31: 1 | F31: NO | H31: SI | I31: =+VLOOKUP(C31,'OCTUBRE 2025'!$C$8:$J$10,3,0) -> #N/A | J31: =+VLOOKUP(C31,'OCTUBRE 2025'!$C$8:$J$10,7,0) -> #N/A | K31: =+'OCTUBRE 2025'!#REF! -> #REF! | M31: =(+(K31)*8.33%)+Q31+R31 -> #REF!
B32: =+B31+1 -> 27 | C32: 954520599 | D32: =+VLOOKUP(C32,'OCTUBRE 2025'!$C$8:$D$10,2,0) -> #N/A | E32: 2 | F32: NO | H32: SI | I32: =+VLOOKUP(C32,'OCTUBRE 2025'!$C$8:$J$10,3,0) -> #N/A | J32: =+VLOOKUP(C32,'OCTUBRE 2025'!$C$8:$J$10,7,0) -> #N/A | K32: =+'OCTUBRE 2025'!#REF! -> #REF! | M32: =(+(K32)*8.33%)+Q32+R32 -> #REF!
B33: =+B32+1 -> 28 | C33: 0943906032 | D33: =+VLOOKUP(C33,'OCTUBRE 2025'!$C$8:$D$10,2,0) -> #N/A | E33: 1 | F33: NO | H33: SI | I33: =+VLOOKUP(C33,'OCTUBRE 2025'!$C$8:$J$10,3,0) -> #N/A | J33: =+VLOOKUP(C33,'OCTUBRE 2025'!$C$8:$J$10,7,0) -> #N/A | K33: =+'OCTUBRE 2025'!#REF! -> #REF! | M33: =(+(K33)*8.33%)+Q33+R33 -> #REF!
B34: =+B33+1 -> 29 | C34: 0919306050 | D34: =+VLOOKUP(C34,'OCTUBRE 2025'!$C$8:$D$10,2,0) -> #N/A | E34: 1 | F34: NO | H34: SI | I34: =+VLOOKUP(C34,'OCTUBRE 2025'!$C$8:$J$10,3,0) -> #N/A | J34: =+VLOOKUP(C34,'OCTUBRE 2025'!$C$8:$J$10,7,0) -> #N/A | K34: =+'OCTUBRE 2025'!#REF! -> #REF! | M34: =(+(K34)*8.33%) -> #REF!
B35: =+B34+1 -> 30 | C35: 0941235376 | D35: =+VLOOKUP(C35,'OCTUBRE 2025'!$C$8:$D$10,2,0) -> #N/A | E35: 1 | F35: NO | H35: SI | I35: =+VLOOKUP(C35,'OCTUBRE 2025'!$C$8:$J$10,3,0) -> #N/A | J35: =+VLOOKUP(C35,'OCTUBRE 2025'!$C$8:$J$10,7,0) -> #N/A | K35: =+'OCTUBRE 2025'!#REF! -> #REF! | M35: =+((K35*8.33%)/30)*14 -> #REF!
B36: =+B35+1 -> 31 | C36: 955395686 | D36: =+VLOOKUP(C36,'OCTUBRE 2025'!$C$8:$D$10,2,0) -> #N/A | E36: 1 | F36: NO | H36: SI | I36: =+VLOOKUP(C36,'OCTUBRE 2025'!$C$8:$J$10,3,0) -> #N/A | J36: =+VLOOKUP(C36,'OCTUBRE 2025'!$C$8:$J$10,7,0) -> #N/A | K36: =+'OCTUBRE 2025'!#REF! -> #REF! | M36: =(+(K36)*8.33%) -> #REF!
B37: =+B36+1 -> 32 | C37: 940991987 | D37: =+VLOOKUP(C37,'OCTUBRE 2025'!$C$8:$D$10,2,0) -> #N/A | E37: 1 | F37: NO | H37: SI | I37: =+VLOOKUP(C37,'OCTUBRE 2025'!$C$8:$J$10,3,0) -> #N/A | J37: =+VLOOKUP(C37,'OCTUBRE 2025'!$C$8:$J$10,7,0) -> #N/A | K37: =+'OCTUBRE 2025'!#REF! -> #REF! | M37: =(+(K37)*8.33%) -> #REF!
B38: =+B37+1 -> 33 | C38: 956929277 | D38: =+VLOOKUP(C38,'OCTUBRE 2025'!$C$8:$D$10,2,0) -> #N/A | F38: NO | H38: NO | I38: =+VLOOKUP(C38,'OCTUBRE 2025'!$C$8:$J$10,3,0) -> #N/A | J38: =+VLOOKUP(C38,'OCTUBRE 2025'!$C$8:$J$10,7,0) -> #N/A | K38: =+'OCTUBRE 2025'!#REF! -> #REF! | M38: 0
B39: =+B38+1 -> 34 | C39: 951763994 | D39: =+VLOOKUP(C39,'OCTUBRE 2025'!$C$8:$D$10,2,0) -> #N/A | E39: 1 | F39: SI | G39: 44991 | H39: SI | I39: =+VLOOKUP(C39,'OCTUBRE 2025'!$C$8:$J$10,3,0) -> #N/A | J39: =+VLOOKUP(C39,'OCTUBRE 2025'!$C$8:$J$10,7,0) -> #N/A | K39: =+'OCTUBRE 2025'!#REF! -> #REF! | M39: ACUMULA
B40: =+B39+1 -> 35 | C40: 950703199 | D40: =+VLOOKUP(C40,'OCTUBRE 2025'!$C$8:$D$10,2,0) -> #N/A | E40: 1 | F40: NO | H40: SI | I40: =+VLOOKUP(C40,'OCTUBRE 2025'!$C$8:$J$10,3,0) -> #N/A | J40: =+VLOOKUP(C40,'OCTUBRE 2025'!$C$8:$J$10,7,0) -> #N/A | K40: =+'OCTUBRE 2025'!#REF! -> #REF! | M40: =(+(K40)*8.33%)+Q40+R40 -> #REF!
B41: =+B40+1 -> 36 | C41: 0923715692 | D41: =+VLOOKUP(C41,'OCTUBRE 2025'!$C$8:$D$10,2,0) -> #N/A | E41: 2 | F41: NO | H41: NO | I41: =+VLOOKUP(C41,'OCTUBRE 2025'!$C$8:$J$10,3,0) -> #N/A | J41: =+VLOOKUP(C41,'OCTUBRE 2025'!$C$8:$J$10,7,0) -> #N/A | K41: =+'OCTUBRE 2025'!#REF! -> #REF! | M41: 0
B42: =+B41+1 -> 37 | C42: 925830689 | D42: =+VLOOKUP(C42,'OCTUBRE 2025'!$C$8:$D$10,2,0) -> #N/A | E42: 1 | F42: NO | H42: SI | I42: =+VLOOKUP(C42,'OCTUBRE 2025'!$C$8:$J$10,3,0) -> #N/A | J42: =+VLOOKUP(C42,'OCTUBRE 2025'!$C$8:$J$10,7,0) -> #N/A | K42: =+'OCTUBRE 2025'!#REF! -> #REF! | M42: =(+(K42)*8.33%)+Q42+R42 -> #REF!
B43: =+B42+1 -> 38 | C43: 944034842 | D43: =+VLOOKUP(C43,'OCTUBRE 2025'!$C$8:$D$10,2,0) -> #N/A | E43: 2 | F43: NO | H43: NO | I43: =+VLOOKUP(C43,'OCTUBRE 2025'!$C$8:$J$10,3,0) -> #N/A | J43: =+VLOOKUP(C43,'OCTUBRE 2025'!$C$8:$J$10,7,0) -> #N/A | K43: =+'OCTUBRE 2025'!#REF! -> #REF!
B44: =+B43+1 -> 39 | C44: 951340702 | D44: =+VLOOKUP(C44,'OCTUBRE 2025'!$C$8:$D$10,2,0) -> #N/A | E44: 1 | F44: NO | H44: SI | I44: =+VLOOKUP(C44,'OCTUBRE 2025'!$C$8:$J$10,3,0) -> #N/A | J44: =+VLOOKUP(C44,'OCTUBRE 2025'!$C$8:$J$10,7,0) -> #N/A | K44: =+'OCTUBRE 2025'!#REF! -> #REF! | M44: =(+(K44)*8.33%) -> #REF!
B45: =+B44+1 -> 40 | C45: 650112949 | D45: =+VLOOKUP(C45,'OCTUBRE 2025'!$C$8:$D$10,2,0) -> #N/A | E45: 1 | F45: NO | H45: SI | I45: =+VLOOKUP(C45,'OCTUBRE 2025'!$C$8:$J$10,3,0) -> #N/A | J45: =+VLOOKUP(C45,'OCTUBRE 2025'!$C$8:$J$10,7,0) -> #N/A | K45: =+'OCTUBRE 2025'!#REF! -> #REF! | M45: =(+(K45)*8.33%) -> #REF!
B46: =+B45+1 -> 41 | C46: 924232804 | D46: =+VLOOKUP(C46,'OCTUBRE 2025'!$C$8:$D$10,2,0) -> #N/A | E46: 1 | F46: NO | H46: SI | I46: =+VLOOKUP(C46,'OCTUBRE 2025'!$C$8:$J$10,3,0) -> #N/A | J46: =+VLOOKUP(C46,'OCTUBRE 2025'!$C$8:$J$10,7,0) -> #N/A | K46: =+'OCTUBRE 2025'!#REF! -> #REF! | M46: =(+(K46)*8.33%) -> #REF!
B47: =+B46+1 -> 42 | C47: 605031145 | D47: =+VLOOKUP(C47,'OCTUBRE 2025'!$C$8:$D$10,2,0) -> #N/A | E47: 1 | F47: NO | H47: SI | I47: =+VLOOKUP(C47,'OCTUBRE 2025'!$C$8:$J$10,3,0) -> #N/A | J47: =+VLOOKUP(C47,'OCTUBRE 2025'!$C$8:$J$10,7,0) -> #N/A | K47: =+'OCTUBRE 2025'!#REF! -> #REF! | M47: =(+(K47)*8.33%) -> #REF!
B48: =+B47+1 -> 43 | C48: 927257576 | D48: =+VLOOKUP(C48,'OCTUBRE 2025'!$C$8:$D$10,2,0) -> #N/A | E48: 1 | F48: NO | H48: SI | I48: =+VLOOKUP(C48,'OCTUBRE 2025'!$C$8:$J$10,3,0) -> #N/A | J48: =+VLOOKUP(C48,'OCTUBRE 2025'!$C$8:$J$10,7,0) -> #N/A | K48: =+'OCTUBRE 2025'!#REF! -> #REF! | M48: =(+(K48)*8.33%) -> #REF!
B49: =+B48+1 -> 44 | C49: 928901800 | D49: =+VLOOKUP(C49,'OCTUBRE 2025'!$C$8:$D$10,2,0) -> #N/A | E49: 1 | F49: NO | H49: SI | I49: =+VLOOKUP(C49,'OCTUBRE 2025'!$C$8:$J$10,3,0) -> #N/A | J49: =+VLOOKUP(C49,'OCTUBRE 2025'!$C$8:$J$10,7,0) -> #N/A | K49: =+'OCTUBRE 2025'!#REF! -> #REF! | M49: =(+(K49)*8.33%) -> #REF!
B50: =+B49+1 -> 45 | C50: 951315746 | D50: =+VLOOKUP(C50,'OCTUBRE 2025'!$C$8:$D$10,2,0) -> #N/A | E50: 1 | F50: NO | H50: SI | I50: =+VLOOKUP(C50,'OCTUBRE 2025'!$C$8:$J$10,3,0) -> #N/A | J50: =+VLOOKUP(C50,'OCTUBRE 2025'!$C$8:$J$10,7,0) -> #N/A | K50: =+'OCTUBRE 2025'!#REF! -> #REF! | M50: =(+(K50)*8.33%) -> #REF!
B51: =+B50+1 -> 46 | C51: 954184321 | D51: =+VLOOKUP(C51,'OCTUBRE 2025'!$C$8:$D$10,2,0) -> #N/A | E51: 1 | F51: NO | H51: SI | I51: =+VLOOKUP(C51,'OCTUBRE 2025'!$C$8:$J$10,3,0) -> #N/A | J51: =+VLOOKUP(C51,'OCTUBRE 2025'!$C$8:$J$10,7,0) -> #N/A | K51: =+'OCTUBRE 2025'!#REF! -> #REF! | M51: =(+(K51)*8.33%) -> #REF!
B52: =+B51+1 -> 47 | C52: 922034772 | D52: =+VLOOKUP(C52,'OCTUBRE 2025'!$C$8:$D$10,2,0) -> #N/A | E52: 1 | F52: NO | H52: SI | I52: =+VLOOKUP(C52,'OCTUBRE 2025'!$C$8:$J$10,3,0) -> #N/A | J52: =+VLOOKUP(C52,'OCTUBRE 2025'!$C$8:$J$10,7,0) -> #N/A | K52: =+'OCTUBRE 2025'!#REF! -> #REF! | M52: =(+(K52)*8.33%) -> #REF!
B53: =+B52+1 -> 48 | C53: 923837991 | D53: =+VLOOKUP(C53,'OCTUBRE 2025'!$C$8:$D$10,2,0) -> YUNDA CUJILEMA MARIA TERESA | E53: 1 | F53: NO | H53: SI | I53: =+VLOOKUP(C53,'OCTUBRE 2025'!$C$8:$J$10,3,0) -> 41426 | J53: =+VLOOKUP(C53,'OCTUBRE 2025'!$C$8:$J$10,7,0) -> 30 | K53: =+'OCTUBRE 2025'!T8 -> 1122.2 | M53: =(+(K53)*8.33%) -> 93.47926
B54: =+B53+1 -> 49 | C54: 941508905 | D54: =+VLOOKUP(C54,'OCTUBRE 2025'!$C$8:$D$10,2,0) -> YUQUILEMA CACUANGO ANGEL JOSE | E54: 1 | F54: NO | H54: SI | I54: =+VLOOKUP(C54,'OCTUBRE 2025'!$C$8:$J$10,3,0) -> 43567 | J54: =+VLOOKUP(C54,'OCTUBRE 2025'!$C$8:$J$10,7,0) -> 30 | K54: =+'OCTUBRE 2025'!T9 -> 622.21 | M54: =(+(K54)*8.33%) -> 51.830093
B55: =+B54+1 -> 50 | C55: 604154575 | D55: =+VLOOKUP(C55,'OCTUBRE 2025'!$C$8:$D$10,2,0) -> YUQUILEMA DELGADO PEDRO ANTONIO | E55: 1 | F55: NO | H55: SI | I55: =+VLOOKUP(C55,'OCTUBRE 2025'!$C$8:$J$10,3,0) -> 43379 | J55: =+VLOOKUP(C55,'OCTUBRE 2025'!$C$8:$J$10,7,0) -> 30 | K55: =+'OCTUBRE 2025'!T10 -> 1022.2 | M55: =(+(K55)*8.33%) -> 85.14926
K56: =SUM(K6:K55) -> #REF! | L56: =SUM(L6:L55) -> 0 | M56: =SUM(M6:M55) -> #REF! | Q56: =SUM(Q6:Q55) -> 0

Sheet Enfermedad
B8: Trabajador(a): | C8: GUARANDA QUITIO BRYAN | F8: Inicio: | G8: 45195
B9: Fecha de ingreso: | C9: 45397 | F9: Fin: | G9: 45278
B10: Sueldo: | C10: 550 | F10: Total de dias | G10: =+G9-G8 -> 83
B11: Subsidio: | C11: Maternidad
B13: Calculo para el Pago:
B14: Sueldo Promedio Diario: | D14: =+C10/30 -> 18.333333 | E14: (1-3 dias) | F14: =+C10/30 -> 18.333333
B15: Promedio Diario (25%): | D15: =+D14*25% -> 4.5833333 | E15: (4-70 dias) | F15: =+F14*25% -> 4.5833333
B17: Nº | C17: Periodo | E17: Pocentajes | F17: Num. Dias | G17: Valor
C18: Desde | D18: Hasta
B19: 1 | C19: 45658
B20: 2
B21: 3
B22: 4
B23: 5
B24: 6
B25: TOTAL | F25: =SUM(F19:F24) -> 0 | G25: =SUM(G19:G24) -> 0
B27: ROL PROPORCIONAL
B29: INGRESOS | C29: VALOR | D29: EGRESOS | E29: VALOR
B30: SUELDO BÁSICO COOPERATIVA | C30: 600 | D30: APORTE INDIVIDUAL AL IESS 9.45 | E30: 56.7
B31: BONO MOVILIZACION | C31: 0 | D31: CUENTAS POR COBRAR | E31: 0
B32: BONO CUMPLIMIENTO | C32: 0
B33: COMISION POR SUPERAR LA META | C33: 0
B34: COMISION POR PLAZOS FIJOS | C34: 0
B35: COMISION POR SOCIOS NUEVOS | C35: 0
B36: HORAS EXTRAS 50% | C36: 0
B37: HORAS EXTRAS 100% | C37: 0
B38: FONDO DE RESERVA | C38: 49.98
B39: DECIMO TERCERO | C39: 0
B40: DECIMO CUARTO | C40: 0
B41: TOTAL INGRESOS | C41: =SUM(C30:C40) -> 649.98 | D41: TOTAL EGRESOS | E41: =SUM(E30:E37) -> 56.7 | F41: 593.28
D42: VALOR NETO A RECIBIR | E42: =+C41-E41 -> 593.28 | F42: =F41-E42 -> 0

Sheet CxC García Henry
C4: CUENTAS POR COBRAR A EMPLEADO
C7: CI | E7: 950929232 | G7: NOMBRE: | H7: =+VLOOKUP($E$7,'OCTUBRE 2025'!$C$8:$J$10,2,0) -> #N/A
C8: SUELDO: | E8: =+VLOOKUP($E$7,'OCTUBRE 2025'!$C$8:$J$10,8,0) -> #N/A | G8: CARGO: | H8: =+VLOOKUP($E$7,'OCTUBRE 2025'!$C$8:$J$10,4,0) -> #N/A
C9: FECHA DE INGRESO: | E9: =+VLOOKUP($E$7,'OCTUBRE 2025'!$C$8:$J$10,3,0) -> #N/A | G9: AGENCIA: | H9: =+VLOOKUP($E$7,'OCTUBRE 2025'!$C$8:$J$10,6,0) -> #N/A
C11: TIPO DE SOLICITUD:
J12: TABLA - FORMA DE PAGO
D13: ANTICIPO | J13: # CUOTA | K13: FECHA | L13: VALOR
D14: Dscto por pérdida de bien | H14: 86 | J14: 1 | K14: 45352 | L14: =+H17 -> 28.666667
D15: SOLICITUD DE # CUOTAS A DESCONTAR | H15: 3 | J15: 2 | K15: 45383 | L15: =+L14 -> 28.666667
J16: 3 | K16: 45413 | L16: =+L15 -> 28.666667
D17: VALOR | H17: =+H14/H15 -> 28.666667 | J17: 4
J18: 5
J19: 6
J20: 7
J21: 8
J22: 9
J23: 10
J24: TOTAL | L24: =SUM(L14:L23) -> 86
C28: OBSERVACIONES
C30: DESCUENTO POR PÉRDIDA DE EQUIPO MÓVIL ( Celular)
C33: FIRMAS Y/O AUTORIZACIÓN
C35: Autorizo a la empresa Coac Los Andes Latinos LTDA., a descontar mediante mi rol de pago mensual o en mi liquidación de haberes de ser el caso
D43: FIRMA DEL SOLICITANTE | I43: ELABORADO POR
D44: C.I. | E44: =+E7 -> 950929232 | I44: DEPARTAMENTO DE RRHH
G56: APROBADO POR
G57: GERENCIA

Sheet CxC Guayanlema
C4: CUENTAS POR COBRAR A EMPLEADO
C7: CI | E7: 956796767 | G7: NOMBRE: | H7: =+VLOOKUP($E$7,'OCTUBRE 2025'!$C$8:$J$10,2,0) -> #N/A
C8: SUELDO: | E8: =+VLOOKUP($E$7,'OCTUBRE 2025'!$C$8:$J$10,8,0) -> #N/A | G8: CARGO: | H8: =+VLOOKUP($E$7,'OCTUBRE 2025'!$C$8:$J$10,4,0) -> #N/A
C9: FECHA DE INGRESO: | E9: =+VLOOKUP($E$7,'OCTUBRE 2025'!$C$8:$J$10,3,0) -> #N/A | G9: AGENCIA: | H9: =+VLOOKUP($E$7,'OCTUBRE 2025'!$C$8:$J$10,6,0) -> #N/A
C11: TIPO DE SOLICITUD:
J12: TABLA - FORMA DE PAGO
D13: ANTICIPO | J13: # CUOTA | K13: FECHA | L13: VALOR
D14: Dscto por pérdida de bien | H14: 119.95 | J14: 1 | K14: 45352 | L14: =+H17 -> 39.983333
D15: SOLICITUD DE # CUOTAS A DESCONTAR | H15: 3 | J15: 2 | K15: 45383 | L15: =+L14 -> 39.983333
J16: 3 | K16: 45413 | L16: =+L15 -> 39.983333
D17: VALOR | H17: =+H14/H15 -> 39.983333 | J17: 4
J18: 5
J19: 6
J20: 7
J21: 8
J22: 9
J23: 10
J24: TOTAL | L24: =SUM(L14:L23) -> 119.95
C28: OBSERVACIONES
C30: DESCUENTO POR PÉRDIDA DE EQUIPO MÓVIL ( Impresora)
C33: FIRMAS Y/O AUTORIZACIÓN
C35: Autorizo a la empresa Coac Los Andes Latinos LTDA., a descontar mediante mi rol de pago mensual o en mi liquidación de haberes de ser el caso
D43: FIRMA DEL SOLICITANTE | I43: ELABORADO POR
D44: C.I. | E44: =+E7 -> 956796767 | I44: DEPARTAMENTO DE RRHH
G56: APROBADO POR
G57: GERENCIA

Sheet ANTICIPOS
B1: No. | C1: CEDULA | D1: NOMBRE | E1: ANTICP. SUELD.
B3: 1 | C3: 925813685 | D3: ASITIMBAY CRIOLLO JOHN ANDERSON | E3: =IFERROR(+VLOOKUP(D3,$D$64:$E$101,2,0),0) -> 720.63
B4: =+B3+1 -> 2 | C4: 944405737 | D4: BARAHONA ZAMBRANO DAYANA NICOLE | E4: =IFERROR(+VLOOKUP(D4,$D$64:$E$101,2,0),0) -> 0
B5: =+B4+1 -> 3 | C5: 604394502 | D5: BETUN CHAFLA JULIO CESAR | E5: =IFERROR(+VLOOKUP(D5,$D$64:$E$101,2,0),0) -> 0
B6: =+B5+1 -> 4 | C6: 955741970 | D6: CHACAGUASAY CHACAGUASAY ROBERTH CRISTHIAN | E6: =IFERROR(+VLOOKUP(D6,$D$64:$E$101,2,0),0) -> 400
B7: =+B6+1 -> 5 | C7: 0943964973 | D7: CHACAGUASAY GUAMAN KEVIN NEHEMIAS
B8: =+B7+1 -> 6 | C8: 944143148 | D8: CHIMBOLEMA YUNGAN MARIO EFRAIN | E8: =IFERROR(+VLOOKUP(D8,$D$64:$E$101,2,0),0) -> 0
B9: =+B8+1 -> 7 | C9: 955325238 | D9: CHOCA CEPEDA INES VIVIANA | E9: =IFERROR(+VLOOKUP(D9,$D$64:$E$101,2,0),0) -> 0
B10: =+B9+1 -> 8 | C10: 914163654 | D10: COCA BENITEZ JORGE MANUEL | E10: =IFERROR(+VLOOKUP(D10,$D$64:$E$101,2,0),0) -> 0
B11: =+B10+1 -> 9 | C11: 956668305 | D11: CORO YUQUILEMA RUT NOEMI | E11: =IFERROR(+VLOOKUP(D11,$D$64:$E$101,2,0),0) -> 0
B12: =+B11+1 -> 10 | C12: 918741448 | D12: DEFAS CHICAIZA JOEL ALBERTO | E12: =IFERROR(+VLOOKUP(D12,$D$64:$E$101,2,0),0) -> 150
B13: =+B12+1 -> 11 | C13: 931097620 | D13: DEL ROSARIO RODRIGUEZ JUDY ANGELICA | E13: =IFERROR(+VLOOKUP(D13,$D$64:$E$101,2,0),0) -> 144.3
B14: =+B13+1 -> 12 | C14: 1105483422 | D14: FLORES HERRERA WENDY DEL CISNE | E14: =IFERROR(+VLOOKUP(D14,$D$64:$E$101,2,0),0) -> 0
B15: =+B14+1 -> 13 | C15: 942614645 | D15: FUELA TOABANDA JOSUE CHRISTIAN | E15: =IFERROR(+VLOOKUP(D15,$D$64:$E$101,2,0),0) -> 350
B16: =+B15+1 -> 14 | C16: 951200062 | D16: GALAN LEMACHE INGRID GISELA | E16: =IFERROR(+VLOOKUP(D16,$D$64:$E$101,2,0),0) -> 300
B17: =+B16+1 -> 15 | C17: 950929232 | D17: GARCIA VERA HENRY LUIS | E17: =IFERROR(+VLOOKUP(D17,$D$64:$E$101,2,0),0) -> 300
B18: =+B17+1 -> 16 | C18: 953819646 | D18: GUALACEO ÑAMO JONATHAN IVÁN | E18: =IFERROR(+VLOOKUP(D18,$D$64:$E$101,2,0),0) -> 0
B19: =+B18+1 -> 17 | C19: 956953392 | D19: GUAPI YUMAGLLA OSCAR EDUARDO | E19: =IFERROR(+VLOOKUP(D19,$D$64:$E$101,2,0),0) -> 150
B20: =+B19+1 -> 18 | C20: 956796767 | D20: GUAYANLEMA RUIZ EDINSON DAVID | E20: =IFERROR(+VLOOKUP(D20,$D$64:$E$101,2,0),0) -> 390
B21: =+B20+1 -> 19 | C21: 0932036049 | D21: HERRERA JIMENEZ CAROLINA ADELIHER | E21: =IFERROR(+VLOOKUP(D21,$D$64:$E$101,2,0),0) -> 0
B22: =+B21+1 -> 20 | C22: 1724102940 | D22: HIDALGO CHERRES NESTOR VLADIMIR | E22: =IFERROR(+VLOOKUP(D22,$D$64:$E$101,2,0),0) -> 500
B23: =+B22+1 -> 21 | C23: 943322974 | D23: JANETA RUIZ ALEXANDRA DEL ROCIO | E23: =IFERROR(+VLOOKUP(D23,$D$64:$E$101,2,0),0) -> 100
B24: =+B23+1 -> 22 | C24: 941096851 | D24: LEMA CHIRAU RAMONA MARIA | E24: =IFERROR(+VLOOKUP(D24,$D$64:$E$101,2,0),0) -> 480.64
B25: =+B24+1 -> 23 | C25: 957093800 | D25: LEMA TADAY BRAYAN WIDINSON | E25: =IFERROR(+VLOOKUP(D25,$D$64:$E$101,2,0),0) -> 0
B26: =+B25+1 -> 24 | C26: 957924350 | D26: LLUMI YUQUILEMA MAYCOOL DANNY | E26: =IFERROR(+VLOOKUP(D26,$D$64:$E$101,2,0),0) -> 0
B27: =+B26+1 -> 25 | C27: 603838657 | D27: MALAN DELGADO JOSE ALBERTO | E27: =IFERROR(+VLOOKUP(D27,$D$64:$E$101,2,0),0) -> 400
B28: =+B27+1 -> 26 | C28: 925240525 | D28: MALAN YUQUILEMA RAUL ALBERTO | E28: =IFERROR(+VLOOKUP(D28,$D$64:$E$101,2,0),0) -> 0
B29: =+B28+1 -> 27 | C29: 954520599 | D29: MARSHALL VEGA YULIANA LISSETT | E29: =IFERROR(+VLOOKUP(D29,$D$64:$E$101,2,0),0) -> 500
B30: =+B29+1 -> 28 | C30: 0943906032 | D30: MEZA RODRIGUEZ MICHAEL FERNANDO | E30: =IFERROR(+VLOOKUP(D30,$D$64:$E$101,2,0),0) -> 300
B31: =+B30+1 -> 29 | C31: 0919306050 | D31: MORAN GARCIA DANNY FAVIAN | E31: =IFERROR(+VLOOKUP(D31,$D$64:$E$101,2,0),0) -> 550
B32: =+B31+1 -> 30 | C32: 0941235376 | D32: MOREIRA ESPINOZA LINDA ELIZABETH | E32: =IFERROR(+VLOOKUP(D32,$D$64:$E$101,2,0),0) -> 332.13
B33: =+B32+1 -> 31 | C33: 955395686 | D33: MOROCHO DUCHI SANDRA STEPHANIE | E33: =IFERROR(+VLOOKUP(D33,$D$64:$E$101,2,0),0) -> 100
B34: =+B33+1 -> 32 | C34: 940991987 | D34: MOROCHO YANTALEMA DINA MAGALY | E34: =IFERROR(+VLOOKUP(D34,$D$64:$E$101,2,0),0) -> 700
B35: =+B34+1 -> 33 | C35: 956929277 | D35: NAULA CRIOLLO CINTHYA ABIGAIL | E35: =IFERROR(+VLOOKUP(D35,$D$64:$E$101,2,0),0) -> 0
B36: =+B35+1 -> 34 | C36: 951763994 | D36: NEVAREZ PEÑAFIEL EVELYN JULEXY | E36: =IFERROR(+VLOOKUP(D36,$D$64:$E$101,2,0),0) -> 0
B37: =+B36+1 -> 35 | C37: 950703199 | D37: ÑAMO GUALACEO BRYAN JAVIER | E37: =IFERROR(+VLOOKUP(D37,$D$64:$E$101,2,0),0) -> 0
B38: =+B37+1 -> 36 | C38: 0923715692 | D38: ORELLANA MANZO WHITNEY YAILYN | E38: =IFERROR(+VLOOKUP(D38,$D$64:$E$101,2,0),0) -> 400
B39: =+B38+1 -> 37 | C39: 925830689 | D39: PERALTA MENDEZ LINA LISSETTE | E39: =IFERROR(+VLOOKUP(D39,$D$64:$E$101,2,0),0) -> 831.44
B40: =+B39+1 -> 38 | C40: 944034842 | D40: PEREZ ZAMORA ANA DE LOS ANGELES | E40: =IFERROR(+VLOOKUP(D40,$D$64:$E$101,2,0),0) -> 0
B41: =+B40+1 -> 39 | C41: 951340702 | D41: QUITO CALDERON JONATHAN ENRIQUE | E41: =IFERROR(+VLOOKUP(D41,$D$64:$E$101,2,0),0) -> 400
B42: =+B41+1 -> 40 | C42: 650112949 | D42: QUITO UCHUBANDA JANETH ALEXANDRA | E42: =IFERROR(+VLOOKUP(D42,$D$64:$E$101,2,0),0) -> 200
B43: =+B42+1 -> 41 | C43: 924232804 | D43: RECALDE NARANJO ANGEL ALEXIS | E43: =IFERROR(+VLOOKUP(D43,$D$64:$E$101,2,0),0) -> 900
B44: =+B43+1 -> 42 | C44: 605031145 | D44: SALAO PEREZ GERMAN FABRICIO | E44: =IFERROR(+VLOOKUP(D44,$D$64:$E$101,2,0),0) -> 0
B45: =+B44+1 -> 43 | C45: 927257576 | D45: SANISACA MITE ISRAEL BENJAMIN | E45: =IFERROR(+VLOOKUP(D45,$D$64:$E$101,2,0),0) -> 426.97
B46: =+B45+1 -> 44 | C46: 928901800 | D46: TADAY GUAMAN NÉSTOR ALONSO | E46: =IFERROR(+VLOOKUP(D46,$D$64:$E$101,2,0),0) -> 150
B47: =+B46+1 -> 45 | C47: 951315746 | D47: TIGUA MONTERO KAREN LISBETH | E47: =IFERROR(+VLOOKUP(D47,$D$64:$E$101,2,0),0) -> 350
B48: =+B47+1 -> 46 | C48: 954184321 | D48: URQUIZO GUARANGA ALEX EFRAIN | E48: =IFERROR(+VLOOKUP(D48,$D$64:$E$101,2,0),0) -> 200
B49: =+B48+1 -> 47 | C49: 922034772 | D49: VERA GUEVARA PAOLA KARINA | E49: =IFERROR(+VLOOKUP(D49,$D$64:$E$101,2,0),0) -> 600
B50: =+B49+1 -> 48 | C50: 923837991 | D50: YUNDA CUJILEMA MARIA TERESA | E50: =IFERROR(+VLOOKUP(D50,$D$64:$E$101,2,0),0) -> 850
... B52: =+B51+1 -> 50 | C52: 604154575 | D52: YUQUILEMA DELGADO PEDRO ANTONIO | E52: =IFERROR(+VLOOKUP(D52,$D$64:$E$101,2,0),0) -> 800
E53: =IFERROR(+VLOOKUP(D53,$D$64:$E$101,2,0),0) -> 0
E54: =IFERROR(+VLOOKUP(D54,$D$64:$E$101,2,0),0) -> 0
D55: TOTALES | E55: =SUBTOTAL(9,E3:E54) -> 13476.11
K56: =+E63-E55 -> 0
C58: ANTICIPOS AL PERSONAL OCTUBRE 2025
B60: N° | C60: Oficina: | D60: Consolidado | E60: Fecha: 30-09-2025
C62: Codigo | D62: Cuenta | E62: Saldo
C63: 1.6.90.05 | D63: ANTICIPOS AL PERSONAL | E63: =SUM(E64:E100) -> 13476.11
B64: 1 | C64: 1.6.90.05.02 | D64: DEFAS CHICAIZA JOEL ALBERTO | E64: 150
B65: 2 | C65: 1.6.90.05.04 | D65: YUQUILEMA CACUANGO ANGEL JOSE | E65: 500
B66: 3 | C66: 1.6.90.05.06 | D66: MOROCHO DUCHI SANDRA STEPHANIE | E66: 100
B67: 4 | C67: 1.6.90.05.07 | D67: ASITIMBAY CRIOLLO JOHN ANDERSON | E67: 720.63
B68: 5 | C68: 1.6.90.05.08 | D68: DEL ROSARIO RODRIGUEZ JUDY ANGELICA | E68: 144.3
B69: 6 | C69: 1.6.90.05.10 | D69: ORELLANA MANZO WHITNEY YAILYN | E69: 400
B70: 7 | C70: 1.6.90.05.13 | D70: JANETA RUIZ ALEXANDRA DEL ROCIO | E70: 100
B71: 8 | C71: 1.6.90.05.15 | D71: HIDALGO CHERRES NESTOR VLADIMIR | E71: 500
B72: 9 | C72: 1.6.90.05.16 | D72: RECALDE NARANJO ANGEL ALEXIS | E72: 900
B73: 10 | C73: 1.6.90.05.17 | D73: YUQUILEMA DELGADO PEDRO ANTONIO | E73: 800
B74: 11 | C74: 1.6.90.05.20 | D74: URQUIZO GUARANGA ALEX EFRAIN | E74: 200
B75: 12 | C75: 1.6.90.05.21 | D75: QUITO CALDERON JONATHAN ENRIQUE | E75: 400
... B95: 32 | C95: 1.6.90.05.95 | D95: YUNDA CUJILEMA MARIA TERESA | E95: 850
B96: 33
B97: 34
B98: 35
B99: 36
B100: 37

Sheet Hoja1
F3: =800/30 -> 26.666667
F4: =+F3*2 -> 53.333333

Sheet comprobación
D2: BETUN CHAFLA JULIO CESAR | E2: 490.16 | F2: 490.16 | G2: =+E2-F2 -> 0
D3: CALDERON QUITO OSCAR JAVIER | E3: 213.66 | F3: 213.66 | G3: =+E3-F3 -> 0
D4: CHACAGUASAY CHACAGUASAY ROBERTH | E4: 250.89 | F4: 250.88715 | G4: =+E4-F4 -> 0.00285
D5: FLORES HERRERA WENDY DEL CISNE | E5: 27.08 | F5: 27.083333 | G5: =+E5-F5 -> -0.0033333333
D6: GALAN LEMACHE INGRID GISELA | E6: 176.12 | F6: 176.12 | G6: =+E6-F6 -> 0
D7: GUALACEO ÑAMO JONATHAN IVAN | E7: 199.65 | F7: 199.65033 | G7: =+E7-F7 -> -0.00033333333
D8: GUAPI YUMAGLLA OSCAR EDUARDO | E8: 255.05 | F8: 255.053 | G8: =+E8-F8 -> -0.003
D9: GUARANDA QUITIO BRYAN ESTEVEN | E9: 29.79 | F9: 29.791667 | G9: =+E9-F9 -> -0.0016666667
D10: GUAYANLEMA RUIZ EDINSON DAVID | E10: 205.17 | F10: 205.16925 | G10: =+E10-F10 -> 0.00075
D11: HIDALGO CHERRES NESTOR VLADIMIR | E11: 177.59 | F11: 177.59021 | G11: =+E11-F11 -> -0.00021333333
D12: JANETA RUIZ ALEXANDRA DEL ROCIO | E12: 325.8 | F12: 325.80407 | G12: =+E12-F12 -> -0.00407
D13: LEMA CHIRAU RAMONA MARIA | E13: 23.56 | F13: 23.56 | G13: =+E13-F13 -> 0
... D34: YUQUILEMA DELGADO PEDRO ANTONIO | E34: 330.33 | F34: 330.3305 | G34: =+E34-F34 -> -0.0005
E35: =SUM(E2:E34) -> 8406.58 | F35: =SUM(F2:F34) -> 8406.5913

Sheet DESCUENTO
J5: 1 | K5: 2 | L5: 3 | M5: 4 | N5: 5 | O5: 6 | P5: 7 | Q5: 8 | R5: 9 | S5: 10 | T5: 11 | U5: 12
B6: Cliente | C6: Identificación | D6: Nombre Cliente | E6: Deuda Inicial | F6: DESCONTADO? | G6: FIR | H6: N° CUOTAS | I6: DESC. MENSUAL | J6: SEPT | K6: OCT | L6: NOV | M6: DIC | N6: ENERO | O6: FEBRERO | P6: MARZO | Q6: ABRIL | R6: MAYO | S6: JUNIO | T6: JULIO | U6: AGOSTO | V6: TOTAL
B7: 9583 | C7: 940991987 | D7: MOROCHO YANTALEMA DINA MAGALY | E7: 25000 | F7: NO | G7: =+IF(F7= "NO",E7*2%,0) -> 500 | H7: 6 | I7: =+G7/H7 -> 83.333333 | J7: =+I7 -> 83.333333 | K7: 83.33 | L7: 83.33 | M7: 83.33 | N7: 83.33 | O7: 83.35 | V7: =SUM(J7:U7) -> 500.00333 | W7: =+G7-V7 -> -0.0033333333
B8: 9364 | C8: 925813685 | D8: ASITIMBAY CRIOLLO JOHN ANDERSON | E8: 1000 | F8: NO | G8: =+IF(F8= "NO",E8*2%,0) -> 20 | H8: 1 | I8: =+G8/H8 -> 20 | J8: 20 | V8: =SUM(J8:U8) -> 20 | W8: =+G8-V8 -> 0
B9: 8569 | C9: 928901800 | D9: TADAY GUAMAN NESTOR ALONSO | E9: 20000 | F9: NO | G9: =+IF(F9= "NO",E9*2%,0) -> 400 | H9: 12 | I9: =+G9/H9 -> 33.333333 | J9: 33.333333 | K9: 33.333333 | L9: 33.333333 | M9: 33.33 | N9: 33.33 | O9: 33.33 | P9: 33.33 | Q9: 33.33 | R9: 33.33 | S9: 33.33 | T9: 33.33 | U9: 33.33 | V9: =SUM(J9:U9) -> 399.97 | W9: =+G9-V9 -> 0.03
B10: 14207 | C10: 604394502 | D10: BETUN CHAFLA JULIO CESAR | E10: 3000 | F10: NO | G10: =+IF(F10= "NO",E10*2%,0) -> 60 | H10: 1 | I10: =+G10/H10 -> 60 | J10: 60 | V10: =SUM(J10:U10) -> 60 | W10: =+G10-V10 -> 0
B11: 12152 | C11: 955395686 | D11: MOROCHO DUCHI SANDRA STEPHANIE | E11: 15000 | F11: NO | G11: =+IF(F11= "NO",E11*2%,0) -> 300 | H11: 3 | I11: =+G11/H11 -> 100 | J11: 100 | K11: 100 | L11: 100 | V11: =SUM(J11:U11) -> 300 | W11: =+G11-V11 -> 0
B12: 5135 | C12: 925830689 | D12: PERALTA MENDEZ LINA LISSETTE | E12: 11000 | F12: NO | G12: =+IF(F12= "NO",E12*2%,0) -> 220 | H12: 1 | I12: =+G12/H12 -> 220 | J12: 220 | V12: =SUM(J12:U12) -> 220 | W12: =+G12-V12 -> 0
B13: 14045 | C13: 953819646 | D13: GUALACEO ÑAMO JONATHAN IVAN | E13: 1500 | F13: NO | G13: =+IF(F13= "NO",E13*2%,0) -> 30 | H13: 1 | I13: =+G13/H13 -> 30 | J13: 30 | V13: =SUM(J13:U13) -> 30 | W13: =+G13-V13 -> 0
B14: TOTAL GENERAL : | E14: =+SUBTOTAL(9,E7:E13) -> 76500 | G14: =+SUBTOTAL(9,G7:G13) -> 1530 | H14: =+SUBTOTAL(9,H7:H13) -> 25 | I14: =+SUBTOTAL(9,I7:I13) -> 546.66667 | J14: =SUM(J7:J13) -> 546.66667 | K14: =SUM(K7:K13) -> 216.66333 | L14: =SUM(L7:L13) -> 216.66333 | M14: =SUM(M7:M13) -> 116.66 | N14: =SUM(N7:N13) -> 116.66 | O14: =SUM(O7:O13) -> 116.68 | P14: =SUM(P7:P13) -> 33.33 | Q14: =SUM(Q7:Q13) -> 33.33 | ... W14: =SUM(W7:W13) -> 0.026666667
N18: 33.333333 | R18: 550
O19: =33.33*12 -> 399.96 | R19: 60 | S19: PAOLA
G20: 83.33 | I20: 33.33 | R20: 67.01 | S20: INGRID
G21: 83.33 | I21: 33.33 | M21: 250 | N21: MIO | R21: 74.68 | S21: GUAPI
G22: 83.33 | I22: 33.33 | M22: =+SUM(M9:U9) -> 299.97 | R22: =SUM(R18:R21) -> 751.69
G23: =SUM(G20:G22) -> 249.99 | I23: =SUM(I20:I22) -> 99.99 | M23: =SUM(M21:M22) -> 549.97 | O23: =33.33*3 -> 99.99
I24: =400-I23 -> 300.01 | R24: 751.69
G25: =500-G23 -> 250.01 | O25: =400-O23 -> 300.01 | R25: =+R24-R22 -> 0

Sheet anticipos-pago yuquilema
H2: 1 | J2: 2 | K2: 3 | L2: 4
B3: Cliente | C3: Identificación | D3: Nombre Cliente | E3: Deuda Inicial | F3: N° CUOTAS | G3: DESC. MENSUAL | H3: AGOSTO | I3: SEPT | J3: OCT | K3: NOV | L3: DIC | M3: TOTAL
B4: 9583 | C4: 0940991987 | D4: LEMA CHIRAU MARIA | E4: 176.06 | F4: 5 | G4: =+E4/5 -> 35.212 | H4: =+G4 -> 35.212 | I4: =+H4 -> 35.212 | J4: =+H4 -> 35.212 | K4: =+J4 -> 35.212 | L4: =+K4 -> 35.212 | M4: =SUM(H4:L4) -> 176.06 | N4: =+E4-M4 -> 0
B5: 9364 | C5: 0925813685 | D5: YUQUILEMA PEDRO | E5: 176.06 | F5: 5 | G5: =+E5/5 -> 35.212 | H5: =+G5 -> 35.212 | I5: =+H5 -> 35.212 | J5: =+H5 -> 35.212 | K5: =+J5 -> 35.212 | L5: =+K5 -> 35.212 | M5: =SUM(H5:L5) -> 176.06 | N5: =+E5-M5 -> 0
